Workbook

Sheet How to update dates
A1: 1. About half way through earnings season export a new files from ToS
A2: 2. Only update future dates, so paste the formula into the next earnings and copy that down.
A3: 3. Paste values and switch format to full year using the little icon that pops up.
A4: 4. Now, sort oldest to newest.
A5: 5. By doing this all past sorting by date will stay the same, but, future dates will be adjusted to be accurate.

Sheet Indices
A1: Stock | B1: Index | C1: Index2 | D1: Sector | E1: As of: | F1: 45616
A2: NVDA | B2: SP500 | C2: NQ100
A3: AAPL | B3: SP500 | C3: NQ100
A4: MSFT | B4: SP500 | C4: NQ100
A5: GOOG | B5: SP500 | C5: NQ100
A6: GOOGL | B6: SP500 | C6: NQ100
A7: AMZN | B7: SP500 | C7: NQ100
A8: META | B8: SP500 | C8: NQ100
A9: TSLA | B9: SP500 | C9: NQ100
A10: BRK.B | B10: SP500
A11: AVGO | B11: SP500 | C11: NQ100
A12: WMT | B12: SP500
A13: JPM | B13: SP500
A14: LLY | B14: SP500
A15: V | B15: SP500
A16: UNH | B16: SP500
A17: XOM | B17: SP500
A18: ORCL | B18: SP500
A19: MA | B19: SP500
A20: COST | B20: SP500 | C20: NQ100
A21: PG | B21: SP500
A22: HD | B22: SP500
A23: NFLX | B23: SP500 | C23: NQ100
A24: JNJ | B24: SP500
A25: BAC | B25: SP500
A26: CRM | B26: SP500
A27: ABBV | B27: SP500
A28: CVX | B28: SP500
A29: TMUS | B29: SP500 | C29: NQ100
A30: KO | B30: SP500
A31: MRK | B31: SP500
A32: WFC | B32: SP500
A33: CSCO | B33: SP500 | C33: NQ100
A34: BX | B34: SP500
A35: ACN | B35: SP500
A36: AMD | B36: SP500 | C36: NQ100
A37: ADBE | B37: SP500 | C37: NQ100
A38: PEP | B38: SP500 | C38: NQ100
A39: LIN | B39: SP500 | C39: NQ100
A40: MS | B40: SP500
A41: NOW | B41: SP500
A42: MCD | B42: SP500
A43: DIS | B43: SP500
A44: PM | B44: SP500
A45: AXP | B45: SP500
A46: ABT | B46: SP500
A47: IBM | B47: SP500
A48: TMO | B48: SP500
A49: ISRG | B49: SP500 | C49: NQ100
A50: GE | B50: SP500
A51: GS | B51: SP500
A52: CAT | B52: SP500
A53: INTU | B53: SP500 | C53: NQ100
A54: TXN | B54: SP500 | C54: NQ100
A55: VZ | B55: SP500
A56: QCOM | B56: SP500 | C56: NQ100
A57: DHR | B57: SP500
A58: BKNG | B58: SP500 | C58: NQ100
A59: T | B59: SP500
A60: CMCSA | B60: SP500 | C60: NQ100
A61: BLK | B61: SP500
A62: RTX | B62: SP500
A63: NEE | B63: SP500
A64: SPGI | B64: SP500
A65: AMGN | B65: SP500 | C65: NQ100
A66: PGR | B66: SP500
A67: LOW | B67: SP500
A68: HON | B68: SP500 | C68: NQ100
A69: SCHW | B69: SP500
A70: SYK | B70: SP500
A71: UBER | B71: SP500
A72: ETN | B72: SP500
A73: UNP | B73: SP500
A74: PLTR | B74: SP500
A75: PFE | B75: SP500
A76: AMAT | B76: SP500 | C76: NQ100
A77: KKR | B77: SP500
A78: TJX | B78: SP500
A79: BSX | B79: SP500
A80: COP | B80: SP500
A81: C | B81: SP500
A82: PANW | B82: SP500 | C82: NQ100
A83: LMT | B83: SP500
A84: FI | B84: SP500
A85: ADP | B85: SP500 | C85: NQ100
A86: ANET | B86: SP500
A87: BMY | B87: SP500
A88: VRTX | B88: SP500 | C88: NQ100
A89: CB | B89: SP500
A90: UPS | B90: SP500
A91: SBUX | B91: SP500 | C91: NQ100
A92: GILD | B92: SP500 | C92: NQ100
A93: DE | B93: SP500
A94: BA | B94: SP500
A95: MMC | B95: SP500
A96: NKE | B96: SP500
A97: MU | B97: SP500 | C97: NQ100
A98: MDT | B98: SP500
A99: PLD | B99: SP500
A100: ADI | B100: SP500 | C100: NQ100
...

Sheet Pivot
A1: Index | B1: (Multiple Items)
A3: Row Labels | B3: Count of Ticker
A4: 7-Jan | B4: 1
A5: 8-Jan | B5: 3
A6: 10-Jan | B6: 4
A7: 14-Jan | B7: 5
A8: 15-Jan | B8: 5
A9: 16-Jan | B9: 9
A10: 17-Jan | B10: 6
A11: 21-Jan | B11: 15
A12: 22-Jan | B12: 22
A13: 23-Jan | B13: 13
A14: 24-Jan | B14: 3
A15: 27-Jan | B15: 10
... A61: Grand Total | B61: 843

Sheet Sector Summary
A1: 2025 -- Q1
A3: Executive Summary:
A4: =_xlfn.CONCAT(" For the ",A1," earnings season, ", TEXT('Stats Roll Up'!R4,"###")& " earnings trades were taken, ",TEXT('Summary Data'!B2,"00%")," were stocks from the S&P 500.") -> For the 2025 -- Q1 earnings season, 443 earnings trades were taken, 88% were stocks from the S&P 500.
A5: ● | B5: =CONCATENATE("Overall, the The Earnings Strategy producted: ") -> Overall, the The Earnings Strategy producted: | O5: =TEXT('Summary Data'!J$4,"0.0") -> 68.6 | Q5: risk units.
A6: Up Trending Stocks:
A7: ● | B7: =_xlfn.CONCAT('Summary Data'!$D$2," of the trades were stocks in an up trend."," This is ", TEXT('Summary Data'!$E$2,"00%")," of all trades.") -> 101 of the trades were stocks in an up trend. This is 23% of all trades.
A8: ● | B8: =_xlfn.CONCAT(TEXT('Stats Roll Up'!$G$4,"00.0%")," of the up trendng stocks opened higher after earnings. The average gap higher was ",TEXT('Stats Roll Up'!$D$4,"0.0%"),".") -> 52.5% of the up trendng stocks opened higher after earnings. The average gap higher was 5.0%.
A9: ● | B9: =_xlfn.CONCAT(TEXT('Stats Roll Up'!$AC$4,"00.0%")," of the up trendng stocks opened lower after earnings. The average gap down from an up trend was ",TEXT('Stats Roll Up'!$AE$4,"0.0%"),".") -> 47.5% of the up trendng stocks opened lower after earnings. The average gap down from an up trend was 4.6%.
A10: ● | B10: =CONCATENATE("For up trends, the strategy produced: ") -> For up trends, the strategy produced: | M10: ='Summary Data'!$D$4 -> 10.009379 | N10: risk units.
A11: ● | B11: Up trends had an expectancy of: | K11: =Expectancy!$Q$3 -> 0.099102767 | M11: risk units per trade.
A13: Down Trending Stocks:
A14: ● | B14: =_xlfn.CONCAT('Summary Data'!$F$2," of the trades were stocks in an down trend."," This is ", TEXT('Summary Data'!$G$2,"00%")," of all trades.") -> 128 of the trades were stocks in an down trend. This is 29% of all trades.
A15: ● | B15: =_xlfn.CONCAT(TEXT('Stats Roll Up'!$Y$4,"00.0%")," of the down trending stocks opened lower after earnings. The average gap down was ",TEXT('Stats Roll Up'!$AA$4,"0.0%"),".") -> 59.4% of the down trending stocks opened lower after earnings. The average gap down was 6.5%.
A16: ● | B16: =_xlfn.CONCAT(TEXT('Stats Roll Up'!$K$4,"00.0%")," of the down trending stocks opened higher after earnings. The average gap up from a down trend was ",TEXT('Stats Roll Up'!$M$4,"0.0%"),".") -> 40.6% of the down trending stocks opened higher after earnings. The average gap up from a down trend was 4.6%.
A17: ● | B17: =CONCATENATE("For down trends, the strategy produced: ") -> For down trends, the strategy produced: | N17: ='Summary Data'!$F$4 -> 43.496895 | O17: =_xlfn.CONCAT("risk units.") -> risk units.
A18: ● | B18: Down trends had an expectancy of: | L18: =Expectancy!$R$3 -> 0.33981949 | N18: risk units per trade.
A20: Sideways Trending Stocks:
A21: ● | B21: =_xlfn.CONCAT('Summary Data'!$H$2," of the trades were stocks in a sideways trend."," This is ", TEXT('Summary Data'!$I$2,"00%")," of all trades.") -> 215 of the trades were stocks in a sideways trend. This is 48% of all trades.
A22: ● | B22: =_xlfn.CONCAT(TEXT('Stats Roll Up'!$O$4,"00.0%")," of the sideways stocks opened higher after earnings. The average gap up was ",TEXT('Stats Roll Up'!$Q$4,"0.0%"),".") -> 51.2% of the sideways stocks opened higher after earnings. The average gap up was 5.0%.
A23: ● | B23: =_xlfn.CONCAT(TEXT('Stats Roll Up'!$AG$4,"00.0%")," of the sideways stocks opened lower after earnings. The average gap down from a sideways trend was ",TEXT('Stats Roll Up'!$AI$4,"0.0%"),".") -> 48.8% of the sideways stocks opened lower after earnings. The average gap down from a sideways trend was 4.4%.
A24: ● | B24: =CONCATENATE("For sideways trends, the strategy produced: ") -> For sideways trends, the strategy produced: | N24: ='Summary Data'!$H$4 -> 15.126535 | O24: =_xlfn.CONCAT("risk units.") -> risk units.
A25: ● | B25: Sideways trends had an expectancy of: | M25: =Expectancy!$S$3 -> 0.070355978 | O25: risk units per trade.
A40: 2025 -- Q1
A42: Sector Performance:
A43: Up Trending Stocks, Risk Units by Sector:
A57: Down Trending Stocks, Risk Units by Sector:
A71: Sideways Trending Stocks:
A85: 2025 -- Q1
A87: Sector Performance, continued:
A88: Total Risk Units by Sector, w/ Expectancy:

Sheet Summary Data
B1: % in SPY | C1: Total | D1: # in Up | E1: % in Up | F1: # in Dwn | G1: % in Dwn | H1: # in SW | I1: % in SW
B2: =COUNTIF('2025-Q1'!$D$4:$D$448,"Y")/C2 -> 0.87640449 | C2: =COUNTA('2025-Q1'!$D$4:$D$448) -> 445 | D2: =COUNTIF('2025-Q1'!$FV$4:$FV$448,"Up") -> 101 | E2: =D2/$C$2 -> 0.22696629 | F2: =COUNTIF('2025-Q1'!$FV$4:$FV$448,"Dwn") -> 128 | G2: =F2/$C$2 -> 0.28764045 | H2: =COUNTIF('2025-Q1'!$FV$4:$FV$448,"Sw") -> 215 | I2: =H2/$C$2 -> 0.48314607
D3: Up: R | F3: Down: R | H3: SW: R | J3: All: R
D4: =SUM('2025-Q1'!$T$4:$T$448) -> 10.009379 | F4: =SUM('2025-Q1'!$V$4:$V$448) -> 43.496895 | H4: =SUM('2025-Q1'!$X$4:$X$448) -> 15.126535 | J4: =D4+F4+H4 -> 68.632809
B8: Risk Units | C8: Expectancy
A9: Up | B9: =D4 -> 10.009379 | C9: =Expectancy!Q3 -> 0.099102767
A10: Down | B10: =F4 -> 43.496895 | C10: =Expectancy!R3 -> 0.33981949
A11: SW | B11: =H4 -> 15.126535 | C11: =Expectancy!S3 -> 0.070355978

Sheet Earnings
A1: Date/Time | B1: Ticker | C1: When | D1: Index
A2: 45659.587 | B2: LFCR | C2: on 1/2/25, 4:05 PM After Market Eastern Standard Time | D2: =_xlfn.XLOOKUP(B2,Indices!$A$2:$A$2676,Indices!$B$2:$B$2676,"")
A3: 45659.59 | B3: RGP | C3: on 1/2/25, 4:10 PM After Market Eastern Standard Time | D3: =_xlfn.XLOOKUP(B3,Indices!$A$2:$A$2676,Indices!$B$2:$B$2676,"") -> IWM
A4: 45660.25 | B4: EMKR | C4: on 1/3/25, 8:00 AM Before Market Eastern Standard Time | D4: =_xlfn.XLOOKUP(B4,Indices!$A$2:$A$2676,Indices!$B$2:$B$2676,"")
A5: 45663.463 | B5: CMC | C5: on 1/6/25, 1:06 PM During Market Eastern Standard Time | D5: =_xlfn.XLOOKUP(B5,Indices!$A$2:$A$2676,Indices!$B$2:$B$2676,"") -> IWM
A6: 45664.188 | B6: APOG | C6: on 1/7/25, 6:30 AM Before Market Eastern Standard Time | D6: =_xlfn.XLOOKUP(B6,Indices!$A$2:$A$2676,Indices!$B$2:$B$2676,"") -> IWM
A7: 45664.198 | B7: LNN | C7: on 1/7/25, 6:45 AM Before Market Eastern Standard Time | D7: =_xlfn.XLOOKUP(B7,Indices!$A$2:$A$2676,Indices!$B$2:$B$2676,"") -> IWM
A8: 45664.198 | B8: RPM | C8: on 1/7/25, 6:45 AM Before Market Eastern Standard Time | D8: =_xlfn.XLOOKUP(B8,Indices!$A$2:$A$2676,Indices!$B$2:$B$2676,"") -> S&P Mid
A9: 45664.587 | B9: CALM | C9: on 1/7/25, 4:05 PM After Market Eastern Standard Time | D9: =_xlfn.XLOOKUP(B9,Indices!$A$2:$A$2676,Indices!$B$2:$B$2676,"") -> IWM
A10: 45664.587 | B10: AIR | C10: on 1/7/25, 4:05 PM After Market Eastern Standard Time | D10: =_xlfn.XLOOKUP(B10,Indices!$A$2:$A$2676,Indices!$B$2:$B$2676,"") -> IWM
A11: 45664.587 | B11: KRUS | C11: on 1/7/25, 4:05 PM After Market Eastern Standard Time | D11: =_xlfn.XLOOKUP(B11,Indices!$A$2:$A$2676,Indices!$B$2:$B$2676,"") -> IWM
A12: 45664.588 | B12: SLP | C12: on 1/7/25, 4:06 PM After Market Eastern Standard Time | D12: =_xlfn.XLOOKUP(B12,Indices!$A$2:$A$2676,Indices!$B$2:$B$2676,"") -> IWM
A13: 45664.594 | B13: AZZ | C13: on 1/7/25, 4:15 PM After Market Eastern Standard Time | D13: =_xlfn.XLOOKUP(B13,Indices!$A$2:$A$2676,Indices!$B$2:$B$2676,"") -> IWM
... A1924: 45706.594 | B1924: ESI | C1924: on 2/18/25, 4:15 PM After Market Eastern Standard Time | D1924: =_xlfn.XLOOKUP(B1924,Indices!$A$2:$A$2676,Indices!$B$2:$B$2676,"")
A1925: 45706.596 | B1925: TRUE | C1925: on 2/18/25, 4:18 PM After Market Eastern Standard Time | D1925: =_xlfn.XLOOKUP(B1925,Indices!$A$2:$A$2676,Indices!$B$2:$B$2676,"")
A1926: 45706.597 | B1926: CE | C1926: on 2/18/25, 4:20 PM After Market Eastern Standard Time | D1926: =_xlfn.XLOOKUP(B1926,Indices!$A$2:$A$2676,Indices!$B$2:$B$2676,"") -> SP500
A1927: 45706.599 | B1927: OXY | C1927: on 2/18/25, 4:22 PM After Market Eastern Standard Time | D1927: =_xlfn.XLOOKUP(B1927,Indices!$A$2:$A$2676,Indices!$B$2:$B$2676,"") -> SP500
A1928: 45706.599 | B1928: STHO | C1928: on 2/18/25, 4:22 PM After Market Eastern Standard Time | D1928: =_xlfn.XLOOKUP(B1928,Indices!$A$2:$A$2676,Indices!$B$2:$B$2676,"")
A1929: 45706.599 | B1929: MTDR | C1929: on 2/18/25, 4:23 PM After Market Eastern Standard Time | D1929: =_xlfn.XLOOKUP(B1929,Indices!$A$2:$A$2676,Indices!$B$2:$B$2676,"") -> S&P Mid
A1930: 45706.601 | B1930: SEVN | C1930: on 2/18/25, 4:25 PM After Market Eastern Standard Time | D1930: =_xlfn.XLOOKUP(B1930,Indices!$A$2:$A$2676,Indices!$B$2:$B$2676,"")
A1931: 45706.604 | B1931: CHCT | C1931: on 2/18/25, 4:30 PM After Market Eastern Standard Time | D1931: =_xlfn.XLOOKUP(B1931,Indices!$A$2:$A$2676,Indices!$B$2:$B$2676,"") -> IWM
A1932: 45706.604 | B1932: EQT | C1932: on 2/18/25, 4:30 PM After Market Eastern Standard Time | D1932: =_xlfn.XLOOKUP(B1932,Indices!$A$2:$A$2676,Indices!$B$2:$B$2676,"") -> SP500
A1933: 45706.604 | B1933: UIS | C1933: on 2/18/25, 4:30 PM After Market Eastern Standard Time | D1933: =_xlfn.XLOOKUP(B1933,Indices!$A$2:$A$2676,Indices!$B$2:$B$2676,"") -> IWM
A1934: 45706.604 | B1934: CSR | C1934: on 2/18/25, 4:30 PM After Market Eastern Standard Time | D1934: =_xlfn.XLOOKUP(B1934,Indices!$A$2:$A$2676,Indices!$B$2:$B$2676,"") -> IWM
A1935: 45706.604 | B1935: SON | C1935: on 2/18/25, 4:30 PM After Market Eastern Standard Time | D1935: =_xlfn.XLOOKUP(B1935,Indices!$A$2:$A$2676,Indices!$B$2:$B$2676,"") -> S&P Mid
A1936: 45706.604 | B1936: TOL | C1936: on 2/18/25, 4:30 PM After Market Eastern Standard Time | D1936: =_xlfn.XLOOKUP(B1936,Indices!$A$2:$A$2676,Indices!$B$2:$B$2676,"") -> S&P Mid
A1937: 45706.609 | B1937: XP | C1937: on 2/18/25, 4:37 PM After Market Eastern Standard Time | D1937: =_xlfn.XLOOKUP(B1937,Indices!$A$2:$A$2676,Indices!$B$2:$B$2676,"")
... A2791: 45714.596 | B2791: KW | C2791: on 2/26/25, 4:18 PM After Market Eastern Standard Time | D2791: =_xlfn.XLOOKUP(B2791,Indices!$A$2:$A$2676,Indices!$B$2:$B$2676,"") -> IWM
A2792: 45714.597 | B2792: FE | C2792: on 2/26/25, 4:20 PM After Market Eastern Standard Time | D2792: =_xlfn.XLOOKUP(B2792,Indices!$A$2:$A$2676,Indices!$B$2:$B$2676,"") -> SP500 | E2792: =_xlfn.XLOOKUP(B2792,'2025-Q1'!$A$402:$A$448,'2025-Q1'!$A$402:$A$448,"avail") -> avail | F2792: =_xlfn.XLOOKUP(B2792,'[2]!! -- Stock Universe 12.11.24'!$C$2:$C$1621,'[2]!! -- Stock Universe 12.11.24'!$E$2:$E$1621,"")
A2793: 45714.597 | B2793: NVDA | C2793: on 2/26/25, 4:20 PM After Market Eastern Standard Time | D2793: =_xlfn.XLOOKUP(B2793,Indices!$A$2:$A$2676,Indices!$B$2:$B$2676,"") -> SP500 | E2793: =_xlfn.XLOOKUP(B2793,'2025-Q1'!$A$402:$A$448,'2025-Q1'!$A$402:$A$448,"avail") -> avail | F2793: =_xlfn.XLOOKUP(B2793,'[2]!! -- Stock Universe 12.11.24'!$C$2:$C$1621,'[2]!! -- Stock Universe 12.11.24'!$E$2:$E$1621,"") -> Technology
A2794: 45714.597 | B2794: SVC | C2794: on 2/26/25, 4:20 PM After Market Eastern Standard Time | D2794: =_xlfn.XLOOKUP(B2794,Indices!$A$2:$A$2676,Indices!$B$2:$B$2676,"") -> IWM | E2794: =_xlfn.XLOOKUP(B2794,'2025-Q1'!$A$402:$A$448,'2025-Q1'!$A$402:$A$448,"avail") -> avail | F2794: =_xlfn.XLOOKUP(B2794,'[2]!! -- Stock Universe 12.11.24'!$C$2:$C$1621,'[2]!! -- Stock Universe 12.11.24'!$E$2:$E$1621,"")
A2795: 45714.597 | B2795: AIN | C2795: on 2/26/25, 4:20 PM After Market Eastern Standard Time | D2795: =_xlfn.XLOOKUP(B2795,Indices!$A$2:$A$2676,Indices!$B$2:$B$2676,"") -> IWM | E2795: =_xlfn.XLOOKUP(B2795,'2025-Q1'!$A$402:$A$448,'2025-Q1'!$A$402:$A$448,"avail") -> avail | F2795: =_xlfn.XLOOKUP(B2795,'[2]!! -- Stock Universe 12.11.24'!$C$2:$C$1621,'[2]!! -- Stock Universe 12.11.24'!$E$2:$E$1621,"")
A2796: 45714.597 | B2796: HG | C2796: on 2/26/25, 4:20 PM After Market Eastern Standard Time | D2796: =_xlfn.XLOOKUP(B2796,Indices!$A$2:$A$2676,Indices!$B$2:$B$2676,"") -> IWM | E2796: =_xlfn.XLOOKUP(B2796,'2025-Q1'!$A$402:$A$448,'2025-Q1'!$A$402:$A$448,"avail") -> avail | F2796: =_xlfn.XLOOKUP(B2796,'[2]!! -- Stock Universe 12.11.24'!$C$2:$C$1621,'[2]!! -- Stock Universe 12.11.24'!$E$2:$E$1621,"")
A2797: 45714.599 | B2797: APA | C2797: on 2/26/25, 4:22 PM After Market Eastern Standard Time | D2797: =_xlfn.XLOOKUP(B2797,Indices!$A$2:$A$2676,Indices!$B$2:$B$2676,"") -> SP500 | E2797: =_xlfn.XLOOKUP(B2797,'2025-Q1'!$A$402:$A$448,'2025-Q1'!$A$402:$A$448,"avail") -> avail | F2797: =_xlfn.XLOOKUP(B2797,'[2]!! -- Stock Universe 12.11.24'!$C$2:$C$1621,'[2]!! -- Stock Universe 12.11.24'!$E$2:$E$1621,"") -> Energy
A2798: 45714.599 | B2798: CRGY | C2798: on 2/26/25, 4:23 PM After Market Eastern Standard Time | D2798: =_xlfn.XLOOKUP(B2798,Indices!$A$2:$A$2676,Indices!$B$2:$B$2676,"") -> IWM | E2798: =_xlfn.XLOOKUP(B2798,'2025-Q1'!$A$402:$A$448,'2025-Q1'!$A$402:$A$448,"avail") -> avail | F2798: =_xlfn.XLOOKUP(B2798,'[2]!! -- Stock Universe 12.11.24'!$C$2:$C$1621,'[2]!! -- Stock Universe 12.11.24'!$E$2:$E$1621,"") -> Energy
A2799: 45714.601 | B2799: LSF | C2799: on 2/26/25, 4:25 PM After Market Eastern Standard Time | D2799: =_xlfn.XLOOKUP(B2799,Indices!$A$2:$A$2676,Indices!$B$2:$B$2676,"") | E2799: =_xlfn.XLOOKUP(B2799,'2025-Q1'!$A$402:$A$448,'2025-Q1'!$A$402:$A$448,"avail") -> avail | F2799: =_xlfn.XLOOKUP(B2799,'[2]!! -- Stock Universe 12.11.24'!$C$2:$C$1621,'[2]!! -- Stock Universe 12.11.24'!$E$2:$E$1621,"")
A2800: 45714.601 | B2800: ARIS | C2800: on 2/26/25, 4:26 PM After Market Eastern Standard Time | D2800: =_xlfn.XLOOKUP(B2800,Indices!$A$2:$A$2676,Indices!$B$2:$B$2676,"") -> IWM | E2800: =_xlfn.XLOOKUP(B2800,'2025-Q1'!$A$402:$A$448,'2025-Q1'!$A$402:$A$448,"avail") -> avail | F2800: =_xlfn.XLOOKUP(B2800,'[2]!! -- Stock Universe 12.11.24'!$C$2:$C$1621,'[2]!! -- Stock Universe 12.11.24'!$E$2:$E$1621,"")
A2801: 45714.604 | B2801: AMED | C2801: on 2/26/25, 4:30 PM After Market Eastern Standard Time | D2801: =_xlfn.XLOOKUP(B2801,Indices!$A$2:$A$2676,Indices!$B$2:$B$2676,"") -> S&P Mid | E2801: =_xlfn.XLOOKUP(B2801,'2025-Q1'!$A$402:$A$448,'2025-Q1'!$A$402:$A$448,"avail") -> avail | F2801: =_xlfn.XLOOKUP(B2801,'[2]!! -- Stock Universe 12.11.24'!$C$2:$C$1621,'[2]!! -- Stock Universe 12.11.24'!$E$2:$E$1621,"")
A2802: 45714.604 | B2802: MEG | C2802: on 2/26/25, 4:30 PM After Market Eastern Standard Time | D2802: =_xlfn.XLOOKUP(B2802,Indices!$A$2:$A$2676,Indices!$B$2:$B$2676,"") -> IWM | E2802: =_xlfn.XLOOKUP(B2802,'2025-Q1'!$A$402:$A$448,'2025-Q1'!$A$402:$A$448,"avail") -> avail | F2802: =_xlfn.XLOOKUP(B2802,'[2]!! -- Stock Universe 12.11.24'!$C$2:$C$1621,'[2]!! -- Stock Universe 12.11.24'!$E$2:$E$1621,"") -> Industrials
A2803: 45714.604 | B2803: UMH | C2803: on 2/26/25, 4:30 PM After Market Eastern Standard Time | D2803: =_xlfn.XLOOKUP(B2803,Indices!$A$2:$A$2676,Indices!$B$2:$B$2676,"") -> IWM | E2803: =_xlfn.XLOOKUP(B2803,'2025-Q1'!$A$402:$A$448,'2025-Q1'!$A$402:$A$448,"avail") -> avail | F2803: =_xlfn.XLOOKUP(B2803,'[2]!! -- Stock Universe 12.11.24'!$C$2:$C$1621,'[2]!! -- Stock Universe 12.11.24'!$E$2:$E$1621,"")
... A4015: 45729.625 | B4015: HEAR | C4015: on 3/13/25 After Market Eastern Standard Time | D4015: =_xlfn.XLOOKUP(B4015,Indices!$A$2:$A$2676,Indices!$B$2:$B$2676,"") -> IWM | E4015: =_xlfn.XLOOKUP(B4015,'2025-Q1'!$A$402:$A$448,'2025-Q1'!$A$402:$A$448,"avail") -> avail | F4015: =_xlfn.XLOOKUP(B4015,'[2]!! -- Stock Universe 12.11.24'!$C$2:$C$1621,'[2]!! -- Stock Universe 12.11.24'!$E$2:$E$1621,"")
A4016: 45729.625 | B4016: SKLZ | C4016: on 3/13/25 After Market Eastern Standard Time | E4016: =_xlfn.XLOOKUP(B4016,'2025-Q1'!$A$402:$A$448,'2025-Q1'!$A$402:$A$448,"avail") -> avail | F4016: =_xlfn.XLOOKUP(B4016,'[2]!! -- Stock Universe 12.11.24'!$C$2:$C$1621,'[2]!! -- Stock Universe 12.11.24'!$E$2:$E$1621,"")
A4017: 45729.625 | B4017: EBR | C4017: on 3/13/25 After Market Eastern Standard Time | E4017: =_xlfn.XLOOKUP(B4017,'2025-Q1'!$A$402:$A$448,'2025-Q1'!$A$402:$A$448,"avail") -> avail | F4017: =_xlfn.XLOOKUP(B4017,'[2]!! -- Stock Universe 12.11.24'!$C$2:$C$1621,'[2]!! -- Stock Universe 12.11.24'!$E$2:$E$1621,"")
A4018: 45729.625 | B4018: TTAN | C4018: on 3/13/25 After Market Eastern Standard Time | E4018: =_xlfn.XLOOKUP(B4018,'2025-Q1'!$A$402:$A$448,'2025-Q1'!$A$402:$A$448,"avail") -> avail | F4018: =_xlfn.XLOOKUP(B4018,'[2]!! -- Stock Universe 12.11.24'!$C$2:$C$1621,'[2]!! -- Stock Universe 12.11.24'!$E$2:$E$1621,"")
A4019: 45729.625 | B4019: ZSPC | C4019: on 3/13/25 After Market Eastern Standard Time | E4019: =_xlfn.XLOOKUP(B4019,'2025-Q1'!$A$402:$A$448,'2025-Q1'!$A$402:$A$448,"avail") -> avail | F4019: =_xlfn.XLOOKUP(B4019,'[2]!! -- Stock Universe 12.11.24'!$C$2:$C$1621,'[2]!! -- Stock Universe 12.11.24'!$E$2:$E$1621,"") -> Consumer Defensive
A4020: 45729.625 | B4020: HGBL | C4020: on 3/13/25 After Market Eastern Standard Time | E4020: =_xlfn.XLOOKUP(B4020,'2025-Q1'!$A$402:$A$448,'2025-Q1'!$A$402:$A$448,"avail") -> avail | F4020: =_xlfn.XLOOKUP(B4020,'[2]!! -- Stock Universe 12.11.24'!$C$2:$C$1621,'[2]!! -- Stock Universe 12.11.24'!$E$2:$E$1621,"")
A4021: 45729.625 | B4021: CTGO | C4021: on 3/13/25 After Market Eastern Standard Time | E4021: =_xlfn.XLOOKUP(B4021,'2025-Q1'!$A$402:$A$448,'2025-Q1'!$A$402:$A$448,"avail") -> avail | F4021: =_xlfn.XLOOKUP(B4021,'[2]!! -- Stock Universe 12.11.24'!$C$2:$C$1621,'[2]!! -- Stock Universe 12.11.24'!$E$2:$E$1621,"")
A4022: 45729.625 | B4022: SDST | C4022: on 3/13/25 After Market Eastern Standard Time | E4022: =_xlfn.XLOOKUP(B4022,'2025-Q1'!$A$402:$A$448,'2025-Q1'!$A$402:$A$448,"avail") -> avail | F4022: =_xlfn.XLOOKUP(B4022,'[2]!! -- Stock Universe 12.11.24'!$C$2:$C$1621,'[2]!! -- Stock Universe 12.11.24'!$E$2:$E$1621,"")
A4023: 45729.625 | B4023: LFT | C4023: on 3/13/25 After Market Eastern Standard Time | E4023: =_xlfn.XLOOKUP(B4023,'2025-Q1'!$A$402:$A$448,'2025-Q1'!$A$402:$A$448,"avail") -> avail | F4023: =_xlfn.XLOOKUP(B4023,'[2]!! -- Stock Universe 12.11.24'!$C$2:$C$1621,'[2]!! -- Stock Universe 12.11.24'!$E$2:$E$1621,"")
A4024: 45729.625 | B4024: VERI | C4024: on 3/13/25 After Market Eastern Standard Time | E4024: =_xlfn.XLOOKUP(B4024,'2025-Q1'!$A$402:$A$448,'2025-Q1'!$A$402:$A$448,"avail") -> avail | F4024: =_xlfn.XLOOKUP(B4024,'[2]!! -- Stock Universe 12.11.24'!$C$2:$C$1621,'[2]!! -- Stock Universe 12.11.24'!$E$2:$E$1621,"") -> Technology
A4025: 45729.625 | B4025: AFYA | C4025: on 3/13/25 After Market Eastern Standard Time | E4025: =_xlfn.XLOOKUP(B4025,'2025-Q1'!$A$402:$A$448,'2025-Q1'!$A$402:$A$448,"avail") -> avail | F4025: =_xlfn.XLOOKUP(B4025,'[2]!! -- Stock Universe 12.11.24'!$C$2:$C$1621,'[2]!! -- Stock Universe 12.11.24'!$E$2:$E$1621,"")
A4026: 45729.625 | B4026: KZR | C4026: on 3/13/25 After Market Eastern Standard Time | E4026: =_xlfn.XLOOKUP(B4026,'2025-Q1'!$A$402:$A$448,'2025-Q1'!$A$402:$A$448,"avail") -> avail | F4026: =_xlfn.XLOOKUP(B4026,'[2]!! -- Stock Universe 12.11.24'!$C$2:$C$1621,'[2]!! -- Stock Universe 12.11.24'!$E$2:$E$1621,"")
A4027: 45729.625 | B4027: PLBY | C4027: on 3/13/25 After Market Eastern Standard Time | E4027: =_xlfn.XLOOKUP(B4027,'2025-Q1'!$A$402:$A$448,'2025-Q1'!$A$402:$A$448,"avail") -> avail | F4027: =_xlfn.XLOOKUP(B4027,'[2]!! -- Stock Universe 12.11.24'!$C$2:$C$1621,'[2]!! -- Stock Universe 12.11.24'!$E$2:$E$1621,"") -> Consumer Cyclical
... A4735: 45757.625 | B4735: FRMO | C4735: on 4/10/25 After Market Eastern Standard Time | E4735: =_xlfn.XLOOKUP(B4735,'2025-Q1'!$A$402:$A$448,'2025-Q1'!$A$402:$A$448,"avail") -> avail | F4735: =_xlfn.XLOOKUP(B4735,'[2]!! -- Stock Universe 12.11.24'!$C$2:$C$1621,'[2]!! -- Stock Universe 12.11.24'!$E$2:$E$1621,"")

Sheet Charts

Sheet SPDR Chart
D1: XLP | E1: XLI | F1: XLF | G1: XLV | H1: XLE | I1: XLRE | J1: XLY | K1: XLC | L1: XLK | M1: XLB | N1: XLU | O1: SMH | P1: INS | Q1: IGV
C2: 45667 | D2: =COUNTIFS('2025-Q1'!$E$4:$E$448,'SPDR Chart'!D$1,'2025-Q1'!$F$4:$F$448,'SPDR Chart'!$C2) -> 2 | E2: =COUNTIFS('2025-Q1'!$E$4:$E$448,'SPDR Chart'!E$1,'2025-Q1'!$F$4:$F$448,'SPDR Chart'!$C2) -> 1 | F2: =COUNTIFS('2025-Q1'!$E$4:$E$448,'SPDR Chart'!F$1,'2025-Q1'!$F$4:$F$448,'SPDR Chart'!$C2) -> 0 | G2: =COUNTIFS('2025-Q1'!$E$4:$E$448,'SPDR Chart'!G$1,'2025-Q1'!$F$4:$F$448,'SPDR Chart'!$C2) -> 0 | H2: =COUNTIFS('2025-Q1'!$E$4:$E$448,'SPDR Chart'!H$1,'2025-Q1'!$F$4:$F$448,'SPDR Chart'!$C2) -> 0 | I2: =COUNTIFS('2025-Q1'!$E$4:$E$448,'SPDR Chart'!I$1,'2025-Q1'!$F$4:$F$448,'SPDR Chart'!$C2) -> 0 | J2: =COUNTIFS('2025-Q1'!$E$4:$E$448,'SPDR Chart'!J$1,'2025-Q1'!$F$4:$F$448,'SPDR Chart'!$C2) -> 0 | K2: =COUNTIFS('2025-Q1'!$E$4:$E$448,'SPDR Chart'!K$1,'2025-Q1'!$F$4:$F$448,'SPDR Chart'!$C2) -> 0 | ... Q2: =COUNTIFS('2025-Q1'!$E$4:$E$448,'SPDR Chart'!Q$1,'2025-Q1'!$F$4:$F$448,'SPDR Chart'!$C2) -> 0
C3: 45672 | D3: =COUNTIFS('2025-Q1'!$E$4:$E$448,'SPDR Chart'!D$1,'2025-Q1'!$F$4:$F$448,'SPDR Chart'!$C3) -> 0 | E3: =COUNTIFS('2025-Q1'!$E$4:$E$448,'SPDR Chart'!E$1,'2025-Q1'!$F$4:$F$448,'SPDR Chart'!$C3) -> 0 | F3: =COUNTIFS('2025-Q1'!$E$4:$E$448,'SPDR Chart'!F$1,'2025-Q1'!$F$4:$F$448,'SPDR Chart'!$C3) -> 6 | G3: =COUNTIFS('2025-Q1'!$E$4:$E$448,'SPDR Chart'!G$1,'2025-Q1'!$F$4:$F$448,'SPDR Chart'!$C3) -> 0 | H3: =COUNTIFS('2025-Q1'!$E$4:$E$448,'SPDR Chart'!H$1,'2025-Q1'!$F$4:$F$448,'SPDR Chart'!$C3) -> 0 | I3: =COUNTIFS('2025-Q1'!$E$4:$E$448,'SPDR Chart'!I$1,'2025-Q1'!$F$4:$F$448,'SPDR Chart'!$C3) -> 0 | J3: =COUNTIFS('2025-Q1'!$E$4:$E$448,'SPDR Chart'!J$1,'2025-Q1'!$F$4:$F$448,'SPDR Chart'!$C3) -> 0 | K3: =COUNTIFS('2025-Q1'!$E$4:$E$448,'SPDR Chart'!K$1,'2025-Q1'!$F$4:$F$448,'SPDR Chart'!$C3) -> 0 | ... Q3: =COUNTIFS('2025-Q1'!$E$4:$E$448,'SPDR Chart'!Q$1,'2025-Q1'!$F$4:$F$448,'SPDR Chart'!$C3) -> 0
C4: 45673 | D4: =COUNTIFS('2025-Q1'!$E$4:$E$448,'SPDR Chart'!D$1,'2025-Q1'!$F$4:$F$448,'SPDR Chart'!$C4) -> 0 | E4: =COUNTIFS('2025-Q1'!$E$4:$E$448,'SPDR Chart'!E$1,'2025-Q1'!$F$4:$F$448,'SPDR Chart'!$C4) -> 1 | F4: =COUNTIFS('2025-Q1'!$E$4:$E$448,'SPDR Chart'!F$1,'2025-Q1'!$F$4:$F$448,'SPDR Chart'!$C4) -> 5 | G4: =COUNTIFS('2025-Q1'!$E$4:$E$448,'SPDR Chart'!G$1,'2025-Q1'!$F$4:$F$448,'SPDR Chart'!$C4) -> 0 | H4: =COUNTIFS('2025-Q1'!$E$4:$E$448,'SPDR Chart'!H$1,'2025-Q1'!$F$4:$F$448,'SPDR Chart'!$C4) -> 0 | I4: =COUNTIFS('2025-Q1'!$E$4:$E$448,'SPDR Chart'!I$1,'2025-Q1'!$F$4:$F$448,'SPDR Chart'!$C4) -> 0 | J4: =COUNTIFS('2025-Q1'!$E$4:$E$448,'SPDR Chart'!J$1,'2025-Q1'!$F$4:$F$448,'SPDR Chart'!$C4) -> 0 | K4: =COUNTIFS('2025-Q1'!$E$4:$E$448,'SPDR Chart'!K$1,'2025-Q1'!$F$4:$F$448,'SPDR Chart'!$C4) -> 0 | ... Q4: =COUNTIFS('2025-Q1'!$E$4:$E$448,'SPDR Chart'!Q$1,'2025-Q1'!$F$4:$F$448,'SPDR Chart'!$C4) -> 0
C5: 45674 | D5: =COUNTIFS('2025-Q1'!$E$4:$E$448,'SPDR Chart'!D$1,'2025-Q1'!$F$4:$F$448,'SPDR Chart'!$C5) -> 0 | E5: =COUNTIFS('2025-Q1'!$E$4:$E$448,'SPDR Chart'!E$1,'2025-Q1'!$F$4:$F$448,'SPDR Chart'!$C5) -> 1 | F5: =COUNTIFS('2025-Q1'!$E$4:$E$448,'SPDR Chart'!F$1,'2025-Q1'!$F$4:$F$448,'SPDR Chart'!$C5) -> 5 | G5: =COUNTIFS('2025-Q1'!$E$4:$E$448,'SPDR Chart'!G$1,'2025-Q1'!$F$4:$F$448,'SPDR Chart'!$C5) -> 0 | H5: =COUNTIFS('2025-Q1'!$E$4:$E$448,'SPDR Chart'!H$1,'2025-Q1'!$F$4:$F$448,'SPDR Chart'!$C5) -> 1 | I5: =COUNTIFS('2025-Q1'!$E$4:$E$448,'SPDR Chart'!I$1,'2025-Q1'!$F$4:$F$448,'SPDR Chart'!$C5) -> 0 | J5: =COUNTIFS('2025-Q1'!$E$4:$E$448,'SPDR Chart'!J$1,'2025-Q1'!$F$4:$F$448,'SPDR Chart'!$C5) -> 0 | K5: =COUNTIFS('2025-Q1'!$E$4:$E$448,'SPDR Chart'!K$1,'2025-Q1'!$F$4:$F$448,'SPDR Chart'!$C5) -> 0 | ... Q5: =COUNTIFS('2025-Q1'!$E$4:$E$448,'SPDR Chart'!Q$1,'2025-Q1'!$F$4:$F$448,'SPDR Chart'!$C5) -> 0
C6: 45678 | D6: =COUNTIFS('2025-Q1'!$E$4:$E$448,'SPDR Chart'!D$1,'2025-Q1'!$F$4:$F$448,'SPDR Chart'!$C6) -> 0 | E6: =COUNTIFS('2025-Q1'!$E$4:$E$448,'SPDR Chart'!E$1,'2025-Q1'!$F$4:$F$448,'SPDR Chart'!$C6) -> 2 | F6: =COUNTIFS('2025-Q1'!$E$4:$E$448,'SPDR Chart'!F$1,'2025-Q1'!$F$4:$F$448,'SPDR Chart'!$C6) -> 4 | G6: =COUNTIFS('2025-Q1'!$E$4:$E$448,'SPDR Chart'!G$1,'2025-Q1'!$F$4:$F$448,'SPDR Chart'!$C6) -> 0 | H6: =COUNTIFS('2025-Q1'!$E$4:$E$448,'SPDR Chart'!H$1,'2025-Q1'!$F$4:$F$448,'SPDR Chart'!$C6) -> 0 | I6: =COUNTIFS('2025-Q1'!$E$4:$E$448,'SPDR Chart'!I$1,'2025-Q1'!$F$4:$F$448,'SPDR Chart'!$C6) -> 0 | J6: =COUNTIFS('2025-Q1'!$E$4:$E$448,'SPDR Chart'!J$1,'2025-Q1'!$F$4:$F$448,'SPDR Chart'!$C6) -> 0 | K6: =COUNTIFS('2025-Q1'!$E$4:$E$448,'SPDR Chart'!K$1,'2025-Q1'!$F$4:$F$448,'SPDR Chart'!$C6) -> 1 | ... Q6: =COUNTIFS('2025-Q1'!$E$4:$E$448,'SPDR Chart'!Q$1,'2025-Q1'!$F$4:$F$448,'SPDR Chart'!$C6) -> 0
C7: 45679 | D7: =COUNTIFS('2025-Q1'!$E$4:$E$448,'SPDR Chart'!D$1,'2025-Q1'!$F$4:$F$448,'SPDR Chart'!$C7) -> 1 | E7: =COUNTIFS('2025-Q1'!$E$4:$E$448,'SPDR Chart'!E$1,'2025-Q1'!$F$4:$F$448,'SPDR Chart'!$C7) -> 2 | F7: =COUNTIFS('2025-Q1'!$E$4:$E$448,'SPDR Chart'!F$1,'2025-Q1'!$F$4:$F$448,'SPDR Chart'!$C7) -> 1 | G7: =COUNTIFS('2025-Q1'!$E$4:$E$448,'SPDR Chart'!G$1,'2025-Q1'!$F$4:$F$448,'SPDR Chart'!$C7) -> 2 | H7: =COUNTIFS('2025-Q1'!$E$4:$E$448,'SPDR Chart'!H$1,'2025-Q1'!$F$4:$F$448,'SPDR Chart'!$C7) -> 2 | I7: =COUNTIFS('2025-Q1'!$E$4:$E$448,'SPDR Chart'!I$1,'2025-Q1'!$F$4:$F$448,'SPDR Chart'!$C7) -> 0 | J7: =COUNTIFS('2025-Q1'!$E$4:$E$448,'SPDR Chart'!J$1,'2025-Q1'!$F$4:$F$448,'SPDR Chart'!$C7) -> 0 | K7: =COUNTIFS('2025-Q1'!$E$4:$E$448,'SPDR Chart'!K$1,'2025-Q1'!$F$4:$F$448,'SPDR Chart'!$C7) -> 0 | ... Q7: =COUNTIFS('2025-Q1'!$E$4:$E$448,'SPDR Chart'!Q$1,'2025-Q1'!$F$4:$F$448,'SPDR Chart'!$C7) -> 0
C8: 45680 | D8: =COUNTIFS('2025-Q1'!$E$4:$E$448,'SPDR Chart'!D$1,'2025-Q1'!$F$4:$F$448,'SPDR Chart'!$C8) -> 1 | E8: =COUNTIFS('2025-Q1'!$E$4:$E$448,'SPDR Chart'!E$1,'2025-Q1'!$F$4:$F$448,'SPDR Chart'!$C8) -> 3 | F8: =COUNTIFS('2025-Q1'!$E$4:$E$448,'SPDR Chart'!F$1,'2025-Q1'!$F$4:$F$448,'SPDR Chart'!$C8) -> 1 | G8: =COUNTIFS('2025-Q1'!$E$4:$E$448,'SPDR Chart'!G$1,'2025-Q1'!$F$4:$F$448,'SPDR Chart'!$C8) -> 1 | H8: =COUNTIFS('2025-Q1'!$E$4:$E$448,'SPDR Chart'!H$1,'2025-Q1'!$F$4:$F$448,'SPDR Chart'!$C8) -> 0 | I8: =COUNTIFS('2025-Q1'!$E$4:$E$448,'SPDR Chart'!I$1,'2025-Q1'!$F$4:$F$448,'SPDR Chart'!$C8) -> 0 | J8: =COUNTIFS('2025-Q1'!$E$4:$E$448,'SPDR Chart'!J$1,'2025-Q1'!$F$4:$F$448,'SPDR Chart'!$C8) -> 0 | K8: =COUNTIFS('2025-Q1'!$E$4:$E$448,'SPDR Chart'!K$1,'2025-Q1'!$F$4:$F$448,'SPDR Chart'!$C8) -> 0 | ... Q8: =COUNTIFS('2025-Q1'!$E$4:$E$448,'SPDR Chart'!Q$1,'2025-Q1'!$F$4:$F$448,'SPDR Chart'!$C8) -> 0
C9: 45681 | D9: =COUNTIFS('2025-Q1'!$E$4:$E$448,'SPDR Chart'!D$1,'2025-Q1'!$F$4:$F$448,'SPDR Chart'!$C9) -> 0 | E9: =COUNTIFS('2025-Q1'!$E$4:$E$448,'SPDR Chart'!E$1,'2025-Q1'!$F$4:$F$448,'SPDR Chart'!$C9) -> 0 | F9: =COUNTIFS('2025-Q1'!$E$4:$E$448,'SPDR Chart'!F$1,'2025-Q1'!$F$4:$F$448,'SPDR Chart'!$C9) -> 1 | G9: =COUNTIFS('2025-Q1'!$E$4:$E$448,'SPDR Chart'!G$1,'2025-Q1'!$F$4:$F$448,'SPDR Chart'!$C9) -> 1 | H9: =COUNTIFS('2025-Q1'!$E$4:$E$448,'SPDR Chart'!H$1,'2025-Q1'!$F$4:$F$448,'SPDR Chart'!$C9) -> 0 | I9: =COUNTIFS('2025-Q1'!$E$4:$E$448,'SPDR Chart'!I$1,'2025-Q1'!$F$4:$F$448,'SPDR Chart'!$C9) -> 0 | J9: =COUNTIFS('2025-Q1'!$E$4:$E$448,'SPDR Chart'!J$1,'2025-Q1'!$F$4:$F$448,'SPDR Chart'!$C9) -> 0 | K9: =COUNTIFS('2025-Q1'!$E$4:$E$448,'SPDR Chart'!K$1,'2025-Q1'!$F$4:$F$448,'SPDR Chart'!$C9) -> 1 | ... Q9: =COUNTIFS('2025-Q1'!$E$4:$E$448,'SPDR Chart'!Q$1,'2025-Q1'!$F$4:$F$448,'SPDR Chart'!$C9) -> 0
C10: 45684 | D10: =COUNTIFS('2025-Q1'!$E$4:$E$448,'SPDR Chart'!D$1,'2025-Q1'!$F$4:$F$448,'SPDR Chart'!$C10) -> 0 | E10: =COUNTIFS('2025-Q1'!$E$4:$E$448,'SPDR Chart'!E$1,'2025-Q1'!$F$4:$F$448,'SPDR Chart'!$C10) -> 0 | F10: =COUNTIFS('2025-Q1'!$E$4:$E$448,'SPDR Chart'!F$1,'2025-Q1'!$F$4:$F$448,'SPDR Chart'!$C10) -> 0 | G10: =COUNTIFS('2025-Q1'!$E$4:$E$448,'SPDR Chart'!G$1,'2025-Q1'!$F$4:$F$448,'SPDR Chart'!$C10) -> 0 | H10: =COUNTIFS('2025-Q1'!$E$4:$E$448,'SPDR Chart'!H$1,'2025-Q1'!$F$4:$F$448,'SPDR Chart'!$C10) -> 0 | I10: =COUNTIFS('2025-Q1'!$E$4:$E$448,'SPDR Chart'!I$1,'2025-Q1'!$F$4:$F$448,'SPDR Chart'!$C10) -> 0 | J10: =COUNTIFS('2025-Q1'!$E$4:$E$448,'SPDR Chart'!J$1,'2025-Q1'!$F$4:$F$448,'SPDR Chart'!$C10) -> 0 | K10: =COUNTIFS('2025-Q1'!$E$4:$E$448,'SPDR Chart'!K$1,'2025-Q1'!$F$4:$F$448,'SPDR Chart'!$C10) -> 1 | ... Q10: =COUNTIFS('2025-Q1'!$E$4:$E$448,'SPDR Chart'!Q$1,'2025-Q1'!$F$4:$F$448,'SPDR Chart'!$C10) -> 0
C11: 45685 | D11: =COUNTIFS('2025-Q1'!$E$4:$E$448,'SPDR Chart'!D$1,'2025-Q1'!$F$4:$F$448,'SPDR Chart'!$C11) -> 2 | E11: =COUNTIFS('2025-Q1'!$E$4:$E$448,'SPDR Chart'!E$1,'2025-Q1'!$F$4:$F$448,'SPDR Chart'!$C11) -> 4 | F11: =COUNTIFS('2025-Q1'!$E$4:$E$448,'SPDR Chart'!F$1,'2025-Q1'!$F$4:$F$448,'SPDR Chart'!$C11) -> 2 | G11: =COUNTIFS('2025-Q1'!$E$4:$E$448,'SPDR Chart'!G$1,'2025-Q1'!$F$4:$F$448,'SPDR Chart'!$C11) -> 1 | H11: =COUNTIFS('2025-Q1'!$E$4:$E$448,'SPDR Chart'!H$1,'2025-Q1'!$F$4:$F$448,'SPDR Chart'!$C11) -> 0 | I11: =COUNTIFS('2025-Q1'!$E$4:$E$448,'SPDR Chart'!I$1,'2025-Q1'!$F$4:$F$448,'SPDR Chart'!$C11) -> 0 | J11: =COUNTIFS('2025-Q1'!$E$4:$E$448,'SPDR Chart'!J$1,'2025-Q1'!$F$4:$F$448,'SPDR Chart'!$C11) -> 3 | K11: =COUNTIFS('2025-Q1'!$E$4:$E$448,'SPDR Chart'!K$1,'2025-Q1'!$F$4:$F$448,'SPDR Chart'!$C11) -> 0 | ... Q11: =COUNTIFS('2025-Q1'!$E$4:$E$448,'SPDR Chart'!Q$1,'2025-Q1'!$F$4:$F$448,'SPDR Chart'!$C11) -> 0
C12: 45686 | D12: =COUNTIFS('2025-Q1'!$E$4:$E$448,'SPDR Chart'!D$1,'2025-Q1'!$F$4:$F$448,'SPDR Chart'!$C12) -> 0 | E12: =COUNTIFS('2025-Q1'!$E$4:$E$448,'SPDR Chart'!E$1,'2025-Q1'!$F$4:$F$448,'SPDR Chart'!$C12) -> 7 | F12: =COUNTIFS('2025-Q1'!$E$4:$E$448,'SPDR Chart'!F$1,'2025-Q1'!$F$4:$F$448,'SPDR Chart'!$C12) -> 3 | G12: =COUNTIFS('2025-Q1'!$E$4:$E$448,'SPDR Chart'!G$1,'2025-Q1'!$F$4:$F$448,'SPDR Chart'!$C12) -> 1 | H12: =COUNTIFS('2025-Q1'!$E$4:$E$448,'SPDR Chart'!H$1,'2025-Q1'!$F$4:$F$448,'SPDR Chart'!$C12) -> 0 | I12: =COUNTIFS('2025-Q1'!$E$4:$E$448,'SPDR Chart'!I$1,'2025-Q1'!$F$4:$F$448,'SPDR Chart'!$C12) -> 0 | J12: =COUNTIFS('2025-Q1'!$E$4:$E$448,'SPDR Chart'!J$1,'2025-Q1'!$F$4:$F$448,'SPDR Chart'!$C12) -> 2 | K12: =COUNTIFS('2025-Q1'!$E$4:$E$448,'SPDR Chart'!K$1,'2025-Q1'!$F$4:$F$448,'SPDR Chart'!$C12) -> 2 | ... Q12: =COUNTIFS('2025-Q1'!$E$4:$E$448,'SPDR Chart'!Q$1,'2025-Q1'!$F$4:$F$448,'SPDR Chart'!$C12) -> 1
C13: 45687 | D13: =COUNTIFS('2025-Q1'!$E$4:$E$448,'SPDR Chart'!D$1,'2025-Q1'!$F$4:$F$448,'SPDR Chart'!$C13) -> 1 | E13: =COUNTIFS('2025-Q1'!$E$4:$E$448,'SPDR Chart'!E$1,'2025-Q1'!$F$4:$F$448,'SPDR Chart'!$C13) -> 8 | F13: =COUNTIFS('2025-Q1'!$E$4:$E$448,'SPDR Chart'!F$1,'2025-Q1'!$F$4:$F$448,'SPDR Chart'!$C13) -> 3 | G13: =COUNTIFS('2025-Q1'!$E$4:$E$448,'SPDR Chart'!G$1,'2025-Q1'!$F$4:$F$448,'SPDR Chart'!$C13) -> 4 | H13: =COUNTIFS('2025-Q1'!$E$4:$E$448,'SPDR Chart'!H$1,'2025-Q1'!$F$4:$F$448,'SPDR Chart'!$C13) -> 2 | I13: =COUNTIFS('2025-Q1'!$E$4:$E$448,'SPDR Chart'!I$1,'2025-Q1'!$F$4:$F$448,'SPDR Chart'!$C13) -> 0 | J13: =COUNTIFS('2025-Q1'!$E$4:$E$448,'SPDR Chart'!J$1,'2025-Q1'!$F$4:$F$448,'SPDR Chart'!$C13) -> 2 | K13: =COUNTIFS('2025-Q1'!$E$4:$E$448,'SPDR Chart'!K$1,'2025-Q1'!$F$4:$F$448,'SPDR Chart'!$C13) -> 1 | ... Q13: =COUNTIFS('2025-Q1'!$E$4:$E$448,'SPDR Chart'!Q$1,'2025-Q1'!$F$4:$F$448,'SPDR Chart'!$C13) -> 5
... C47: 45757 | D47: =COUNTIFS('2025-Q1'!$E$4:$E$448,'SPDR Chart'!D$1,'2025-Q1'!$F$4:$F$448,'SPDR Chart'!$C47) -> 0 | E47: =COUNTIFS('2025-Q1'!$E$4:$E$448,'SPDR Chart'!E$1,'2025-Q1'!$F$4:$F$448,'SPDR Chart'!$C47) -> 0 | F47: =COUNTIFS('2025-Q1'!$E$4:$E$448,'SPDR Chart'!F$1,'2025-Q1'!$F$4:$F$448,'SPDR Chart'!$C47) -> 0 | G47: =COUNTIFS('2025-Q1'!$E$4:$E$448,'SPDR Chart'!G$1,'2025-Q1'!$F$4:$F$448,'SPDR Chart'!$C47) -> 0 | H47: =COUNTIFS('2025-Q1'!$E$4:$E$448,'SPDR Chart'!H$1,'2025-Q1'!$F$4:$F$448,'SPDR Chart'!$C47) -> 0 | I47: =COUNTIFS('2025-Q1'!$E$4:$E$448,'SPDR Chart'!I$1,'2025-Q1'!$F$4:$F$448,'SPDR Chart'!$C47) -> 0 | J47: =COUNTIFS('2025-Q1'!$E$4:$E$448,'SPDR Chart'!J$1,'2025-Q1'!$F$4:$F$448,'SPDR Chart'!$C47) -> 0 | K47: =COUNTIFS('2025-Q1'!$E$4:$E$448,'SPDR Chart'!K$1,'2025-Q1'!$F$4:$F$448,'SPDR Chart'!$C47) -> 0 | ... Q47: =COUNTIFS('2025-Q1'!$E$4:$E$448,'SPDR Chart'!Q$1,'2025-Q1'!$F$4:$F$448,'SPDR Chart'!$C47) -> 0

Sheet Rev Curves
AB43: .
A441: Up Trends
A442: Sector | B442: # | C442: % Gap Up | D442: Expectancy
A443: XLK | B443: =_xlfn.XLOOKUP('Rev Curves'!$A443,'Stats Roll Up'!$B$4:$B$20,'Stats Roll Up'!$F$4:$F$20) -> 10 | C443: =_xlfn.XLOOKUP('Rev Curves'!$A443,'Stats Roll Up'!$B$4:$B$20,'Stats Roll Up'!$G$4:$G$20) -> 0.7 | D443: =_xlfn.XLOOKUP(A443,Expectancy!$P$3:$P$19,Expectancy!$Q$3:$Q$19) -> 0.35290545
A444: XLC | B444: =_xlfn.XLOOKUP('Rev Curves'!A444,'Stats Roll Up'!$B$4:$B$20,'Stats Roll Up'!$F$4:$F$20) -> 6 | C444: =_xlfn.XLOOKUP('Rev Curves'!$A444,'Stats Roll Up'!$B$4:$B$20,'Stats Roll Up'!$G$4:$G$20) -> 0.83333333 | D444: =_xlfn.XLOOKUP(A444,Expectancy!$P$3:$P$19,Expectancy!$Q$3:$Q$19) -> 0.43526477
A445: IGV | B445: =_xlfn.XLOOKUP('Rev Curves'!A445,'Stats Roll Up'!$B$4:$B$20,'Stats Roll Up'!$F$4:$F$20) -> 10 | C445: =_xlfn.XLOOKUP('Rev Curves'!$A445,'Stats Roll Up'!$B$4:$B$20,'Stats Roll Up'!$G$4:$G$20) -> 0.7 | D445: =_xlfn.XLOOKUP(A445,Expectancy!$P$3:$P$19,Expectancy!$Q$3:$Q$19) -> 1.0051962
A446: SMH | B446: =_xlfn.XLOOKUP('Rev Curves'!A446,'Stats Roll Up'!$B$4:$B$20,'Stats Roll Up'!$F$4:$F$20) -> 0 | C446: =_xlfn.XLOOKUP('Rev Curves'!$A446,'Stats Roll Up'!$B$4:$B$20,'Stats Roll Up'!$G$4:$G$20) -> 0 | D446: =_xlfn.XLOOKUP(A446,Expectancy!$P$3:$P$19,Expectancy!$Q$3:$Q$19) -> 0
A447: XLI | B447: =_xlfn.XLOOKUP('Rev Curves'!A447,'Stats Roll Up'!$B$4:$B$20,'Stats Roll Up'!$F$4:$F$20) -> 15 | C447: =_xlfn.XLOOKUP('Rev Curves'!$A447,'Stats Roll Up'!$B$4:$B$20,'Stats Roll Up'!$G$4:$G$20) -> 0.6 | D447: =_xlfn.XLOOKUP(A447,Expectancy!$P$3:$P$19,Expectancy!$Q$3:$Q$19) -> -0.041762477
A448: XLY | B448: =_xlfn.XLOOKUP('Rev Curves'!A448,'Stats Roll Up'!$B$4:$B$20,'Stats Roll Up'!$F$4:$F$20) -> 9 | C448: =_xlfn.XLOOKUP('Rev Curves'!$A448,'Stats Roll Up'!$B$4:$B$20,'Stats Roll Up'!$G$4:$G$20) -> 0.33333333 | D448: =_xlfn.XLOOKUP(A448,Expectancy!$P$3:$P$19,Expectancy!$Q$3:$Q$19) -> 0.094642214
A449: XLP | B449: =_xlfn.XLOOKUP('Rev Curves'!A449,'Stats Roll Up'!$B$4:$B$20,'Stats Roll Up'!$F$4:$F$20) -> 4 | C449: =_xlfn.XLOOKUP('Rev Curves'!$A449,'Stats Roll Up'!$B$4:$B$20,'Stats Roll Up'!$G$4:$G$20) -> 0.5 | D449: =_xlfn.XLOOKUP(A449,Expectancy!$P$3:$P$19,Expectancy!$Q$3:$Q$19) -> 0.26476024
A450: XLF | B450: =_xlfn.XLOOKUP('Rev Curves'!A450,'Stats Roll Up'!$B$4:$B$20,'Stats Roll Up'!$F$4:$F$20) -> 28 | C450: =_xlfn.XLOOKUP('Rev Curves'!$A450,'Stats Roll Up'!$B$4:$B$20,'Stats Roll Up'!$G$4:$G$20) -> 0.5 | D450: =_xlfn.XLOOKUP(A450,Expectancy!$P$3:$P$19,Expectancy!$Q$3:$Q$19) -> -0.079483353
A451: XLV | B451: =_xlfn.XLOOKUP('Rev Curves'!A451,'Stats Roll Up'!$B$4:$B$20,'Stats Roll Up'!$F$4:$F$20) -> 13 | C451: =_xlfn.XLOOKUP('Rev Curves'!$A451,'Stats Roll Up'!$B$4:$B$20,'Stats Roll Up'!$G$4:$G$20) -> 0.23076923 | D451: =_xlfn.XLOOKUP(A451,Expectancy!$P$3:$P$19,Expectancy!$Q$3:$Q$19) -> -0.45514117
A452: XLB | B452: =_xlfn.XLOOKUP('Rev Curves'!A452,'Stats Roll Up'!$B$4:$B$20,'Stats Roll Up'!$F$4:$F$20) -> 2 | C452: =_xlfn.XLOOKUP('Rev Curves'!$A452,'Stats Roll Up'!$B$4:$B$20,'Stats Roll Up'!$G$4:$G$20) -> 0 | D452: =_xlfn.XLOOKUP(A452,Expectancy!$P$3:$P$19,Expectancy!$Q$3:$Q$19) -> -0.11318819
A453: ALL | B453: =_xlfn.XLOOKUP('Rev Curves'!A453,'Stats Roll Up'!$B$4:$B$20,'Stats Roll Up'!$F$4:$F$20) -> 101 | C453: =_xlfn.XLOOKUP('Rev Curves'!$A453,'Stats Roll Up'!$B$4:$B$20,'Stats Roll Up'!$G$4:$G$20) -> 0.52475248 | D453: =_xlfn.XLOOKUP(A453,Expectancy!$P$3:$P$19,Expectancy!$Q$3:$Q$19) -> 0.099102767
A469: Down Trends
A470: Sector | B470: # | C470: % Gap Dn | D470: Expectancy
A471: XLK | B471: =_xlfn.XLOOKUP('Rev Curves'!$A471,'Stats Roll Up'!$B$4:$B$20,'Stats Roll Up'!$J$4:$J$20) -> 7 | C471: =_xlfn.XLOOKUP('Rev Curves'!$A471,'Stats Roll Up'!$B$4:$B$20,'Stats Roll Up'!$Y$4:$Y$20) -> 0.57142857 | D471: =_xlfn.XLOOKUP(A471,Expectancy!$P$3:$P$19,Expectancy!$R$3:$R$19) -> 1.1895734
A472: XLC | B472: =_xlfn.XLOOKUP('Rev Curves'!A472,'Stats Roll Up'!$B$4:$B$20,'Stats Roll Up'!$J$4:$J$20) -> 5 | C472: =_xlfn.XLOOKUP('Rev Curves'!$A472,'Stats Roll Up'!$B$4:$B$20,'Stats Roll Up'!$Y$4:$Y$20) -> 0.4 | D472: =_xlfn.XLOOKUP(A472,Expectancy!$P$3:$P$19,Expectancy!$R$3:$R$19) -> -0.040038914
A473: IGV | B473: =_xlfn.XLOOKUP('Rev Curves'!A473,'Stats Roll Up'!$B$4:$B$20,'Stats Roll Up'!$J$4:$J$20) -> 11 | C473: =_xlfn.XLOOKUP('Rev Curves'!$A473,'Stats Roll Up'!$B$4:$B$20,'Stats Roll Up'!$Y$4:$Y$20) -> 0.72727273 | D473: =_xlfn.XLOOKUP(A473,Expectancy!$P$3:$P$19,Expectancy!$R$3:$R$19) -> 0.78642334
A474: SMH | B474: =_xlfn.XLOOKUP('Rev Curves'!A474,'Stats Roll Up'!$B$4:$B$20,'Stats Roll Up'!$J$4:$J$20) -> 6 | C474: =_xlfn.XLOOKUP('Rev Curves'!$A474,'Stats Roll Up'!$B$4:$B$20,'Stats Roll Up'!$Y$4:$Y$20) -> 0.66666667 | D474: =_xlfn.XLOOKUP(A474,Expectancy!$P$3:$P$19,Expectancy!$R$3:$R$19) -> 0.69153964
A475: XLI | B475: =_xlfn.XLOOKUP('Rev Curves'!A475,'Stats Roll Up'!$B$4:$B$20,'Stats Roll Up'!$J$4:$J$20) -> 15 | C475: =_xlfn.XLOOKUP('Rev Curves'!$A475,'Stats Roll Up'!$B$4:$B$20,'Stats Roll Up'!$Y$4:$Y$20) -> 0.66666667 | D475: =_xlfn.XLOOKUP(A475,Expectancy!$P$3:$P$19,Expectancy!$R$3:$R$19) -> 0.3117803
A476: XLY | B476: =_xlfn.XLOOKUP('Rev Curves'!A476,'Stats Roll Up'!$B$4:$B$20,'Stats Roll Up'!$J$4:$J$20) -> 17 | C476: =_xlfn.XLOOKUP('Rev Curves'!$A476,'Stats Roll Up'!$B$4:$B$20,'Stats Roll Up'!$Y$4:$Y$20) -> 0.47058824 | D476: =_xlfn.XLOOKUP(A476,Expectancy!$P$3:$P$19,Expectancy!$R$3:$R$19) -> -0.094786291
A477: XLP | B477: =_xlfn.XLOOKUP('Rev Curves'!A477,'Stats Roll Up'!$B$4:$B$20,'Stats Roll Up'!$J$4:$J$20) -> 20 | C477: =_xlfn.XLOOKUP('Rev Curves'!$A477,'Stats Roll Up'!$B$4:$B$20,'Stats Roll Up'!$Y$4:$Y$20) -> 0.7 | D477: =_xlfn.XLOOKUP(A477,Expectancy!$P$3:$P$19,Expectancy!$R$3:$R$19) -> 0.3076902
A478: XLF | B478: =_xlfn.XLOOKUP('Rev Curves'!A478,'Stats Roll Up'!$B$4:$B$20,'Stats Roll Up'!$J$4:$J$20) -> 3 | C478: =_xlfn.XLOOKUP('Rev Curves'!$A478,'Stats Roll Up'!$B$4:$B$20,'Stats Roll Up'!$Y$4:$Y$20) -> 0 | D478: =_xlfn.XLOOKUP(A478,Expectancy!$P$3:$P$19,Expectancy!$R$3:$R$19) -> -0.57605219
A479: XLV | B479: =_xlfn.XLOOKUP('Rev Curves'!A479,'Stats Roll Up'!$B$4:$B$20,'Stats Roll Up'!$J$4:$J$20) -> 13 | C479: =_xlfn.XLOOKUP('Rev Curves'!$A479,'Stats Roll Up'!$B$4:$B$20,'Stats Roll Up'!$Y$4:$Y$20) -> 0.61538462 | D479: =_xlfn.XLOOKUP(A479,Expectancy!$P$3:$P$19,Expectancy!$R$3:$R$19) -> 0.18997806
A480: XLB | B480: =_xlfn.XLOOKUP('Rev Curves'!A480,'Stats Roll Up'!$B$4:$B$20,'Stats Roll Up'!$J$4:$J$20) -> 14 | C480: =_xlfn.XLOOKUP('Rev Curves'!$A480,'Stats Roll Up'!$B$4:$B$20,'Stats Roll Up'!$Y$4:$Y$20) -> 0.64285714 | D480: =_xlfn.XLOOKUP(A480,Expectancy!$P$3:$P$19,Expectancy!$R$3:$R$19) -> 0.73529829
A481: ALL | B481: =_xlfn.XLOOKUP('Rev Curves'!A481,'Stats Roll Up'!$B$4:$B$20,'Stats Roll Up'!$J$4:$J$20) -> 128 | C481: =_xlfn.XLOOKUP('Rev Curves'!$A481,'Stats Roll Up'!$B$4:$B$20,'Stats Roll Up'!$Y$4:$Y$20) -> 0.59375 | D481: =_xlfn.XLOOKUP(A481,Expectancy!$P$3:$P$19,Expectancy!$R$3:$R$19) -> 0.33981949
A498: SW Trends
A499: Sector | B499: # | C499: % Gap Up | D499: Expectancy
A500: XLK | B500: =_xlfn.XLOOKUP('Rev Curves'!$A500,'Stats Roll Up'!$B$4:$B$20,'Stats Roll Up'!$N$4:$N$20) -> 16 | C500: =_xlfn.XLOOKUP('Rev Curves'!$A500,'Stats Roll Up'!$B$4:$B$20,'Stats Roll Up'!$O$4:$O$20) -> 0.5 | D500: =_xlfn.XLOOKUP(A500,Expectancy!$P$3:$P$19,Expectancy!$S$3:$S$19) -> -0.17081772
A501: XLC | B501: =_xlfn.XLOOKUP('Rev Curves'!A501,'Stats Roll Up'!$B$4:$B$20,'Stats Roll Up'!$N$4:$N$20) -> 6 | C501: =_xlfn.XLOOKUP('Rev Curves'!$A501,'Stats Roll Up'!$B$4:$B$20,'Stats Roll Up'!$O$4:$O$20) -> 0.66666667 | D501: =_xlfn.XLOOKUP(A501,Expectancy!$P$3:$P$19,Expectancy!$S$3:$S$19) -> 0.70195709
A502: IGV | B502: =_xlfn.XLOOKUP('Rev Curves'!A502,'Stats Roll Up'!$B$4:$B$20,'Stats Roll Up'!$N$4:$N$20) -> 23 | C502: =_xlfn.XLOOKUP('Rev Curves'!$A502,'Stats Roll Up'!$B$4:$B$20,'Stats Roll Up'!$O$4:$O$20) -> 0.47826087 | D502: =_xlfn.XLOOKUP(A502,Expectancy!$P$3:$P$19,Expectancy!$S$3:$S$19) -> 0.27741611
A503: SMH | B503: =_xlfn.XLOOKUP('Rev Curves'!A503,'Stats Roll Up'!$B$4:$B$20,'Stats Roll Up'!$N$4:$N$20) -> 14 | C503: =_xlfn.XLOOKUP('Rev Curves'!$A503,'Stats Roll Up'!$B$4:$B$20,'Stats Roll Up'!$O$4:$O$20) -> 0.57142857 | D503: =_xlfn.XLOOKUP(A503,Expectancy!$P$3:$P$19,Expectancy!$S$3:$S$19) -> -0.16876071
A504: XLI | B504: =_xlfn.XLOOKUP('Rev Curves'!A504,'Stats Roll Up'!$B$4:$B$20,'Stats Roll Up'!$N$4:$N$20) -> 38 | C504: =_xlfn.XLOOKUP('Rev Curves'!$A504,'Stats Roll Up'!$B$4:$B$20,'Stats Roll Up'!$O$4:$O$20) -> 0.47368421 | D504: =_xlfn.XLOOKUP(A504,Expectancy!$P$3:$P$19,Expectancy!$S$3:$S$19) -> 0.02407352
A505: XLY | B505: =_xlfn.XLOOKUP('Rev Curves'!A505,'Stats Roll Up'!$B$4:$B$20,'Stats Roll Up'!$N$4:$N$20) -> 23 | C505: =_xlfn.XLOOKUP('Rev Curves'!$A505,'Stats Roll Up'!$B$4:$B$20,'Stats Roll Up'!$O$4:$O$20) -> 0.73913043 | D505: =_xlfn.XLOOKUP(A505,Expectancy!$P$3:$P$19,Expectancy!$S$3:$S$19) -> 0.48685637
A506: XLP | B506: =_xlfn.XLOOKUP('Rev Curves'!A506,'Stats Roll Up'!$B$4:$B$20,'Stats Roll Up'!$N$4:$N$20) -> 11 | C506: =_xlfn.XLOOKUP('Rev Curves'!$A506,'Stats Roll Up'!$B$4:$B$20,'Stats Roll Up'!$O$4:$O$20) -> 0.54545455 | D506: =_xlfn.XLOOKUP(A506,Expectancy!$P$3:$P$19,Expectancy!$S$3:$S$19) -> 0.40561946
A507: XLF | B507: =_xlfn.XLOOKUP('Rev Curves'!A507,'Stats Roll Up'!$B$4:$B$20,'Stats Roll Up'!$N$4:$N$20) -> 18 | C507: =_xlfn.XLOOKUP('Rev Curves'!$A507,'Stats Roll Up'!$B$4:$B$20,'Stats Roll Up'!$O$4:$O$20) -> 0.61111111 | D507: =_xlfn.XLOOKUP(A507,Expectancy!$P$3:$P$19,Expectancy!$S$3:$S$19) -> 0.099793136
A508: XLV | B508: =_xlfn.XLOOKUP('Rev Curves'!A508,'Stats Roll Up'!$B$4:$B$20,'Stats Roll Up'!$N$4:$N$20) -> 29 | C508: =_xlfn.XLOOKUP('Rev Curves'!$A508,'Stats Roll Up'!$B$4:$B$20,'Stats Roll Up'!$O$4:$O$20) -> 0.44827586 | D508: =_xlfn.XLOOKUP(A508,Expectancy!$P$3:$P$19,Expectancy!$S$3:$S$19) -> -0.15084751
A509: XLB | B509: =_xlfn.XLOOKUP('Rev Curves'!A509,'Stats Roll Up'!$B$4:$B$20,'Stats Roll Up'!$N$4:$N$20) -> 10 | C509: =_xlfn.XLOOKUP('Rev Curves'!$A509,'Stats Roll Up'!$B$4:$B$20,'Stats Roll Up'!$O$4:$O$20) -> 0.3 | D509: =_xlfn.XLOOKUP(A509,Expectancy!$P$3:$P$19,Expectancy!$S$3:$S$19) -> -0.22212962
A510: ALL | B510: =_xlfn.XLOOKUP('Rev Curves'!A510,'Stats Roll Up'!$B$4:$B$20,'Stats Roll Up'!$N$4:$N$20) -> 215 | C510: =_xlfn.XLOOKUP('Rev Curves'!$A510,'Stats Roll Up'!$B$4:$B$20,'Stats Roll Up'!$O$4:$O$20) -> 0.51162791 | D510: =_xlfn.XLOOKUP(A510,Expectancy!$P$3:$P$19,Expectancy!$S$3:$S$19) -> 0.070355978

Sheet 2025-Q1
A1: Formulas --> | B1: {=IFERROR(_xlfn.XLOOKUP(A4,Earnings!$B$2:$B$9985,LEFT(Earnings!$C$2:$C$9985,37)),"Can't Find Date***")} -> on 1/10/25, 7:30 AM Before Market Eas | E1: =_xlfn.XLOOKUP(A1,[1]SP500!$A$2:$A$655,[1]SP500!$B$2:$B$655) -> #N/A | F1: =IFERROR(TRIM(MID(B1,FIND("/",B1,1)-2,8)),"") -> 1/10/25 | I1: ------------- Gap Data ------------- | N1: Hide These these columns track the strategies three pillars per trade and cumulatively | T1: Hide These these columns track the strategies three pillars per trade and cumulatively | Z1: Hide These (Sector 3 Pillars) these columns track the strategies three pillars per trade and cumulatively | AG1: Hide These (Sector 3 Pillars) these columns track the strategies three pillars per trade and cumulatively | AN1: Hide These (Sector 3 Pillars) these columns track the strategies three pillars per trade and cumulatively | AU1: Hide These (Sector 3 Pillars) these columns track the strategies three pillars per trade and cumulatively | BB1: Hide These (Sector 3 Pillars) these columns track the strategies three pillars per trade and cumulatively | BI1: Hide These (Sector 3 Pillars) these columns track the strategies three pillars per trade and cumulatively | BP1: Hide These (Sector 3 Pillars) these columns track the strategies three pillars per trade and cumulatively | BW1: Hide These (Sector 3 Pillars) these columns track the strategies three pillars per trade and cumulatively | CD1: Hide These (Sector 3 Pillars) these columns track the strategies three pillars per trade and cumulatively | CK1: Hide These (Sector 3 Pillars) these columns track the strategies three pillars per trade and cumulatively | CR1: Hide These (Sector 3 Pillars) these columns track the strategies three pillars per trade and cumulatively | CY1: Hide These (Sector 3 Pillars) these columns track the strategies three pillars per trade and cumulatively | DF1: Hide These (Sector 3 Pillars) these columns track the strategies three pillars per trade and cumulatively | DM1: Hide These (Sector 3 Pillars) these columns track the strategies three pillars per trade and cumulatively | DT1: Hide These (Sector 3 Pillars) these columns track the strategies three pillars per trade and cumulatively | EA1: Hide These (Sector 3 Pillars) these columns track the strategies three pillars per trade and cumulatively | EH1: Strategy P&L | FX1: Hide These | GL1: MOC P&L | HB1: Actual P&L | HJ1: Money | HN1: Key Stats | HQ1: Risk Units | HX1: Expectancy | HZ1: Number of Stocks
A2: Cheat -> | B2: hide | C2: hide | E2: form | F2: form | G2: form | H2: f | I2: entry | J2: entry | K2: form | L2: form | M2: form | N2: form | O2: form | P2: form | Q2: form | R2: form | S2: form | T2: form | U2: form | V2: form | W2: form | X2: form | Y2: form | Z2: XLK | AA2: form | AB2: form | AC2: form | AD2: form | AE2: form | AF2: form | AG2: IGV | AH2: form | AI2: form | AJ2: form | AK2: form | AL2: form | AM2: form | AN2: XLY | AO2: form | AP2: form | AQ2: form | AR2: form | AS2: form | AT2: form | AU2: XLP | AV2: form | AW2: form | AX2: form | AY2: form | AZ2: form | BA2: form | BB2: XLC | BC2: form | BD2: form | BE2: form | BF2: form | BG2: form | BH2: form | BI2: XLF | BJ2: form | BK2: form | BL2: form | BM2: form | BN2: form | BO2: form | BP2: XLI | BQ2: form | BR2: form | BS2: form | BT2: form | BU2: form | BV2: form | BW2: XLV | BX2: form | BY2: form | BZ2: form | CA2: form | CB2: form | CC2: form | CD2: XLB | CE2: form | CF2: form | CG2: form | CH2: form | CI2: form | CJ2: form | CK2: SMH | CL2: form | CM2: form | CN2: form | CO2: form | CP2: form | CQ2: form | CR2: XLE | CS2: form | CT2: form | CU2: form | CV2: form | CW2: form | CX2: form | CY2: XLU | CZ2: form | DA2: form | DB2: form | DC2: form | DD2: form | DE2: form | DF2: XLRE | DG2: form | DH2: form | DI2: form | DJ2: form | DK2: form | DL2: form | DM2: INS | DN2: form | DO2: form | DP2: form | DQ2: form | DR2: form | DS2: form | DT2: H-INS | DU2: form | DV2: form | DW2: form | DX2: form | DY2: form | DZ2: form | EA2: XHB | EB2: form | EC2: form | ED2: form | EE2: form | EF2: form | EG2: form | EH2: form | EI2: form | EJ2: form | EK2: form | EL2: SPY | EM2: SPY | EN2: SPY | EO2: SPY | EP2: SPY | EQ2: SPY | ER2: SPY | ES2: SPY | ET2: Not Spy | EU2: Not Spy | EV2: Not Spy | EW2: Not Spy | EX2: Not Spy | EY2: Not Spy | EZ2: Not Spy | FA2: Not Spy | FB2: Gap ↓ from Dwn Tr | FD2: Gap ↑ from Dwn Tr | FF2: Gap ↑ from Up Tr | FH2: Gap ↓ from Up Tr | FJ2: Gap ↑ from Sw Tr | FL2: Gap ↓ from Sw Tr | FN2: hide | FO2: hide | FP2: form | FQ2: form | FR2: form | FS2: hide | FT2: hide | FU2: form | FV2: form | FW2: entry | GE2: form | GF2: entry | GG2: F/E | GH2: form | GI2: entry | GJ2: entry | GK2: form | GL2: form | GM2: Hide | GN2: Hide | GO2: Hide | GP2: Hide | GQ2: Hide | GR2: Hide | GS2: Hide | GT2: Hide | GU2: Hide | GV2: Hide | GW2: Hide | GX2: Hide | GY2: Hide | GZ2: entry | HA2: form | HB2: entry | HC2: form | HD2: form | HE2: form | HF2: form | HG2: form | HJ2: AveW | HK2: AveL | HL2: Sharpe$ | HM2: P/L | HN2: wins | HO2: losers | HP2: BA% | HQ2: AveW | HR2: AveL | HS2: Sharpe$ | HT2: Units | HU2: Overrides | HV2: SPY | HW2: Not SPY | HX2: SPY | HY2: Not SPY | HZ2: SPY | IA2: Not SPY
A3: Stock | B3: Earnings Date | C3: TrCh | D3: In SPY? | E3: Sector | F3: Date | G3: AMO, BMO | H3: S/O | I3: Close [entry] | J3: Open | K3: Gap % | L3: Gap P/L | M3: P&L Var. from Slippage | N3: Playing Up Trends Long | O3: Cumulative Playing Up Trends Long | P3: Playing Down Trends Short | Q3: Cumulative Playing Dwn Trends Short | R3: Playing Sideways Trends Long | S3: Cumulative Playing SW Trends Long | T3: R, Playing Up Trends Long | U3: Cumulative Playing Up Trends Long | V3: R, Playing Down Trends Short | W3: Cumulative Playing Dwn Trends Short | X3: R, Playing Sideways Trends Long | Y3: Cumulative Playing SW Trends Long | Z3: Playing Up Trends Long | AA3: Cumulative Playing Up Trends Long | AB3: Playing Down Trends Short | AC3: Cumulative Playing Dwn Trends Short | AD3: Playing Sideways Trends Long | AE3: Cumulative Playing SW Trends Long | AF3: TOTAL of Three Pillars | AG3: Playing Up Trends Long | AH3: Cumulative Playing Up Trends Long | AI3: Playing Down Trends Short | AJ3: Cumulative Playing Dwn Trends Short | AK3: Playing Sideways Trends Long | AL3: Cumulative Playing SW Trends Long | AM3: TOTAL of Three Pillars | AN3: Playing Up Trends Long | AO3: Cumulative Playing Up Trends Long | AP3: Playing Down Trends Short | AQ3: Cumulative Playing Dwn Trends Short | AR3: Playing Sideways Trends Long | AS3: Cumulative Playing SW Trends Long | AT3: TOTAL of Three Pillars | AU3: Playing Up Trends Long | AV3: Cumulative Playing Up Trends Long | AW3: Playing Down Trends Short | AX3: Cumulative Playing Dwn Trends Short | AY3: Playing Sideways Trends Long | AZ3: Cumulative Playing SW Trends Long | BA3: TOTAL of Three Pillars | BB3: Playing Up Trends Long | BC3: Cumulative Playing Up Trends Long | BD3: Playing Down Trends Short | BE3: Cumulative Playing Dwn Trends Short | BF3: Playing Sideways Trends Long | BG3: Cumulative Playing SW Trends Long | BH3: TOTAL of Three Pillars | BI3: Playing Up Trends Long | BJ3: Cumulative Playing Up Trends Long | BK3: Playing Down Trends Short | BL3: Cumulative Playing Dwn Trends Short | BM3: Playing Sideways Trends Long | BN3: Cumulative Playing SW Trends Long | BO3: TOTAL of Three Pillars | BP3: Playing Up Trends Long | BQ3: Cumulative Playing Up Trends Long | BR3: Playing Down Trends Short | BS3: Cumulative Playing Dwn Trends Short | BT3: Playing Sideways Trends Long | BU3: Cumulative Playing SW Trends Long | BV3: TOTAL of Three Pillars | BW3: Playing Up Trends Long | BX3: Cumulative Playing Up Trends Long | BY3: Playing Down Trends Short | BZ3: Cumulative Playing Dwn Trends Short | CA3: Playing Sideways Trends Long | CB3: Cumulative Playing SW Trends Long | CC3: TOTAL of Three Pillars | CD3: Playing Up Trends Long | CE3: Cumulative Playing Up Trends Long | CF3: Playing Down Trends Short | CG3: Cumulative Playing Dwn Trends Short | CH3: Playing Sideways Trends Long | CI3: Cumulative Playing SW Trends Long | CJ3: TOTAL of Three Pillars | CK3: Playing Up Trends Long | CL3: Cumulative Playing Up Trends Long | CM3: Playing Down Trends Short | CN3: Cumulative Playing Dwn Trends Short | CO3: Playing Sideways Trends Long | CP3: Cumulative Playing SW Trends Long | CQ3: TOTAL of Three Pillars | CR3: Playing Up Trends Long | CS3: Cumulative Playing Up Trends Long | CT3: Playing Down Trends Short | CU3: Cumulative Playing Dwn Trends Short | CV3: Playing Sideways Trends Long | CW3: Cumulative Playing SW Trends Long | CX3: TOTAL of Three Pillars | CY3: Playing Up Trends Long | CZ3: Cumulative Playing Up Trends Long | DA3: Playing Down Trends Short | DB3: Cumulative Playing Dwn Trends Short | DC3: Playing Sideways Trends Long | DD3: Cumulative Playing SW Trends Long | DE3: TOTAL of Three Pillars | DF3: Playing Up Trends Long | DG3: Cumulative Playing Up Trends Long | DH3: Playing Down Trends Short | DI3: Cumulative Playing Dwn Trends Short | DJ3: Playing Sideways Trends Long | DK3: Cumulative Playing SW Trends Long | DL3: TOTAL of Three Pillars | DM3: Playing Up Trends Long | DN3: Cumulative Playing Up Trends Long | DO3: Playing Down Trends Short | DP3: Cumulative Playing Dwn Trends Short | DQ3: Playing Sideways Trends Long | DR3: Cumulative Playing SW Trends Long | DS3: TOTAL of Three Pillars | DT3: Playing Up Trends Long | DU3: Cumulative Playing Up Trends Long | DV3: Playing Down Trends Short | DW3: Cumulative Playing Dwn Trends Short | DX3: Playing Sideways Trends Long | DY3: Cumulative Playing SW Trends Long | DZ3: TOTAL of Three Pillars | EA3: Playing Up Trends Long | EB3: Cumulative Playing Up Trends Long | EC3: Playing Down Trends Short | ED3: Cumulative Playing Dwn Trends Short | EE3: Playing Sideways Trends Long | EF3: Cumulative Playing SW Trends Long | EG3: TOTAL of Three Pillars | EH3: P/L per Trade | EI3: P/L Total | EJ3: P/L per Trade MOC | EK3: P/L MOC Total | EL3: R per Trade | EM3: R Total | EN3: R per Trade Up | EO3: R Total Up Trends | EP3: R per Trade SW | EQ3: R Total SW Trends | ER3: R per Trade Dwn | ES3: R Total Dwn Trends | ET3: R per Trade | EU3: R Total | EV3: R per Trade Up | EW3: R Total Up Trends | EX3: R per Trade SW | EY3: R Total SW Trends | EZ3: R per Trade Dwn | FA3: R Total Dwn Trends | FB3: R Dwn per Trade MOC | FC3: R Dwn MOC Total | FD3: R Dwn per Trade MOC | FE3: R Dwn MOC Total | FF3: R per Trade MOC | FG3: R MOC Total | FH3: R Dwn per Trade MOC | FI3: R Dwn MOC Total | FJ3: R per Trade MOC | FK3: R MOC Total | FL3: R Dwn per Trade MOC | FM3: R Dwn MOC Total | FN3: R per Trade MOC | FO3: R MOC Total | FP3: R per Trade | FQ3: R Total | FR3: OverallExp. | FS3: Exp 50-ma | FT3: Exp 25-ma | FU3: Variance Act v. Strat Total | FV3: Daily Trend | FW3: Trend Tracking | FX3: Gap Ups with trend | FY3: Gap Ups Against Trend | FZ3: Gap Ups NA | GA3: Theoretical Direction with trend and sideways going Long | GB3: Gap Dns with trend | GC3: Gap Dns Against Trend | GD3: Gap Dns NA | GE3: Entry | GF3: L / S | GG3: Entry Shares | GH3: Cost | GI3: Exit Shares | GJ3: Exit at Open or "Other" | GK3: P&L if Using MKT at Open or Other Exit | GL3: MOC P / L | GM3: Sw Trends MOC R | GN3: Total Sw Trends MOC R | GO3: UP Trends MOC R | GP3: Total UP Trends MOC R | GQ3: Dwn Trends MOC R | GR3: Total Dwn Trends MOC R | GS3: Sw Trends MOC P/L | GT3: Total Sw Trends MOC P/L | GU3: UP Trends MOC P/L | GV3: Total UP Trends MOC P/L | GW3: Dwn Trends MOC P/L | GX3: Total Dwn Trends MOC P/L | GY3: Total MOC P / L | GZ3: Exit Using MOC | HA3: Var vs. Strategy | HB3: Exit Type | HC3: Trade Exp | HD3: R per Trade | HE3: R Total | HF3: P/L Total | HG3: P/L per Trade | HH3: MOC R | HJ3: =AVERAGEIF($EH$4:$EH$448,">0") -> 49.334696 | HK3: =AVERAGEIF($EH$4:$EH$448,"<0") -> -45.175088 | HL3: =HJ3/-HK3 -> 1.0920775 | HM3: =(HN3*HJ3)+(HO3*HK3) -> 2530.0994 | HN3: =COUNTIF($EH$4:$EH$448,">0") -> 239 | HO3: =COUNTIF($EH$4:$EH$448,"<0") -> 205 | HP3: =HN3/(HN3+HO3) -> 0.53828829 | HQ3: =AVERAGEIF($FP$4:$FP$448,">0") -> 0.92852474 | HR3: =AVERAGEIF($FP$4:$FP$448,"<0") -> -0.74772978 | HS3: =HQ3/-HR3 -> 1.2417919 | HT3: =(HN3*HQ3)+(HR3*HO3) -> 68.632809 | HU3: =SUMIFS($FP$4:$FP$448,$H$4:$H$448,"o") -> 37.440139 | HV3: =SUMIFS($FP$4:$FP$448,$D$4:$D$448,"Y") -> 25.097747 | HW3: =SUMIFS($FP$4:$FP$448,$D$4:$D$448,"N") -> 43.535062 | HX3: =SUMIFS($FP$4:$FP$448,$D$4:$D$448,"Y")/COUNTIF($D$4:$D$448,"Y") -> 0.064353199 | HY3: =SUMIFS($FP$4:$FP$448,$D$4:$D$448,"N")/COUNTIF($D$4:$D$448,"N") -> 0.79154658 | HZ3: =COUNTIF($D$4:$D$448,"Y") -> 390 | IA3: =COUNTIF($D$4:$D$448,"N") -> 55
A4: STZ | B4: on 1/10/25, 7:30 AM Before Market Eas | C4: =IF(FV4="Dwn",2,IF(FV4="Up",1,IF(FV4="SW",3,"x"))) -> 2 | D4: =_xlfn.XLOOKUP(A4,[1]SP500!$A$2:$A$502,[1]SP500!$D$2:$D$502,"N") -> Y | E4: =_xlfn.XLOOKUP(A4,[1]SP500!$A$2:$A$655,[1]SP500!$B$2:$B$655) -> XLP | F4: 45667 | G4: =IF(ISNUMBER(FIND("After",B4,1)),"AMC",IF(ISNUMBER(FIND("Before",B4,1)),"BMO","err")) -> BMO | H4: =IF(HB4="other","o",IF(HB4="Skip","o",IF(OR(FV4="",GF4=""),"",IF(AND(FV4="Dwn",GF4="Short"),"s",IF(AND(FV4="Up",GF4="Long"),"s",IF(AND(FV4="SW",GF4="Long"),"s","o")))))) -> o | I4: 219.28 | J4: 203.11 | K4: =IF(J4="","",(J4-I4)/I4) -> -0.073741335 | L4: =IF(OR($GI4="",J4=""),"",IF($GF4="Long",(($J4*$GI4)-$GH4),($GH4-($J4*$GI4)))) -> 29.496534 | M4: =IF(L4="","",IF(HG4="","",HG4-L4)) | N4: =IF(AND($FV4="Up",$GA4="Long"),$EH4,"") | O4: =IF($J4="",#N/A,SUM(N$4:N4)) -> 0 | P4: =IF(AND($FV4="Dwn",$GA4="Short"),$EH4,"") -> 29.496534 | Q4: =IF($J4="",#N/A,SUM(P$4:P4)) -> 29.496534 | R4: =IF(AND($FV4="SW",$GA4="Long"),$EH4,"") | S4: =IF($J4="",#N/A,SUM(R$4:R4)) -> 0 | T4: =IF(AND($FV4="Up",$GA4="Long"),$FP4,"") | U4: =IF($J4="",#N/A,SUM(T$4:T4)) -> 0 | V4: =IF(AND($FV4="Dwn",$GA4="Short"),$FP4,"") -> 1.2290223 | W4: =IF($J4="",#N/A,SUM(V$4:V4)) -> 1.2290223 | X4: =IF(AND($FV4="SW",$GA4="Long"),$FP4,"") | Y4: =IF($J4="",#N/A,SUM(X$4:X4)) -> 0 | Z4: =IF(AND($FV4="Up",$GA4="Long",$E4=Z$2),$FP4,"") | AA4: =IF($J4="",#N/A,SUM(Z$4:Z4)) -> 0 | AB4: =IF(AND($FV4="Dwn",$GA4="Short",$E4=Z$2),$FP4,"") | AC4: =IF($J4="",#N/A,SUM(AB$4:AB4)) -> 0 | AD4: =IF(AND($FV4="SW",$GA4="Long",$E4=Z$2),$FP4,"") | AE4: =IF($J4="",#N/A,SUM(AD$4:AD4)) -> 0 | AF4: =IF($J4="",#N/A,SUM(AD$4:AD4,AB$4:AB4,Z$4:Z4)) -> 0 | AG4: =IF(AND($FV4="Up",$GA4="Long",$E4=AG$2),$FP4,"") | AH4: =IF($J4="",#N/A,SUM(AG$4:AG4)) -> 0 | AI4: =IF(AND($FV4="Dwn",$GA4="Short",$E4=AG$2),$FP4,"") | AJ4: =IF($J4="",#N/A,SUM(AI$4:AI4)) -> 0 | AK4: =IF(AND($FV4="SW",$GA4="Long",$E4=AG$2),$FP4,"") | AL4: =IF($J4="",#N/A,SUM(AK$4:AK4)) -> 0 | AM4: =IF($J4="",#N/A,SUM(AK$4:AK4,AI$4:AI4,AG$4:AG4)) -> 0 | AN4: =IF(AND($FV4="Up",$GA4="Long",$E4=AN$2),$FP4,"") | AO4: =IF($J4="",#N/A,SUM(AN$4:AN4)) -> 0 | AP4: =IF(AND($FV4="Dwn",$GA4="Short",$E4=AN$2),$FP4,"") | AQ4: =IF($J4="",#N/A,SUM(AP$4:AP4)) -> 0 | AR4: =IF(AND($FV4="SW",$GA4="Long",$E4=AN$2),$FP4,"") | AS4: =IF($J4="",#N/A,SUM(AR$4:AR4)) -> 0 | AT4: =IF($J4="",#N/A,SUM(AR$4:AR4,AP$4:AP4,AN$4:AN4)) -> 0 | AU4: =IF(AND($FV4="Up",$GA4="Long",$E4=AU$2),$FP4,"") | AV4: =IF($J4="",#N/A,SUM(AU$4:AU4)) -> 0 | AW4: =IF(AND($FV4="Dwn",$GA4="Short",$E4=AU$2),$FP4,"") -> 1.2290223 | AX4: =IF($J4="",#N/A,SUM(AW$4:AW4)) -> 1.2290223 | AY4: =IF(AND($FV4="SW",$GA4="Long",$E4=AU$2),$FP4,"") | AZ4: =IF($J4="",#N/A,SUM(AY$4:AY4)) -> 0 | BA4: =IF($J4="",#N/A,SUM(AY$4:AY4,AW$4:AW4,AU$4:AU4)) -> 1.2290223 | BB4: =IF(AND($FV4="Up",$GA4="Long",$E4=BB$2),$FP4,"") | BC4: =IF($J4="",#N/A,SUM(BB$4:BB4)) -> 0 | BD4: =IF(AND($FV4="Dwn",$GA4="Short",$E4=BB$2),$FP4,"") | BE4: =IF($J4="",#N/A,SUM(BD$4:BD4)) -> 0 | BF4: =IF(AND($FV4="SW",$GA4="Long",$E4=BB$2),$FP4,"") | BG4: =IF($J4="",#N/A,SUM(BF$4:BF4)) -> 0 | BH4: =IF($J4="",#N/A,SUM(BF$4:BF4,BD$4:BD4,BB$4:BB4)) -> 0 | BI4: =IF(AND($FV4="Up",$GA4="Long",$E4=BI$2),$FP4,"") | BJ4: =IF($J4="",#N/A,SUM(BI$4:BI4)) -> 0 | BK4: =IF(AND($FV4="Dwn",$GA4="Short",$E4=BI$2),$FP4,"") | BL4: =IF($J4="",#N/A,SUM(BK$4:BK4)) -> 0 | BM4: =IF(AND($FV4="SW",$GA4="Long",$E4=BI$2),$FP4,"") | BN4: =IF($J4="",#N/A,SUM(BM$4:BM4)) -> 0 | BO4: =IF($J4="",#N/A,SUM(BM$4:BM4,BK$4:BK4,BI$4:BI4)) -> 0 | BP4: =IF(AND($FV4="Up",$GA4="Long",$E4=BP$2),$FP4,"") | BQ4: =IF($J4="",#N/A,SUM(BP$4:BP4)) -> 0 | BR4: =IF(AND($FV4="Dwn",$GA4="Short",$E4=BP$2),$FP4,"") | BS4: =IF($J4="",#N/A,SUM(BR$4:BR4)) -> 0 | BT4: =IF(AND($FV4="SW",$GA4="Long",$E4=BP$2),$FP4,"") | BU4: =IF($J4="",#N/A,SUM(BT$4:BT4)) -> 0 | BV4: =IF($J4="",#N/A,SUM(BT$4:BT4,BR$4:BR4,BP$4:BP4)) -> 0 | BW4: =IF(AND($FV4="Up",$GA4="Long",$E4=BW$2),$FP4,"") | BX4: =IF($J4="",#N/A,SUM(BW$4:BW4)) -> 0 | BY4: =IF(AND($FV4="Dwn",$GA4="Short",$E4=BW$2),$FP4,"") | BZ4: =IF($J4="",#N/A,SUM(BY$4:BY4)) -> 0 | CA4: =IF(AND($FV4="SW",$GA4="Long",$E4=BW$2),$FP4,"") | CB4: =IF($J4="",#N/A,SUM(CA$4:CA4)) -> 0 | CC4: =IF($J4="",#N/A,SUM(CA$4:CA4,BY$4:BY4,BW$4:BW4)) -> 0 | CD4: =IF(AND($FV4="Up",$GA4="Long",$E4=CD$2),$FP4,"") | CE4: =IF($J4="",#N/A,SUM(CD$4:CD4)) -> 0 | CF4: =IF(AND($FV4="Dwn",$GA4="Short",$E4=CD$2),$FP4,"") | CG4: =IF($J4="",#N/A,SUM(CF$4:CF4)) -> 0 | CH4: =IF(AND($FV4="SW",$GA4="Long",$E4=CD$2),$FP4,"") | CI4: =IF($J4="",#N/A,SUM(CH$4:CH4)) -> 0 | CJ4: =IF($J4="",#N/A,SUM(CH$4:CH4,CF$4:CF4,CD$4:CD4)) -> 0 | CK4: =IF(AND($FV4="Up",$GA4="Long",$E4=CK$2),$FP4,"") | CL4: =IF($J4="",#N/A,SUM(CK$4:CK4)) -> 0 | CM4: =IF(AND($FV4="Dwn",$GA4="Short",$E4=CK$2),$FP4,"") | CN4: =IF($J4="",#N/A,SUM(CM$4:CM4)) -> 0 | CO4: =IF(AND($FV4="SW",$GA4="Long",$E4=CK$2),$FP4,"") | CP4: =IF($J4="",#N/A,SUM(CO$4:CO4)) -> 0 | CQ4: =IF($J4="",#N/A,SUM(CO$4:CO4,CM$4:CM4,CK$4:CK4)) -> 0 | CR4: =IF(AND($FV4="Up",$GA4="Long",$E4=CR$2),$FP4,"") | CS4: =IF($J4="",#N/A,SUM(CR$4:CR4)) -> 0 | CT4: =IF(AND($FV4="Dwn",$GA4="Short",$E4=CR$2),$FP4,"") | CU4: =IF($J4="",#N/A,SUM(CT$4:CT4)) -> 0 | CV4: =IF(AND($FV4="SW",$GA4="Long",$E4=CR$2),$FP4,"") | CW4: =IF($J4="",#N/A,SUM(CV$4:CV4)) -> 0 | CX4: =IF($J4="",#N/A,SUM(CV$4:CV4,CT$4:CT4,CR$4:CR4)) -> 0 | CY4: =IF(AND($FV4="Up",$GA4="Long",$E4=CY$2),$FP4,"") | CZ4: =IF($J4="",#N/A,SUM(CY$4:CY4)) -> 0 | DA4: =IF(AND($FV4="Dwn",$GA4="Short",$E4=CY$2),$FP4,"") | DB4: =IF($J4="",#N/A,SUM(DA$4:DA4)) -> 0 | DC4: =IF(AND($FV4="SW",$GA4="Long",$E4=CY$2),$FP4,"") | DD4: =IF($J4="",#N/A,SUM(DC$4:DC4)) -> 0 | DE4: =IF($J4="",#N/A,SUM(DC$4:DC4,DA$4:DA4,CY$4:CY4)) -> 0 | DF4: =IF(AND($FV4="Up",$GA4="Long",$E4=DF$2),$FP4,"") | DG4: =IF($J4="",#N/A,SUM(DF$4:DF4)) -> 0 | DH4: =IF(AND($FV4="Dwn",$GA4="Short",$E4=DF$2),$FP4,"") | DI4: =IF($J4="",#N/A,SUM(DH$4:DH4)) -> 0 | DJ4: =IF(AND($FV4="SW",$GA4="Long",$E4=DF$2),$FP4,"") | DK4: =IF($J4="",#N/A,SUM(DJ$4:DJ4)) -> 0 | DL4: =IF($J4="",#N/A,SUM(DJ$4:DJ4,DH$4:DH4,DF$4:DF4)) -> 0 | DM4: =IF(AND($FV4="Up",$GA4="Long",$E4=DM$2),$FP4,"") | DN4: =IF($J4="",#N/A,SUM(DM$4:DM4)) -> 0 | DO4: =IF(AND($FV4="Dwn",$GA4="Short",$E4=DM$2),$FP4,"") | DP4: =IF($J4="",#N/A,SUM(DO$4:DO4)) -> 0 | DQ4: =IF(AND($FV4="SW",$GA4="Long",$E4=DM$2),$FP4,"") | DR4: =IF($J4="",#N/A,SUM(DQ$4:DQ4)) -> 0 | DS4: =IF($J4="",#N/A,SUM(DQ$4:DQ4,DO$4:DO4,DM$4:DM4)) -> 0 | DT4: =IF(AND($FV4="Up",$GA4="Long",$E4=DT$2),$FP4,"") | DU4: =IF($J4="",#N/A,SUM(DT$4:DT4)) -> 0 | DV4: =IF(AND($FV4="Dwn",$GA4="Short",$E4=DT$2),$FP4,"") | DW4: =IF($J4="",#N/A,SUM(DV$4:DV4)) -> 0 | DX4: =IF(AND($FV4="SW",$GA4="Long",$E4=DT$2),$FP4,"") | DY4: =IF($J4="",#N/A,SUM(DX$4:DX4)) -> 0 | DZ4: =IF($J4="",#N/A,SUM(DX$4:DX4,DV$4:DV4,DT$4:DT4)) -> 0 | EA4: =IF(AND($FV4="Up",$GA4="Long",$E4=EA$2),$FP4,"") | EB4: =IF($J4="",#N/A,SUM(EA$4:EA4)) -> 0 | EC4: =IF(AND($FV4="Dwn",$GA4="Short",$E4=EA$2),$FP4,"") | ED4: =IF($J4="",#N/A,SUM(EC$4:EC4)) -> 0 | EE4: =IF(AND($FV4="SW",$GA4="Long",$E4=EA$2),$FP4,"") | EF4: =IF($J4="",#N/A,SUM(EE$4:EE4)) -> 0 | EG4: =IF($J4="",#N/A,SUM(EE$4:EE4,EC$4:EC4,EA$4:EA4)) -> 0 | EH4: =IF(OR($GI4="",L4=""),"",IF($GA4="Long",(($J4*$GI4)-$GH4),($GH4-($J4*$GI4)))) -> 29.496534 | EI4: =IF($EH4="",#N/A,SUM($EH$4:EH4)) -> 29.496534 | EJ4: =IF(GZ4="","",IF(OR($GI4="",AM4=""),"",IF($GA4="Long",(($GZ4*$GI4)-$GH4),($GH4-($GZ4*$GI4))))) -> 68.350967 | EK4: =IF($GZ4="",#N/A,SUM(EJ$4:EJ4)) -> 68.350967 | EL4: =IF($J4="","",IF($D4="Y",$FP4,"")) -> 1.2290223 | EM4: =IF(EL4="",NA(),SUM($EL$4:EL4)) -> 1.2290223 | EN4: =IF(AND($FV4="Up",$GA4="Long",$D4="Y"),$EL4,"") | EO4: =IF(EN4="",NA(),SUM($EN$4:EN4)) -> #N/A | EP4: =IF(AND($FV4="SW",$GA4="Long",$D4="Y"),$EL4,"") | EQ4: =IF(EP4="",NA(),SUM($EP$4:EP4)) -> #N/A | ER4: =IF(AND($FV4="Dwn",$GA4="Short",$D4="Y"),$EL4,"") -> 1.2290223 | ES4: =IF(ER4="",NA(),SUM($ER$4:ER4)) -> 1.2290223 | ET4: =IF($J4="","",IF($D4="N",$FP4,"")) | EU4: =IF(ET4="",NA(),SUM($ET$4:ET4)) -> #N/A | EV4: =IF(AND($FV4="Up",$GA4="Long",$D4="N"),$ET4,"") | EW4: =IF(EV4="",NA(),SUM($EV$4:EV4)) -> #N/A | EX4: =IF(AND($FV4="SW",$GA4="Long",$D4="N"),$ET4,"") | EY4: =IF(EX4="",NA(),SUM($EX$4:EX4)) -> #N/A | EZ4: =IF(AND($FV4="Dwn",$GA4="Short",$D4="N"),$ET4,"") | FA4: =IF(EZ4="",NA(),SUM($EZ$4:EZ4)) -> #N/A | FB4: =IF($GZ4="","",IF(AND($FV4="Dwn",$K4<0),$FN4-$FP4,"")) -> 1.6189347 | FC4: =IF($FB4="",#N/A,SUM(FB$4:$FB4)) -> 1.6189347 | FD4: =IF($GZ4="","",IF(AND($FV4="Dwn",$K4>0),$FN4-$FP4,"")) | FE4: =IF($FD4="",#N/A,SUM($FD$4:FD4)) -> #N/A | FF4: =IF($GZ4="","",IF(AND($FV4="Up",$K4>0),$FN4-$FP4,"")) | FG4: =IF($FF4="",#N/A,SUM($FF$4:FF4)) -> #N/A | FH4: =IF($GZ4="","",IF(AND($FV4="Up",$K4<0),$FN4-$FP4,"")) | FI4: =IF($FH4="",#N/A,SUM($FH$4:FH4)) -> #N/A | FJ4: =IF($GZ4="","",IF(AND($FV4="SW",$K4>0),$FN4-$FP4,"")) | FK4: =IF($FJ4="",#N/A,SUM($FJ$4:FJ4)) -> #N/A | FL4: =IF($GZ4="","",IF(AND($FV4="SW",$K4<0),$FN4-$FP4,"")) | FM4: =IF($FL4="",#N/A,SUM($FL$4:FL4)) -> #N/A | FN4: =IF(OR($GI4="",$GZ4=""),"",IF($GA4="Long",(($GZ4*$GI4)-$GH4)/($GH4*0.06),($GH4-($GZ4*$GI4))/($GH4*0.06))) -> 2.847957 | FO4: =IF($FN4="",#N/A,SUM(FN$4:$FN4)) -> 2.847957 | FP4: =IF(OR($GI4="",$L4=""),"",IF($GA4="Long",(($J4*$GI4)-$GH4)/($GH4*0.06),($GH4-($J4*$GI4))/($GH4*0.06))) -> 1.2290223 | FQ4: =IF($EH4="",#N/A,SUM($FP$4:FP4)) -> 1.2290223 | FU4: #N/A | FV4: =IF(FW4="Down","Dwn",IF(FW4="Up","Up",IF(AND(FW4="",K4=""),"",IF(AND(K4<0,FW4="Yes"),"Dwn",IF(AND(K4>0,FW4="Yes"),"Up",IF(AND(K4<0,FW4="No"),"Up",IF(AND(K4>0,FW4="No"),"Dwn",IF(FW4="NA","SW","err")))))))) -> Dwn | FW4: Yes | FX4: =IF(K4="","",IF(AND(K4>0,FW4="Yes"),1,"")) | FY4: =IF(K4="","",IF(AND($K4>0,$FW4="No"),1,"")) | FZ4: =IF(K4="","",IF(AND($K4>0,$FW4="NA"),1,"")) | GA4: =IF(FV4="Dwn","Short","Long") -> Short | GB4: =IF(K4="","",IF(AND($K4<0,$FW4="Yes"),1,"")) -> 1 | GC4: =IF(K4="","",IF(AND($K4<0,$FW4="No"),1,"")) | GD4: =IF(K4="","",IF(AND($K4<0,$FW4="NA"),1,"")) | GE4: =I4 -> 219.28 | GF4: Short | GG4: =400/I4 -> 1.8241518 | GH4: =IF(GG4="","",GE4*GG4) -> 400 | GI4: =GG4 -> 1.8241518 | GJ4: =J4 -> 203.11 | GK4: =IF($GI4="","",IF($GF4="Long",(($GJ4*$GI4)-$GH4),($GH4-($GJ4*$GI4)))) -> 29.496534 | GL4: =IF($GI4="","",IF($GF4="Long",(($GZ4*$GI4)-$GH4),($GH4-($GZ4*$GI4)))) -> 68.350967 | GM4: =IF(AND($FV4="SW",$GA4="Long"),$FN4,"") | GN4: =IF($GZ4="",#N/A,SUM(GM$4:GM4)) -> 0 | GO4: =IF(AND($FV4="UP",$GA4="Long"),$FN4,"") | GP4: =IF($GZ4="",#N/A,SUM(GO$4:GO4)) -> 0 | GQ4: =IF(AND($FV4="Dwn",$GA4="Short"),$FN4,"") -> 2.847957 | GR4: =IF($GZ4="",#N/A,SUM(GQ$4:GQ4)) -> 2.847957 | GS4: =IF(AND($FV4="SW",$GA4="Long"),$EJ4,"") | GT4: =IF($GZ4="",#N/A,SUM(GS$4:GS4)) -> 0 | GU4: =IF(AND($FV4="UP",$GA4="Long"),$EJ4,"") | GV4: =IF($GZ4="",#N/A,SUM(GU$4:GU4)) -> 0 | GW4: =IF(AND($FV4="Dwn",$GA4="Short"),$EJ4,"") -> 68.350967 | GX4: =IF($GZ4="",#N/A,SUM(GW$4:GW4)) -> 68.350967 | GY4: =IF($EJ4="",#N/A,SUM($EJ$4:$EJ4)) -> 68.350967 | GZ4: 181.81 | HA4: =IF(OR(GL4="",GZ4=""),"",GL4-EH4) -> 38.854433 | HB4: Skip | HC4: =IFERROR(VLOOKUP(E4,Expectancy!$P$4:$S$19,1+C4,FALSE),"") -> 0.3076902 | HD4: =IF(AND(HB4="MOC",GZ4=""),"",IF(GI4="","",IF(HB4="Skip","",IF(HG4=0,0,HG4/(GH4*0.06))))) | HE4: =IF(HD4="",#N/A,SUM($HD4:HD$4)) -> #N/A | HF4: =IF(HD4="",#N/A,IF(HB4="Skip",#N/A,SUM($HG$4:HG4))) -> #N/A | HG4: =IF(HB4="","",IF(HB4="Skip","",IF(OR(HB4="open",HB4="Other"),GK4,IF(HB4="MOC",GL4,"Err")))) | HH4: =IF(OR($GI4="",$L4=""),"",IF($GA4="Long",(($GZ4*$GI4)-$GH4)/($GH4*0.06),($GH4-($GZ4*$GI4))/($GH4*0.06))) -> 2.847957
A5: DAL | B5: on 1/10/25, 6:30 AM Before Market Eas | C5: =IF(FV5="Dwn",2,IF(FV5="Up",1,IF(FV5="SW",3,"x"))) -> 1 | D5: =_xlfn.XLOOKUP(A5,[1]SP500!$A$2:$A$502,[1]SP500!$D$2:$D$502,"N") -> Y | E5: =_xlfn.XLOOKUP(A5,[1]SP500!$A$2:$A$655,[1]SP500!$B$2:$B$655) -> XLI | F5: 45667 | G5: =IF(ISNUMBER(FIND("After",B5,1)),"AMC",IF(ISNUMBER(FIND("Before",B5,1)),"BMO","err")) -> BMO | H5: =IF(HB5="other","o",IF(HB5="Skip","o",IF(OR(FV5="",GF5=""),"",IF(AND(FV5="Dwn",GF5="Short"),"s",IF(AND(FV5="Up",GF5="Long"),"s",IF(AND(FV5="SW",GF5="Long"),"s","o")))))) -> o | I5: 61.42 | J5: 64.99 | K5: =IF(J5="","",(J5-I5)/I5) -> 0.058124389 | L5: =IF(OR($GI5="",J5=""),"",IF($GF5="Long",(($J5*$GI5)-$GH5),($GH5-($J5*$GI5)))) -> 23.249756 | M5: =IF(L5="","",IF(HG5="","",HG5-L5)) | N5: =IF(AND($FV5="Up",$GA5="Long"),$EH5,"") -> 23.249756 | O5: =IF($J5="",#N/A,SUM($N$4:N5)) -> 23.249756 | P5: =IF(AND($FV5="Dwn",$GA5="Short"),$EH5,"") | Q5: =IF($J5="",#N/A,SUM($P$4:P5)) -> 29.496534 | R5: =IF(AND($FV5="SW",$GA5="Long"),$EH5,"") | S5: =IF($J5="",#N/A,SUM($R$4:R5)) -> 0 | T5: =IF(AND($FV5="Up",$GA5="Long"),$FP5,"") -> 0.96873982 | U5: =IF($J5="",#N/A,SUM($T$4:T5)) -> 0.96873982 | V5: =IF(AND($FV5="Dwn",$GA5="Short"),$FP5,"") | W5: =IF($J5="",#N/A,SUM($V$4:V5)) -> 1.2290223 | X5: =IF(AND($FV5="SW",$GA5="Long"),$FP5,"") | Y5: =IF($J5="",#N/A,SUM($X$4:X5)) -> 0 | Z5: =IF(AND($FV5="Up",$GA5="Long",$E5=Z$2),$FP5,"") | AA5: =IF($J5="",#N/A,SUM(Z$4:Z5)) -> 0 | AB5: =IF(AND($FV5="Dwn",$GA5="Short",$E5=Z$2),$FP5,"") | AC5: =IF($J5="",#N/A,SUM(AB$4:AB5)) -> 0 | AD5: =IF(AND($FV5="SW",$GA5="Long",$E5=Z$2),$FP5,"") | AE5: =IF($J5="",#N/A,SUM(AD$4:AD5)) -> 0 | AF5: =IF($J5="",#N/A,SUM(AD$4:AD5,AB$4:AB5,Z$4:Z5)) -> 0 | AG5: =IF(AND($FV5="Up",$GA5="Long",$E5=AG$2),$FP5,"") | AH5: =IF($J5="",#N/A,SUM(AG$4:AG5)) -> 0 | AI5: =IF(AND($FV5="Dwn",$GA5="Short",$E5=AG$2),$FP5,"") | AJ5: =IF($J5="",#N/A,SUM(AI$4:AI5)) -> 0 | AK5: =IF(AND($FV5="SW",$GA5="Long",$E5=AG$2),$FP5,"") | AL5: =IF($J5="",#N/A,SUM(AK$4:AK5)) -> 0 | AM5: =IF($J5="",#N/A,SUM(AK$4:AK5,AI$4:AI5,AG$4:AG5)) -> 0 | AN5: =IF(AND($FV5="Up",$GA5="Long",$E5=AN$2),$FP5,"") | AO5: =IF($J5="",#N/A,SUM(AN$4:AN5)) -> 0 | AP5: =IF(AND($FV5="Dwn",$GA5="Short",$E5=AN$2),$FP5,"") | AQ5: =IF($J5="",#N/A,SUM(AP$4:AP5)) -> 0 | AR5: =IF(AND($FV5="SW",$GA5="Long",$E5=AN$2),$FP5,"") | AS5: =IF($J5="",#N/A,SUM(AR$4:AR5)) -> 0 | AT5: =IF($J5="",#N/A,SUM(AR$4:AR5,AP$4:AP5,AN$4:AN5)) -> 0 | AU5: =IF(AND($FV5="Up",$GA5="Long",$E5=AU$2),$FP5,"") | AV5: =IF($J5="",#N/A,SUM(AU$4:AU5)) -> 0 | AW5: =IF(AND($FV5="Dwn",$GA5="Short",$E5=AU$2),$FP5,"") | AX5: =IF($J5="",#N/A,SUM(AW$4:AW5)) -> 1.2290223 | AY5: =IF(AND($FV5="SW",$GA5="Long",$E5=AU$2),$FP5,"") | AZ5: =IF($J5="",#N/A,SUM(AY$4:AY5)) -> 0 | BA5: =IF($J5="",#N/A,SUM(AY$4:AY5,AW$4:AW5,AU$4:AU5)) -> 1.2290223 | BB5: =IF(AND($FV5="Up",$GA5="Long",$E5=BB$2),$FP5,"") | BC5: =IF($J5="",#N/A,SUM(BB$4:BB5)) -> 0 | BD5: =IF(AND($FV5="Dwn",$GA5="Short",$E5=BB$2),$FP5,"") | BE5: =IF($J5="",#N/A,SUM(BD$4:BD5)) -> 0 | BF5: =IF(AND($FV5="SW",$GA5="Long",$E5=BB$2),$FP5,"") | BG5: =IF($J5="",#N/A,SUM(BF$4:BF5)) -> 0 | BH5: =IF($J5="",#N/A,SUM(BF$4:BF5,BD$4:BD5,BB$4:BB5)) -> 0 | BI5: =IF(AND($FV5="Up",$GA5="Long",$E5=BI$2),$FP5,"") | BJ5: =IF($J5="",#N/A,SUM(BI$4:BI5)) -> 0 | BK5: =IF(AND($FV5="Dwn",$GA5="Short",$E5=BI$2),$FP5,"") | BL5: =IF($J5="",#N/A,SUM(BK$4:BK5)) -> 0 | BM5: =IF(AND($FV5="SW",$GA5="Long",$E5=BI$2),$FP5,"") | BN5: =IF($J5="",#N/A,SUM(BM$4:BM5)) -> 0 | BO5: =IF($J5="",#N/A,SUM(BM$4:BM5,BK$4:BK5,BI$4:BI5)) -> 0 | BP5: =IF(AND($FV5="Up",$GA5="Long",$E5=BP$2),$FP5,"") -> 0.96873982 | BQ5: =IF($J5="",#N/A,SUM(BP$4:BP5)) -> 0.96873982 | BR5: =IF(AND($FV5="Dwn",$GA5="Short",$E5=BP$2),$FP5,"") | BS5: =IF($J5="",#N/A,SUM(BR$4:BR5)) -> 0 | BT5: =IF(AND($FV5="SW",$GA5="Long",$E5=BP$2),$FP5,"") | BU5: =IF($J5="",#N/A,SUM(BT$4:BT5)) -> 0 | BV5: =IF($J5="",#N/A,SUM(BT$4:BT5,BR$4:BR5,BP$4:BP5)) -> 0.96873982 | BW5: =IF(AND($FV5="Up",$GA5="Long",$E5=BW$2),$FP5,"") | BX5: =IF($J5="",#N/A,SUM(BW$4:BW5)) -> 0 | BY5: =IF(AND($FV5="Dwn",$GA5="Short",$E5=BW$2),$FP5,"") | BZ5: =IF($J5="",#N/A,SUM(BY$4:BY5)) -> 0 | CA5: =IF(AND($FV5="SW",$GA5="Long",$E5=BW$2),$FP5,"") | CB5: =IF($J5="",#N/A,SUM(CA$4:CA5)) -> 0 | CC5: =IF($J5="",#N/A,SUM(CA$4:CA5,BY$4:BY5,BW$4:BW5)) -> 0 | CD5: =IF(AND($FV5="Up",$GA5="Long",$E5=CD$2),$FP5,"") | CE5: =IF($J5="",#N/A,SUM(CD$4:CD5)) -> 0 | CF5: =IF(AND($FV5="Dwn",$GA5="Short",$E5=CD$2),$FP5,"") | CG5: =IF($J5="",#N/A,SUM(CF$4:CF5)) -> 0 | CH5: =IF(AND($FV5="SW",$GA5="Long",$E5=CD$2),$FP5,"") | CI5: =IF($J5="",#N/A,SUM(CH$4:CH5)) -> 0 | CJ5: =IF($J5="",#N/A,SUM(CH$4:CH5,CF$4:CF5,CD$4:CD5)) -> 0 | CK5: =IF(AND($FV5="Up",$GA5="Long",$E5=CK$2),$FP5,"") | CL5: =IF($J5="",#N/A,SUM(CK$4:CK5)) -> 0 | CM5: =IF(AND($FV5="Dwn",$GA5="Short",$E5=CK$2),$FP5,"") | CN5: =IF($J5="",#N/A,SUM(CM$4:CM5)) -> 0 | CO5: =IF(AND($FV5="SW",$GA5="Long",$E5=CK$2),$FP5,"") | CP5: =IF($J5="",#N/A,SUM(CO$4:CO5)) -> 0 | CQ5: =IF($J5="",#N/A,SUM(CO$4:CO5,CM$4:CM5,CK$4:CK5)) -> 0 | CR5: =IF(AND($FV5="Up",$GA5="Long",$E5=CR$2),$FP5,"") | CS5: =IF($J5="",#N/A,SUM(CR$4:CR5)) -> 0 | CT5: =IF(AND($FV5="Dwn",$GA5="Short",$E5=CR$2),$FP5,"") | CU5: =IF($J5="",#N/A,SUM(CT$4:CT5)) -> 0 | CV5: =IF(AND($FV5="SW",$GA5="Long",$E5=CR$2),$FP5,"") | CW5: =IF($J5="",#N/A,SUM(CV$4:CV5)) -> 0 | CX5: =IF($J5="",#N/A,SUM(CV$4:CV5,CT$4:CT5,CR$4:CR5)) -> 0 | CY5: =IF(AND($FV5="Up",$GA5="Long",$E5=CY$2),$FP5,"") | CZ5: =IF($J5="",#N/A,SUM(CY$4:CY5)) -> 0 | DA5: =IF(AND($FV5="Dwn",$GA5="Short",$E5=CY$2),$FP5,"") | DB5: =IF($J5="",#N/A,SUM(DA$4:DA5)) -> 0 | DC5: =IF(AND($FV5="SW",$GA5="Long",$E5=CY$2),$FP5,"") | DD5: =IF($J5="",#N/A,SUM(DC$4:DC5)) -> 0 | DE5: =IF($J5="",#N/A,SUM(DC$4:DC5,DA$4:DA5,CY$4:CY5)) -> 0 | DF5: =IF(AND($FV5="Up",$GA5="Long",$E5=DF$2),$FP5,"") | DG5: =IF($J5="",#N/A,SUM(DF$4:DF5)) -> 0 | DH5: =IF(AND($FV5="Dwn",$GA5="Short",$E5=DF$2),$FP5,"") | DI5: =IF($J5="",#N/A,SUM(DH$4:DH5)) -> 0 | DJ5: =IF(AND($FV5="SW",$GA5="Long",$E5=DF$2),$FP5,"") | DK5: =IF($J5="",#N/A,SUM(DJ$4:DJ5)) -> 0 | DL5: =IF($J5="",#N/A,SUM(DJ$4:DJ5,DH$4:DH5,DF$4:DF5)) -> 0 | DM5: =IF(AND($FV5="Up",$GA5="Long",$E5=DM$2),$FP5,"") | DN5: =IF($J5="",#N/A,SUM(DM$4:DM5)) -> 0 | DO5: =IF(AND($FV5="Dwn",$GA5="Short",$E5=DM$2),$FP5,"") | DP5: =IF($J5="",#N/A,SUM(DO$4:DO5)) -> 0 | DQ5: =IF(AND($FV5="SW",$GA5="Long",$E5=DM$2),$FP5,"") | DR5: =IF($J5="",#N/A,SUM(DQ$4:DQ5)) -> 0 | DS5: =IF($J5="",#N/A,SUM(DQ$4:DQ5,DO$4:DO5,DM$4:DM5)) -> 0 | DT5: =IF(AND($FV5="Up",$GA5="Long",$E5=DT$2),$FP5,"") | DU5: =IF($J5="",#N/A,SUM(DT$4:DT5)) -> 0 | DV5: =IF(AND($FV5="Dwn",$GA5="Short",$E5=DT$2),$FP5,"") | DW5: =IF($J5="",#N/A,SUM(DV$4:DV5)) -> 0 | DX5: =IF(AND($FV5="SW",$GA5="Long",$E5=DT$2),$FP5,"") | DY5: =IF($J5="",#N/A,SUM(DX$4:DX5)) -> 0 | DZ5: =IF($J5="",#N/A,SUM(DX$4:DX5,DV$4:DV5,DT$4:DT5)) -> 0 | EA5: =IF(AND($FV5="Up",$GA5="Long",$E5=EA$2),$FP5,"") | EB5: =IF($J5="",#N/A,SUM(EA$4:EA5)) -> 0 | EC5: =IF(AND($FV5="Dwn",$GA5="Short",$E5=EA$2),$FP5,"") | ED5: =IF($J5="",#N/A,SUM(EC$4:EC5)) -> 0 | EE5: =IF(AND($FV5="SW",$GA5="Long",$E5=EA$2),$FP5,"") | EF5: =IF($J5="",#N/A,SUM(EE$4:EE5)) -> 0 | EG5: =IF($J5="",#N/A,SUM(EE$4:EE5,EC$4:EC5,EA$4:EA5)) -> 0 | EH5: =IF(OR($GI5="",L5=""),"",IF($GA5="Long",(($J5*$GI5)-$GH5),($GH5-($J5*$GI5)))) -> 23.249756 | EI5: =IF(EH5="",#N/A,SUM($EH$4:EH5)) -> 52.74629 | EJ5: =IF(GZ5="","",IF(OR($GI5="",AM5=""),"",IF($GA5="Long",(($GZ5*$GI5)-$GH5),($GH5-($GZ5*$GI5))))) -> 36.014328 | EK5: =IF($GZ5="",#N/A,SUM(EJ$4:EJ5)) -> 104.36529 | EL5: =IF(J5="","",IF(D5="Y",FP5,"")) -> 0.96873982 | EM5: =IF(EL5="",NA(),SUM($EL$4:EL5)) -> 2.1977621 | EN5: =IF(AND($FV5="Up",$GA5="Long",$D5="Y"),$EL5,"") -> 0.96873982 | EO5: =IF(EN5="",NA(),SUM($EN$4:EN5)) -> 0.96873982 | EP5: =IF(AND($FV5="SW",$GA5="Long",$D5="Y"),$EL5,"") | EQ5: =IF(EP5="",NA(),SUM($EP$4:EP5)) -> #N/A | ER5: =IF(AND($FV5="Dwn",$GA5="Short",$D5="Y"),$EL5,"") | ES5: =IF(ER5="",NA(),SUM($ER$4:ER5)) -> #N/A | ET5: =IF($J5="","",IF($D5="N",$FP5,"")) | EU5: =IF(ET5="",NA(),SUM($ET$4:ET5)) -> #N/A | EV5: =IF(AND($FV5="Up",$GA5="Long",$D5="N"),$ET5,"") | EW5: =IF(EV5="",NA(),SUM($EV$4:EV5)) -> #N/A | EX5: =IF(AND($FV5="SW",$GA5="Long",$D5="N"),$ET5,"") | EY5: =IF(EX5="",NA(),SUM($EX$4:EX5)) -> #N/A | EZ5: =IF(AND($FV5="Dwn",$GA5="Short",$D5="N"),$ET5,"") | FA5: =IF(EZ5="",NA(),SUM($EZ$4:EZ5)) -> #N/A | FB5: =IF($GZ5="","",IF(AND($FV5="Dwn",$K5<0),$FN5-FP5,"")) | FC5: =IF($FB5="",#N/A,SUM(FB$4:$FB5)) -> #N/A | FD5: =IF($GZ5="","",IF(AND($FV5="Dwn",$K5>0),$FN5-$FP5,"")) | FE5: =IF($FD5="",#N/A,SUM($FD$4:FD5)) -> #N/A | FF5: =IF($GZ5="","",IF(AND($FV5="Up",$K5>0),$FN5-$FP5,"")) -> 0.53185716 | FG5: =IF($FF5="",#N/A,SUM($FF$4:FF5)) -> 0.53185716 | FH5: =IF($GZ5="","",IF(AND($FV5="Up",$K5<0),$FN5-$FP5,"")) | FI5: =IF($FH5="",#N/A,SUM($FH$4:FH5)) -> #N/A | FJ5: =IF($GZ5="","",IF(AND($FV5="SW",$K5>0),$FN5-$FP5,"")) | FK5: =IF($FJ5="",#N/A,SUM($FJ$4:FJ5)) -> #N/A | FL5: =IF($GZ5="","",IF(AND($FV5="SW",$K5<0),$FN5-$FP5,"")) | FM5: =IF($FL5="",#N/A,SUM($FL$4:FL5)) -> #N/A | FN5: =IF(OR($GI5="",$GZ5=""),"",IF($GA5="Long",(($GZ5*$GI5)-$GH5)/($GH5*0.06),($GH5-($GZ5*$GI5))/($GH5*0.06))) -> 1.500597 | FO5: =IF($FN5="",#N/A,SUM(FN$4:$FN5)) -> 4.3485539 | FP5: =IF(OR($GI5="",L5=""),"",IF($GA5="Long",(($J5*$GI5)-$GH5)/(GH5*0.06),($GH5-($J5*$GI5))/(GH5*0.06))) -> 0.96873982 | FQ5: =IF($EH5="",#N/A,SUM($FP$4:FP5)) -> 2.1977621 | FU5: #N/A | FV5: =IF(FW5="Down","Dwn",IF(FW5="Up","Up",IF(AND(FW5="",K5=""),"",IF(AND(K5<0,FW5="Yes"),"Dwn",IF(AND(K5>0,FW5="Yes"),"Up",IF(AND(K5<0,FW5="No"),"Up",IF(AND(K5>0,FW5="No"),"Dwn",IF(FW5="NA","SW","err")))))))) -> Up | FW5: Yes | FX5: =IF(K5="","",IF(AND(K5>0,FW5="Yes"),1,"")) -> 1 | FY5: =IF(K5="","",IF(AND($K5>0,$FW5="No"),1,"")) | FZ5: =IF(K5="","",IF(AND($K5>0,$FW5="NA"),1,"")) | GA5: =IF(FV5="Dwn","Short","Long") -> Long | GB5: =IF(K5="","",IF(AND($K5<0,$FW5="Yes"),1,"")) | GC5: =IF(K5="","",IF(AND($K5<0,$FW5="No"),1,"")) | GD5: =IF(K5="","",IF(AND($K5<0,$FW5="NA"),1,"")) | GE5: =I5 -> 61.42 | GF5: Long | GG5: =400/I5 -> 6.5125366 | GH5: =IF(GG5="","",GE5*GG5) -> 400 | GI5: =GG5 -> 6.5125366 | GJ5: =J5 -> 64.99 | GK5: =IF($GI5="","",IF($GF5="Long",(($GJ5*$GI5)-$GH5),($GH5-($GJ5*$GI5)))) -> 23.249756 | GL5: =IF($GI5="","",IF($GF5="Long",(($GZ5*$GI5)-$GH5),($GH5-($GZ5*$GI5)))) -> 36.014328 | GM5: =IF(AND($FV5="SW",$GA5="Long"),$FN5,"") | GN5: =IF($GZ5="",#N/A,SUM(GM$4:GM5)) -> 0 | GO5: =IF(AND($FV5="UP",$GA5="Long"),$FN5,"") -> 1.500597 | GP5: =IF($GZ5="",#N/A,SUM(GO$4:GO5)) -> 1.500597 | GQ5: =IF(AND($FV5="Dwn",$GA5="Short"),$FN5,"") | GR5: =IF($GZ5="",#N/A,SUM(GQ$4:GQ5)) -> 2.847957 | GS5: =IF(AND(FV5="SW",GA5="Long"),$EJ5,"") | GT5: =IF($GZ5="",#N/A,SUM(GS$4:GS5)) -> 0 | GU5: =IF(AND(FV5="UP",GA5="Long"),$EJ5,"") -> 36.014328 | GV5: =IF($GZ5="",#N/A,SUM(GU$4:GU5)) -> 36.014328 | GW5: =IF(AND(FV5="Dwn",GA5="Short"),$EJ5,"") | GX5: =IF($GZ5="",#N/A,SUM(GW$4:GW5)) -> 68.350967 | GY5: =IF(EJ5="",#N/A,SUM($EJ$4:EJ5)) -> 104.36529 | GZ5: 66.95 | HA5: =IF(OR(GL5="",GZ5=""),"",GL5-EH5) -> 12.764572 | HB5: Skip | HC5: =IFERROR(VLOOKUP(E5,Expectancy!$P$4:$S$19,1+C5,FALSE),"") -> -0.041762477 | HD5: =IF(AND(HB5="MOC",GZ5=""),"",IF(GI5="","",IF(HB5="Skip","",IF(HG5=0,0,HG5/(GH5*0.06))))) | HE5: =IF(HD5="",#N/A,SUM($HD$4:HD5)) -> #N/A | HF5: =IF(HD5="",#N/A,IF(HB5="Skip",#N/A,SUM($HG$4:HG5))) -> #N/A | HG5: =IF(HB5="","",IF(HB5="Skip","",IF(OR(HB5="open",HB5="Other"),GK5,IF(HB5="MOC",GL5,"Err")))) | HH5: =IF(OR($GI5="",$L5=""),"",IF($GA5="Long",(($GZ5*$GI5)-$GH5)/($GH5*0.06),($GH5-($GZ5*$GI5))/($GH5*0.06))) -> 1.500597
A6: WBA | B6: on 1/10/25, 7:00 AM Before Market Eas | C6: =IF(FV6="Dwn",2,IF(FV6="Up",1,IF(FV6="SW",3,"x"))) -> 3 | D6: =_xlfn.XLOOKUP(A6,[1]SP500!$A$2:$A$502,[1]SP500!$D$2:$D$502,"N") -> Y | E6: =_xlfn.XLOOKUP(A6,[1]SP500!$A$2:$A$655,[1]SP500!$B$2:$B$655) -> XLP | F6: 45667 | G6: =IF(ISNUMBER(FIND("After",B6,1)),"AMC",IF(ISNUMBER(FIND("Before",B6,1)),"BMO","err")) -> BMO | H6: =IF(HB6="other","o",IF(HB6="Skip","o",IF(OR(FV6="",GF6=""),"",IF(AND(FV6="Dwn",GF6="Short"),"s",IF(AND(FV6="Up",GF6="Long"),"s",IF(AND(FV6="SW",GF6="Long"),"s","o")))))) -> o | I6: 9.22 | J6: 10.6 | K6: =IF(J6="","",(J6-I6)/I6) -> 0.14967462 | L6: =IF(OR($GI6="",J6=""),"",IF($GF6="Long",(($J6*$GI6)-$GH6),($GH6-($J6*$GI6)))) -> 59.869848 | M6: =IF(L6="","",IF(HG6="","",HG6-L6)) | N6: =IF(AND($FV6="Up",$GA6="Long"),$EH6,"") | O6: =IF($J6="",#N/A,SUM($N$4:N6)) -> 23.249756 | P6: =IF(AND($FV6="Dwn",$GA6="Short"),$EH6,"") | Q6: =IF($J6="",#N/A,SUM($P$4:P6)) -> 29.496534 | R6: =IF(AND($FV6="SW",$GA6="Long"),$EH6,"") -> 59.869848 | S6: =IF($J6="",#N/A,SUM($R$4:R6)) -> 59.869848 | T6: =IF(AND($FV6="Up",$GA6="Long"),$FP6,"") | U6: =IF($J6="",#N/A,SUM($T$4:T6)) -> 0.96873982 | V6: =IF(AND($FV6="Dwn",$GA6="Short"),$FP6,"") | W6: =IF($J6="",#N/A,SUM($V$4:V6)) -> 1.2290223 | X6: =IF(AND($FV6="SW",$GA6="Long"),$FP6,"") -> 2.494577 | Y6: =IF($J6="",#N/A,SUM($X$4:X6)) -> 2.494577 | Z6: =IF(AND($FV6="Up",$GA6="Long",$E6=Z$2),$FP6,"") | AA6: =IF($J6="",#N/A,SUM(Z$4:Z6)) -> 0 | AB6: =IF(AND($FV6="Dwn",$GA6="Short",$E6=Z$2),$FP6,"") | AC6: =IF($J6="",#N/A,SUM(AB$4:AB6)) -> 0 | AD6: =IF(AND($FV6="SW",$GA6="Long",$E6=Z$2),$FP6,"") | AE6: =IF($J6="",#N/A,SUM(AD$4:AD6)) -> 0 | AF6: =IF($J6="",#N/A,SUM(AD$4:AD6,AB$4:AB6,Z$4:Z6)) -> 0 | AG6: =IF(AND($FV6="Up",$GA6="Long",$E6=AG$2),$FP6,"") | AH6: =IF($J6="",#N/A,SUM(AG$4:AG6)) -> 0 | AI6: =IF(AND($FV6="Dwn",$GA6="Short",$E6=AG$2),$FP6,"") | AJ6: =IF($J6="",#N/A,SUM(AI$4:AI6)) -> 0 | AK6: =IF(AND($FV6="SW",$GA6="Long",$E6=AG$2),$FP6,"") | AL6: =IF($J6="",#N/A,SUM(AK$4:AK6)) -> 0 | AM6: =IF($J6="",#N/A,SUM(AK$4:AK6,AI$4:AI6,AG$4:AG6)) -> 0 | AN6: =IF(AND($FV6="Up",$GA6="Long",$E6=AN$2),$FP6,"") | AO6: =IF($J6="",#N/A,SUM(AN$4:AN6)) -> 0 | AP6: =IF(AND($FV6="Dwn",$GA6="Short",$E6=AN$2),$FP6,"") | AQ6: =IF($J6="",#N/A,SUM(AP$4:AP6)) -> 0 | AR6: =IF(AND($FV6="SW",$GA6="Long",$E6=AN$2),$FP6,"") | AS6: =IF($J6="",#N/A,SUM(AR$4:AR6)) -> 0 | AT6: =IF($J6="",#N/A,SUM(AR$4:AR6,AP$4:AP6,AN$4:AN6)) -> 0 | AU6: =IF(AND($FV6="Up",$GA6="Long",$E6=AU$2),$FP6,"") | AV6: =IF($J6="",#N/A,SUM(AU$4:AU6)) -> 0 | AW6: =IF(AND($FV6="Dwn",$GA6="Short",$E6=AU$2),$FP6,"") | AX6: =IF($J6="",#N/A,SUM(AW$4:AW6)) -> 1.2290223 | AY6: =IF(AND($FV6="SW",$GA6="Long",$E6=AU$2),$FP6,"") -> 2.494577 | AZ6: =IF($J6="",#N/A,SUM(AY$4:AY6)) -> 2.494577 | BA6: =IF($J6="",#N/A,SUM(AY$4:AY6,AW$4:AW6,AU$4:AU6)) -> 3.7235993 | BB6: =IF(AND($FV6="Up",$GA6="Long",$E6=BB$2),$FP6,"") | BC6: =IF($J6="",#N/A,SUM(BB$4:BB6)) -> 0 | BD6: =IF(AND($FV6="Dwn",$GA6="Short",$E6=BB$2),$FP6,"") | BE6: =IF($J6="",#N/A,SUM(BD$4:BD6)) -> 0 | BF6: =IF(AND($FV6="SW",$GA6="Long",$E6=BB$2),$FP6,"") | BG6: =IF($J6="",#N/A,SUM(BF$4:BF6)) -> 0 | BH6: =IF($J6="",#N/A,SUM(BF$4:BF6,BD$4:BD6,BB$4:BB6)) -> 0 | BI6: =IF(AND($FV6="Up",$GA6="Long",$E6=BI$2),$FP6,"") | BJ6: =IF($J6="",#N/A,SUM(BI$4:BI6)) -> 0 | BK6: =IF(AND($FV6="Dwn",$GA6="Short",$E6=BI$2),$FP6,"") | BL6: =IF($J6="",#N/A,SUM(BK$4:BK6)) -> 0 | BM6: =IF(AND($FV6="SW",$GA6="Long",$E6=BI$2),$FP6,"") | BN6: =IF($J6="",#N/A,SUM(BM$4:BM6)) -> 0 | BO6: =IF($J6="",#N/A,SUM(BM$4:BM6,BK$4:BK6,BI$4:BI6)) -> 0 | BP6: =IF(AND($FV6="Up",$GA6="Long",$E6=BP$2),$FP6,"") | BQ6: =IF($J6="",#N/A,SUM(BP$4:BP6)) -> 0.96873982 | BR6: =IF(AND($FV6="Dwn",$GA6="Short",$E6=BP$2),$FP6,"") | BS6: =IF($J6="",#N/A,SUM(BR$4:BR6)) -> 0 | BT6: =IF(AND($FV6="SW",$GA6="Long",$E6=BP$2),$FP6,"") | BU6: =IF($J6="",#N/A,SUM(BT$4:BT6)) -> 0 | BV6: =IF($J6="",#N/A,SUM(BT$4:BT6,BR$4:BR6,BP$4:BP6)) -> 0.96873982 | BW6: =IF(AND($FV6="Up",$GA6="Long",$E6=BW$2),$FP6,"") | BX6: =IF($J6="",#N/A,SUM(BW$4:BW6)) -> 0 | BY6: =IF(AND($FV6="Dwn",$GA6="Short",$E6=BW$2),$FP6,"") | BZ6: =IF($J6="",#N/A,SUM(BY$4:BY6)) -> 0 | CA6: =IF(AND($FV6="SW",$GA6="Long",$E6=BW$2),$FP6,"") | CB6: =IF($J6="",#N/A,SUM(CA$4:CA6)) -> 0 | CC6: =IF($J6="",#N/A,SUM(CA$4:CA6,BY$4:BY6,BW$4:BW6)) -> 0 | CD6: =IF(AND($FV6="Up",$GA6="Long",$E6=CD$2),$FP6,"") | CE6: =IF($J6="",#N/A,SUM(CD$4:CD6)) -> 0 | CF6: =IF(AND($FV6="Dwn",$GA6="Short",$E6=CD$2),$FP6,"") | CG6: =IF($J6="",#N/A,SUM(CF$4:CF6)) -> 0 | CH6: =IF(AND($FV6="SW",$GA6="Long",$E6=CD$2),$FP6,"") | CI6: =IF($J6="",#N/A,SUM(CH$4:CH6)) -> 0 | CJ6: =IF($J6="",#N/A,SUM(CH$4:CH6,CF$4:CF6,CD$4:CD6)) -> 0 | CK6: =IF(AND($FV6="Up",$GA6="Long",$E6=CK$2),$FP6,"") | CL6: =IF($J6="",#N/A,SUM(CK$4:CK6)) -> 0 | CM6: =IF(AND($FV6="Dwn",$GA6="Short",$E6=CK$2),$FP6,"") | CN6: =IF($J6="",#N/A,SUM(CM$4:CM6)) -> 0 | CO6: =IF(AND($FV6="SW",$GA6="Long",$E6=CK$2),$FP6,"") | CP6: =IF($J6="",#N/A,SUM(CO$4:CO6)) -> 0 | CQ6: =IF($J6="",#N/A,SUM(CO$4:CO6,CM$4:CM6,CK$4:CK6)) -> 0 | CR6: =IF(AND($FV6="Up",$GA6="Long",$E6=CR$2),$FP6,"") | CS6: =IF($J6="",#N/A,SUM(CR$4:CR6)) -> 0 | CT6: =IF(AND($FV6="Dwn",$GA6="Short",$E6=CR$2),$FP6,"") | CU6: =IF($J6="",#N/A,SUM(CT$4:CT6)) -> 0 | CV6: =IF(AND($FV6="SW",$GA6="Long",$E6=CR$2),$FP6,"") | CW6: =IF($J6="",#N/A,SUM(CV$4:CV6)) -> 0 | CX6: =IF($J6="",#N/A,SUM(CV$4:CV6,CT$4:CT6,CR$4:CR6)) -> 0 | CY6: =IF(AND($FV6="Up",$GA6="Long",$E6=CY$2),$FP6,"") | CZ6: =IF($J6="",#N/A,SUM(CY$4:CY6)) -> 0 | DA6: =IF(AND($FV6="Dwn",$GA6="Short",$E6=CY$2),$FP6,"") | DB6: =IF($J6="",#N/A,SUM(DA$4:DA6)) -> 0 | DC6: =IF(AND($FV6="SW",$GA6="Long",$E6=CY$2),$FP6,"") | DD6: =IF($J6="",#N/A,SUM(DC$4:DC6)) -> 0 | DE6: =IF($J6="",#N/A,SUM(DC$4:DC6,DA$4:DA6,CY$4:CY6)) -> 0 | DF6: =IF(AND($FV6="Up",$GA6="Long",$E6=DF$2),$FP6,"") | DG6: =IF($J6="",#N/A,SUM(DF$4:DF6)) -> 0 | DH6: =IF(AND($FV6="Dwn",$GA6="Short",$E6=DF$2),$FP6,"") | DI6: =IF($J6="",#N/A,SUM(DH$4:DH6)) -> 0 | DJ6: =IF(AND($FV6="SW",$GA6="Long",$E6=DF$2),$FP6,"") | DK6: =IF($J6="",#N/A,SUM(DJ$4:DJ6)) -> 0 | DL6: =IF($J6="",#N/A,SUM(DJ$4:DJ6,DH$4:DH6,DF$4:DF6)) -> 0 | DM6: =IF(AND($FV6="Up",$GA6="Long",$E6=DM$2),$FP6,"") | DN6: =IF($J6="",#N/A,SUM(DM$4:DM6)) -> 0 | DO6: =IF(AND($FV6="Dwn",$GA6="Short",$E6=DM$2),$FP6,"") | DP6: =IF($J6="",#N/A,SUM(DO$4:DO6)) -> 0 | DQ6: =IF(AND($FV6="SW",$GA6="Long",$E6=DM$2),$FP6,"") | DR6: =IF($J6="",#N/A,SUM(DQ$4:DQ6)) -> 0 | DS6: =IF($J6="",#N/A,SUM(DQ$4:DQ6,DO$4:DO6,DM$4:DM6)) -> 0 | DT6: =IF(AND($FV6="Up",$GA6="Long",$E6=DT$2),$FP6,"") | DU6: =IF($J6="",#N/A,SUM(DT$4:DT6)) -> 0 | DV6: =IF(AND($FV6="Dwn",$GA6="Short",$E6=DT$2),$FP6,"") | DW6: =IF($J6="",#N/A,SUM(DV$4:DV6)) -> 0 | DX6: =IF(AND($FV6="SW",$GA6="Long",$E6=DT$2),$FP6,"") | DY6: =IF($J6="",#N/A,SUM(DX$4:DX6)) -> 0 | DZ6: =IF($J6="",#N/A,SUM(DX$4:DX6,DV$4:DV6,DT$4:DT6)) -> 0 | EA6: =IF(AND($FV6="Up",$GA6="Long",$E6=EA$2),$FP6,"") | EB6: =IF($J6="",#N/A,SUM(EA$4:EA6)) -> 0 | EC6: =IF(AND($FV6="Dwn",$GA6="Short",$E6=EA$2),$FP6,"") | ED6: =IF($J6="",#N/A,SUM(EC$4:EC6)) -> 0 | EE6: =IF(AND($FV6="SW",$GA6="Long",$E6=EA$2),$FP6,"") | EF6: =IF($J6="",#N/A,SUM(EE$4:EE6)) -> 0 | EG6: =IF($J6="",#N/A,SUM(EE$4:EE6,EC$4:EC6,EA$4:EA6)) -> 0 | EH6: =IF(OR($GI6="",L6=""),"",IF($GA6="Long",(($J6*$GI6)-$GH6),($GH6-($J6*$GI6)))) -> 59.869848 | EI6: =IF(EH6="",#N/A,SUM($EH$4:EH6)) -> 112.61614 | EJ6: =IF(GZ6="","",IF(OR($GI6="",AM6=""),"",IF($GA6="Long",(($GZ6*$GI6)-$GH6),($GH6-($GZ6*$GI6))))) -> 110.19523 | EK6: =IF($GZ6="",#N/A,SUM(EJ$4:EJ6)) -> 214.56052 | EL6: =IF(J6="","",IF(D6="Y",FP6,"")) -> 2.494577 | EM6: =IF(EL6="",NA(),SUM($EL$4:EL6)) -> 4.6923391 | EN6: =IF(AND($FV6="Up",$GA6="Long",$D6="Y"),$EL6,"") | EO6: =IF(EN6="",NA(),SUM($EN$4:EN6)) -> #N/A | EP6: =IF(AND($FV6="SW",$GA6="Long",$D6="Y"),$EL6,"") -> 2.494577 | EQ6: =IF(EP6="",NA(),SUM($EP$4:EP6)) -> 2.494577 | ER6: =IF(AND($FV6="Dwn",$GA6="Short",$D6="Y"),$EL6,"") | ES6: =IF(ER6="",NA(),SUM($ER$4:ER6)) -> #N/A | ET6: =IF($J6="","",IF($D6="N",$FP6,"")) | EU6: =IF(ET6="",NA(),SUM($ET$4:ET6)) -> #N/A | EV6: =IF(AND($FV6="Up",$GA6="Long",$D6="N"),$ET6,"") | EW6: =IF(EV6="",NA(),SUM($EV$4:EV6)) -> #N/A | EX6: =IF(AND($FV6="SW",$GA6="Long",$D6="N"),$ET6,"") | EY6: =IF(EX6="",NA(),SUM($EX$4:EX6)) -> #N/A | EZ6: =IF(AND($FV6="Dwn",$GA6="Short",$D6="N"),$ET6,"") | FA6: =IF(EZ6="",NA(),SUM($EZ$4:EZ6)) -> #N/A | FB6: =IF($GZ6="","",IF(AND($FV6="Dwn",$K6<0),$FN6-FP6,"")) | FC6: =IF($FB6="",#N/A,SUM(FB$4:$FB6)) -> #N/A | FD6: =IF($GZ6="","",IF(AND($FV6="Dwn",$K6>0),$FN6-$FP6,"")) | FE6: =IF($FD6="",#N/A,SUM($FD$4:FD6)) -> #N/A | FF6: =IF($GZ6="","",IF(AND($FV6="Up",$K6>0),$FN6-$FP6,"")) | FG6: =IF($FF6="",#N/A,SUM($FF$4:FF6)) -> #N/A | FH6: =IF($GZ6="","",IF(AND($FV6="Up",$K6<0),$FN6-$FP6,"")) | FI6: =IF($FH6="",#N/A,SUM($FH$4:FH6)) -> #N/A | FJ6: =IF($GZ6="","",IF(AND($FV6="SW",$K6>0),$FN6-$FP6,"")) -> 2.0968908 | FK6: =IF($FJ6="",#N/A,SUM($FJ$4:FJ6)) -> 2.0968908 | FL6: =IF($GZ6="","",IF(AND($FV6="SW",$K6<0),$FN6-$FP6,"")) | FM6: =IF($FL6="",#N/A,SUM($FL$4:FL6)) -> #N/A | FN6: =IF(OR($GI6="",$GZ6=""),"",IF($GA6="Long",(($GZ6*$GI6)-$GH6)/($GH6*0.06),($GH6-($GZ6*$GI6))/($GH6*0.06))) -> 4.5914678 | FO6: =IF($FN6="",#N/A,SUM(FN$4:$FN6)) -> 8.9400218 | FP6: =IF(OR($GI6="",L6=""),"",IF($GA6="Long",(($J6*$GI6)-$GH6)/(GH6*0.06),($GH6-($J6*$GI6))/(GH6*0.06))) -> 2.494577 | FQ6: =IF($EH6="",#N/A,SUM($FP$4:FP6)) -> 4.6923391 | FU6: #N/A | FV6: =IF(FW6="Down","Dwn",IF(FW6="Up","Up",IF(AND(FW6="",K6=""),"",IF(AND(K6<0,FW6="Yes"),"Dwn",IF(AND(K6>0,FW6="Yes"),"Up",IF(AND(K6<0,FW6="No"),"Up",IF(AND(K6>0,FW6="No"),"Dwn",IF(FW6="NA","SW","err")))))))) -> SW | FW6: NA | FX6: =IF(K6="","",IF(AND(K6>0,FW6="Yes"),1,"")) | FY6: =IF(K6="","",IF(AND($K6>0,$FW6="No"),1,"")) | FZ6: =IF(K6="","",IF(AND($K6>0,$FW6="NA"),1,"")) -> 1 | GA6: =IF(FV6="Dwn","Short","Long") -> Long | GB6: =IF(K6="","",IF(AND($K6<0,$FW6="Yes"),1,"")) | GC6: =IF(K6="","",IF(AND($K6<0,$FW6="No"),1,"")) | GD6: =IF(K6="","",IF(AND($K6<0,$FW6="NA"),1,"")) | GE6: =I6 -> 9.22 | GF6: Long | GG6: =400/I6 -> 43.383948 | GH6: =IF(GG6="","",GE6*GG6) -> 400 | GI6: =GG6 -> 43.383948 | GJ6: =J6 -> 10.6 | GK6: =IF($GI6="","",IF($GF6="Long",(($GJ6*$GI6)-$GH6),($GH6-($GJ6*$GI6)))) -> 59.869848 | GL6: =IF($GI6="","",IF($GF6="Long",(($GZ6*$GI6)-$GH6),($GH6-($GZ6*$GI6)))) -> 110.19523 | GM6: =IF(AND($FV6="SW",$GA6="Long"),$FN6,"") -> 4.5914678 | GN6: =IF($GZ6="",#N/A,SUM(GM$4:GM6)) -> 4.5914678 | GO6: =IF(AND($FV6="UP",$GA6="Long"),$FN6,"") | GP6: =IF($GZ6="",#N/A,SUM(GO$4:GO6)) -> 1.500597 | GQ6: =IF(AND($FV6="Dwn",$GA6="Short"),$FN6,"") | GR6: =IF($GZ6="",#N/A,SUM(GQ$4:GQ6)) -> 2.847957 | GS6: =IF(AND(FV6="SW",GA6="Long"),$EJ6,"") -> 110.19523 | GT6: =IF($GZ6="",#N/A,SUM(GS$4:GS6)) -> 110.19523 | GU6: =IF(AND(FV6="UP",GA6="Long"),$EJ6,"") | GV6: =IF($GZ6="",#N/A,SUM(GU$4:GU6)) -> 36.014328 | GW6: =IF(AND(FV6="Dwn",GA6="Short"),$EJ6,"") | GX6: =IF($GZ6="",#N/A,SUM(GW$4:GW6)) -> 68.350967 | GY6: =IF(EJ6="",#N/A,SUM($EJ$4:EJ6)) -> 214.56052 | GZ6: 11.76 | HA6: =IF(OR(GL6="",GZ6=""),"",GL6-EH6) -> 50.32538 | HB6: Skip | HC6: =IFERROR(VLOOKUP(E6,Expectancy!$P$4:$S$19,1+C6,FALSE),"") -> 0.40561946 | HD6: =IF(AND(HB6="MOC",GZ6=""),"",IF(GI6="","",IF(HB6="Skip","",IF(HG6=0,0,HG6/(GH6*0.06))))) | HE6: =IF(HD6="",#N/A,SUM($HD$4:HD6)) -> #N/A | HF6: =IF(HD6="",#N/A,IF(HB6="Skip",#N/A,SUM($HG$4:HG6))) -> #N/A | HG6: =IF(HB6="","",IF(HB6="Skip","",IF(OR(HB6="open",HB6="Other"),GK6,IF(HB6="MOC",GL6,"Err")))) | HH6: =IF(OR($GI6="",$L6=""),"",IF($GA6="Long",(($GZ6*$GI6)-$GH6)/($GH6*0.06),($GH6-($GZ6*$GI6))/($GH6*0.06))) -> 4.5914678
A7: JPM | B7: on 1/15/25, 1:00 AM Before Market Eas | C7: =IF(FV7="Dwn",2,IF(FV7="Up",1,IF(FV7="SW",3,"x"))) -> 1 | D7: =_xlfn.XLOOKUP(A7,[1]SP500!$A$2:$A$502,[1]SP500!$D$2:$D$502,"N") -> Y | E7: =_xlfn.XLOOKUP(A7,[1]SP500!$A$2:$A$655,[1]SP500!$B$2:$B$655) -> XLF | F7: 45672 | G7: =IF(ISNUMBER(FIND("After",B7,1)),"AMC",IF(ISNUMBER(FIND("Before",B7,1)),"BMO","err")) -> BMO | H7: =IF(HB7="other","o",IF(HB7="Skip","o",IF(OR(FV7="",GF7=""),"",IF(AND(FV7="Dwn",GF7="Short"),"s",IF(AND(FV7="Up",GF7="Long"),"s",IF(AND(FV7="SW",GF7="Long"),"s","o")))))) -> o | I7: 247.47 | J7: 250.4 | K7: =IF(J7="","",(J7-I7)/I7) -> 0.011839819 | L7: =IF(OR($GI7="",J7=""),"",IF($GF7="Long",(($J7*$GI7)-$GH7),($GH7-($J7*$GI7)))) -> 4.7359276 | M7: =IF(L7="","",IF(HG7="","",HG7-L7)) | N7: =IF(AND($FV7="Up",$GA7="Long"),$EH7,"") -> 4.7359276 | O7: =IF($J7="",#N/A,SUM($N$4:N7)) -> 27.985683 | P7: =IF(AND($FV7="Dwn",$GA7="Short"),$EH7,"") | Q7: =IF($J7="",#N/A,SUM($P$4:P7)) -> 29.496534 | R7: =IF(AND($FV7="SW",$GA7="Long"),$EH7,"") | S7: =IF($J7="",#N/A,SUM($R$4:R7)) -> 59.869848 | T7: =IF(AND($FV7="Up",$GA7="Long"),$FP7,"") -> 0.19733032 | U7: =IF($J7="",#N/A,SUM($T$4:T7)) -> 1.1660701 | V7: =IF(AND($FV7="Dwn",$GA7="Short"),$FP7,"") | W7: =IF($J7="",#N/A,SUM($V$4:V7)) -> 1.2290223 | X7: =IF(AND($FV7="SW",$GA7="Long"),$FP7,"") | Y7: =IF($J7="",#N/A,SUM($X$4:X7)) -> 2.494577 | Z7: =IF(AND($FV7="Up",$GA7="Long",$E7=Z$2),$FP7,"") | AA7: =IF($J7="",#N/A,SUM(Z$4:Z7)) -> 0 | AB7: =IF(AND($FV7="Dwn",$GA7="Short",$E7=Z$2),$FP7,"") | AC7: =IF($J7="",#N/A,SUM(AB$4:AB7)) -> 0 | AD7: =IF(AND($FV7="SW",$GA7="Long",$E7=Z$2),$FP7,"") | AE7: =IF($J7="",#N/A,SUM(AD$4:AD7)) -> 0 | AF7: =IF($J7="",#N/A,SUM(AD$4:AD7,AB$4:AB7,Z$4:Z7)) -> 0 | AG7: =IF(AND($FV7="Up",$GA7="Long",$E7=AG$2),$FP7,"") | AH7: =IF($J7="",#N/A,SUM(AG$4:AG7)) -> 0 | AI7: =IF(AND($FV7="Dwn",$GA7="Short",$E7=AG$2),$FP7,"") | AJ7: =IF($J7="",#N/A,SUM(AI$4:AI7)) -> 0 | AK7: =IF(AND($FV7="SW",$GA7="Long",$E7=AG$2),$FP7,"") | AL7: =IF($J7="",#N/A,SUM(AK$4:AK7)) -> 0 | AM7: =IF($J7="",#N/A,SUM(AK$4:AK7,AI$4:AI7,AG$4:AG7)) -> 0 | AN7: =IF(AND($FV7="Up",$GA7="Long",$E7=AN$2),$FP7,"") | AO7: =IF($J7="",#N/A,SUM(AN$4:AN7)) -> 0 | AP7: =IF(AND($FV7="Dwn",$GA7="Short",$E7=AN$2),$FP7,"") | AQ7: =IF($J7="",#N/A,SUM(AP$4:AP7)) -> 0 | AR7: =IF(AND($FV7="SW",$GA7="Long",$E7=AN$2),$FP7,"") | AS7: =IF($J7="",#N/A,SUM(AR$4:AR7)) -> 0 | AT7: =IF($J7="",#N/A,SUM(AR$4:AR7,AP$4:AP7,AN$4:AN7)) -> 0 | AU7: =IF(AND($FV7="Up",$GA7="Long",$E7=AU$2),$FP7,"") | AV7: =IF($J7="",#N/A,SUM(AU$4:AU7)) -> 0 | AW7: =IF(AND($FV7="Dwn",$GA7="Short",$E7=AU$2),$FP7,"") | AX7: =IF($J7="",#N/A,SUM(AW$4:AW7)) -> 1.2290223 | AY7: =IF(AND($FV7="SW",$GA7="Long",$E7=AU$2),$FP7,"") | AZ7: =IF($J7="",#N/A,SUM(AY$4:AY7)) -> 2.494577 | BA7: =IF($J7="",#N/A,SUM(AY$4:AY7,AW$4:AW7,AU$4:AU7)) -> 3.7235993 | BB7: =IF(AND($FV7="Up",$GA7="Long",$E7=BB$2),$FP7,"") | BC7: =IF($J7="",#N/A,SUM(BB$4:BB7)) -> 0 | BD7: =IF(AND($FV7="Dwn",$GA7="Short",$E7=BB$2),$FP7,"") | BE7: =IF($J7="",#N/A,SUM(BD$4:BD7)) -> 0 | BF7: =IF(AND($FV7="SW",$GA7="Long",$E7=BB$2),$FP7,"") | BG7: =IF($J7="",#N/A,SUM(BF$4:BF7)) -> 0 | BH7: =IF($J7="",#N/A,SUM(BF$4:BF7,BD$4:BD7,BB$4:BB7)) -> 0 | BI7: =IF(AND($FV7="Up",$GA7="Long",$E7=BI$2),$FP7,"") -> 0.19733032 | BJ7: =IF($J7="",#N/A,SUM(BI$4:BI7)) -> 0.19733032 | BK7: =IF(AND($FV7="Dwn",$GA7="Short",$E7=BI$2),$FP7,"") | BL7: =IF($J7="",#N/A,SUM(BK$4:BK7)) -> 0 | BM7: =IF(AND($FV7="SW",$GA7="Long",$E7=BI$2),$FP7,"") | BN7: =IF($J7="",#N/A,SUM(BM$4:BM7)) -> 0 | BO7: =IF($J7="",#N/A,SUM(BM$4:BM7,BK$4:BK7,BI$4:BI7)) -> 0.19733032 | BP7: =IF(AND($FV7="Up",$GA7="Long",$E7=BP$2),$FP7,"") | BQ7: =IF($J7="",#N/A,SUM(BP$4:BP7)) -> 0.96873982 | BR7: =IF(AND($FV7="Dwn",$GA7="Short",$E7=BP$2),$FP7,"") | BS7: =IF($J7="",#N/A,SUM(BR$4:BR7)) -> 0 | BT7: =IF(AND($FV7="SW",$GA7="Long",$E7=BP$2),$FP7,"") | BU7: =IF($J7="",#N/A,SUM(BT$4:BT7)) -> 0 | BV7: =IF($J7="",#N/A,SUM(BT$4:BT7,BR$4:BR7,BP$4:BP7)) -> 0.96873982 | BW7: =IF(AND($FV7="Up",$GA7="Long",$E7=BW$2),$FP7,"") | BX7: =IF($J7="",#N/A,SUM(BW$4:BW7)) -> 0 | BY7: =IF(AND($FV7="Dwn",$GA7="Short",$E7=BW$2),$FP7,"") | BZ7: =IF($J7="",#N/A,SUM(BY$4:BY7)) -> 0 | CA7: =IF(AND($FV7="SW",$GA7="Long",$E7=BW$2),$FP7,"") | CB7: =IF($J7="",#N/A,SUM(CA$4:CA7)) -> 0 | CC7: =IF($J7="",#N/A,SUM(CA$4:CA7,BY$4:BY7,BW$4:BW7)) -> 0 | CD7: =IF(AND($FV7="Up",$GA7="Long",$E7=CD$2),$FP7,"") | CE7: =IF($J7="",#N/A,SUM(CD$4:CD7)) -> 0 | CF7: =IF(AND($FV7="Dwn",$GA7="Short",$E7=CD$2),$FP7,"") | CG7: =IF($J7="",#N/A,SUM(CF$4:CF7)) -> 0 | CH7: =IF(AND($FV7="SW",$GA7="Long",$E7=CD$2),$FP7,"") | CI7: =IF($J7="",#N/A,SUM(CH$4:CH7)) -> 0 | CJ7: =IF($J7="",#N/A,SUM(CH$4:CH7,CF$4:CF7,CD$4:CD7)) -> 0 | CK7: =IF(AND($FV7="Up",$GA7="Long",$E7=CK$2),$FP7,"") | CL7: =IF($J7="",#N/A,SUM(CK$4:CK7)) -> 0 | CM7: =IF(AND($FV7="Dwn",$GA7="Short",$E7=CK$2),$FP7,"") | CN7: =IF($J7="",#N/A,SUM(CM$4:CM7)) -> 0 | CO7: =IF(AND($FV7="SW",$GA7="Long",$E7=CK$2),$FP7,"") | CP7: =IF($J7="",#N/A,SUM(CO$4:CO7)) -> 0 | CQ7: =IF($J7="",#N/A,SUM(CO$4:CO7,CM$4:CM7,CK$4:CK7)) -> 0 | CR7: =IF(AND($FV7="Up",$GA7="Long",$E7=CR$2),$FP7,"") | CS7: =IF($J7="",#N/A,SUM(CR$4:CR7)) -> 0 | CT7: =IF(AND($FV7="Dwn",$GA7="Short",$E7=CR$2),$FP7,"") | CU7: =IF($J7="",#N/A,SUM(CT$4:CT7)) -> 0 | CV7: =IF(AND($FV7="SW",$GA7="Long",$E7=CR$2),$FP7,"") | CW7: =IF($J7="",#N/A,SUM(CV$4:CV7)) -> 0 | CX7: =IF($J7="",#N/A,SUM(CV$4:CV7,CT$4:CT7,CR$4:CR7)) -> 0 | CY7: =IF(AND($FV7="Up",$GA7="Long",$E7=CY$2),$FP7,"") | CZ7: =IF($J7="",#N/A,SUM(CY$4:CY7)) -> 0 | DA7: =IF(AND($FV7="Dwn",$GA7="Short",$E7=CY$2),$FP7,"") | DB7: =IF($J7="",#N/A,SUM(DA$4:DA7)) -> 0 | DC7: =IF(AND($FV7="SW",$GA7="Long",$E7=CY$2),$FP7,"") | DD7: =IF($J7="",#N/A,SUM(DC$4:DC7)) -> 0 | DE7: =IF($J7="",#N/A,SUM(DC$4:DC7,DA$4:DA7,CY$4:CY7)) -> 0 | DF7: =IF(AND($FV7="Up",$GA7="Long",$E7=DF$2),$FP7,"") | DG7: =IF($J7="",#N/A,SUM(DF$4:DF7)) -> 0 | DH7: =IF(AND($FV7="Dwn",$GA7="Short",$E7=DF$2),$FP7,"") | DI7: =IF($J7="",#N/A,SUM(DH$4:DH7)) -> 0 | DJ7: =IF(AND($FV7="SW",$GA7="Long",$E7=DF$2),$FP7,"") | DK7: =IF($J7="",#N/A,SUM(DJ$4:DJ7)) -> 0 | DL7: =IF($J7="",#N/A,SUM(DJ$4:DJ7,DH$4:DH7,DF$4:DF7)) -> 0 | DM7: =IF(AND($FV7="Up",$GA7="Long",$E7=DM$2),$FP7,"") | DN7: =IF($J7="",#N/A,SUM(DM$4:DM7)) -> 0 | DO7: =IF(AND($FV7="Dwn",$GA7="Short",$E7=DM$2),$FP7,"") | DP7: =IF($J7="",#N/A,SUM(DO$4:DO7)) -> 0 | DQ7: =IF(AND($FV7="SW",$GA7="Long",$E7=DM$2),$FP7,"") | DR7: =IF($J7="",#N/A,SUM(DQ$4:DQ7)) -> 0 | DS7: =IF($J7="",#N/A,SUM(DQ$4:DQ7,DO$4:DO7,DM$4:DM7)) -> 0 | DT7: =IF(AND($FV7="Up",$GA7="Long",$E7=DT$2),$FP7,"") | DU7: =IF($J7="",#N/A,SUM(DT$4:DT7)) -> 0 | DV7: =IF(AND($FV7="Dwn",$GA7="Short",$E7=DT$2),$FP7,"") | DW7: =IF($J7="",#N/A,SUM(DV$4:DV7)) -> 0 | DX7: =IF(AND($FV7="SW",$GA7="Long",$E7=DT$2),$FP7,"") | DY7: =IF($J7="",#N/A,SUM(DX$4:DX7)) -> 0 | DZ7: =IF($J7="",#N/A,SUM(DX$4:DX7,DV$4:DV7,DT$4:DT7)) -> 0 | EA7: =IF(AND($FV7="Up",$GA7="Long",$E7=EA$2),$FP7,"") | EB7: =IF($J7="",#N/A,SUM(EA$4:EA7)) -> 0 | EC7: =IF(AND($FV7="Dwn",$GA7="Short",$E7=EA$2),$FP7,"") | ED7: =IF($J7="",#N/A,SUM(EC$4:EC7)) -> 0 | EE7: =IF(AND($FV7="SW",$GA7="Long",$E7=EA$2),$FP7,"") | EF7: =IF($J7="",#N/A,SUM(EE$4:EE7)) -> 0 | EG7: =IF($J7="",#N/A,SUM(EE$4:EE7,EC$4:EC7,EA$4:EA7)) -> 0 | EH7: =IF(OR($GI7="",L7=""),"",IF($GA7="Long",(($J7*$GI7)-$GH7),($GH7-($J7*$GI7)))) -> 4.7359276 | EI7: =IF(EH7="",#N/A,SUM($EH$4:EH7)) -> 117.35207 | EJ7: =IF(GZ7="","",IF(OR($GI7="",AM7=""),"",IF($GA7="Long",(($GZ7*$GI7)-$GH7),($GH7-($GZ7*$GI7))))) -> 7.8878248 | EK7: =IF($GZ7="",#N/A,SUM(EJ$4:EJ7)) -> 222.44835 | EL7: =IF(J7="","",IF(D7="Y",FP7,"")) -> 0.19733032 | EM7: =IF(EL7="",NA(),SUM($EL$4:EL7)) -> 4.8896694 | EN7: =IF(AND($FV7="Up",$GA7="Long",$D7="Y"),$EL7,"") -> 0.19733032 | EO7: =IF(EN7="",NA(),SUM($EN$4:EN7)) -> 1.1660701 | EP7: =IF(AND($FV7="SW",$GA7="Long",$D7="Y"),$EL7,"") | EQ7: =IF(EP7="",NA(),SUM($EP$4:EP7)) -> #N/A | ER7: =IF(AND($FV7="Dwn",$GA7="Short",$D7="Y"),$EL7,"") | ES7: =IF(ER7="",NA(),SUM($ER$4:ER7)) -> #N/A | ET7: =IF($J7="","",IF($D7="N",$FP7,"")) | EU7: =IF(ET7="",NA(),SUM($ET$4:ET7)) -> #N/A | EV7: =IF(AND($FV7="Up",$GA7="Long",$D7="N"),$ET7,"") | EW7: =IF(EV7="",NA(),SUM($EV$4:EV7)) -> #N/A | EX7: =IF(AND($FV7="SW",$GA7="Long",$D7="N"),$ET7,"") | EY7: =IF(EX7="",NA(),SUM($EX$4:EX7)) -> #N/A | EZ7: =IF(AND($FV7="Dwn",$GA7="Short",$D7="N"),$ET7,"") | FA7: =IF(EZ7="",NA(),SUM($EZ$4:EZ7)) -> #N/A | FB7: =IF($GZ7="","",IF(AND($FV7="Dwn",$K7<0),$FN7-FP7,"")) | FC7: =IF($FB7="",#N/A,SUM(FB$4:$FB7)) -> #N/A | FD7: =IF($GZ7="","",IF(AND($FV7="Dwn",$K7>0),$FN7-$FP7,"")) | FE7: =IF($FD7="",#N/A,SUM($FD$4:FD7)) -> #N/A | FF7: =IF($GZ7="","",IF(AND($FV7="Up",$K7>0),$FN7-$FP7,"")) -> 0.13132905 | FG7: =IF($FF7="",#N/A,SUM($FF$4:FF7)) -> 0.66318621 | FH7: =IF($GZ7="","",IF(AND($FV7="Up",$K7<0),$FN7-$FP7,"")) | FI7: =IF($FH7="",#N/A,SUM($FH$4:FH7)) -> #N/A | FJ7: =IF($GZ7="","",IF(AND($FV7="SW",$K7>0),$FN7-$FP7,"")) | FK7: =IF($FJ7="",#N/A,SUM($FJ$4:FJ7)) -> #N/A | FL7: =IF($GZ7="","",IF(AND($FV7="SW",$K7<0),$FN7-$FP7,"")) | FM7: =IF($FL7="",#N/A,SUM($FL$4:FL7)) -> #N/A | FN7: =IF(OR($GI7="",$GZ7=""),"",IF($GA7="Long",(($GZ7*$GI7)-$GH7)/($GH7*0.06),($GH7-($GZ7*$GI7))/($GH7*0.06))) -> 0.32865937 | FO7: =IF($FN7="",#N/A,SUM(FN$4:$FN7)) -> 9.2686811 | FP7: =IF(OR($GI7="",L7=""),"",IF($GA7="Long",(($J7*$GI7)-$GH7)/(GH7*0.06),($GH7-($J7*$GI7))/(GH7*0.06))) -> 0.19733032 | FQ7: =IF($EH7="",#N/A,SUM($FP$4:FP7)) -> 4.8896694 | FU7: #N/A | FV7: =IF(FW7="Down","Dwn",IF(FW7="Up","Up",IF(AND(FW7="",K7=""),"",IF(AND(K7<0,FW7="Yes"),"Dwn",IF(AND(K7>0,FW7="Yes"),"Up",IF(AND(K7<0,FW7="No"),"Up",IF(AND(K7>0,FW7="No"),"Dwn",IF(FW7="NA","SW","err")))))))) -> Up | FW7: Yes | FX7: =IF(K7="","",IF(AND(K7>0,FW7="Yes"),1,"")) -> 1 | FY7: =IF(K7="","",IF(AND($K7>0,$FW7="No"),1,"")) | FZ7: =IF(K7="","",IF(AND($K7>0,$FW7="NA"),1,"")) | GA7: =IF(FV7="Dwn","Short","Long") -> Long | GB7: =IF(K7="","",IF(AND($K7<0,$FW7="Yes"),1,"")) | GC7: =IF(K7="","",IF(AND($K7<0,$FW7="No"),1,"")) | GD7: =IF(K7="","",IF(AND($K7<0,$FW7="NA"),1,"")) | GE7: =I7 -> 247.47 | GF7: Long | GG7: =400/I7 -> 1.6163575 | GH7: =IF(GG7="","",GE7*GG7) -> 400 | GI7: =GG7 -> 1.6163575 | GJ7: =J7 -> 250.4 | GK7: =IF($GI7="","",IF($GF7="Long",(($GJ7*$GI7)-$GH7),($GH7-($GJ7*$GI7)))) -> 4.7359276 | GL7: =IF($GI7="","",IF($GF7="Long",(($GZ7*$GI7)-$GH7),($GH7-($GZ7*$GI7)))) -> 7.8878248 | GM7: =IF(AND($FV7="SW",$GA7="Long"),$FN7,"") | GN7: =IF($GZ7="",#N/A,SUM(GM$4:GM7)) -> 4.5914678 | GO7: =IF(AND($FV7="UP",$GA7="Long"),$FN7,"") -> 0.32865937 | GP7: =IF($GZ7="",#N/A,SUM(GO$4:GO7)) -> 1.8292563 | GQ7: =IF(AND($FV7="Dwn",$GA7="Short"),$FN7,"") | GR7: =IF($GZ7="",#N/A,SUM(GQ$4:GQ7)) -> 2.847957 | GS7: =IF(AND(FV7="SW",GA7="Long"),$EJ7,"") | GT7: =IF($GZ7="",#N/A,SUM(GS$4:GS7)) -> 110.19523 | GU7: =IF(AND(FV7="UP",GA7="Long"),$EJ7,"") -> 7.8878248 | GV7: =IF($GZ7="",#N/A,SUM(GU$4:GU7)) -> 43.902152 | GW7: =IF(AND(FV7="Dwn",GA7="Short"),$EJ7,"") | GX7: =IF($GZ7="",#N/A,SUM(GW$4:GW7)) -> 68.350967 | GY7: =IF(EJ7="",#N/A,SUM($EJ$4:EJ7)) -> 222.44835 | GZ7: 252.35 | HA7: =IF(OR(GL7="",GZ7=""),"",GL7-EH7) -> 3.1518972 | HB7: Skip | HC7: =IFERROR(VLOOKUP(E7,Expectancy!$P$4:$S$19,1+C7,FALSE),"") -> -0.079483353 | HD7: =IF(AND(HB7="MOC",GZ7=""),"",IF(GI7="","",IF(HB7="Skip","",IF(HG7=0,0,HG7/(GH7*0.06))))) | HE7: =IF(HD7="",#N/A,SUM($HD$4:HD7)) -> #N/A | HF7: =IF(HD7="",#N/A,IF(HB7="Skip",#N/A,SUM($HG$4:HG7))) -> #N/A | HG7: =IF(HB7="","",IF(HB7="Skip","",IF(OR(HB7="open",HB7="Other"),GK7,IF(HB7="MOC",GL7,"Err")))) | HH7: =IF(OR($GI7="",$L7=""),"",IF($GA7="Long",(($GZ7*$GI7)-$GH7)/($GH7*0.06),($GH7-($GZ7*$GI7))/($GH7*0.06))) -> 0.32865937
A8: WFC | B8: on 1/15/25, 1:00 AM Before Market Eas | C8: =IF(FV8="Dwn",2,IF(FV8="Up",1,IF(FV8="SW",3,"x"))) -> 1 | D8: =_xlfn.XLOOKUP(A8,[1]SP500!$A$2:$A$502,[1]SP500!$D$2:$D$502,"N") -> Y | E8: =_xlfn.XLOOKUP(A8,[1]SP500!$A$2:$A$655,[1]SP500!$B$2:$B$655) -> XLF | F8: 45672 | G8: =IF(ISNUMBER(FIND("After",B8,1)),"AMC",IF(ISNUMBER(FIND("Before",B8,1)),"BMO","err")) -> BMO | H8: =IF(HB8="other","o",IF(HB8="Skip","o",IF(OR(FV8="",GF8=""),"",IF(AND(FV8="Dwn",GF8="Short"),"s",IF(AND(FV8="Up",GF8="Long"),"s",IF(AND(FV8="SW",GF8="Long"),"s","o")))))) -> o | I8: 71.19 | J8: 75.36 | K8: =IF(J8="","",(J8-I8)/I8) -> 0.058575643 | L8: =IF(OR($GI8="",J8=""),"",IF($GF8="Long",(($J8*$GI8)-$GH8),($GH8-($J8*$GI8)))) -> 23.430257 | M8: =IF(L8="","",IF(HG8="","",HG8-L8)) | N8: =IF(AND($FV8="Up",$GA8="Long"),$EH8,"") -> 23.430257 | O8: =IF($J8="",#N/A,SUM($N$4:N8)) -> 51.41594 | P8: =IF(AND($FV8="Dwn",$GA8="Short"),$EH8,"") | Q8: =IF($J8="",#N/A,SUM($P$4:P8)) -> 29.496534 | R8: =IF(AND($FV8="SW",$GA8="Long"),$EH8,"") | S8: =IF($J8="",#N/A,SUM($R$4:R8)) -> 59.869848 | T8: =IF(AND($FV8="Up",$GA8="Long"),$FP8,"") -> 0.97626071 | U8: =IF($J8="",#N/A,SUM($T$4:T8)) -> 2.1423309 | V8: =IF(AND($FV8="Dwn",$GA8="Short"),$FP8,"") | W8: =IF($J8="",#N/A,SUM($V$4:V8)) -> 1.2290223 | X8: =IF(AND($FV8="SW",$GA8="Long"),$FP8,"") | Y8: =IF($J8="",#N/A,SUM($X$4:X8)) -> 2.494577 | Z8: =IF(AND($FV8="Up",$GA8="Long",$E8=Z$2),$FP8,"") | AA8: =IF($J8="",#N/A,SUM(Z$4:Z8)) -> 0 | AB8: =IF(AND($FV8="Dwn",$GA8="Short",$E8=Z$2),$FP8,"") | AC8: =IF($J8="",#N/A,SUM(AB$4:AB8)) -> 0 | AD8: =IF(AND($FV8="SW",$GA8="Long",$E8=Z$2),$FP8,"") | AE8: =IF($J8="",#N/A,SUM(AD$4:AD8)) -> 0 | AF8: =IF($J8="",#N/A,SUM(AD$4:AD8,AB$4:AB8,Z$4:Z8)) -> 0 | AG8: =IF(AND($FV8="Up",$GA8="Long",$E8=AG$2),$FP8,"") | AH8: =IF($J8="",#N/A,SUM(AG$4:AG8)) -> 0 | AI8: =IF(AND($FV8="Dwn",$GA8="Short",$E8=AG$2),$FP8,"") | AJ8: =IF($J8="",#N/A,SUM(AI$4:AI8)) -> 0 | AK8: =IF(AND($FV8="SW",$GA8="Long",$E8=AG$2),$FP8,"") | AL8: =IF($J8="",#N/A,SUM(AK$4:AK8)) -> 0 | AM8: =IF($J8="",#N/A,SUM(AK$4:AK8,AI$4:AI8,AG$4:AG8)) -> 0 | AN8: =IF(AND($FV8="Up",$GA8="Long",$E8=AN$2),$FP8,"") | AO8: =IF($J8="",#N/A,SUM(AN$4:AN8)) -> 0 | AP8: =IF(AND($FV8="Dwn",$GA8="Short",$E8=AN$2),$FP8,"") | AQ8: =IF($J8="",#N/A,SUM(AP$4:AP8)) -> 0 | AR8: =IF(AND($FV8="SW",$GA8="Long",$E8=AN$2),$FP8,"") | AS8: =IF($J8="",#N/A,SUM(AR$4:AR8)) -> 0 | AT8: =IF($J8="",#N/A,SUM(AR$4:AR8,AP$4:AP8,AN$4:AN8)) -> 0 | AU8: =IF(AND($FV8="Up",$GA8="Long",$E8=AU$2),$FP8,"") | AV8: =IF($J8="",#N/A,SUM(AU$4:AU8)) -> 0 | AW8: =IF(AND($FV8="Dwn",$GA8="Short",$E8=AU$2),$FP8,"") | AX8: =IF($J8="",#N/A,SUM(AW$4:AW8)) -> 1.2290223 | AY8: =IF(AND($FV8="SW",$GA8="Long",$E8=AU$2),$FP8,"") | AZ8: =IF($J8="",#N/A,SUM(AY$4:AY8)) -> 2.494577 | BA8: =IF($J8="",#N/A,SUM(AY$4:AY8,AW$4:AW8,AU$4:AU8)) -> 3.7235993 | BB8: =IF(AND($FV8="Up",$GA8="Long",$E8=BB$2),$FP8,"") | BC8: =IF($J8="",#N/A,SUM(BB$4:BB8)) -> 0 | BD8: =IF(AND($FV8="Dwn",$GA8="Short",$E8=BB$2),$FP8,"") | BE8: =IF($J8="",#N/A,SUM(BD$4:BD8)) -> 0 | BF8: =IF(AND($FV8="SW",$GA8="Long",$E8=BB$2),$FP8,"") | BG8: =IF($J8="",#N/A,SUM(BF$4:BF8)) -> 0 | BH8: =IF($J8="",#N/A,SUM(BF$4:BF8,BD$4:BD8,BB$4:BB8)) -> 0 | BI8: =IF(AND($FV8="Up",$GA8="Long",$E8=BI$2),$FP8,"") -> 0.97626071 | BJ8: =IF($J8="",#N/A,SUM(BI$4:BI8)) -> 1.173591 | BK8: =IF(AND($FV8="Dwn",$GA8="Short",$E8=BI$2),$FP8,"") | BL8: =IF($J8="",#N/A,SUM(BK$4:BK8)) -> 0 | BM8: =IF(AND($FV8="SW",$GA8="Long",$E8=BI$2),$FP8,"") | BN8: =IF($J8="",#N/A,SUM(BM$4:BM8)) -> 0 | BO8: =IF($J8="",#N/A,SUM(BM$4:BM8,BK$4:BK8,BI$4:BI8)) -> 1.173591 | BP8: =IF(AND($FV8="Up",$GA8="Long",$E8=BP$2),$FP8,"") | BQ8: =IF($J8="",#N/A,SUM(BP$4:BP8)) -> 0.96873982 | BR8: =IF(AND($FV8="Dwn",$GA8="Short",$E8=BP$2),$FP8,"") | BS8: =IF($J8="",#N/A,SUM(BR$4:BR8)) -> 0 | BT8: =IF(AND($FV8="SW",$GA8="Long",$E8=BP$2),$FP8,"") | BU8: =IF($J8="",#N/A,SUM(BT$4:BT8)) -> 0 | BV8: =IF($J8="",#N/A,SUM(BT$4:BT8,BR$4:BR8,BP$4:BP8)) -> 0.96873982 | BW8: =IF(AND($FV8="Up",$GA8="Long",$E8=BW$2),$FP8,"") | BX8: =IF($J8="",#N/A,SUM(BW$4:BW8)) -> 0 | BY8: =IF(AND($FV8="Dwn",$GA8="Short",$E8=BW$2),$FP8,"") | BZ8: =IF($J8="",#N/A,SUM(BY$4:BY8)) -> 0 | CA8: =IF(AND($FV8="SW",$GA8="Long",$E8=BW$2),$FP8,"") | CB8: =IF($J8="",#N/A,SUM(CA$4:CA8)) -> 0 | CC8: =IF($J8="",#N/A,SUM(CA$4:CA8,BY$4:BY8,BW$4:BW8)) -> 0 | CD8: =IF(AND($FV8="Up",$GA8="Long",$E8=CD$2),$FP8,"") | CE8: =IF($J8="",#N/A,SUM(CD$4:CD8)) -> 0 | CF8: =IF(AND($FV8="Dwn",$GA8="Short",$E8=CD$2),$FP8,"") | CG8: =IF($J8="",#N/A,SUM(CF$4:CF8)) -> 0 | CH8: =IF(AND($FV8="SW",$GA8="Long",$E8=CD$2),$FP8,"") | CI8: =IF($J8="",#N/A,SUM(CH$4:CH8)) -> 0 | CJ8: =IF($J8="",#N/A,SUM(CH$4:CH8,CF$4:CF8,CD$4:CD8)) -> 0 | CK8: =IF(AND($FV8="Up",$GA8="Long",$E8=CK$2),$FP8,"") | CL8: =IF($J8="",#N/A,SUM(CK$4:CK8)) -> 0 | CM8: =IF(AND($FV8="Dwn",$GA8="Short",$E8=CK$2),$FP8,"") | CN8: =IF($J8="",#N/A,SUM(CM$4:CM8)) -> 0 | CO8: =IF(AND($FV8="SW",$GA8="Long",$E8=CK$2),$FP8,"") | CP8: =IF($J8="",#N/A,SUM(CO$4:CO8)) -> 0 | CQ8: =IF($J8="",#N/A,SUM(CO$4:CO8,CM$4:CM8,CK$4:CK8)) -> 0 | CR8: =IF(AND($FV8="Up",$GA8="Long",$E8=CR$2),$FP8,"") | CS8: =IF($J8="",#N/A,SUM(CR$4:CR8)) -> 0 | CT8: =IF(AND($FV8="Dwn",$GA8="Short",$E8=CR$2),$FP8,"") | CU8: =IF($J8="",#N/A,SUM(CT$4:CT8)) -> 0 | CV8: =IF(AND($FV8="SW",$GA8="Long",$E8=CR$2),$FP8,"") | CW8: =IF($J8="",#N/A,SUM(CV$4:CV8)) -> 0 | CX8: =IF($J8="",#N/A,SUM(CV$4:CV8,CT$4:CT8,CR$4:CR8)) -> 0 | CY8: =IF(AND($FV8="Up",$GA8="Long",$E8=CY$2),$FP8,"") | CZ8: =IF($J8="",#N/A,SUM(CY$4:CY8)) -> 0 | DA8: =IF(AND($FV8="Dwn",$GA8="Short",$E8=CY$2),$FP8,"") | DB8: =IF($J8="",#N/A,SUM(DA$4:DA8)) -> 0 | DC8: =IF(AND($FV8="SW",$GA8="Long",$E8=CY$2),$FP8,"") | DD8: =IF($J8="",#N/A,SUM(DC$4:DC8)) -> 0 | DE8: =IF($J8="",#N/A,SUM(DC$4:DC8,DA$4:DA8,CY$4:CY8)) -> 0 | DF8: =IF(AND($FV8="Up",$GA8="Long",$E8=DF$2),$FP8,"") | DG8: =IF($J8="",#N/A,SUM(DF$4:DF8)) -> 0 | DH8: =IF(AND($FV8="Dwn",$GA8="Short",$E8=DF$2),$FP8,"") | DI8: =IF($J8="",#N/A,SUM(DH$4:DH8)) -> 0 | DJ8: =IF(AND($FV8="SW",$GA8="Long",$E8=DF$2),$FP8,"") | DK8: =IF($J8="",#N/A,SUM(DJ$4:DJ8)) -> 0 | DL8: =IF($J8="",#N/A,SUM(DJ$4:DJ8,DH$4:DH8,DF$4:DF8)) -> 0 | DM8: =IF(AND($FV8="Up",$GA8="Long",$E8=DM$2),$FP8,"") | DN8: =IF($J8="",#N/A,SUM(DM$4:DM8)) -> 0 | DO8: =IF(AND($FV8="Dwn",$GA8="Short",$E8=DM$2),$FP8,"") | DP8: =IF($J8="",#N/A,SUM(DO$4:DO8)) -> 0 | DQ8: =IF(AND($FV8="SW",$GA8="Long",$E8=DM$2),$FP8,"") | DR8: =IF($J8="",#N/A,SUM(DQ$4:DQ8)) -> 0 | DS8: =IF($J8="",#N/A,SUM(DQ$4:DQ8,DO$4:DO8,DM$4:DM8)) -> 0 | DT8: =IF(AND($FV8="Up",$GA8="Long",$E8=DT$2),$FP8,"") | DU8: =IF($J8="",#N/A,SUM(DT$4:DT8)) -> 0 | DV8: =IF(AND($FV8="Dwn",$GA8="Short",$E8=DT$2),$FP8,"") | DW8: =IF($J8="",#N/A,SUM(DV$4:DV8)) -> 0 | DX8: =IF(AND($FV8="SW",$GA8="Long",$E8=DT$2),$FP8,"") | DY8: =IF($J8="",#N/A,SUM(DX$4:DX8)) -> 0 | DZ8: =IF($J8="",#N/A,SUM(DX$4:DX8,DV$4:DV8,DT$4:DT8)) -> 0 | EA8: =IF(AND($FV8="Up",$GA8="Long",$E8=EA$2),$FP8,"") | EB8: =IF($J8="",#N/A,SUM(EA$4:EA8)) -> 0 | EC8: =IF(AND($FV8="Dwn",$GA8="Short",$E8=EA$2),$FP8,"") | ED8: =IF($J8="",#N/A,SUM(EC$4:EC8)) -> 0 | EE8: =IF(AND($FV8="SW",$GA8="Long",$E8=EA$2),$FP8,"") | EF8: =IF($J8="",#N/A,SUM(EE$4:EE8)) -> 0 | EG8: =IF($J8="",#N/A,SUM(EE$4:EE8,EC$4:EC8,EA$4:EA8)) -> 0 | EH8: =IF(OR($GI8="",L8=""),"",IF($GA8="Long",(($J8*$GI8)-$GH8),($GH8-($J8*$GI8)))) -> 23.430257 | EI8: =IF(EH8="",#N/A,SUM($EH$4:EH8)) -> 140.78232 | EJ8: =IF(GZ8="","",IF(OR($GI8="",AM8=""),"",IF($GA8="Long",(($GZ8*$GI8)-$GH8),($GH8-($GZ8*$GI8))))) -> 26.745329 | EK8: =IF($GZ8="",#N/A,SUM(EJ$4:EJ8)) -> 249.19368 | EL8: =IF(J8="","",IF(D8="Y",FP8,"")) -> 0.97626071 | EM8: =IF(EL8="",NA(),SUM($EL$4:EL8)) -> 5.8659301 | EN8: =IF(AND($FV8="Up",$GA8="Long",$D8="Y"),$EL8,"") -> 0.97626071 | EO8: =IF(EN8="",NA(),SUM($EN$4:EN8)) -> 2.1423309 | EP8: =IF(AND($FV8="SW",$GA8="Long",$D8="Y"),$EL8,"") | EQ8: =IF(EP8="",NA(),SUM($EP$4:EP8)) -> #N/A | ER8: =IF(AND($FV8="Dwn",$GA8="Short",$D8="Y"),$EL8,"") | ES8: =IF(ER8="",NA(),SUM($ER$4:ER8)) -> #N/A | ET8: =IF($J8="","",IF($D8="N",$FP8,"")) | EU8: =IF(ET8="",NA(),SUM($ET$4:ET8)) -> #N/A | EV8: =IF(AND($FV8="Up",$GA8="Long",$D8="N"),$ET8,"") | EW8: =IF(EV8="",NA(),SUM($EV$4:EV8)) -> #N/A | EX8: =IF(AND($FV8="SW",$GA8="Long",$D8="N"),$ET8,"") | EY8: =IF(EX8="",NA(),SUM($EX$4:EX8)) -> #N/A | EZ8: =IF(AND($FV8="Dwn",$GA8="Short",$D8="N"),$ET8,"") | FA8: =IF(EZ8="",NA(),SUM($EZ$4:EZ8)) -> #N/A | FB8: =IF($GZ8="","",IF(AND($FV8="Dwn",$K8<0),$FN8-FP8,"")) | FC8: =IF($FB8="",#N/A,SUM(FB$4:$FB8)) -> #N/A | FD8: =IF($GZ8="","",IF(AND($FV8="Dwn",$K8>0),$FN8-$FP8,"")) | FE8: =IF($FD8="",#N/A,SUM($FD$4:FD8)) -> #N/A | FF8: =IF($GZ8="","",IF(AND($FV8="Up",$K8>0),$FN8-$FP8,"")) -> 0.13812801 | FG8: =IF($FF8="",#N/A,SUM($FF$4:FF8)) -> 0.80131422 | FH8: =IF($GZ8="","",IF(AND($FV8="Up",$K8<0),$FN8-$FP8,"")) | FI8: =IF($FH8="",#N/A,SUM($FH$4:FH8)) -> #N/A | FJ8: =IF($GZ8="","",IF(AND($FV8="SW",$K8>0),$FN8-$FP8,"")) | FK8: =IF($FJ8="",#N/A,SUM($FJ$4:FJ8)) -> #N/A | FL8: =IF($GZ8="","",IF(AND($FV8="SW",$K8<0),$FN8-$FP8,"")) | FM8: =IF($FL8="",#N/A,SUM($FL$4:FL8)) -> #N/A | FN8: =IF(OR($GI8="",$GZ8=""),"",IF($GA8="Long",(($GZ8*$GI8)-$GH8)/($GH8*0.06),($GH8-($GZ8*$GI8))/($GH8*0.06))) -> 1.1143887 | FO8: =IF($FN8="",#N/A,SUM(FN$4:$FN8)) -> 10.38307 | FP8: =IF(OR($GI8="",L8=""),"",IF($GA8="Long",(($J8*$GI8)-$GH8)/(GH8*0.06),($GH8-($J8*$GI8))/(GH8*0.06))) -> 0.97626071 | FQ8: =IF($EH8="",#N/A,SUM($FP$4:FP8)) -> 5.8659301 | FU8: #N/A | FV8: =IF(FW8="Down","Dwn",IF(FW8="Up","Up",IF(AND(FW8="",K8=""),"",IF(AND(K8<0,FW8="Yes"),"Dwn",IF(AND(K8>0,FW8="Yes"),"Up",IF(AND(K8<0,FW8="No"),"Up",IF(AND(K8>0,FW8="No"),"Dwn",IF(FW8="NA","SW","err")))))))) -> Up | FW8: Yes | FX8: =IF(K8="","",IF(AND(K8>0,FW8="Yes"),1,"")) -> 1 | FY8: =IF(K8="","",IF(AND($K8>0,$FW8="No"),1,"")) | FZ8: =IF(K8="","",IF(AND($K8>0,$FW8="NA"),1,"")) | GA8: =IF(FV8="Dwn","Short","Long") -> Long | GB8: =IF(K8="","",IF(AND($K8<0,$FW8="Yes"),1,"")) | GC8: =IF(K8="","",IF(AND($K8<0,$FW8="No"),1,"")) | GD8: =IF(K8="","",IF(AND($K8<0,$FW8="NA"),1,"")) | GE8: =I8 -> 71.19 | GF8: Long | GG8: =400/I8 -> 5.6187667 | GH8: =IF(GG8="","",GE8*GG8) -> 400 | GI8: =GG8 -> 5.6187667 | GJ8: =J8 -> 75.36 | GK8: =IF($GI8="","",IF($GF8="Long",(($GJ8*$GI8)-$GH8),($GH8-($GJ8*$GI8)))) -> 23.430257 | GL8: =IF($GI8="","",IF($GF8="Long",(($GZ8*$GI8)-$GH8),($GH8-($GZ8*$GI8)))) -> 26.745329 | GM8: =IF(AND($FV8="SW",$GA8="Long"),$FN8,"") | GN8: =IF($GZ8="",#N/A,SUM(GM$4:GM8)) -> 4.5914678 | GO8: =IF(AND($FV8="UP",$GA8="Long"),$FN8,"") -> 1.1143887 | GP8: =IF($GZ8="",#N/A,SUM(GO$4:GO8)) -> 2.9436451 | GQ8: =IF(AND($FV8="Dwn",$GA8="Short"),$FN8,"") | GR8: =IF($GZ8="",#N/A,SUM(GQ$4:GQ8)) -> 2.847957 | GS8: =IF(AND(FV8="SW",GA8="Long"),$EJ8,"") | GT8: =IF($GZ8="",#N/A,SUM(GS$4:GS8)) -> 110.19523 | GU8: =IF(AND(FV8="UP",GA8="Long"),$EJ8,"") -> 26.745329 | GV8: =IF($GZ8="",#N/A,SUM(GU$4:GU8)) -> 70.647482 | GW8: =IF(AND(FV8="Dwn",GA8="Short"),$EJ8,"") | GX8: =IF($GZ8="",#N/A,SUM(GW$4:GW8)) -> 68.350967 | GY8: =IF(EJ8="",#N/A,SUM($EJ$4:EJ8)) -> 249.19368 | GZ8: 75.95 | HA8: =IF(OR(GL8="",GZ8=""),"",GL8-EH8) -> 3.3150723 | HB8: Skip | HC8: =IFERROR(VLOOKUP(E8,Expectancy!$P$4:$S$19,1+C8,FALSE),"") -> -0.079483353 | HD8: =IF(AND(HB8="MOC",GZ8=""),"",IF(GI8="","",IF(HB8="Skip","",IF(HG8=0,0,HG8/(GH8*0.06))))) | HE8: =IF(HD8="",#N/A,SUM($HD$4:HD8)) -> #N/A | HF8: =IF(HD8="",#N/A,IF(HB8="Skip",#N/A,SUM($HG$4:HG8))) -> #N/A | HG8: =IF(HB8="","",IF(HB8="Skip","",IF(OR(HB8="open",HB8="Other"),GK8,IF(HB8="MOC",GL8,"Err")))) | HH8: =IF(OR($GI8="",$L8=""),"",IF($GA8="Long",(($GZ8*$GI8)-$GH8)/($GH8*0.06),($GH8-($GZ8*$GI8))/($GH8*0.06))) -> 1.1143887
A9: GS | B9: on 1/15/25, 1:00 AM Before Market Eas | C9: =IF(FV9="Dwn",2,IF(FV9="Up",1,IF(FV9="SW",3,"x"))) -> 1 | D9: =_xlfn.XLOOKUP(A9,[1]SP500!$A$2:$A$502,[1]SP500!$D$2:$D$502,"N") -> Y | E9: =_xlfn.XLOOKUP(A9,[1]SP500!$A$2:$A$655,[1]SP500!$B$2:$B$655) -> XLF | F9: 45672 | G9: =IF(ISNUMBER(FIND("After",B9,1)),"AMC",IF(ISNUMBER(FIND("Before",B9,1)),"BMO","err")) -> BMO | H9: =IF(HB9="other","o",IF(HB9="Skip","o",IF(OR(FV9="",GF9=""),"",IF(AND(FV9="Dwn",GF9="Short"),"s",IF(AND(FV9="Up",GF9="Long"),"s",IF(AND(FV9="SW",GF9="Long"),"s","o")))))) -> o | I9: 571.53 | J9: 598 | K9: =IF(J9="","",(J9-I9)/I9) -> 0.046314279 | L9: =IF(OR($GI9="",J9=""),"",IF($GF9="Long",(($J9*$GI9)-$GH9),($GH9-($J9*$GI9)))) -> 18.525712 | M9: =IF(L9="","",IF(HG9="","",HG9-L9)) | N9: =IF(AND($FV9="Up",$GA9="Long"),$EH9,"") -> 18.525712 | O9: =IF($J9="",#N/A,SUM($N$4:N9)) -> 69.941652 | P9: =IF(AND($FV9="Dwn",$GA9="Short"),$EH9,"") | Q9: =IF($J9="",#N/A,SUM($P$4:P9)) -> 29.496534 | R9: =IF(AND($FV9="SW",$GA9="Long"),$EH9,"") | S9: =IF($J9="",#N/A,SUM($R$4:R9)) -> 59.869848 | T9: =IF(AND($FV9="Up",$GA9="Long"),$FP9,"") -> 0.77190465 | U9: =IF($J9="",#N/A,SUM($T$4:T9)) -> 2.9142355 | V9: =IF(AND($FV9="Dwn",$GA9="Short"),$FP9,"") | W9: =IF($J9="",#N/A,SUM($V$4:V9)) -> 1.2290223 | X9: =IF(AND($FV9="SW",$GA9="Long"),$FP9,"") | Y9: =IF($J9="",#N/A,SUM($X$4:X9)) -> 2.494577 | Z9: =IF(AND($FV9="Up",$GA9="Long",$E9=Z$2),$FP9,"") | AA9: =IF($J9="",#N/A,SUM(Z$4:Z9)) -> 0 | AB9: =IF(AND($FV9="Dwn",$GA9="Short",$E9=Z$2),$FP9,"") | AC9: =IF($J9="",#N/A,SUM(AB$4:AB9)) -> 0 | AD9: =IF(AND($FV9="SW",$GA9="Long",$E9=Z$2),$FP9,"") | AE9: =IF($J9="",#N/A,SUM(AD$4:AD9)) -> 0 | AF9: =IF($J9="",#N/A,SUM(AD$4:AD9,AB$4:AB9,Z$4:Z9)) -> 0 | AG9: =IF(AND($FV9="Up",$GA9="Long",$E9=AG$2),$FP9,"") | AH9: =IF($J9="",#N/A,SUM(AG$4:AG9)) -> 0 | AI9: =IF(AND($FV9="Dwn",$GA9="Short",$E9=AG$2),$FP9,"") | AJ9: =IF($J9="",#N/A,SUM(AI$4:AI9)) -> 0 | AK9: =IF(AND($FV9="SW",$GA9="Long",$E9=AG$2),$FP9,"") | AL9: =IF($J9="",#N/A,SUM(AK$4:AK9)) -> 0 | AM9: =IF($J9="",#N/A,SUM(AK$4:AK9,AI$4:AI9,AG$4:AG9)) -> 0 | AN9: =IF(AND($FV9="Up",$GA9="Long",$E9=AN$2),$FP9,"") | AO9: =IF($J9="",#N/A,SUM(AN$4:AN9)) -> 0 | AP9: =IF(AND($FV9="Dwn",$GA9="Short",$E9=AN$2),$FP9,"") | AQ9: =IF($J9="",#N/A,SUM(AP$4:AP9)) -> 0 | AR9: =IF(AND($FV9="SW",$GA9="Long",$E9=AN$2),$FP9,"") | AS9: =IF($J9="",#N/A,SUM(AR$4:AR9)) -> 0 | AT9: =IF($J9="",#N/A,SUM(AR$4:AR9,AP$4:AP9,AN$4:AN9)) -> 0 | AU9: =IF(AND($FV9="Up",$GA9="Long",$E9=AU$2),$FP9,"") | AV9: =IF($J9="",#N/A,SUM(AU$4:AU9)) -> 0 | AW9: =IF(AND($FV9="Dwn",$GA9="Short",$E9=AU$2),$FP9,"") | AX9: =IF($J9="",#N/A,SUM(AW$4:AW9)) -> 1.2290223 | AY9: =IF(AND($FV9="SW",$GA9="Long",$E9=AU$2),$FP9,"") | AZ9: =IF($J9="",#N/A,SUM(AY$4:AY9)) -> 2.494577 | BA9: =IF($J9="",#N/A,SUM(AY$4:AY9,AW$4:AW9,AU$4:AU9)) -> 3.7235993 | BB9: =IF(AND($FV9="Up",$GA9="Long",$E9=BB$2),$FP9,"") | BC9: =IF($J9="",#N/A,SUM(BB$4:BB9)) -> 0 | BD9: =IF(AND($FV9="Dwn",$GA9="Short",$E9=BB$2),$FP9,"") | BE9: =IF($J9="",#N/A,SUM(BD$4:BD9)) -> 0 | BF9: =IF(AND($FV9="SW",$GA9="Long",$E9=BB$2),$FP9,"") | BG9: =IF($J9="",#N/A,SUM(BF$4:BF9)) -> 0 | BH9: =IF($J9="",#N/A,SUM(BF$4:BF9,BD$4:BD9,BB$4:BB9)) -> 0 | BI9: =IF(AND($FV9="Up",$GA9="Long",$E9=BI$2),$FP9,"") -> 0.77190465 | BJ9: =IF($J9="",#N/A,SUM(BI$4:BI9)) -> 1.9454957 | BK9: =IF(AND($FV9="Dwn",$GA9="Short",$E9=BI$2),$FP9,"") | BL9: =IF($J9="",#N/A,SUM(BK$4:BK9)) -> 0 | BM9: =IF(AND($FV9="SW",$GA9="Long",$E9=BI$2),$FP9,"") | BN9: =IF($J9="",#N/A,SUM(BM$4:BM9)) -> 0 | BO9: =IF($J9="",#N/A,SUM(BM$4:BM9,BK$4:BK9,BI$4:BI9)) -> 1.9454957 | BP9: =IF(AND($FV9="Up",$GA9="Long",$E9=BP$2),$FP9,"") | BQ9: =IF($J9="",#N/A,SUM(BP$4:BP9)) -> 0.96873982 | BR9: =IF(AND($FV9="Dwn",$GA9="Short",$E9=BP$2),$FP9,"") | BS9: =IF($J9="",#N/A,SUM(BR$4:BR9)) -> 0 | BT9: =IF(AND($FV9="SW",$GA9="Long",$E9=BP$2),$FP9,"") | BU9: =IF($J9="",#N/A,SUM(BT$4:BT9)) -> 0 | BV9: =IF($J9="",#N/A,SUM(BT$4:BT9,BR$4:BR9,BP$4:BP9)) -> 0.96873982 | BW9: =IF(AND($FV9="Up",$GA9="Long",$E9=BW$2),$FP9,"") | BX9: =IF($J9="",#N/A,SUM(BW$4:BW9)) -> 0 | BY9: =IF(AND($FV9="Dwn",$GA9="Short",$E9=BW$2),$FP9,"") | BZ9: =IF($J9="",#N/A,SUM(BY$4:BY9)) -> 0 | CA9: =IF(AND($FV9="SW",$GA9="Long",$E9=BW$2),$FP9,"") | CB9: =IF($J9="",#N/A,SUM(CA$4:CA9)) -> 0 | CC9: =IF($J9="",#N/A,SUM(CA$4:CA9,BY$4:BY9,BW$4:BW9)) -> 0 | CD9: =IF(AND($FV9="Up",$GA9="Long",$E9=CD$2),$FP9,"") | CE9: =IF($J9="",#N/A,SUM(CD$4:CD9)) -> 0 | CF9: =IF(AND($FV9="Dwn",$GA9="Short",$E9=CD$2),$FP9,"") | CG9: =IF($J9="",#N/A,SUM(CF$4:CF9)) -> 0 | CH9: =IF(AND($FV9="SW",$GA9="Long",$E9=CD$2),$FP9,"") | CI9: =IF($J9="",#N/A,SUM(CH$4:CH9)) -> 0 | CJ9: =IF($J9="",#N/A,SUM(CH$4:CH9,CF$4:CF9,CD$4:CD9)) -> 0 | CK9: =IF(AND($FV9="Up",$GA9="Long",$E9=CK$2),$FP9,"") | CL9: =IF($J9="",#N/A,SUM(CK$4:CK9)) -> 0 | CM9: =IF(AND($FV9="Dwn",$GA9="Short",$E9=CK$2),$FP9,"") | CN9: =IF($J9="",#N/A,SUM(CM$4:CM9)) -> 0 | CO9: =IF(AND($FV9="SW",$GA9="Long",$E9=CK$2),$FP9,"") | CP9: =IF($J9="",#N/A,SUM(CO$4:CO9)) -> 0 | CQ9: =IF($J9="",#N/A,SUM(CO$4:CO9,CM$4:CM9,CK$4:CK9)) -> 0 | CR9: =IF(AND($FV9="Up",$GA9="Long",$E9=CR$2),$FP9,"") | CS9: =IF($J9="",#N/A,SUM(CR$4:CR9)) -> 0 | CT9: =IF(AND($FV9="Dwn",$GA9="Short",$E9=CR$2),$FP9,"") | CU9: =IF($J9="",#N/A,SUM(CT$4:CT9)) -> 0 | CV9: =IF(AND($FV9="SW",$GA9="Long",$E9=CR$2),$FP9,"") | CW9: =IF($J9="",#N/A,SUM(CV$4:CV9)) -> 0 | CX9: =IF($J9="",#N/A,SUM(CV$4:CV9,CT$4:CT9,CR$4:CR9)) -> 0 | CY9: =IF(AND($FV9="Up",$GA9="Long",$E9=CY$2),$FP9,"") | CZ9: =IF($J9="",#N/A,SUM(CY$4:CY9)) -> 0 | DA9: =IF(AND($FV9="Dwn",$GA9="Short",$E9=CY$2),$FP9,"") | DB9: =IF($J9="",#N/A,SUM(DA$4:DA9)) -> 0 | DC9: =IF(AND($FV9="SW",$GA9="Long",$E9=CY$2),$FP9,"") | DD9: =IF($J9="",#N/A,SUM(DC$4:DC9)) -> 0 | DE9: =IF($J9="",#N/A,SUM(DC$4:DC9,DA$4:DA9,CY$4:CY9)) -> 0 | DF9: =IF(AND($FV9="Up",$GA9="Long",$E9=DF$2),$FP9,"") | DG9: =IF($J9="",#N/A,SUM(DF$4:DF9)) -> 0 | DH9: =IF(AND($FV9="Dwn",$GA9="Short",$E9=DF$2),$FP9,"") | DI9: =IF($J9="",#N/A,SUM(DH$4:DH9)) -> 0 | DJ9: =IF(AND($FV9="SW",$GA9="Long",$E9=DF$2),$FP9,"") | DK9: =IF($J9="",#N/A,SUM(DJ$4:DJ9)) -> 0 | DL9: =IF($J9="",#N/A,SUM(DJ$4:DJ9,DH$4:DH9,DF$4:DF9)) -> 0 | DM9: =IF(AND($FV9="Up",$GA9="Long",$E9=DM$2),$FP9,"") | DN9: =IF($J9="",#N/A,SUM(DM$4:DM9)) -> 0 | DO9: =IF(AND($FV9="Dwn",$GA9="Short",$E9=DM$2),$FP9,"") | DP9: =IF($J9="",#N/A,SUM(DO$4:DO9)) -> 0 | DQ9: =IF(AND($FV9="SW",$GA9="Long",$E9=DM$2),$FP9,"") | DR9: =IF($J9="",#N/A,SUM(DQ$4:DQ9)) -> 0 | DS9: =IF($J9="",#N/A,SUM(DQ$4:DQ9,DO$4:DO9,DM$4:DM9)) -> 0 | DT9: =IF(AND($FV9="Up",$GA9="Long",$E9=DT$2),$FP9,"") | DU9: =IF($J9="",#N/A,SUM(DT$4:DT9)) -> 0 | DV9: =IF(AND($FV9="Dwn",$GA9="Short",$E9=DT$2),$FP9,"") | DW9: =IF($J9="",#N/A,SUM(DV$4:DV9)) -> 0 | DX9: =IF(AND($FV9="SW",$GA9="Long",$E9=DT$2),$FP9,"") | DY9: =IF($J9="",#N/A,SUM(DX$4:DX9)) -> 0 | DZ9: =IF($J9="",#N/A,SUM(DX$4:DX9,DV$4:DV9,DT$4:DT9)) -> 0 | EA9: =IF(AND($FV9="Up",$GA9="Long",$E9=EA$2),$FP9,"") | EB9: =IF($J9="",#N/A,SUM(EA$4:EA9)) -> 0 | EC9: =IF(AND($FV9="Dwn",$GA9="Short",$E9=EA$2),$FP9,"") | ED9: =IF($J9="",#N/A,SUM(EC$4:EC9)) -> 0 | EE9: =IF(AND($FV9="SW",$GA9="Long",$E9=EA$2),$FP9,"") | EF9: =IF($J9="",#N/A,SUM(EE$4:EE9)) -> 0 | EG9: =IF($J9="",#N/A,SUM(EE$4:EE9,EC$4:EC9,EA$4:EA9)) -> 0 | EH9: =IF(OR($GI9="",L9=""),"",IF($GA9="Long",(($J9*$GI9)-$GH9),($GH9-($J9*$GI9)))) -> 18.525712 | EI9: =IF(EH9="",#N/A,SUM($EH$4:EH9)) -> 159.30803 | EJ9: =IF(GZ9="","",IF(OR($GI9="",AM9=""),"",IF($GA9="Long",(($GZ9*$GI9)-$GH9),($GH9-($GZ9*$GI9))))) -> 24.068728 | EK9: =IF($GZ9="",#N/A,SUM(EJ$4:EJ9)) -> 273.2624 | EL9: =IF(J9="","",IF(D9="Y",FP9,"")) -> 0.77190465 | EM9: =IF(EL9="",NA(),SUM($EL$4:EL9)) -> 6.6378348 | EN9: =IF(AND($FV9="Up",$GA9="Long",$D9="Y"),$EL9,"") -> 0.77190465 | EO9: =IF(EN9="",NA(),SUM($EN$4:EN9)) -> 2.9142355 | EP9: =IF(AND($FV9="SW",$GA9="Long",$D9="Y"),$EL9,"") | EQ9: =IF(EP9="",NA(),SUM($EP$4:EP9)) -> #N/A | ER9: =IF(AND($FV9="Dwn",$GA9="Short",$D9="Y"),$EL9,"") | ES9: =IF(ER9="",NA(),SUM($ER$4:ER9)) -> #N/A | ET9: =IF($J9="","",IF($D9="N",$FP9,"")) | EU9: =IF(ET9="",NA(),SUM($ET$4:ET9)) -> #N/A | EV9: =IF(AND($FV9="Up",$GA9="Long",$D9="N"),$ET9,"") | EW9: =IF(EV9="",NA(),SUM($EV$4:EV9)) -> #N/A | EX9: =IF(AND($FV9="SW",$GA9="Long",$D9="N"),$ET9,"") | EY9: =IF(EX9="",NA(),SUM($EX$4:EX9)) -> #N/A | EZ9: =IF(AND($FV9="Dwn",$GA9="Short",$D9="N"),$ET9,"") | FA9: =IF(EZ9="",NA(),SUM($EZ$4:EZ9)) -> #N/A | FB9: =IF($GZ9="","",IF(AND($FV9="Dwn",$K9<0),$FN9-FP9,"")) | FC9: =IF($FB9="",#N/A,SUM(FB$4:$FB9)) -> #N/A | FD9: =IF($GZ9="","",IF(AND($FV9="Dwn",$K9>0),$FN9-$FP9,"")) | FE9: =IF($FD9="",#N/A,SUM($FD$4:FD9)) -> #N/A | FF9: =IF($GZ9="","",IF(AND($FV9="Up",$K9>0),$FN9-$FP9,"")) -> 0.230959 | FG9: =IF($FF9="",#N/A,SUM($FF$4:FF9)) -> 1.0322732 | FH9: =IF($GZ9="","",IF(AND($FV9="Up",$K9<0),$FN9-$FP9,"")) | FI9: =IF($FH9="",#N/A,SUM($FH$4:FH9)) -> #N/A | FJ9: =IF($GZ9="","",IF(AND($FV9="SW",$K9>0),$FN9-$FP9,"")) | FK9: =IF($FJ9="",#N/A,SUM($FJ$4:FJ9)) -> #N/A | FL9: =IF($GZ9="","",IF(AND($FV9="SW",$K9<0),$FN9-$FP9,"")) | FM9: =IF($FL9="",#N/A,SUM($FL$4:FL9)) -> #N/A | FN9: =IF(OR($GI9="",$GZ9=""),"",IF($GA9="Long",(($GZ9*$GI9)-$GH9)/($GH9*0.06),($GH9-($GZ9*$GI9))/($GH9*0.06))) -> 1.0028637 | FO9: =IF($FN9="",#N/A,SUM(FN$4:$FN9)) -> 11.385934 | FP9: =IF(OR($GI9="",L9=""),"",IF($GA9="Long",(($J9*$GI9)-$GH9)/(GH9*0.06),($GH9-($J9*$GI9))/(GH9*0.06))) -> 0.77190465 | FQ9: =IF($EH9="",#N/A,SUM($FP$4:FP9)) -> 6.6378348 | FU9: #N/A | FV9: =IF(FW9="Down","Dwn",IF(FW9="Up","Up",IF(AND(FW9="",K9=""),"",IF(AND(K9<0,FW9="Yes"),"Dwn",IF(AND(K9>0,FW9="Yes"),"Up",IF(AND(K9<0,FW9="No"),"Up",IF(AND(K9>0,FW9="No"),"Dwn",IF(FW9="NA","SW","err")))))))) -> Up | FW9: Yes | FX9: =IF(K9="","",IF(AND(K9>0,FW9="Yes"),1,"")) -> 1 | FY9: =IF(K9="","",IF(AND($K9>0,$FW9="No"),1,"")) | FZ9: =IF(K9="","",IF(AND($K9>0,$FW9="NA"),1,"")) | GA9: =IF(FV9="Dwn","Short","Long") -> Long | GB9: =IF(K9="","",IF(AND($K9<0,$FW9="Yes"),1,"")) | GC9: =IF(K9="","",IF(AND($K9<0,$FW9="No"),1,"")) | GD9: =IF(K9="","",IF(AND($K9<0,$FW9="NA"),1,"")) | GE9: =I9 -> 571.53 | GF9: Long | GG9: =400/I9 -> 0.69987577 | GH9: =IF(GG9="","",GE9*GG9) -> 400 | GI9: =GG9 -> 0.69987577 | GJ9: =J9 -> 598 | GK9: =IF($GI9="","",IF($GF9="Long",(($GJ9*$GI9)-$GH9),($GH9-($GJ9*$GI9)))) -> 18.525712 | GL9: =IF($GI9="","",IF($GF9="Long",(($GZ9*$GI9)-$GH9),($GH9-($GZ9*$GI9)))) -> 24.068728 | GM9: =IF(AND($FV9="SW",$GA9="Long"),$FN9,"") | GN9: =IF($GZ9="",#N/A,SUM(GM$4:GM9)) -> 4.5914678 | GO9: =IF(AND($FV9="UP",$GA9="Long"),$FN9,"") -> 1.0028637 | GP9: =IF($GZ9="",#N/A,SUM(GO$4:GO9)) -> 3.9465087 | GQ9: =IF(AND($FV9="Dwn",$GA9="Short"),$FN9,"") | GR9: =IF($GZ9="",#N/A,SUM(GQ$4:GQ9)) -> 2.847957 | GS9: =IF(AND(FV9="SW",GA9="Long"),$EJ9,"") | GT9: =IF($GZ9="",#N/A,SUM(GS$4:GS9)) -> 110.19523 | GU9: =IF(AND(FV9="UP",GA9="Long"),$EJ9,"") -> 24.068728 | GV9: =IF($GZ9="",#N/A,SUM(GU$4:GU9)) -> 94.71621 | GW9: =IF(AND(FV9="Dwn",GA9="Short"),$EJ9,"") | GX9: =IF($GZ9="",#N/A,SUM(GW$4:GW9)) -> 68.350967 | GY9: =IF(EJ9="",#N/A,SUM($EJ$4:EJ9)) -> 273.2624 | GZ9: 605.92 | HA9: =IF(OR(GL9="",GZ9=""),"",GL9-EH9) -> 5.5430161 | HB9: Skip | HC9: =IFERROR(VLOOKUP(E9,Expectancy!$P$4:$S$19,1+C9,FALSE),"") -> -0.079483353 | HD9: =IF(AND(HB9="MOC",GZ9=""),"",IF(GI9="","",IF(HB9="Skip","",IF(HG9=0,0,HG9/(GH9*0.06))))) | HE9: =IF(HD9="",#N/A,SUM($HD$4:HD9)) -> #N/A | HF9: =IF(HD9="",#N/A,IF(HB9="Skip",#N/A,SUM($HG$4:HG9))) -> #N/A | HG9: =IF(HB9="","",IF(HB9="Skip","",IF(OR(HB9="open",HB9="Other"),GK9,IF(HB9="MOC",GL9,"Err")))) | HH9: =IF(OR($GI9="",$L9=""),"",IF($GA9="Long",(($GZ9*$GI9)-$GH9)/($GH9*0.06),($GH9-($GZ9*$GI9))/($GH9*0.06))) -> 1.0028637
A10: BLK | B10: on 1/15/25, 5:59 AM Before Market Eas | C10: =IF(FV10="Dwn",2,IF(FV10="Up",1,IF(FV10="SW",3,"x"))) -> 3 | D10: =_xlfn.XLOOKUP(A10,[1]SP500!$A$2:$A$502,[1]SP500!$D$2:$D$502,"N") -> Y | E10: =_xlfn.XLOOKUP(A10,[1]SP500!$A$2:$A$655,[1]SP500!$B$2:$B$655) -> XLF | F10: 45672 | G10: =IF(ISNUMBER(FIND("After",B10,1)),"AMC",IF(ISNUMBER(FIND("Before",B10,1)),"BMO","err")) -> BMO | H10: =IF(HB10="other","o",IF(HB10="Skip","o",IF(OR(FV10="",GF10=""),"",IF(AND(FV10="Dwn",GF10="Short"),"s",IF(AND(FV10="Up",GF10="Long"),"s",IF(AND(FV10="SW",GF10="Long"),"s","o")))))) -> o | I10: 963.17 | J10: 1019.77 | K10: =IF(J10="","",(J10-I10)/I10) -> 0.058764289 | L10: =IF(OR($GI10="",J10=""),"",IF($GF10="Long",(($J10*$GI10)-$GH10),($GH10-($J10*$GI10)))) -> 23.505716 | M10: =IF(L10="","",IF(HG10="","",HG10-L10)) | N10: =IF(AND($FV10="Up",$GA10="Long"),$EH10,"") | O10: =IF($J10="",#N/A,SUM($N$4:N10)) -> 69.941652 | P10: =IF(AND($FV10="Dwn",$GA10="Short"),$EH10,"") | Q10: =IF($J10="",#N/A,SUM($P$4:P10)) -> 29.496534 | R10: =IF(AND($FV10="SW",$GA10="Long"),$EH10,"") -> 23.505716 | S10: =IF($J10="",#N/A,SUM($R$4:R10)) -> 83.375564 | T10: =IF(AND($FV10="Up",$GA10="Long"),$FP10,"") | U10: =IF($J10="",#N/A,SUM($T$4:T10)) -> 2.9142355 | V10: =IF(AND($FV10="Dwn",$GA10="Short"),$FP10,"") | W10: =IF($J10="",#N/A,SUM($V$4:V10)) -> 1.2290223 | X10: =IF(AND($FV10="SW",$GA10="Long"),$FP10,"") -> 0.97940481 | Y10: =IF($J10="",#N/A,SUM($X$4:X10)) -> 3.4739818 | Z10: =IF(AND($FV10="Up",$GA10="Long",$E10=Z$2),$FP10,"") | AA10: =IF($J10="",#N/A,SUM(Z$4:Z10)) -> 0 | AB10: =IF(AND($FV10="Dwn",$GA10="Short",$E10=Z$2),$FP10,"") | AC10: =IF($J10="",#N/A,SUM(AB$4:AB10)) -> 0 | AD10: =IF(AND($FV10="SW",$GA10="Long",$E10=Z$2),$FP10,"") | AE10: =IF($J10="",#N/A,SUM(AD$4:AD10)) -> 0 | AF10: =IF($J10="",#N/A,SUM(AD$4:AD10,AB$4:AB10,Z$4:Z10)) -> 0 | AG10: =IF(AND($FV10="Up",$GA10="Long",$E10=AG$2),$FP10,"") | AH10: =IF($J10="",#N/A,SUM(AG$4:AG10)) -> 0 | AI10: =IF(AND($FV10="Dwn",$GA10="Short",$E10=AG$2),$FP10,"") | AJ10: =IF($J10="",#N/A,SUM(AI$4:AI10)) -> 0 | AK10: =IF(AND($FV10="SW",$GA10="Long",$E10=AG$2),$FP10,"") | AL10: =IF($J10="",#N/A,SUM(AK$4:AK10)) -> 0 | AM10: =IF($J10="",#N/A,SUM(AK$4:AK10,AI$4:AI10,AG$4:AG10)) -> 0 | AN10: =IF(AND($FV10="Up",$GA10="Long",$E10=AN$2),$FP10,"") | AO10: =IF($J10="",#N/A,SUM(AN$4:AN10)) -> 0 | AP10: =IF(AND($FV10="Dwn",$GA10="Short",$E10=AN$2),$FP10,"") | AQ10: =IF($J10="",#N/A,SUM(AP$4:AP10)) -> 0 | AR10: =IF(AND($FV10="SW",$GA10="Long",$E10=AN$2),$FP10,"") | AS10: =IF($J10="",#N/A,SUM(AR$4:AR10)) -> 0 | AT10: =IF($J10="",#N/A,SUM(AR$4:AR10,AP$4:AP10,AN$4:AN10)) -> 0 | AU10: =IF(AND($FV10="Up",$GA10="Long",$E10=AU$2),$FP10,"") | AV10: =IF($J10="",#N/A,SUM(AU$4:AU10)) -> 0 | AW10: =IF(AND($FV10="Dwn",$GA10="Short",$E10=AU$2),$FP10,"") | AX10: =IF($J10="",#N/A,SUM(AW$4:AW10)) -> 1.2290223 | AY10: =IF(AND($FV10="SW",$GA10="Long",$E10=AU$2),$FP10,"") | AZ10: =IF($J10="",#N/A,SUM(AY$4:AY10)) -> 2.494577 | BA10: =IF($J10="",#N/A,SUM(AY$4:AY10,AW$4:AW10,AU$4:AU10)) -> 3.7235993 | BB10: =IF(AND($FV10="Up",$GA10="Long",$E10=BB$2),$FP10,"") | BC10: =IF($J10="",#N/A,SUM(BB$4:BB10)) -> 0 | BD10: =IF(AND($FV10="Dwn",$GA10="Short",$E10=BB$2),$FP10,"") | BE10: =IF($J10="",#N/A,SUM(BD$4:BD10)) -> 0 | BF10: =IF(AND($FV10="SW",$GA10="Long",$E10=BB$2),$FP10,"") | BG10: =IF($J10="",#N/A,SUM(BF$4:BF10)) -> 0 | BH10: =IF($J10="",#N/A,SUM(BF$4:BF10,BD$4:BD10,BB$4:BB10)) -> 0 | BI10: =IF(AND($FV10="Up",$GA10="Long",$E10=BI$2),$FP10,"") | BJ10: =IF($J10="",#N/A,SUM(BI$4:BI10)) -> 1.9454957 | BK10: =IF(AND($FV10="Dwn",$GA10="Short",$E10=BI$2),$FP10,"") | BL10: =IF($J10="",#N/A,SUM(BK$4:BK10)) -> 0 | BM10: =IF(AND($FV10="SW",$GA10="Long",$E10=BI$2),$FP10,"") -> 0.97940481 | BN10: =IF($J10="",#N/A,SUM(BM$4:BM10)) -> 0.97940481 | BO10: =IF($J10="",#N/A,SUM(BM$4:BM10,BK$4:BK10,BI$4:BI10)) -> 2.9249005 | BP10: =IF(AND($FV10="Up",$GA10="Long",$E10=BP$2),$FP10,"") | BQ10: =IF($J10="",#N/A,SUM(BP$4:BP10)) -> 0.96873982 | BR10: =IF(AND($FV10="Dwn",$GA10="Short",$E10=BP$2),$FP10,"") | BS10: =IF($J10="",#N/A,SUM(BR$4:BR10)) -> 0 | BT10: =IF(AND($FV10="SW",$GA10="Long",$E10=BP$2),$FP10,"") | BU10: =IF($J10="",#N/A,SUM(BT$4:BT10)) -> 0 | BV10: =IF($J10="",#N/A,SUM(BT$4:BT10,BR$4:BR10,BP$4:BP10)) -> 0.96873982 | BW10: =IF(AND($FV10="Up",$GA10="Long",$E10=BW$2),$FP10,"") | BX10: =IF($J10="",#N/A,SUM(BW$4:BW10)) -> 0 | BY10: =IF(AND($FV10="Dwn",$GA10="Short",$E10=BW$2),$FP10,"") | BZ10: =IF($J10="",#N/A,SUM(BY$4:BY10)) -> 0 | CA10: =IF(AND($FV10="SW",$GA10="Long",$E10=BW$2),$FP10,"") | CB10: =IF($J10="",#N/A,SUM(CA$4:CA10)) -> 0 | CC10: =IF($J10="",#N/A,SUM(CA$4:CA10,BY$4:BY10,BW$4:BW10)) -> 0 | CD10: =IF(AND($FV10="Up",$GA10="Long",$E10=CD$2),$FP10,"") | CE10: =IF($J10="",#N/A,SUM(CD$4:CD10)) -> 0 | CF10: =IF(AND($FV10="Dwn",$GA10="Short",$E10=CD$2),$FP10,"") | CG10: =IF($J10="",#N/A,SUM(CF$4:CF10)) -> 0 | CH10: =IF(AND($FV10="SW",$GA10="Long",$E10=CD$2),$FP10,"") | CI10: =IF($J10="",#N/A,SUM(CH$4:CH10)) -> 0 | CJ10: =IF($J10="",#N/A,SUM(CH$4:CH10,CF$4:CF10,CD$4:CD10)) -> 0 | CK10: =IF(AND($FV10="Up",$GA10="Long",$E10=CK$2),$FP10,"") | CL10: =IF($J10="",#N/A,SUM(CK$4:CK10)) -> 0 | CM10: =IF(AND($FV10="Dwn",$GA10="Short",$E10=CK$2),$FP10,"") | CN10: =IF($J10="",#N/A,SUM(CM$4:CM10)) -> 0 | CO10: =IF(AND($FV10="SW",$GA10="Long",$E10=CK$2),$FP10,"") | CP10: =IF($J10="",#N/A,SUM(CO$4:CO10)) -> 0 | CQ10: =IF($J10="",#N/A,SUM(CO$4:CO10,CM$4:CM10,CK$4:CK10)) -> 0 | CR10: =IF(AND($FV10="Up",$GA10="Long",$E10=CR$2),$FP10,"") | CS10: =IF($J10="",#N/A,SUM(CR$4:CR10)) -> 0 | CT10: =IF(AND($FV10="Dwn",$GA10="Short",$E10=CR$2),$FP10,"") | CU10: =IF($J10="",#N/A,SUM(CT$4:CT10)) -> 0 | CV10: =IF(AND($FV10="SW",$GA10="Long",$E10=CR$2),$FP10,"") | CW10: =IF($J10="",#N/A,SUM(CV$4:CV10)) -> 0 | CX10: =IF($J10="",#N/A,SUM(CV$4:CV10,CT$4:CT10,CR$4:CR10)) -> 0 | CY10: =IF(AND($FV10="Up",$GA10="Long",$E10=CY$2),$FP10,"") | CZ10: =IF($J10="",#N/A,SUM(CY$4:CY10)) -> 0 | DA10: =IF(AND($FV10="Dwn",$GA10="Short",$E10=CY$2),$FP10,"") | DB10: =IF($J10="",#N/A,SUM(DA$4:DA10)) -> 0 | DC10: =IF(AND($FV10="SW",$GA10="Long",$E10=CY$2),$FP10,"") | DD10: =IF($J10="",#N/A,SUM(DC$4:DC10)) -> 0 | DE10: =IF($J10="",#N/A,SUM(DC$4:DC10,DA$4:DA10,CY$4:CY10)) -> 0 | DF10: =IF(AND($FV10="Up",$GA10="Long",$E10=DF$2),$FP10,"") | DG10: =IF($J10="",#N/A,SUM(DF$4:DF10)) -> 0 | DH10: =IF(AND($FV10="Dwn",$GA10="Short",$E10=DF$2),$FP10,"") | DI10: =IF($J10="",#N/A,SUM(DH$4:DH10)) -> 0 | DJ10: =IF(AND($FV10="SW",$GA10="Long",$E10=DF$2),$FP10,"") | DK10: =IF($J10="",#N/A,SUM(DJ$4:DJ10)) -> 0 | DL10: =IF($J10="",#N/A,SUM(DJ$4:DJ10,DH$4:DH10,DF$4:DF10)) -> 0 | DM10: =IF(AND($FV10="Up",$GA10="Long",$E10=DM$2),$FP10,"") | DN10: =IF($J10="",#N/A,SUM(DM$4:DM10)) -> 0 | DO10: =IF(AND($FV10="Dwn",$GA10="Short",$E10=DM$2),$FP10,"") | DP10: =IF($J10="",#N/A,SUM(DO$4:DO10)) -> 0 | DQ10: =IF(AND($FV10="SW",$GA10="Long",$E10=DM$2),$FP10,"") | DR10: =IF($J10="",#N/A,SUM(DQ$4:DQ10)) -> 0 | DS10: =IF($J10="",#N/A,SUM(DQ$4:DQ10,DO$4:DO10,DM$4:DM10)) -> 0 | DT10: =IF(AND($FV10="Up",$GA10="Long",$E10=DT$2),$FP10,"") | DU10: =IF($J10="",#N/A,SUM(DT$4:DT10)) -> 0 | DV10: =IF(AND($FV10="Dwn",$GA10="Short",$E10=DT$2),$FP10,"") | DW10: =IF($J10="",#N/A,SUM(DV$4:DV10)) -> 0 | DX10: =IF(AND($FV10="SW",$GA10="Long",$E10=DT$2),$FP10,"") | DY10: =IF($J10="",#N/A,SUM(DX$4:DX10)) -> 0 | DZ10: =IF($J10="",#N/A,SUM(DX$4:DX10,DV$4:DV10,DT$4:DT10)) -> 0 | EA10: =IF(AND($FV10="Up",$GA10="Long",$E10=EA$2),$FP10,"") | EB10: =IF($J10="",#N/A,SUM(EA$4:EA10)) -> 0 | EC10: =IF(AND($FV10="Dwn",$GA10="Short",$E10=EA$2),$FP10,"") | ED10: =IF($J10="",#N/A,SUM(EC$4:EC10)) -> 0 | EE10: =IF(AND($FV10="SW",$GA10="Long",$E10=EA$2),$FP10,"") | EF10: =IF($J10="",#N/A,SUM(EE$4:EE10)) -> 0 | EG10: =IF($J10="",#N/A,SUM(EE$4:EE10,EC$4:EC10,EA$4:EA10)) -> 0 | EH10: =IF(OR($GI10="",L10=""),"",IF($GA10="Long",(($J10*$GI10)-$GH10),($GH10-($J10*$GI10)))) -> 23.505716 | EI10: =IF(EH10="",#N/A,SUM($EH$4:EH10)) -> 182.81375 | EJ10: =IF(GZ10="","",IF(OR($GI10="",AM10=""),"",IF($GA10="Long",(($GZ10*$GI10)-$GH10),($GH10-($GZ10*$GI10))))) -> 20.768919 | EK10: =IF($GZ10="",#N/A,SUM(EJ$4:EJ10)) -> 294.03132 | EL10: =IF(J10="","",IF(D10="Y",FP10,"")) -> 0.97940481 | EM10: =IF(EL10="",NA(),SUM($EL$4:EL10)) -> 7.6172396 | EN10: =IF(AND($FV10="Up",$GA10="Long",$D10="Y"),$EL10,"") | EO10: =IF(EN10="",NA(),SUM($EN$4:EN10)) -> #N/A | EP10: =IF(AND($FV10="SW",$GA10="Long",$D10="Y"),$EL10,"") -> 0.97940481 | EQ10: =IF(EP10="",NA(),SUM($EP$4:EP10)) -> 3.4739818 | ER10: =IF(AND($FV10="Dwn",$GA10="Short",$D10="Y"),$EL10,"") | ES10: =IF(ER10="",NA(),SUM($ER$4:ER10)) -> #N/A | ET10: =IF($J10="","",IF($D10="N",$FP10,"")) | EU10: =IF(ET10="",NA(),SUM($ET$4:ET10)) -> #N/A | EV10: =IF(AND($FV10="Up",$GA10="Long",$D10="N"),$ET10,"") | EW10: =IF(EV10="",NA(),SUM($EV$4:EV10)) -> #N/A | EX10: =IF(AND($FV10="SW",$GA10="Long",$D10="N"),$ET10,"") | EY10: =IF(EX10="",NA(),SUM($EX$4:EX10)) -> #N/A | EZ10: =IF(AND($FV10="Dwn",$GA10="Short",$D10="N"),$ET10,"") | FA10: =IF(EZ10="",NA(),SUM($EZ$4:EZ10)) -> #N/A | FB10: =IF($GZ10="","",IF(AND($FV10="Dwn",$K10<0),$FN10-FP10,"")) | FC10: =IF($FB10="",#N/A,SUM(FB$4:$FB10)) -> #N/A | FD10: =IF($GZ10="","",IF(AND($FV10="Dwn",$K10>0),$FN10-$FP10,"")) | FE10: =IF($FD10="",#N/A,SUM($FD$4:FD10)) -> #N/A | FF10: =IF($GZ10="","",IF(AND($FV10="Up",$K10>0),$FN10-$FP10,"")) | FG10: =IF($FF10="",#N/A,SUM($FF$4:FF10)) -> #N/A | FH10: =IF($GZ10="","",IF(AND($FV10="Up",$K10<0),$FN10-$FP10,"")) | FI10: =IF($FH10="",#N/A,SUM($FH$4:FH10)) -> #N/A | FJ10: =IF($GZ10="","",IF(AND($FV10="SW",$K10>0),$FN10-$FP10,"")) -> -0.11403318 | FK10: =IF($FJ10="",#N/A,SUM($FJ$4:FJ10)) -> 1.9828576 | FL10: =IF($GZ10="","",IF(AND($FV10="SW",$K10<0),$FN10-$FP10,"")) | FM10: =IF($FL10="",#N/A,SUM($FL$4:FL10)) -> #N/A | FN10: =IF(OR($GI10="",$GZ10=""),"",IF($GA10="Long",(($GZ10*$GI10)-$GH10)/($GH10*0.06),($GH10-($GZ10*$GI10))/($GH10*0.06))) -> 0.86537164 | FO10: =IF($FN10="",#N/A,SUM(FN$4:$FN10)) -> 12.251305 | FP10: =IF(OR($GI10="",L10=""),"",IF($GA10="Long",(($J10*$GI10)-$GH10)/(GH10*0.06),($GH10-($J10*$GI10))/(GH10*0.06))) -> 0.97940481 | FQ10: =IF($EH10="",#N/A,SUM($FP$4:FP10)) -> 7.6172396 | FU10: #N/A | FV10: =IF(FW10="Down","Dwn",IF(FW10="Up","Up",IF(AND(FW10="",K10=""),"",IF(AND(K10<0,FW10="Yes"),"Dwn",IF(AND(K10>0,FW10="Yes"),"Up",IF(AND(K10<0,FW10="No"),"Up",IF(AND(K10>0,FW10="No"),"Dwn",IF(FW10="NA","SW","err")))))))) -> SW | FW10: NA | FX10: =IF(K10="","",IF(AND(K10>0,FW10="Yes"),1,"")) | FY10: =IF(K10="","",IF(AND($K10>0,$FW10="No"),1,"")) | FZ10: =IF(K10="","",IF(AND($K10>0,$FW10="NA"),1,"")) -> 1 | GA10: =IF(FV10="Dwn","Short","Long") -> Long | GB10: =IF(K10="","",IF(AND($K10<0,$FW10="Yes"),1,"")) | GC10: =IF(K10="","",IF(AND($K10<0,$FW10="No"),1,"")) | GD10: =IF(K10="","",IF(AND($K10<0,$FW10="NA"),1,"")) | GE10: =I10 -> 963.17 | GF10: Long | GG10: =400/I10 -> 0.41529533 | GH10: =IF(GG10="","",GE10*GG10) -> 400 | GI10: =GG10 -> 0.41529533 | GJ10: =J10 -> 1019.77 | GK10: =IF($GI10="","",IF($GF10="Long",(($GJ10*$GI10)-$GH10),($GH10-($GJ10*$GI10)))) -> 23.505716 | GL10: =IF($GI10="","",IF($GF10="Long",(($GZ10*$GI10)-$GH10),($GH10-($GZ10*$GI10)))) -> 20.768919 | GM10: =IF(AND($FV10="SW",$GA10="Long"),$FN10,"") -> 0.86537164 | GN10: =IF($GZ10="",#N/A,SUM(GM$4:GM10)) -> 5.4568395 | GO10: =IF(AND($FV10="UP",$GA10="Long"),$FN10,"") | GP10: =IF($GZ10="",#N/A,SUM(GO$4:GO10)) -> 3.9465087 | GQ10: =IF(AND($FV10="Dwn",$GA10="Short"),$FN10,"") | GR10: =IF($GZ10="",#N/A,SUM(GQ$4:GQ10)) -> 2.847957 | GS10: =IF(AND(FV10="SW",GA10="Long"),$EJ10,"") -> 20.768919 | GT10: =IF($GZ10="",#N/A,SUM(GS$4:GS10)) -> 130.96415 | GU10: =IF(AND(FV10="UP",GA10="Long"),$EJ10,"") | GV10: =IF($GZ10="",#N/A,SUM(GU$4:GU10)) -> 94.71621 | GW10: =IF(AND(FV10="Dwn",GA10="Short"),$EJ10,"") | GX10: =IF($GZ10="",#N/A,SUM(GW$4:GW10)) -> 68.350967 | GY10: =IF(EJ10="",#N/A,SUM($EJ$4:EJ10)) -> 294.03132 | GZ10: 1013.18 | HA10: =IF(OR(GL10="",GZ10=""),"",GL10-EH10) -> -2.7367962 | HB10: Skip | HC10: =IFERROR(VLOOKUP(E10,Expectancy!$P$4:$S$19,1+C10,FALSE),"") -> 0.099793136 | HD10: =IF(AND(HB10="MOC",GZ10=""),"",IF(GI10="","",IF(HB10="Skip","",IF(HG10=0,0,HG10/(GH10*0.06))))) | HE10: =IF(HD10="",#N/A,SUM($HD$4:HD10)) -> #N/A | HF10: =IF(HD10="",#N/A,IF(HB10="Skip",#N/A,SUM($HG$4:HG10))) -> #N/A | HG10: =IF(HB10="","",IF(HB10="Skip","",IF(OR(HB10="open",HB10="Other"),GK10,IF(HB10="MOC",GL10,"Err")))) | HH10: =IF(OR($GI10="",$L10=""),"",IF($GA10="Long",(($GZ10*$GI10)-$GH10)/($GH10*0.06),($GH10-($GZ10*$GI10))/($GH10*0.06))) -> 0.86537164
A11: C | B11: on 1/15/25, 1:00 AM Before Market Eas | C11: =IF(FV11="Dwn",2,IF(FV11="Up",1,IF(FV11="SW",3,"x"))) -> 1 | D11: =_xlfn.XLOOKUP(A11,[1]SP500!$A$2:$A$502,[1]SP500!$D$2:$D$502,"N") -> Y | E11: =_xlfn.XLOOKUP(A11,[1]SP500!$A$2:$A$655,[1]SP500!$B$2:$B$655) -> XLF | F11: 45672 | G11: =IF(ISNUMBER(FIND("After",B11,1)),"AMC",IF(ISNUMBER(FIND("Before",B11,1)),"BMO","err")) -> BMO | H11: =IF(HB11="other","o",IF(HB11="Skip","o",IF(OR(FV11="",GF11=""),"",IF(AND(FV11="Dwn",GF11="Short"),"s",IF(AND(FV11="Up",GF11="Long"),"s",IF(AND(FV11="SW",GF11="Long"),"s","o")))))) -> o | I11: 73.5 | J11: 76.2 | K11: =IF(J11="","",(J11-I11)/I11) -> 0.036734694 | L11: =IF(OR($GI11="",J11=""),"",IF($GF11="Long",(($J11*$GI11)-$GH11),($GH11-($J11*$GI11)))) -> 14.693878 | M11: =IF(L11="","",IF(HG11="","",HG11-L11)) | N11: =IF(AND($FV11="Up",$GA11="Long"),$EH11,"") -> 14.693878 | O11: =IF($J11="",#N/A,SUM($N$4:N11)) -> 84.63553 | P11: =IF(AND($FV11="Dwn",$GA11="Short"),$EH11,"") | Q11: =IF($J11="",#N/A,SUM($P$4:P11)) -> 29.496534 | R11: =IF(AND($FV11="SW",$GA11="Long"),$EH11,"") | S11: =IF($J11="",#N/A,SUM($R$4:R11)) -> 83.375564 | T11: =IF(AND($FV11="Up",$GA11="Long"),$FP11,"") -> 0.6122449 | U11: =IF($J11="",#N/A,SUM($T$4:T11)) -> 3.5264804 | V11: =IF(AND($FV11="Dwn",$GA11="Short"),$FP11,"") | W11: =IF($J11="",#N/A,SUM($V$4:V11)) -> 1.2290223 | X11: =IF(AND($FV11="SW",$GA11="Long"),$FP11,"") | Y11: =IF($J11="",#N/A,SUM($X$4:X11)) -> 3.4739818 | Z11: =IF(AND($FV11="Up",$GA11="Long",$E11=Z$2),$FP11,"") | AA11: =IF($J11="",#N/A,SUM(Z$4:Z11)) -> 0 | AB11: =IF(AND($FV11="Dwn",$GA11="Short",$E11=Z$2),$FP11,"") | AC11: =IF($J11="",#N/A,SUM(AB$4:AB11)) -> 0 | AD11: =IF(AND($FV11="SW",$GA11="Long",$E11=Z$2),$FP11,"") | AE11: =IF($J11="",#N/A,SUM(AD$4:AD11)) -> 0 | AF11: =IF($J11="",#N/A,SUM(AD$4:AD11,AB$4:AB11,Z$4:Z11)) -> 0 | AG11: =IF(AND($FV11="Up",$GA11="Long",$E11=AG$2),$FP11,"") | AH11: =IF($J11="",#N/A,SUM(AG$4:AG11)) -> 0 | AI11: =IF(AND($FV11="Dwn",$GA11="Short",$E11=AG$2),$FP11,"") | AJ11: =IF($J11="",#N/A,SUM(AI$4:AI11)) -> 0 | AK11: =IF(AND($FV11="SW",$GA11="Long",$E11=AG$2),$FP11,"") | AL11: =IF($J11="",#N/A,SUM(AK$4:AK11)) -> 0 | AM11: =IF($J11="",#N/A,SUM(AK$4:AK11,AI$4:AI11,AG$4:AG11)) -> 0 | AN11: =IF(AND($FV11="Up",$GA11="Long",$E11=AN$2),$FP11,"") | AO11: =IF($J11="",#N/A,SUM(AN$4:AN11)) -> 0 | AP11: =IF(AND($FV11="Dwn",$GA11="Short",$E11=AN$2),$FP11,"") | AQ11: =IF($J11="",#N/A,SUM(AP$4:AP11)) -> 0 | AR11: =IF(AND($FV11="SW",$GA11="Long",$E11=AN$2),$FP11,"") | AS11: =IF($J11="",#N/A,SUM(AR$4:AR11)) -> 0 | AT11: =IF($J11="",#N/A,SUM(AR$4:AR11,AP$4:AP11,AN$4:AN11)) -> 0 | AU11: =IF(AND($FV11="Up",$GA11="Long",$E11=AU$2),$FP11,"") | AV11: =IF($J11="",#N/A,SUM(AU$4:AU11)) -> 0 | AW11: =IF(AND($FV11="Dwn",$GA11="Short",$E11=AU$2),$FP11,"") | AX11: =IF($J11="",#N/A,SUM(AW$4:AW11)) -> 1.2290223 | AY11: =IF(AND($FV11="SW",$GA11="Long",$E11=AU$2),$FP11,"") | AZ11: =IF($J11="",#N/A,SUM(AY$4:AY11)) -> 2.494577 | BA11: =IF($J11="",#N/A,SUM(AY$4:AY11,AW$4:AW11,AU$4:AU11)) -> 3.7235993 | BB11: =IF(AND($FV11="Up",$GA11="Long",$E11=BB$2),$FP11,"") | BC11: =IF($J11="",#N/A,SUM(BB$4:BB11)) -> 0 | BD11: =IF(AND($FV11="Dwn",$GA11="Short",$E11=BB$2),$FP11,"") | BE11: =IF($J11="",#N/A,SUM(BD$4:BD11)) -> 0 | BF11: =IF(AND($FV11="SW",$GA11="Long",$E11=BB$2),$FP11,"") | BG11: =IF($J11="",#N/A,SUM(BF$4:BF11)) -> 0 | BH11: =IF($J11="",#N/A,SUM(BF$4:BF11,BD$4:BD11,BB$4:BB11)) -> 0 | BI11: =IF(AND($FV11="Up",$GA11="Long",$E11=BI$2),$FP11,"") -> 0.6122449 | BJ11: =IF($J11="",#N/A,SUM(BI$4:BI11)) -> 2.5577406 | BK11: =IF(AND($FV11="Dwn",$GA11="Short",$E11=BI$2),$FP11,"") | BL11: =IF($J11="",#N/A,SUM(BK$4:BK11)) -> 0 | BM11: =IF(AND($FV11="SW",$GA11="Long",$E11=BI$2),$FP11,"") | BN11: =IF($J11="",#N/A,SUM(BM$4:BM11)) -> 0.97940481 | BO11: =IF($J11="",#N/A,SUM(BM$4:BM11,BK$4:BK11,BI$4:BI11)) -> 3.5371454 | BP11: =IF(AND($FV11="Up",$GA11="Long",$E11=BP$2),$FP11,"") | BQ11: =IF($J11="",#N/A,SUM(BP$4:BP11)) -> 0.96873982 | BR11: =IF(AND($FV11="Dwn",$GA11="Short",$E11=BP$2),$FP11,"") | BS11: =IF($J11="",#N/A,SUM(BR$4:BR11)) -> 0 | BT11: =IF(AND($FV11="SW",$GA11="Long",$E11=BP$2),$FP11,"") | BU11: =IF($J11="",#N/A,SUM(BT$4:BT11)) -> 0 | BV11: =IF($J11="",#N/A,SUM(BT$4:BT11,BR$4:BR11,BP$4:BP11)) -> 0.96873982 | BW11: =IF(AND($FV11="Up",$GA11="Long",$E11=BW$2),$FP11,"") | BX11: =IF($J11="",#N/A,SUM(BW$4:BW11)) -> 0 | BY11: =IF(AND($FV11="Dwn",$GA11="Short",$E11=BW$2),$FP11,"") | BZ11: =IF($J11="",#N/A,SUM(BY$4:BY11)) -> 0 | CA11: =IF(AND($FV11="SW",$GA11="Long",$E11=BW$2),$FP11,"") | CB11: =IF($J11="",#N/A,SUM(CA$4:CA11)) -> 0 | CC11: =IF($J11="",#N/A,SUM(CA$4:CA11,BY$4:BY11,BW$4:BW11)) -> 0 | CD11: =IF(AND($FV11="Up",$GA11="Long",$E11=CD$2),$FP11,"") | CE11: =IF($J11="",#N/A,SUM(CD$4:CD11)) -> 0 | CF11: =IF(AND($FV11="Dwn",$GA11="Short",$E11=CD$2),$FP11,"") | CG11: =IF($J11="",#N/A,SUM(CF$4:CF11)) -> 0 | CH11: =IF(AND($FV11="SW",$GA11="Long",$E11=CD$2),$FP11,"") | CI11: =IF($J11="",#N/A,SUM(CH$4:CH11)) -> 0 | CJ11: =IF($J11="",#N/A,SUM(CH$4:CH11,CF$4:CF11,CD$4:CD11)) -> 0 | CK11: =IF(AND($FV11="Up",$GA11="Long",$E11=CK$2),$FP11,"") | CL11: =IF($J11="",#N/A,SUM(CK$4:CK11)) -> 0 | CM11: =IF(AND($FV11="Dwn",$GA11="Short",$E11=CK$2),$FP11,"") | CN11: =IF($J11="",#N/A,SUM(CM$4:CM11)) -> 0 | CO11: =IF(AND($FV11="SW",$GA11="Long",$E11=CK$2),$FP11,"") | CP11: =IF($J11="",#N/A,SUM(CO$4:CO11)) -> 0 | CQ11: =IF($J11="",#N/A,SUM(CO$4:CO11,CM$4:CM11,CK$4:CK11)) -> 0 | CR11: =IF(AND($FV11="Up",$GA11="Long",$E11=CR$2),$FP11,"") | CS11: =IF($J11="",#N/A,SUM(CR$4:CR11)) -> 0 | CT11: =IF(AND($FV11="Dwn",$GA11="Short",$E11=CR$2),$FP11,"") | CU11: =IF($J11="",#N/A,SUM(CT$4:CT11)) -> 0 | CV11: =IF(AND($FV11="SW",$GA11="Long",$E11=CR$2),$FP11,"") | CW11: =IF($J11="",#N/A,SUM(CV$4:CV11)) -> 0 | CX11: =IF($J11="",#N/A,SUM(CV$4:CV11,CT$4:CT11,CR$4:CR11)) -> 0 | CY11: =IF(AND($FV11="Up",$GA11="Long",$E11=CY$2),$FP11,"") | CZ11: =IF($J11="",#N/A,SUM(CY$4:CY11)) -> 0 | DA11: =IF(AND($FV11="Dwn",$GA11="Short",$E11=CY$2),$FP11,"") | DB11: =IF($J11="",#N/A,SUM(DA$4:DA11)) -> 0 | DC11: =IF(AND($FV11="SW",$GA11="Long",$E11=CY$2),$FP11,"") | DD11: =IF($J11="",#N/A,SUM(DC$4:DC11)) -> 0 | DE11: =IF($J11="",#N/A,SUM(DC$4:DC11,DA$4:DA11,CY$4:CY11)) -> 0 | DF11: =IF(AND($FV11="Up",$GA11="Long",$E11=DF$2),$FP11,"") | DG11: =IF($J11="",#N/A,SUM(DF$4:DF11)) -> 0 | DH11: =IF(AND($FV11="Dwn",$GA11="Short",$E11=DF$2),$FP11,"") | DI11: =IF($J11="",#N/A,SUM(DH$4:DH11)) -> 0 | DJ11: =IF(AND($FV11="SW",$GA11="Long",$E11=DF$2),$FP11,"") | DK11: =IF($J11="",#N/A,SUM(DJ$4:DJ11)) -> 0 | DL11: =IF($J11="",#N/A,SUM(DJ$4:DJ11,DH$4:DH11,DF$4:DF11)) -> 0 | DM11: =IF(AND($FV11="Up",$GA11="Long",$E11=DM$2),$FP11,"") | DN11: =IF($J11="",#N/A,SUM(DM$4:DM11)) -> 0 | DO11: =IF(AND($FV11="Dwn",$GA11="Short",$E11=DM$2),$FP11,"") | DP11: =IF($J11="",#N/A,SUM(DO$4:DO11)) -> 0 | DQ11: =IF(AND($FV11="SW",$GA11="Long",$E11=DM$2),$FP11,"") | DR11: =IF($J11="",#N/A,SUM(DQ$4:DQ11)) -> 0 | DS11: =IF($J11="",#N/A,SUM(DQ$4:DQ11,DO$4:DO11,DM$4:DM11)) -> 0 | DT11: =IF(AND($FV11="Up",$GA11="Long",$E11=DT$2),$FP11,"") | DU11: =IF($J11="",#N/A,SUM(DT$4:DT11)) -> 0 | DV11: =IF(AND($FV11="Dwn",$GA11="Short",$E11=DT$2),$FP11,"") | DW11: =IF($J11="",#N/A,SUM(DV$4:DV11)) -> 0 | DX11: =IF(AND($FV11="SW",$GA11="Long",$E11=DT$2),$FP11,"") | DY11: =IF($J11="",#N/A,SUM(DX$4:DX11)) -> 0 | DZ11: =IF($J11="",#N/A,SUM(DX$4:DX11,DV$4:DV11,DT$4:DT11)) -> 0 | EA11: =IF(AND($FV11="Up",$GA11="Long",$E11=EA$2),$FP11,"") | EB11: =IF($J11="",#N/A,SUM(EA$4:EA11)) -> 0 | EC11: =IF(AND($FV11="Dwn",$GA11="Short",$E11=EA$2),$FP11,"") | ED11: =IF($J11="",#N/A,SUM(EC$4:EC11)) -> 0 | EE11: =IF(AND($FV11="SW",$GA11="Long",$E11=EA$2),$FP11,"") | EF11: =IF($J11="",#N/A,SUM(EE$4:EE11)) -> 0 | EG11: =IF($J11="",#N/A,SUM(EE$4:EE11,EC$4:EC11,EA$4:EA11)) -> 0 | EH11: =IF(OR($GI11="",L11=""),"",IF($GA11="Long",(($J11*$GI11)-$GH11),($GH11-($J11*$GI11)))) -> 14.693878 | EI11: =IF(EH11="",#N/A,SUM($EH$4:EH11)) -> 197.50763 | EJ11: =IF(GZ11="","",IF(OR($GI11="",AM11=""),"",IF($GA11="Long",(($GZ11*$GI11)-$GH11),($GH11-($GZ11*$GI11))))) -> 25.959184 | EK11: =IF($GZ11="",#N/A,SUM(EJ$4:EJ11)) -> 319.99051 | EL11: =IF(J11="","",IF(D11="Y",FP11,"")) -> 0.6122449 | EM11: =IF(EL11="",NA(),SUM($EL$4:EL11)) -> 8.2294845 | EN11: =IF(AND($FV11="Up",$GA11="Long",$D11="Y"),$EL11,"") -> 0.6122449 | EO11: =IF(EN11="",NA(),SUM($EN$4:EN11)) -> 3.5264804 | EP11: =IF(AND($FV11="SW",$GA11="Long",$D11="Y"),$EL11,"") | EQ11: =IF(EP11="",NA(),SUM($EP$4:EP11)) -> #N/A | ER11: =IF(AND($FV11="Dwn",$GA11="Short",$D11="Y"),$EL11,"") | ES11: =IF(ER11="",NA(),SUM($ER$4:ER11)) -> #N/A | ET11: =IF($J11="","",IF($D11="N",$FP11,"")) | EU11: =IF(ET11="",NA(),SUM($ET$4:ET11)) -> #N/A | EV11: =IF(AND($FV11="Up",$GA11="Long",$D11="N"),$ET11,"") | EW11: =IF(EV11="",NA(),SUM($EV$4:EV11)) -> #N/A | EX11: =IF(AND($FV11="SW",$GA11="Long",$D11="N"),$ET11,"") | EY11: =IF(EX11="",NA(),SUM($EX$4:EX11)) -> #N/A | EZ11: =IF(AND($FV11="Dwn",$GA11="Short",$D11="N"),$ET11,"") | FA11: =IF(EZ11="",NA(),SUM($EZ$4:EZ11)) -> #N/A | FB11: =IF($GZ11="","",IF(AND($FV11="Dwn",$K11<0),$FN11-FP11,"")) | FC11: =IF($FB11="",#N/A,SUM(FB$4:$FB11)) -> #N/A | FD11: =IF($GZ11="","",IF(AND($FV11="Dwn",$K11>0),$FN11-$FP11,"")) | FE11: =IF($FD11="",#N/A,SUM($FD$4:FD11)) -> #N/A | FF11: =IF($GZ11="","",IF(AND($FV11="Up",$K11>0),$FN11-$FP11,"")) -> 0.46938776 | FG11: =IF($FF11="",#N/A,SUM($FF$4:FF11)) -> 1.501661 | FH11: =IF($GZ11="","",IF(AND($FV11="Up",$K11<0),$FN11-$FP11,"")) | FI11: =IF($FH11="",#N/A,SUM($FH$4:FH11)) -> #N/A | FJ11: =IF($GZ11="","",IF(AND($FV11="SW",$K11>0),$FN11-$FP11,"")) | FK11: =IF($FJ11="",#N/A,SUM($FJ$4:FJ11)) -> #N/A | FL11: =IF($GZ11="","",IF(AND($FV11="SW",$K11<0),$FN11-$FP11,"")) | FM11: =IF($FL11="",#N/A,SUM($FL$4:FL11)) -> #N/A | FN11: =IF(OR($GI11="",$GZ11=""),"",IF($GA11="Long",(($GZ11*$GI11)-$GH11)/($GH11*0.06),($GH11-($GZ11*$GI11))/($GH11*0.06))) -> 1.0816327 | FO11: =IF($FN11="",#N/A,SUM(FN$4:$FN11)) -> 13.332938 | FP11: =IF(OR($GI11="",L11=""),"",IF($GA11="Long",(($J11*$GI11)-$GH11)/(GH11*0.06),($GH11-($J11*$GI11))/(GH11*0.06))) -> 0.6122449 | FQ11: =IF($EH11="",#N/A,SUM($FP$4:FP11)) -> 8.2294845 | FU11: #N/A | FV11: =IF(FW11="Down","Dwn",IF(FW11="Up","Up",IF(AND(FW11="",K11=""),"",IF(AND(K11<0,FW11="Yes"),"Dwn",IF(AND(K11>0,FW11="Yes"),"Up",IF(AND(K11<0,FW11="No"),"Up",IF(AND(K11>0,FW11="No"),"Dwn",IF(FW11="NA","SW","err")))))))) -> Up | FW11: Yes | FX11: =IF(K11="","",IF(AND(K11>0,FW11="Yes"),1,"")) -> 1 | FY11: =IF(K11="","",IF(AND($K11>0,$FW11="No"),1,"")) | FZ11: =IF(K11="","",IF(AND($K11>0,$FW11="NA"),1,"")) | GA11: =IF(FV11="Dwn","Short","Long") -> Long | GB11: =IF(K11="","",IF(AND($K11<0,$FW11="Yes"),1,"")) | GC11: =IF(K11="","",IF(AND($K11<0,$FW11="No"),1,"")) | GD11: =IF(K11="","",IF(AND($K11<0,$FW11="NA"),1,"")) | GE11: =I11 -> 73.5 | GF11: Long | GG11: =400/I11 -> 5.4421769 | GH11: =IF(GG11="","",GE11*GG11) -> 400 | GI11: =GG11 -> 5.4421769 | GJ11: =J11 -> 76.2 | GK11: =IF($GI11="","",IF($GF11="Long",(($GJ11*$GI11)-$GH11),($GH11-($GJ11*$GI11)))) -> 14.693878 | GL11: =IF($GI11="","",IF($GF11="Long",(($GZ11*$GI11)-$GH11),($GH11-($GZ11*$GI11)))) -> 25.959184 | GM11: =IF(AND($FV11="SW",$GA11="Long"),$FN11,"") | GN11: =IF($GZ11="",#N/A,SUM(GM$4:GM11)) -> 5.4568395 | GO11: =IF(AND($FV11="UP",$GA11="Long"),$FN11,"") -> 1.0816327 | GP11: =IF($GZ11="",#N/A,SUM(GO$4:GO11)) -> 5.0281414 | GQ11: =IF(AND($FV11="Dwn",$GA11="Short"),$FN11,"") | GR11: =IF($GZ11="",#N/A,SUM(GQ$4:GQ11)) -> 2.847957 | GS11: =IF(AND(FV11="SW",GA11="Long"),$EJ11,"") | GT11: =IF($GZ11="",#N/A,SUM(GS$4:GS11)) -> 130.96415 | GU11: =IF(AND(FV11="UP",GA11="Long"),$EJ11,"") -> 25.959184 | GV11: =IF($GZ11="",#N/A,SUM(GU$4:GU11)) -> 120.67539 | GW11: =IF(AND(FV11="Dwn",GA11="Short"),$EJ11,"") | GX11: =IF($GZ11="",#N/A,SUM(GW$4:GW11)) -> 68.350967 | GY11: =IF(EJ11="",#N/A,SUM($EJ$4:EJ11)) -> 319.99051 | GZ11: 78.27 | HA11: =IF(OR(GL11="",GZ11=""),"",GL11-EH11) -> 11.265306 | HB11: Skip | HC11: =IFERROR(VLOOKUP(E11,Expectancy!$P$4:$S$19,1+C11,FALSE),"") -> -0.079483353 | HD11: =IF(AND(HB11="MOC",GZ11=""),"",IF(GI11="","",IF(HB11="Skip","",IF(HG11=0,0,HG11/(GH11*0.06))))) | HE11: =IF(HD11="",#N/A,SUM($HD$4:HD11)) -> #N/A | HF11: =IF(HD11="",#N/A,IF(HB11="Skip",#N/A,SUM($HG$4:HG11))) -> #N/A | HG11: =IF(HB11="","",IF(HB11="Skip","",IF(OR(HB11="open",HB11="Other"),GK11,IF(HB11="MOC",GL11,"Err")))) | HH11: =IF(OR($GI11="",$L11=""),"",IF($GA11="Long",(($GZ11*$GI11)-$GH11)/($GH11*0.06),($GH11-($GZ11*$GI11))/($GH11*0.06))) -> 1.0816327
A12: BK | B12: on 1/15/25, 1:00 AM Before Market Eas | C12: =IF(FV12="Dwn",2,IF(FV12="Up",1,IF(FV12="SW",3,"x"))) -> 3 | D12: =_xlfn.XLOOKUP(A12,[1]SP500!$A$2:$A$502,[1]SP500!$D$2:$D$502,"N") -> Y | E12: =_xlfn.XLOOKUP(A12,[1]SP500!$A$2:$A$655,[1]SP500!$B$2:$B$655) -> XLF | F12: 45672 | G12: =IF(ISNUMBER(FIND("After",B12,1)),"AMC",IF(ISNUMBER(FIND("Before",B12,1)),"BMO","err")) -> BMO | H12: =IF(HB12="other","o",IF(HB12="Skip","o",IF(OR(FV12="",GF12=""),"",IF(AND(FV12="Dwn",GF12="Short"),"s",IF(AND(FV12="Up",GF12="Long"),"s",IF(AND(FV12="SW",GF12="Long"),"s","o")))))) -> o | I12: 75.94 | J12: 79.1 | K12: =IF(J12="","",(J12-I12)/I12) -> 0.041611799 | L12: =IF(OR($GI12="",J12=""),"",IF($GF12="Long",(($J12*$GI12)-$GH12),($GH12-($J12*$GI12)))) -> 16.64472 | M12: =IF(L12="","",IF(HG12="","",HG12-L12)) | N12: =IF(AND($FV12="Up",$GA12="Long"),$EH12,"") | O12: =IF($J12="",#N/A,SUM($N$4:N12)) -> 84.63553 | P12: =IF(AND($FV12="Dwn",$GA12="Short"),$EH12,"") | Q12: =IF($J12="",#N/A,SUM($P$4:P12)) -> 29.496534 | R12: =IF(AND($FV12="SW",$GA12="Long"),$EH12,"") -> 16.64472 | S12: =IF($J12="",#N/A,SUM($R$4:R12)) -> 100.02028 | T12: =IF(AND($FV12="Up",$GA12="Long"),$FP12,"") | U12: =IF($J12="",#N/A,SUM($T$4:T12)) -> 3.5264804 | V12: =IF(AND($FV12="Dwn",$GA12="Short"),$FP12,"") | W12: =IF($J12="",#N/A,SUM($V$4:V12)) -> 1.2290223 | X12: =IF(AND($FV12="SW",$GA12="Long"),$FP12,"") -> 0.69352998 | Y12: =IF($J12="",#N/A,SUM($X$4:X12)) -> 4.1675118 | Z12: =IF(AND($FV12="Up",$GA12="Long",$E12=Z$2),$FP12,"") | AA12: =IF($J12="",#N/A,SUM(Z$4:Z12)) -> 0 | AB12: =IF(AND($FV12="Dwn",$GA12="Short",$E12=Z$2),$FP12,"") | AC12: =IF($J12="",#N/A,SUM(AB$4:AB12)) -> 0 | AD12: =IF(AND($FV12="SW",$GA12="Long",$E12=Z$2),$FP12,"") | AE12: =IF($J12="",#N/A,SUM(AD$4:AD12)) -> 0 | AF12: =IF($J12="",#N/A,SUM(AD$4:AD12,AB$4:AB12,Z$4:Z12)) -> 0 | AG12: =IF(AND($FV12="Up",$GA12="Long",$E12=AG$2),$FP12,"") | AH12: =IF($J12="",#N/A,SUM(AG$4:AG12)) -> 0 | AI12: =IF(AND($FV12="Dwn",$GA12="Short",$E12=AG$2),$FP12,"") | AJ12: =IF($J12="",#N/A,SUM(AI$4:AI12)) -> 0 | AK12: =IF(AND($FV12="SW",$GA12="Long",$E12=AG$2),$FP12,"") | AL12: =IF($J12="",#N/A,SUM(AK$4:AK12)) -> 0 | AM12: =IF($J12="",#N/A,SUM(AK$4:AK12,AI$4:AI12,AG$4:AG12)) -> 0 | AN12: =IF(AND($FV12="Up",$GA12="Long",$E12=AN$2),$FP12,"") | AO12: =IF($J12="",#N/A,SUM(AN$4:AN12)) -> 0 | AP12: =IF(AND($FV12="Dwn",$GA12="Short",$E12=AN$2),$FP12,"") | AQ12: =IF($J12="",#N/A,SUM(AP$4:AP12)) -> 0 | AR12: =IF(AND($FV12="SW",$GA12="Long",$E12=AN$2),$FP12,"") | AS12: =IF($J12="",#N/A,SUM(AR$4:AR12)) -> 0 | AT12: =IF($J12="",#N/A,SUM(AR$4:AR12,AP$4:AP12,AN$4:AN12)) -> 0 | AU12: =IF(AND($FV12="Up",$GA12="Long",$E12=AU$2),$FP12,"") | AV12: =IF($J12="",#N/A,SUM(AU$4:AU12)) -> 0 | AW12: =IF(AND($FV12="Dwn",$GA12="Short",$E12=AU$2),$FP12,"") | AX12: =IF($J12="",#N/A,SUM(AW$4:AW12)) -> 1.2290223 | AY12: =IF(AND($FV12="SW",$GA12="Long",$E12=AU$2),$FP12,"") | AZ12: =IF($J12="",#N/A,SUM(AY$4:AY12)) -> 2.494577 | BA12: =IF($J12="",#N/A,SUM(AY$4:AY12,AW$4:AW12,AU$4:AU12)) -> 3.7235993 | BB12: =IF(AND($FV12="Up",$GA12="Long",$E12=BB$2),$FP12,"") | BC12: =IF($J12="",#N/A,SUM(BB$4:BB12)) -> 0 | BD12: =IF(AND($FV12="Dwn",$GA12="Short",$E12=BB$2),$FP12,"") | BE12: =IF($J12="",#N/A,SUM(BD$4:BD12)) -> 0 | BF12: =IF(AND($FV12="SW",$GA12="Long",$E12=BB$2),$FP12,"") | BG12: =IF($J12="",#N/A,SUM(BF$4:BF12)) -> 0 | BH12: =IF($J12="",#N/A,SUM(BF$4:BF12,BD$4:BD12,BB$4:BB12)) -> 0 | BI12: =IF(AND($FV12="Up",$GA12="Long",$E12=BI$2),$FP12,"") | BJ12: =IF($J12="",#N/A,SUM(BI$4:BI12)) -> 2.5577406 | BK12: =IF(AND($FV12="Dwn",$GA12="Short",$E12=BI$2),$FP12,"") | BL12: =IF($J12="",#N/A,SUM(BK$4:BK12)) -> 0 | BM12: =IF(AND($FV12="SW",$GA12="Long",$E12=BI$2),$FP12,"") -> 0.69352998 | BN12: =IF($J12="",#N/A,SUM(BM$4:BM12)) -> 1.6729348 | BO12: =IF($J12="",#N/A,SUM(BM$4:BM12,BK$4:BK12,BI$4:BI12)) -> 4.2306754 | BP12: =IF(AND($FV12="Up",$GA12="Long",$E12=BP$2),$FP12,"") | BQ12: =IF($J12="",#N/A,SUM(BP$4:BP12)) -> 0.96873982 | BR12: =IF(AND($FV12="Dwn",$GA12="Short",$E12=BP$2),$FP12,"") | BS12: =IF($J12="",#N/A,SUM(BR$4:BR12)) -> 0 | BT12: =IF(AND($FV12="SW",$GA12="Long",$E12=BP$2),$FP12,"") | BU12: =IF($J12="",#N/A,SUM(BT$4:BT12)) -> 0 | BV12: =IF($J12="",#N/A,SUM(BT$4:BT12,BR$4:BR12,BP$4:BP12)) -> 0.96873982 | BW12: =IF(AND($FV12="Up",$GA12="Long",$E12=BW$2),$FP12,"") | BX12: =IF($J12="",#N/A,SUM(BW$4:BW12)) -> 0 | BY12: =IF(AND($FV12="Dwn",$GA12="Short",$E12=BW$2),$FP12,"") | BZ12: =IF($J12="",#N/A,SUM(BY$4:BY12)) -> 0 | CA12: =IF(AND($FV12="SW",$GA12="Long",$E12=BW$2),$FP12,"") | CB12: =IF($J12="",#N/A,SUM(CA$4:CA12)) -> 0 | CC12: =IF($J12="",#N/A,SUM(CA$4:CA12,BY$4:BY12,BW$4:BW12)) -> 0 | CD12: =IF(AND($FV12="Up",$GA12="Long",$E12=CD$2),$FP12,"") | CE12: =IF($J12="",#N/A,SUM(CD$4:CD12)) -> 0 | CF12: =IF(AND($FV12="Dwn",$GA12="Short",$E12=CD$2),$FP12,"") | CG12: =IF($J12="",#N/A,SUM(CF$4:CF12)) -> 0 | CH12: =IF(AND($FV12="SW",$GA12="Long",$E12=CD$2),$FP12,"") | CI12: =IF($J12="",#N/A,SUM(CH$4:CH12)) -> 0 | CJ12: =IF($J12="",#N/A,SUM(CH$4:CH12,CF$4:CF12,CD$4:CD12)) -> 0 | CK12: =IF(AND($FV12="Up",$GA12="Long",$E12=CK$2),$FP12,"") | CL12: =IF($J12="",#N/A,SUM(CK$4:CK12)) -> 0 | CM12: =IF(AND($FV12="Dwn",$GA12="Short",$E12=CK$2),$FP12,"") | CN12: =IF($J12="",#N/A,SUM(CM$4:CM12)) -> 0 | CO12: =IF(AND($FV12="SW",$GA12="Long",$E12=CK$2),$FP12,"") | CP12: =IF($J12="",#N/A,SUM(CO$4:CO12)) -> 0 | CQ12: =IF($J12="",#N/A,SUM(CO$4:CO12,CM$4:CM12,CK$4:CK12)) -> 0 | CR12: =IF(AND($FV12="Up",$GA12="Long",$E12=CR$2),$FP12,"") | CS12: =IF($J12="",#N/A,SUM(CR$4:CR12)) -> 0 | CT12: =IF(AND($FV12="Dwn",$GA12="Short",$E12=CR$2),$FP12,"") | CU12: =IF($J12="",#N/A,SUM(CT$4:CT12)) -> 0 | CV12: =IF(AND($FV12="SW",$GA12="Long",$E12=CR$2),$FP12,"") | CW12: =IF($J12="",#N/A,SUM(CV$4:CV12)) -> 0 | CX12: =IF($J12="",#N/A,SUM(CV$4:CV12,CT$4:CT12,CR$4:CR12)) -> 0 | CY12: =IF(AND($FV12="Up",$GA12="Long",$E12=CY$2),$FP12,"") | CZ12: =IF($J12="",#N/A,SUM(CY$4:CY12)) -> 0 | DA12: =IF(AND($FV12="Dwn",$GA12="Short",$E12=CY$2),$FP12,"") | DB12: =IF($J12="",#N/A,SUM(DA$4:DA12)) -> 0 | DC12: =IF(AND($FV12="SW",$GA12="Long",$E12=CY$2),$FP12,"") | DD12: =IF($J12="",#N/A,SUM(DC$4:DC12)) -> 0 | DE12: =IF($J12="",#N/A,SUM(DC$4:DC12,DA$4:DA12,CY$4:CY12)) -> 0 | DF12: =IF(AND($FV12="Up",$GA12="Long",$E12=DF$2),$FP12,"") | DG12: =IF($J12="",#N/A,SUM(DF$4:DF12)) -> 0 | DH12: =IF(AND($FV12="Dwn",$GA12="Short",$E12=DF$2),$FP12,"") | DI12: =IF($J12="",#N/A,SUM(DH$4:DH12)) -> 0 | DJ12: =IF(AND($FV12="SW",$GA12="Long",$E12=DF$2),$FP12,"") | DK12: =IF($J12="",#N/A,SUM(DJ$4:DJ12)) -> 0 | DL12: =IF($J12="",#N/A,SUM(DJ$4:DJ12,DH$4:DH12,DF$4:DF12)) -> 0 | DM12: =IF(AND($FV12="Up",$GA12="Long",$E12=DM$2),$FP12,"") | DN12: =IF($J12="",#N/A,SUM(DM$4:DM12)) -> 0 | DO12: =IF(AND($FV12="Dwn",$GA12="Short",$E12=DM$2),$FP12,"") | DP12: =IF($J12="",#N/A,SUM(DO$4:DO12)) -> 0 | DQ12: =IF(AND($FV12="SW",$GA12="Long",$E12=DM$2),$FP12,"") | DR12: =IF($J12="",#N/A,SUM(DQ$4:DQ12)) -> 0 | DS12: =IF($J12="",#N/A,SUM(DQ$4:DQ12,DO$4:DO12,DM$4:DM12)) -> 0 | DT12: =IF(AND($FV12="Up",$GA12="Long",$E12=DT$2),$FP12,"") | DU12: =IF($J12="",#N/A,SUM(DT$4:DT12)) -> 0 | DV12: =IF(AND($FV12="Dwn",$GA12="Short",$E12=DT$2),$FP12,"") | DW12: =IF($J12="",#N/A,SUM(DV$4:DV12)) -> 0 | DX12: =IF(AND($FV12="SW",$GA12="Long",$E12=DT$2),$FP12,"") | DY12: =IF($J12="",#N/A,SUM(DX$4:DX12)) -> 0 | DZ12: =IF($J12="",#N/A,SUM(DX$4:DX12,DV$4:DV12,DT$4:DT12)) -> 0 | EA12: =IF(AND($FV12="Up",$GA12="Long",$E12=EA$2),$FP12,"") | EB12: =IF($J12="",#N/A,SUM(EA$4:EA12)) -> 0 | EC12: =IF(AND($FV12="Dwn",$GA12="Short",$E12=EA$2),$FP12,"") | ED12: =IF($J12="",#N/A,SUM(EC$4:EC12)) -> 0 | EE12: =IF(AND($FV12="SW",$GA12="Long",$E12=EA$2),$FP12,"") | EF12: =IF($J12="",#N/A,SUM(EE$4:EE12)) -> 0 | EG12: =IF($J12="",#N/A,SUM(EE$4:EE12,EC$4:EC12,EA$4:EA12)) -> 0 | EH12: =IF(OR($GI12="",L12=""),"",IF($GA12="Long",(($J12*$GI12)-$GH12),($GH12-($J12*$GI12)))) -> 16.64472 | EI12: =IF(EH12="",#N/A,SUM($EH$4:EH12)) -> 214.15235 | EJ12: =IF(GZ12="","",IF(OR($GI12="",AM12=""),"",IF($GA12="Long",(($GZ12*$GI12)-$GH12),($GH12-($GZ12*$GI12))))) -> 32.130629 | EK12: =IF($GZ12="",#N/A,SUM(EJ$4:EJ12)) -> 352.12114 | EL12: =IF(J12="","",IF(D12="Y",FP12,"")) -> 0.69352998 | EM12: =IF(EL12="",NA(),SUM($EL$4:EL12)) -> 8.9230145 | EN12: =IF(AND($FV12="Up",$GA12="Long",$D12="Y"),$EL12,"") | EO12: =IF(EN12="",NA(),SUM($EN$4:EN12)) -> #N/A | EP12: =IF(AND($FV12="SW",$GA12="Long",$D12="Y"),$EL12,"") -> 0.69352998 | EQ12: =IF(EP12="",NA(),SUM($EP$4:EP12)) -> 4.1675118 | ER12: =IF(AND($FV12="Dwn",$GA12="Short",$D12="Y"),$EL12,"") | ES12: =IF(ER12="",NA(),SUM($ER$4:ER12)) -> #N/A | ET12: =IF($J12="","",IF($D12="N",$FP12,"")) | EU12: =IF(ET12="",NA(),SUM($ET$4:ET12)) -> #N/A | EV12: =IF(AND($FV12="Up",$GA12="Long",$D12="N"),$ET12,"") | EW12: =IF(EV12="",NA(),SUM($EV$4:EV12)) -> #N/A | EX12: =IF(AND($FV12="SW",$GA12="Long",$D12="N"),$ET12,"") | EY12: =IF(EX12="",NA(),SUM($EX$4:EX12)) -> #N/A | EZ12: =IF(AND($FV12="Dwn",$GA12="Short",$D12="N"),$ET12,"") | FA12: =IF(EZ12="",NA(),SUM($EZ$4:EZ12)) -> #N/A | FB12: =IF($GZ12="","",IF(AND($FV12="Dwn",$K12<0),$FN12-FP12,"")) | FC12: =IF($FB12="",#N/A,SUM(FB$4:$FB12)) -> #N/A | FD12: =IF($GZ12="","",IF(AND($FV12="Dwn",$K12>0),$FN12-$FP12,"")) | FE12: =IF($FD12="",#N/A,SUM($FD$4:FD12)) -> #N/A | FF12: =IF($GZ12="","",IF(AND($FV12="Up",$K12>0),$FN12-$FP12,"")) | FG12: =IF($FF12="",#N/A,SUM($FF$4:FF12)) -> #N/A | FH12: =IF($GZ12="","",IF(AND($FV12="Up",$K12<0),$FN12-$FP12,"")) | FI12: =IF($FH12="",#N/A,SUM($FH$4:FH12)) -> #N/A | FJ12: =IF($GZ12="","",IF(AND($FV12="SW",$K12>0),$FN12-$FP12,"")) -> 0.64524625 | FK12: =IF($FJ12="",#N/A,SUM($FJ$4:FJ12)) -> 2.6281039 | FL12: =IF($GZ12="","",IF(AND($FV12="SW",$K12<0),$FN12-$FP12,"")) | FM12: =IF($FL12="",#N/A,SUM($FL$4:FL12)) -> #N/A | FN12: =IF(OR($GI12="",$GZ12=""),"",IF($GA12="Long",(($GZ12*$GI12)-$GH12)/($GH12*0.06),($GH12-($GZ12*$GI12))/($GH12*0.06))) -> 1.3387762 | FO12: =IF($FN12="",#N/A,SUM(FN$4:$FN12)) -> 14.671714 | FP12: =IF(OR($GI12="",L12=""),"",IF($GA12="Long",(($J12*$GI12)-$GH12)/(GH12*0.06),($GH12-($J12*$GI12))/(GH12*0.06))) -> 0.69352998 | FQ12: =IF($EH12="",#N/A,SUM($FP$4:FP12)) -> 8.9230145 | FU12: #N/A | FV12: =IF(FW12="Down","Dwn",IF(FW12="Up","Up",IF(AND(FW12="",K12=""),"",IF(AND(K12<0,FW12="Yes"),"Dwn",IF(AND(K12>0,FW12="Yes"),"Up",IF(AND(K12<0,FW12="No"),"Up",IF(AND(K12>0,FW12="No"),"Dwn",IF(FW12="NA","SW","err")))))))) -> SW | FW12: NA | FX12: =IF(K12="","",IF(AND(K12>0,FW12="Yes"),1,"")) | FY12: =IF(K12="","",IF(AND($K12>0,$FW12="No"),1,"")) | FZ12: =IF(K12="","",IF(AND($K12>0,$FW12="NA"),1,"")) -> 1 | GA12: =IF(FV12="Dwn","Short","Long") -> Long | GB12: =IF(K12="","",IF(AND($K12<0,$FW12="Yes"),1,"")) | GC12: =IF(K12="","",IF(AND($K12<0,$FW12="No"),1,"")) | GD12: =IF(K12="","",IF(AND($K12<0,$FW12="NA"),1,"")) | GE12: =I12 -> 75.94 | GF12: Long | GG12: =400/I12 -> 5.2673163 | GH12: =IF(GG12="","",GE12*GG12) -> 400 | GI12: =GG12 -> 5.2673163 | GJ12: =J12 -> 79.1 | GK12: =IF($GI12="","",IF($GF12="Long",(($GJ12*$GI12)-$GH12),($GH12-($GJ12*$GI12)))) -> 16.64472 | GL12: =IF($GI12="","",IF($GF12="Long",(($GZ12*$GI12)-$GH12),($GH12-($GZ12*$GI12)))) -> 32.130629 | GM12: =IF(AND($FV12="SW",$GA12="Long"),$FN12,"") -> 1.3387762 | GN12: =IF($GZ12="",#N/A,SUM(GM$4:GM12)) -> 6.7956157 | GO12: =IF(AND($FV12="UP",$GA12="Long"),$FN12,"") | GP12: =IF($GZ12="",#N/A,SUM(GO$4:GO12)) -> 5.0281414 | GQ12: =IF(AND($FV12="Dwn",$GA12="Short"),$FN12,"") | GR12: =IF($GZ12="",#N/A,SUM(GQ$4:GQ12)) -> 2.847957 | GS12: =IF(AND(FV12="SW",GA12="Long"),$EJ12,"") -> 32.130629 | GT12: =IF($GZ12="",#N/A,SUM(GS$4:GS12)) -> 163.09478 | GU12: =IF(AND(FV12="UP",GA12="Long"),$EJ12,"") | GV12: =IF($GZ12="",#N/A,SUM(GU$4:GU12)) -> 120.67539 | GW12: =IF(AND(FV12="Dwn",GA12="Short"),$EJ12,"") | GX12: =IF($GZ12="",#N/A,SUM(GW$4:GW12)) -> 68.350967 | GY12: =IF(EJ12="",#N/A,SUM($EJ$4:EJ12)) -> 352.12114 | GZ12: 82.04 | HA12: =IF(OR(GL12="",GZ12=""),"",GL12-EH12) -> 15.48591 | HB12: Skip | HC12: =IFERROR(VLOOKUP(E12,Expectancy!$P$4:$S$19,1+C12,FALSE),"") -> 0.099793136 | HD12: =IF(AND(HB12="MOC",GZ12=""),"",IF(GI12="","",IF(HB12="Skip","",IF(HG12=0,0,HG12/(GH12*0.06))))) | HE12: =IF(HD12="",#N/A,SUM($HD$4:HD12)) -> #N/A | HF12: =IF(HD12="",#N/A,IF(HB12="Skip",#N/A,SUM($HG$4:HG12))) -> #N/A | HG12: =IF(HB12="","",IF(HB12="Skip","",IF(OR(HB12="open",HB12="Other"),GK12,IF(HB12="MOC",GL12,"Err")))) | HH12: =IF(OR($GI12="",$L12=""),"",IF($GA12="Long",(($GZ12*$GI12)-$GH12)/($GH12*0.06),($GH12-($GZ12*$GI12))/($GH12*0.06))) -> 1.3387762
A13: UNH | B13: on 1/16/25, 5:55 AM Before Market Eas | C13: =IF(FV13="Dwn",2,IF(FV13="Up",1,IF(FV13="SW",3,"x"))) -> 2 | D13: =_xlfn.XLOOKUP(A13,[1]SP500!$A$2:$A$502,[1]SP500!$D$2:$D$502,"N") -> Y | E13: =_xlfn.XLOOKUP(A13,[1]SP500!$A$2:$A$655,[1]SP500!$B$2:$B$655) -> H-INS | F13: 45673 | G13: =IF(ISNUMBER(FIND("After",B13,1)),"AMC",IF(ISNUMBER(FIND("Before",B13,1)),"BMO","err")) -> BMO | H13: =IF(HB13="other","o",IF(HB13="Skip","o",IF(OR(FV13="",GF13=""),"",IF(AND(FV13="Dwn",GF13="Short"),"s",IF(AND(FV13="Up",GF13="Long"),"s",IF(AND(FV13="SW",GF13="Long"),"s","o")))))) -> o | I13: 543.42 | J13: 530.35 | K13: =IF(J13="","",(J13-I13)/I13) -> -0.024051378 | L13: =IF(OR($GI13="",J13=""),"",IF($GF13="Long",(($J13*$GI13)-$GH13),($GH13-($J13*$GI13)))) -> 9.6205513 | M13: =IF(L13="","",IF(HG13="","",HG13-L13)) | N13: =IF(AND($FV13="Up",$GA13="Long"),$EH13,"") | O13: =IF($J13="",#N/A,SUM($N$4:N13)) -> 84.63553 | P13: =IF(AND($FV13="Dwn",$GA13="Short"),$EH13,"") -> 9.6205513 | Q13: =IF($J13="",#N/A,SUM($P$4:P13)) -> 39.117085 | R13: =IF(AND($FV13="SW",$GA13="Long"),$EH13,"") | S13: =IF($J13="",#N/A,SUM($R$4:R13)) -> 100.02028 | T13: =IF(AND($FV13="Up",$GA13="Long"),$FP13,"") | U13: =IF($J13="",#N/A,SUM($T$4:T13)) -> 3.5264804 | V13: =IF(AND($FV13="Dwn",$GA13="Short"),$FP13,"") -> 0.40085631 | W13: =IF($J13="",#N/A,SUM($V$4:V13)) -> 1.6298786 | X13: =IF(AND($FV13="SW",$GA13="Long"),$FP13,"") | Y13: =IF($J13="",#N/A,SUM($X$4:X13)) -> 4.1675118 | Z13: =IF(AND($FV13="Up",$GA13="Long",$E13=Z$2),$FP13,"") | AA13: =IF($J13="",#N/A,SUM(Z$4:Z13)) -> 0 | AB13: =IF(AND($FV13="Dwn",$GA13="Short",$E13=Z$2),$FP13,"") | AC13: =IF($J13="",#N/A,SUM(AB$4:AB13)) -> 0 | AD13: =IF(AND($FV13="SW",$GA13="Long",$E13=Z$2),$FP13,"") | AE13: =IF($J13="",#N/A,SUM(AD$4:AD13)) -> 0 | AF13: =IF($J13="",#N/A,SUM(AD$4:AD13,AB$4:AB13,Z$4:Z13)) -> 0 | AG13: =IF(AND($FV13="Up",$GA13="Long",$E13=AG$2),$FP13,"") | AH13: =IF($J13="",#N/A,SUM(AG$4:AG13)) -> 0 | AI13: =IF(AND($FV13="Dwn",$GA13="Short",$E13=AG$2),$FP13,"") | AJ13: =IF($J13="",#N/A,SUM(AI$4:AI13)) -> 0 | AK13: =IF(AND($FV13="SW",$GA13="Long",$E13=AG$2),$FP13,"") | AL13: =IF($J13="",#N/A,SUM(AK$4:AK13)) -> 0 | AM13: =IF($J13="",#N/A,SUM(AK$4:AK13,AI$4:AI13,AG$4:AG13)) -> 0 | AN13: =IF(AND($FV13="Up",$GA13="Long",$E13=AN$2),$FP13,"") | AO13: =IF($J13="",#N/A,SUM(AN$4:AN13)) -> 0 | AP13: =IF(AND($FV13="Dwn",$GA13="Short",$E13=AN$2),$FP13,"") | AQ13: =IF($J13="",#N/A,SUM(AP$4:AP13)) -> 0 | AR13: =IF(AND($FV13="SW",$GA13="Long",$E13=AN$2),$FP13,"") | AS13: =IF($J13="",#N/A,SUM(AR$4:AR13)) -> 0 | AT13: =IF($J13="",#N/A,SUM(AR$4:AR13,AP$4:AP13,AN$4:AN13)) -> 0 | AU13: =IF(AND($FV13="Up",$GA13="Long",$E13=AU$2),$FP13,"") | AV13: =IF($J13="",#N/A,SUM(AU$4:AU13)) -> 0 | AW13: =IF(AND($FV13="Dwn",$GA13="Short",$E13=AU$2),$FP13,"") | AX13: =IF($J13="",#N/A,SUM(AW$4:AW13)) -> 1.2290223 | AY13: =IF(AND($FV13="SW",$GA13="Long",$E13=AU$2),$FP13,"") | AZ13: =IF($J13="",#N/A,SUM(AY$4:AY13)) -> 2.494577 | BA13: =IF($J13="",#N/A,SUM(AY$4:AY13,AW$4:AW13,AU$4:AU13)) -> 3.7235993 | BB13: =IF(AND($FV13="Up",$GA13="Long",$E13=BB$2),$FP13,"") | BC13: =IF($J13="",#N/A,SUM(BB$4:BB13)) -> 0 | BD13: =IF(AND($FV13="Dwn",$GA13="Short",$E13=BB$2),$FP13,"") | BE13: =IF($J13="",#N/A,SUM(BD$4:BD13)) -> 0 | BF13: =IF(AND($FV13="SW",$GA13="Long",$E13=BB$2),$FP13,"") | BG13: =IF($J13="",#N/A,SUM(BF$4:BF13)) -> 0 | BH13: =IF($J13="",#N/A,SUM(BF$4:BF13,BD$4:BD13,BB$4:BB13)) -> 0 | BI13: =IF(AND($FV13="Up",$GA13="Long",$E13=BI$2),$FP13,"") | BJ13: =IF($J13="",#N/A,SUM(BI$4:BI13)) -> 2.5577406 | BK13: =IF(AND($FV13="Dwn",$GA13="Short",$E13=BI$2),$FP13,"") | BL13: =IF($J13="",#N/A,SUM(BK$4:BK13)) -> 0 | BM13: =IF(AND($FV13="SW",$GA13="Long",$E13=BI$2),$FP13,"") | BN13: =IF($J13="",#N/A,SUM(BM$4:BM13)) -> 1.6729348 | BO13: =IF($J13="",#N/A,SUM(BM$4:BM13,BK$4:BK13,BI$4:BI13)) -> 4.2306754 | BP13: =IF(AND($FV13="Up",$GA13="Long",$E13=BP$2),$FP13,"") | BQ13: =IF($J13="",#N/A,SUM(BP$4:BP13)) -> 0.96873982 | BR13: =IF(AND($FV13="Dwn",$GA13="Short",$E13=BP$2),$FP13,"") | BS13: =IF($J13="",#N/A,SUM(BR$4:BR13)) -> 0 | BT13: =IF(AND($FV13="SW",$GA13="Long",$E13=BP$2),$FP13,"") | BU13: =IF($J13="",#N/A,SUM(BT$4:BT13)) -> 0 | BV13: =IF($J13="",#N/A,SUM(BT$4:BT13,BR$4:BR13,BP$4:BP13)) -> 0.96873982 | BW13: =IF(AND($FV13="Up",$GA13="Long",$E13=BW$2),$FP13,"") | BX13: =IF($J13="",#N/A,SUM(BW$4:BW13)) -> 0 | BY13: =IF(AND($FV13="Dwn",$GA13="Short",$E13=BW$2),$FP13,"") | BZ13: =IF($J13="",#N/A,SUM(BY$4:BY13)) -> 0 | CA13: =IF(AND($FV13="SW",$GA13="Long",$E13=BW$2),$FP13,"") | CB13: =IF($J13="",#N/A,SUM(CA$4:CA13)) -> 0 | CC13: =IF($J13="",#N/A,SUM(CA$4:CA13,BY$4:BY13,BW$4:BW13)) -> 0 | CD13: =IF(AND($FV13="Up",$GA13="Long",$E13=CD$2),$FP13,"") | CE13: =IF($J13="",#N/A,SUM(CD$4:CD13)) -> 0 | CF13: =IF(AND($FV13="Dwn",$GA13="Short",$E13=CD$2),$FP13,"") | CG13: =IF($J13="",#N/A,SUM(CF$4:CF13)) -> 0 | CH13: =IF(AND($FV13="SW",$GA13="Long",$E13=CD$2),$FP13,"") | CI13: =IF($J13="",#N/A,SUM(CH$4:CH13)) -> 0 | CJ13: =IF($J13="",#N/A,SUM(CH$4:CH13,CF$4:CF13,CD$4:CD13)) -> 0 | CK13: =IF(AND($FV13="Up",$GA13="Long",$E13=CK$2),$FP13,"") | CL13: =IF($J13="",#N/A,SUM(CK$4:CK13)) -> 0 | CM13: =IF(AND($FV13="Dwn",$GA13="Short",$E13=CK$2),$FP13,"") | CN13: =IF($J13="",#N/A,SUM(CM$4:CM13)) -> 0 | CO13: =IF(AND($FV13="SW",$GA13="Long",$E13=CK$2),$FP13,"") | CP13: =IF($J13="",#N/A,SUM(CO$4:CO13)) -> 0 | CQ13: =IF($J13="",#N/A,SUM(CO$4:CO13,CM$4:CM13,CK$4:CK13)) -> 0 | CR13: =IF(AND($FV13="Up",$GA13="Long",$E13=CR$2),$FP13,"") | CS13: =IF($J13="",#N/A,SUM(CR$4:CR13)) -> 0 | CT13: =IF(AND($FV13="Dwn",$GA13="Short",$E13=CR$2),$FP13,"") | CU13: =IF($J13="",#N/A,SUM(CT$4:CT13)) -> 0 | CV13: =IF(AND($FV13="SW",$GA13="Long",$E13=CR$2),$FP13,"") | CW13: =IF($J13="",#N/A,SUM(CV$4:CV13)) -> 0 | CX13: =IF($J13="",#N/A,SUM(CV$4:CV13,CT$4:CT13,CR$4:CR13)) -> 0 | CY13: =IF(AND($FV13="Up",$GA13="Long",$E13=CY$2),$FP13,"") | CZ13: =IF($J13="",#N/A,SUM(CY$4:CY13)) -> 0 | DA13: =IF(AND($FV13="Dwn",$GA13="Short",$E13=CY$2),$FP13,"") | DB13: =IF($J13="",#N/A,SUM(DA$4:DA13)) -> 0 | DC13: =IF(AND($FV13="SW",$GA13="Long",$E13=CY$2),$FP13,"") | DD13: =IF($J13="",#N/A,SUM(DC$4:DC13)) -> 0 | DE13: =IF($J13="",#N/A,SUM(DC$4:DC13,DA$4:DA13,CY$4:CY13)) -> 0 | DF13: =IF(AND($FV13="Up",$GA13="Long",$E13=DF$2),$FP13,"") | DG13: =IF($J13="",#N/A,SUM(DF$4:DF13)) -> 0 | DH13: =IF(AND($FV13="Dwn",$GA13="Short",$E13=DF$2),$FP13,"") | DI13: =IF($J13="",#N/A,SUM(DH$4:DH13)) -> 0 | DJ13: =IF(AND($FV13="SW",$GA13="Long",$E13=DF$2),$FP13,"") | DK13: =IF($J13="",#N/A,SUM(DJ$4:DJ13)) -> 0 | DL13: =IF($J13="",#N/A,SUM(DJ$4:DJ13,DH$4:DH13,DF$4:DF13)) -> 0 | DM13: =IF(AND($FV13="Up",$GA13="Long",$E13=DM$2),$FP13,"") | DN13: =IF($J13="",#N/A,SUM(DM$4:DM13)) -> 0 | DO13: =IF(AND($FV13="Dwn",$GA13="Short",$E13=DM$2),$FP13,"") | DP13: =IF($J13="",#N/A,SUM(DO$4:DO13)) -> 0 | DQ13: =IF(AND($FV13="SW",$GA13="Long",$E13=DM$2),$FP13,"") | DR13: =IF($J13="",#N/A,SUM(DQ$4:DQ13)) -> 0 | DS13: =IF($J13="",#N/A,SUM(DQ$4:DQ13,DO$4:DO13,DM$4:DM13)) -> 0 | DT13: =IF(AND($FV13="Up",$GA13="Long",$E13=DT$2),$FP13,"") | DU13: =IF($J13="",#N/A,SUM(DT$4:DT13)) -> 0 | DV13: =IF(AND($FV13="Dwn",$GA13="Short",$E13=DT$2),$FP13,"") -> 0.40085631 | DW13: =IF($J13="",#N/A,SUM(DV$4:DV13)) -> 0.40085631 | DX13: =IF(AND($FV13="SW",$GA13="Long",$E13=DT$2),$FP13,"") | DY13: =IF($J13="",#N/A,SUM(DX$4:DX13)) -> 0 | DZ13: =IF($J13="",#N/A,SUM(DX$4:DX13,DV$4:DV13,DT$4:DT13)) -> 0.40085631 | EA13: =IF(AND($FV13="Up",$GA13="Long",$E13=EA$2),$FP13,"") | EB13: =IF($J13="",#N/A,SUM(EA$4:EA13)) -> 0 | EC13: =IF(AND($FV13="Dwn",$GA13="Short",$E13=EA$2),$FP13,"") | ED13: =IF($J13="",#N/A,SUM(EC$4:EC13)) -> 0 | EE13: =IF(AND($FV13="SW",$GA13="Long",$E13=EA$2),$FP13,"") | EF13: =IF($J13="",#N/A,SUM(EE$4:EE13)) -> 0 | EG13: =IF($J13="",#N/A,SUM(EE$4:EE13,EC$4:EC13,EA$4:EA13)) -> 0 | EH13: =IF(OR($GI13="",L13=""),"",IF($GA13="Long",(($J13*$GI13)-$GH13),($GH13-($J13*$GI13)))) -> 9.6205513 | EI13: =IF(EH13="",#N/A,SUM($EH$4:EH13)) -> 223.7729 | EJ13: =IF(GZ13="","",IF(OR($GI13="",AM13=""),"",IF($GA13="Long",(($GZ13*$GI13)-$GH13),($GH13-($GZ13*$GI13))))) -> 24.165471 | EK13: =IF($GZ13="",#N/A,SUM(EJ$4:EJ13)) -> 376.28661 | EL13: =IF(J13="","",IF(D13="Y",FP13,"")) -> 0.40085631 | EM13: =IF(EL13="",NA(),SUM($EL$4:EL13)) -> 9.3238708 | EN13: =IF(AND($FV13="Up",$GA13="Long",$D13="Y"),$EL13,"") | EO13: =IF(EN13="",NA(),SUM($EN$4:EN13)) -> #N/A | EP13: =IF(AND($FV13="SW",$GA13="Long",$D13="Y"),$EL13,"") | EQ13: =IF(EP13="",NA(),SUM($EP$4:EP13)) -> #N/A | ER13: =IF(AND($FV13="Dwn",$GA13="Short",$D13="Y"),$EL13,"") -> 0.40085631 | ES13: =IF(ER13="",NA(),SUM($ER$4:ER13)) -> 1.6298786 | ET13: =IF($J13="","",IF($D13="N",$FP13,"")) | EU13: =IF(ET13="",NA(),SUM($ET$4:ET13)) -> #N/A | EV13: =IF(AND($FV13="Up",$GA13="Long",$D13="N"),$ET13,"") | EW13: =IF(EV13="",NA(),SUM($EV$4:EV13)) -> #N/A | EX13: =IF(AND($FV13="SW",$GA13="Long",$D13="N"),$ET13,"") | EY13: =IF(EX13="",NA(),SUM($EX$4:EX13)) -> #N/A | EZ13: =IF(AND($FV13="Dwn",$GA13="Short",$D13="N"),$ET13,"") | FA13: =IF(EZ13="",NA(),SUM($EZ$4:EZ13)) -> #N/A | FB13: =IF($GZ13="","",IF(AND($FV13="Dwn",$K13<0),$FN13-FP13,"")) -> 0.6060383 | FC13: =IF($FB13="",#N/A,SUM(FB$4:$FB13)) -> 2.224973 | FD13: =IF($GZ13="","",IF(AND($FV13="Dwn",$K13>0),$FN13-$FP13,"")) | FE13: =IF($FD13="",#N/A,SUM($FD$4:FD13)) -> #N/A | FF13: =IF($GZ13="","",IF(AND($FV13="Up",$K13>0),$FN13-$FP13,"")) | FG13: =IF($FF13="",#N/A,SUM($FF$4:FF13)) -> #N/A | FH13: =IF($GZ13="","",IF(AND($FV13="Up",$K13<0),$FN13-$FP13,"")) | FI13: =IF($FH13="",#N/A,SUM($FH$4:FH13)) -> #N/A | FJ13: =IF($GZ13="","",IF(AND($FV13="SW",$K13>0),$FN13-$FP13,"")) | FK13: =IF($FJ13="",#N/A,SUM($FJ$4:FJ13)) -> #N/A | FL13: =IF($GZ13="","",IF(AND($FV13="SW",$K13<0),$FN13-$FP13,"")) | FM13: =IF($FL13="",#N/A,SUM($FL$4:FL13)) -> #N/A | FN13: =IF(OR($GI13="",$GZ13=""),"",IF($GA13="Long",(($GZ13*$GI13)-$GH13)/($GH13*0.06),($GH13-($GZ13*$GI13))/($GH13*0.06))) -> 1.0068946 | FO13: =IF($FN13="",#N/A,SUM(FN$4:$FN13)) -> 15.678609 | FP13: =IF(OR($GI13="",L13=""),"",IF($GA13="Long",(($J13*$GI13)-$GH13)/(GH13*0.06),($GH13-($J13*$GI13))/(GH13*0.06))) -> 0.40085631 | FQ13: =IF($EH13="",#N/A,SUM($FP$4:FP13)) -> 9.3238708 | FU13: #N/A | FV13: =IF(FW13="Down","Dwn",IF(FW13="Up","Up",IF(AND(FW13="",K13=""),"",IF(AND(K13<0,FW13="Yes"),"Dwn",IF(AND(K13>0,FW13="Yes"),"Up",IF(AND(K13<0,FW13="No"),"Up",IF(AND(K13>0,FW13="No"),"Dwn",IF(FW13="NA","SW","err")))))))) -> Dwn | FW13: Yes | FX13: =IF(K13="","",IF(AND(K13>0,FW13="Yes"),1,"")) | FY13: =IF(K13="","",IF(AND($K13>0,$FW13="No"),1,"")) | FZ13: =IF(K13="","",IF(AND($K13>0,$FW13="NA"),1,"")) | GA13: =IF(FV13="Dwn","Short","Long") -> Short | GB13: =IF(K13="","",IF(AND($K13<0,$FW13="Yes"),1,"")) -> 1 | GC13: =IF(K13="","",IF(AND($K13<0,$FW13="No"),1,"")) | GD13: =IF(K13="","",IF(AND($K13<0,$FW13="NA"),1,"")) | GE13: =I13 -> 543.42 | GF13: Short | GG13: =400/I13 -> 0.73607891 | GH13: =IF(GG13="","",GE13*GG13) -> 400 | GI13: =GG13 -> 0.73607891 | GJ13: =J13 -> 530.35 | GK13: =IF($GI13="","",IF($GF13="Long",(($GJ13*$GI13)-$GH13),($GH13-($GJ13*$GI13)))) -> 9.6205513 | GL13: =IF($GI13="","",IF($GF13="Long",(($GZ13*$GI13)-$GH13),($GH13-($GZ13*$GI13)))) -> 24.165471 | GM13: =IF(AND($FV13="SW",$GA13="Long"),$FN13,"") | GN13: =IF($GZ13="",#N/A,SUM(GM$4:GM13)) -> 6.7956157 | GO13: =IF(AND($FV13="UP",$GA13="Long"),$FN13,"") | GP13: =IF($GZ13="",#N/A,SUM(GO$4:GO13)) -> 5.0281414 | GQ13: =IF(AND($FV13="Dwn",$GA13="Short"),$FN13,"") -> 1.0068946 | GR13: =IF($GZ13="",#N/A,SUM(GQ$4:GQ13)) -> 3.8548516 | GS13: =IF(AND(FV13="SW",GA13="Long"),$EJ13,"") | GT13: =IF($GZ13="",#N/A,SUM(GS$4:GS13)) -> 163.09478 | GU13: =IF(AND(FV13="UP",GA13="Long"),$EJ13,"") | GV13: =IF($GZ13="",#N/A,SUM(GU$4:GU13)) -> 120.67539 | GW13: =IF(AND(FV13="Dwn",GA13="Short"),$EJ13,"") -> 24.165471 | GX13: =IF($GZ13="",#N/A,SUM(GW$4:GW13)) -> 92.516437 | GY13: =IF(EJ13="",#N/A,SUM($EJ$4:EJ13)) -> 376.28661 | GZ13: 510.59 | HA13: =IF(OR(GL13="",GZ13=""),"",GL13-EH13) -> 14.544919 | HB13: Skip | HC13: =IFERROR(VLOOKUP(E13,Expectancy!$P$4:$S$19,1+C13,FALSE),"") -> 0.50993627 | HD13: =IF(AND(HB13="MOC",GZ13=""),"",IF(GI13="","",IF(HB13="Skip","",IF(HG13=0,0,HG13/(GH13*0.06))))) | HE13: =IF(HD13="",#N/A,SUM($HD$4:HD13)) -> #N/A | HF13: =IF(HD13="",#N/A,IF(HB13="Skip",#N/A,SUM($HG$4:HG13))) -> #N/A | HG13: =IF(HB13="","",IF(HB13="Skip","",IF(OR(HB13="open",HB13="Other"),GK13,IF(HB13="MOC",GL13,"Err")))) | HH13: =IF(OR($GI13="",$L13=""),"",IF($GA13="Long",(($GZ13*$GI13)-$GH13)/($GH13*0.06),($GH13-($GZ13*$GI13))/($GH13*0.06))) -> 1.0068946
A14: BAC | B14: on 1/16/25, 6:45 AM Before Market Eas | C14: =IF(FV14="Dwn",2,IF(FV14="Up",1,IF(FV14="SW",3,"x"))) -> 1 | D14: =_xlfn.XLOOKUP(A14,[1]SP500!$A$2:$A$502,[1]SP500!$D$2:$D$502,"N") -> Y | E14: =_xlfn.XLOOKUP(A14,[1]SP500!$A$2:$A$655,[1]SP500!$B$2:$B$655) -> XLF | F14: 45673 | G14: =IF(ISNUMBER(FIND("After",B14,1)),"AMC",IF(ISNUMBER(FIND("Before",B14,1)),"BMO","err")) -> BMO | H14: =IF(HB14="other","o",IF(HB14="Skip","o",IF(OR(FV14="",GF14=""),"",IF(AND(FV14="Dwn",GF14="Short"),"s",IF(AND(FV14="Up",GF14="Long"),"s",IF(AND(FV14="SW",GF14="Long"),"s","o")))))) -> o | I14: 47.1 | J14: 47 | K14: =IF(J14="","",(J14-I14)/I14) -> -0.0021231423 | L14: =IF(OR($GI14="",J14=""),"",IF($GF14="Long",(($J14*$GI14)-$GH14),($GH14-($J14*$GI14)))) -> -0.8492569 | M14: =IF(L14="","",IF(HG14="","",HG14-L14)) | N14: =IF(AND($FV14="Up",$GA14="Long"),$EH14,"") -> -0.8492569 | O14: =IF($J14="",#N/A,SUM($N$4:N14)) -> 83.786273 | P14: =IF(AND($FV14="Dwn",$GA14="Short"),$EH14,"") | Q14: =IF($J14="",#N/A,SUM($P$4:P14)) -> 39.117085 | R14: =IF(AND($FV14="SW",$GA14="Long"),$EH14,"") | S14: =IF($J14="",#N/A,SUM($R$4:R14)) -> 100.02028 | T14: =IF(AND($FV14="Up",$GA14="Long"),$FP14,"") -> -0.035385704 | U14: =IF($J14="",#N/A,SUM($T$4:T14)) -> 3.4910947 | V14: =IF(AND($FV14="Dwn",$GA14="Short"),$FP14,"") | W14: =IF($J14="",#N/A,SUM($V$4:V14)) -> 1.6298786 | X14: =IF(AND($FV14="SW",$GA14="Long"),$FP14,"") | Y14: =IF($J14="",#N/A,SUM($X$4:X14)) -> 4.1675118 | Z14: =IF(AND($FV14="Up",$GA14="Long",$E14=Z$2),$FP14,"") | AA14: =IF($J14="",#N/A,SUM(Z$4:Z14)) -> 0 | AB14: =IF(AND($FV14="Dwn",$GA14="Short",$E14=Z$2),$FP14,"") | AC14: =IF($J14="",#N/A,SUM(AB$4:AB14)) -> 0 | AD14: =IF(AND($FV14="SW",$GA14="Long",$E14=Z$2),$FP14,"") | AE14: =IF($J14="",#N/A,SUM(AD$4:AD14)) -> 0 | AF14: =IF($J14="",#N/A,SUM(AD$4:AD14,AB$4:AB14,Z$4:Z14)) -> 0 | AG14: =IF(AND($FV14="Up",$GA14="Long",$E14=AG$2),$FP14,"") | AH14: =IF($J14="",#N/A,SUM(AG$4:AG14)) -> 0 | AI14: =IF(AND($FV14="Dwn",$GA14="Short",$E14=AG$2),$FP14,"") | AJ14: =IF($J14="",#N/A,SUM(AI$4:AI14)) -> 0 | AK14: =IF(AND($FV14="SW",$GA14="Long",$E14=AG$2),$FP14,"") | AL14: =IF($J14="",#N/A,SUM(AK$4:AK14)) -> 0 | AM14: =IF($J14="",#N/A,SUM(AK$4:AK14,AI$4:AI14,AG$4:AG14)) -> 0 | AN14: =IF(AND($FV14="Up",$GA14="Long",$E14=AN$2),$FP14,"") | AO14: =IF($J14="",#N/A,SUM(AN$4:AN14)) -> 0 | AP14: =IF(AND($FV14="Dwn",$GA14="Short",$E14=AN$2),$FP14,"") | AQ14: =IF($J14="",#N/A,SUM(AP$4:AP14)) -> 0 | AR14: =IF(AND($FV14="SW",$GA14="Long",$E14=AN$2),$FP14,"") | AS14: =IF($J14="",#N/A,SUM(AR$4:AR14)) -> 0 | AT14: =IF($J14="",#N/A,SUM(AR$4:AR14,AP$4:AP14,AN$4:AN14)) -> 0 | AU14: =IF(AND($FV14="Up",$GA14="Long",$E14=AU$2),$FP14,"") | AV14: =IF($J14="",#N/A,SUM(AU$4:AU14)) -> 0 | AW14: =IF(AND($FV14="Dwn",$GA14="Short",$E14=AU$2),$FP14,"") | AX14: =IF($J14="",#N/A,SUM(AW$4:AW14)) -> 1.2290223 | AY14: =IF(AND($FV14="SW",$GA14="Long",$E14=AU$2),$FP14,"") | AZ14: =IF($J14="",#N/A,SUM(AY$4:AY14)) -> 2.494577 | BA14: =IF($J14="",#N/A,SUM(AY$4:AY14,AW$4:AW14,AU$4:AU14)) -> 3.7235993 | BB14: =IF(AND($FV14="Up",$GA14="Long",$E14=BB$2),$FP14,"") | BC14: =IF($J14="",#N/A,SUM(BB$4:BB14)) -> 0 | BD14: =IF(AND($FV14="Dwn",$GA14="Short",$E14=BB$2),$FP14,"") | BE14: =IF($J14="",#N/A,SUM(BD$4:BD14)) -> 0 | BF14: =IF(AND($FV14="SW",$GA14="Long",$E14=BB$2),$FP14,"") | BG14: =IF($J14="",#N/A,SUM(BF$4:BF14)) -> 0 | BH14: =IF($J14="",#N/A,SUM(BF$4:BF14,BD$4:BD14,BB$4:BB14)) -> 0 | BI14: =IF(AND($FV14="Up",$GA14="Long",$E14=BI$2),$FP14,"") -> -0.035385704 | BJ14: =IF($J14="",#N/A,SUM(BI$4:BI14)) -> 2.5223549 | BK14: =IF(AND($FV14="Dwn",$GA14="Short",$E14=BI$2),$FP14,"") | BL14: =IF($J14="",#N/A,SUM(BK$4:BK14)) -> 0 | BM14: =IF(AND($FV14="SW",$GA14="Long",$E14=BI$2),$FP14,"") | BN14: =IF($J14="",#N/A,SUM(BM$4:BM14)) -> 1.6729348 | BO14: =IF($J14="",#N/A,SUM(BM$4:BM14,BK$4:BK14,BI$4:BI14)) -> 4.1952897 | BP14: =IF(AND($FV14="Up",$GA14="Long",$E14=BP$2),$FP14,"") | BQ14: =IF($J14="",#N/A,SUM(BP$4:BP14)) -> 0.96873982 | BR14: =IF(AND($FV14="Dwn",$GA14="Short",$E14=BP$2),$FP14,"") | BS14: =IF($J14="",#N/A,SUM(BR$4:BR14)) -> 0 | BT14: =IF(AND($FV14="SW",$GA14="Long",$E14=BP$2),$FP14,"") | BU14: =IF($J14="",#N/A,SUM(BT$4:BT14)) -> 0 | BV14: =IF($J14="",#N/A,SUM(BT$4:BT14,BR$4:BR14,BP$4:BP14)) -> 0.96873982 | BW14: =IF(AND($FV14="Up",$GA14="Long",$E14=BW$2),$FP14,"") | BX14: =IF($J14="",#N/A,SUM(BW$4:BW14)) -> 0 | BY14: =IF(AND($FV14="Dwn",$GA14="Short",$E14=BW$2),$FP14,"") | BZ14: =IF($J14="",#N/A,SUM(BY$4:BY14)) -> 0 | CA14: =IF(AND($FV14="SW",$GA14="Long",$E14=BW$2),$FP14,"") | CB14: =IF($J14="",#N/A,SUM(CA$4:CA14)) -> 0 | CC14: =IF($J14="",#N/A,SUM(CA$4:CA14,BY$4:BY14,BW$4:BW14)) -> 0 | CD14: =IF(AND($FV14="Up",$GA14="Long",$E14=CD$2),$FP14,"") | CE14: =IF($J14="",#N/A,SUM(CD$4:CD14)) -> 0 | CF14: =IF(AND($FV14="Dwn",$GA14="Short",$E14=CD$2),$FP14,"") | CG14: =IF($J14="",#N/A,SUM(CF$4:CF14)) -> 0 | CH14: =IF(AND($FV14="SW",$GA14="Long",$E14=CD$2),$FP14,"") | CI14: =IF($J14="",#N/A,SUM(CH$4:CH14)) -> 0 | CJ14: =IF($J14="",#N/A,SUM(CH$4:CH14,CF$4:CF14,CD$4:CD14)) -> 0 | CK14: =IF(AND($FV14="Up",$GA14="Long",$E14=CK$2),$FP14,"") | CL14: =IF($J14="",#N/A,SUM(CK$4:CK14)) -> 0 | CM14: =IF(AND($FV14="Dwn",$GA14="Short",$E14=CK$2),$FP14,"") | CN14: =IF($J14="",#N/A,SUM(CM$4:CM14)) -> 0 | CO14: =IF(AND($FV14="SW",$GA14="Long",$E14=CK$2),$FP14,"") | CP14: =IF($J14="",#N/A,SUM(CO$4:CO14)) -> 0 | CQ14: =IF($J14="",#N/A,SUM(CO$4:CO14,CM$4:CM14,CK$4:CK14)) -> 0 | CR14: =IF(AND($FV14="Up",$GA14="Long",$E14=CR$2),$FP14,"") | CS14: =IF($J14="",#N/A,SUM(CR$4:CR14)) -> 0 | CT14: =IF(AND($FV14="Dwn",$GA14="Short",$E14=CR$2),$FP14,"") | CU14: =IF($J14="",#N/A,SUM(CT$4:CT14)) -> 0 | CV14: =IF(AND($FV14="SW",$GA14="Long",$E14=CR$2),$FP14,"") | CW14: =IF($J14="",#N/A,SUM(CV$4:CV14)) -> 0 | CX14: =IF($J14="",#N/A,SUM(CV$4:CV14,CT$4:CT14,CR$4:CR14)) -> 0 | CY14: =IF(AND($FV14="Up",$GA14="Long",$E14=CY$2),$FP14,"") | CZ14: =IF($J14="",#N/A,SUM(CY$4:CY14)) -> 0 | DA14: =IF(AND($FV14="Dwn",$GA14="Short",$E14=CY$2),$FP14,"") | DB14: =IF($J14="",#N/A,SUM(DA$4:DA14)) -> 0 | DC14: =IF(AND($FV14="SW",$GA14="Long",$E14=CY$2),$FP14,"") | DD14: =IF($J14="",#N/A,SUM(DC$4:DC14)) -> 0 | DE14: =IF($J14="",#N/A,SUM(DC$4:DC14,DA$4:DA14,CY$4:CY14)) -> 0 | DF14: =IF(AND($FV14="Up",$GA14="Long",$E14=DF$2),$FP14,"") | DG14: =IF($J14="",#N/A,SUM(DF$4:DF14)) -> 0 | DH14: =IF(AND($FV14="Dwn",$GA14="Short",$E14=DF$2),$FP14,"") | DI14: =IF($J14="",#N/A,SUM(DH$4:DH14)) -> 0 | DJ14: =IF(AND($FV14="SW",$GA14="Long",$E14=DF$2),$FP14,"") | DK14: =IF($J14="",#N/A,SUM(DJ$4:DJ14)) -> 0 | DL14: =IF($J14="",#N/A,SUM(DJ$4:DJ14,DH$4:DH14,DF$4:DF14)) -> 0 | DM14: =IF(AND($FV14="Up",$GA14="Long",$E14=DM$2),$FP14,"") | DN14: =IF($J14="",#N/A,SUM(DM$4:DM14)) -> 0 | DO14: =IF(AND($FV14="Dwn",$GA14="Short",$E14=DM$2),$FP14,"") | DP14: =IF($J14="",#N/A,SUM(DO$4:DO14)) -> 0 | DQ14: =IF(AND($FV14="SW",$GA14="Long",$E14=DM$2),$FP14,"") | DR14: =IF($J14="",#N/A,SUM(DQ$4:DQ14)) -> 0 | DS14: =IF($J14="",#N/A,SUM(DQ$4:DQ14,DO$4:DO14,DM$4:DM14)) -> 0 | DT14: =IF(AND($FV14="Up",$GA14="Long",$E14=DT$2),$FP14,"") | DU14: =IF($J14="",#N/A,SUM(DT$4:DT14)) -> 0 | DV14: =IF(AND($FV14="Dwn",$GA14="Short",$E14=DT$2),$FP14,"") | DW14: =IF($J14="",#N/A,SUM(DV$4:DV14)) -> 0.40085631 | DX14: =IF(AND($FV14="SW",$GA14="Long",$E14=DT$2),$FP14,"") | DY14: =IF($J14="",#N/A,SUM(DX$4:DX14)) -> 0 | DZ14: =IF($J14="",#N/A,SUM(DX$4:DX14,DV$4:DV14,DT$4:DT14)) -> 0.40085631 | EA14: =IF(AND($FV14="Up",$GA14="Long",$E14=EA$2),$FP14,"") | EB14: =IF($J14="",#N/A,SUM(EA$4:EA14)) -> 0 | EC14: =IF(AND($FV14="Dwn",$GA14="Short",$E14=EA$2),$FP14,"") | ED14: =IF($J14="",#N/A,SUM(EC$4:EC14)) -> 0 | EE14: =IF(AND($FV14="SW",$GA14="Long",$E14=EA$2),$FP14,"") | EF14: =IF($J14="",#N/A,SUM(EE$4:EE14)) -> 0 | EG14: =IF($J14="",#N/A,SUM(EE$4:EE14,EC$4:EC14,EA$4:EA14)) -> 0 | EH14: =IF(OR($GI14="",L14=""),"",IF($GA14="Long",(($J14*$GI14)-$GH14),($GH14-($J14*$GI14)))) -> -0.8492569 | EI14: =IF(EH14="",#N/A,SUM($EH$4:EH14)) -> 222.92364 | EJ14: =IF(GZ14="","",IF(OR($GI14="",AM14=""),"",IF($GA14="Long",(($GZ14*$GI14)-$GH14),($GH14-($GZ14*$GI14))))) -> 0 | EK14: =IF($GZ14="",#N/A,SUM(EJ$4:EJ14)) -> 376.28661 | EL14: =IF(J14="","",IF(D14="Y",FP14,"")) -> -0.035385704 | EM14: =IF(EL14="",NA(),SUM($EL$4:EL14)) -> 9.2884851 | EN14: =IF(AND($FV14="Up",$GA14="Long",$D14="Y"),$EL14,"") -> -0.035385704 | EO14: =IF(EN14="",NA(),SUM($EN$4:EN14)) -> 3.4910947 | EP14: =IF(AND($FV14="SW",$GA14="Long",$D14="Y"),$EL14,"") | EQ14: =IF(EP14="",NA(),SUM($EP$4:EP14)) -> #N/A | ER14: =IF(AND($FV14="Dwn",$GA14="Short",$D14="Y"),$EL14,"") | ES14: =IF(ER14="",NA(),SUM($ER$4:ER14)) -> #N/A | ET14: =IF($J14="","",IF($D14="N",$FP14,"")) | EU14: =IF(ET14="",NA(),SUM($ET$4:ET14)) -> #N/A | EV14: =IF(AND($FV14="Up",$GA14="Long",$D14="N"),$ET14,"") | EW14: =IF(EV14="",NA(),SUM($EV$4:EV14)) -> #N/A | EX14: =IF(AND($FV14="SW",$GA14="Long",$D14="N"),$ET14,"") | EY14: =IF(EX14="",NA(),SUM($EX$4:EX14)) -> #N/A | EZ14: =IF(AND($FV14="Dwn",$GA14="Short",$D14="N"),$ET14,"") | FA14: =IF(EZ14="",NA(),SUM($EZ$4:EZ14)) -> #N/A | FB14: =IF($GZ14="","",IF(AND($FV14="Dwn",$K14<0),$FN14-FP14,"")) | FC14: =IF($FB14="",#N/A,SUM(FB$4:$FB14)) -> #N/A | FD14: =IF($GZ14="","",IF(AND($FV14="Dwn",$K14>0),$FN14-$FP14,"")) | FE14: =IF($FD14="",#N/A,SUM($FD$4:FD14)) -> #N/A | FF14: =IF($GZ14="","",IF(AND($FV14="Up",$K14>0),$FN14-$FP14,"")) | FG14: =IF($FF14="",#N/A,SUM($FF$4:FF14)) -> #N/A | FH14: =IF($GZ14="","",IF(AND($FV14="Up",$K14<0),$FN14-$FP14,"")) -> 0.035385704 | FI14: =IF($FH14="",#N/A,SUM($FH$4:FH14)) -> 0.035385704 | FJ14: =IF($GZ14="","",IF(AND($FV14="SW",$K14>0),$FN14-$FP14,"")) | FK14: =IF($FJ14="",#N/A,SUM($FJ$4:FJ14)) -> #N/A | FL14: =IF($GZ14="","",IF(AND($FV14="SW",$K14<0),$FN14-$FP14,"")) | FM14: =IF($FL14="",#N/A,SUM($FL$4:FL14)) -> #N/A | FN14: =IF(OR($GI14="",$GZ14=""),"",IF($GA14="Long",(($GZ14*$GI14)-$GH14)/($GH14*0.06),($GH14-($GZ14*$GI14))/($GH14*0.06))) -> 0 | FO14: =IF($FN14="",#N/A,SUM(FN$4:$FN14)) -> 15.678609 | FP14: =IF(OR($GI14="",L14=""),"",IF($GA14="Long",(($J14*$GI14)-$GH14)/(GH14*0.06),($GH14-($J14*$GI14))/(GH14*0.06))) -> -0.035385704 | FQ14: =IF($EH14="",#N/A,SUM($FP$4:FP14)) -> 9.2884851 | FU14: #N/A | FV14: =IF(FW14="Down","Dwn",IF(FW14="Up","Up",IF(AND(FW14="",K14=""),"",IF(AND(K14<0,FW14="Yes"),"Dwn",IF(AND(K14>0,FW14="Yes"),"Up",IF(AND(K14<0,FW14="No"),"Up",IF(AND(K14>0,FW14="No"),"Dwn",IF(FW14="NA","SW","err")))))))) -> Up | FW14: No | FX14: =IF(K14="","",IF(AND(K14>0,FW14="Yes"),1,"")) | FY14: =IF(K14="","",IF(AND($K14>0,$FW14="No"),1,"")) | FZ14: =IF(K14="","",IF(AND($K14>0,$FW14="NA"),1,"")) | GA14: =IF(FV14="Dwn","Short","Long") -> Long | GB14: =IF(K14="","",IF(AND($K14<0,$FW14="Yes"),1,"")) | GC14: =IF(K14="","",IF(AND($K14<0,$FW14="No"),1,"")) -> 1 | GD14: =IF(K14="","",IF(AND($K14<0,$FW14="NA"),1,"")) | GE14: =I14 -> 47.1 | GF14: Long | GG14: =400/I14 -> 8.492569 | GH14: =IF(GG14="","",GE14*GG14) -> 400 | GI14: =GG14 -> 8.492569 | GJ14: =J14 -> 47 | GK14: =IF($GI14="","",IF($GF14="Long",(($GJ14*$GI14)-$GH14),($GH14-($GJ14*$GI14)))) -> -0.8492569 | GL14: =IF($GI14="","",IF($GF14="Long",(($GZ14*$GI14)-$GH14),($GH14-($GZ14*$GI14)))) -> 0 | GM14: =IF(AND($FV14="SW",$GA14="Long"),$FN14,"") | GN14: =IF($GZ14="",#N/A,SUM(GM$4:GM14)) -> 6.7956157 | GO14: =IF(AND($FV14="UP",$GA14="Long"),$FN14,"") -> 0 | GP14: =IF($GZ14="",#N/A,SUM(GO$4:GO14)) -> 5.0281414 | GQ14: =IF(AND($FV14="Dwn",$GA14="Short"),$FN14,"") | GR14: =IF($GZ14="",#N/A,SUM(GQ$4:GQ14)) -> 3.8548516 | GS14: =IF(AND(FV14="SW",GA14="Long"),$EJ14,"") | GT14: =IF($GZ14="",#N/A,SUM(GS$4:GS14)) -> 163.09478 | GU14: =IF(AND(FV14="UP",GA14="Long"),$EJ14,"") -> 0 | GV14: =IF($GZ14="",#N/A,SUM(GU$4:GU14)) -> 120.67539 | GW14: =IF(AND(FV14="Dwn",GA14="Short"),$EJ14,"") | GX14: =IF($GZ14="",#N/A,SUM(GW$4:GW14)) -> 92.516437 | GY14: =IF(EJ14="",#N/A,SUM($EJ$4:EJ14)) -> 376.28661 | GZ14: 47.1 | HA14: =IF(OR(GL14="",GZ14=""),"",GL14-EH14) -> 0.8492569 | HB14: Skip | HC14: =IFERROR(VLOOKUP(E14,Expectancy!$P$4:$S$19,1+C14,FALSE),"") -> -0.079483353 | HD14: =IF(AND(HB14="MOC",GZ14=""),"",IF(GI14="","",IF(HB14="Skip","",IF(HG14=0,0,HG14/(GH14*0.06))))) | HE14: =IF(HD14="",#N/A,SUM($HD$4:HD14)) -> #N/A | HF14: =IF(HD14="",#N/A,IF(HB14="Skip",#N/A,SUM($HG$4:HG14))) -> #N/A | HG14: =IF(HB14="","",IF(HB14="Skip","",IF(OR(HB14="open",HB14="Other"),GK14,IF(HB14="MOC",GL14,"Err")))) | HH14: =IF(OR($GI14="",$L14=""),"",IF($GA14="Long",(($GZ14*$GI14)-$GH14)/($GH14*0.06),($GH14-($GZ14*$GI14))/($GH14*0.06))) -> 0
