Workbook

Sheet Indices
A1: Stock | B1: Index | C1: Index2 | D1: Sector | E1: As of: | F1: 45616
A2: NVDA | B2: SP500 | C2: NQ100
A3: AAPL | B3: SP500 | C3: NQ100
A4: MSFT | B4: SP500 | C4: NQ100
A5: GOOG | B5: SP500 | C5: NQ100
A6: GOOGL | B6: SP500 | C6: NQ100
A7: AMZN | B7: SP500 | C7: NQ100
A8: META | B8: SP500 | C8: NQ100
A9: TSLA | B9: SP500 | C9: NQ100
A10: BRK.B | B10: SP500
A11: AVGO | B11: SP500 | C11: NQ100
A12: WMT | B12: SP500
A13: JPM | B13: SP500
A14: LLY | B14: SP500
A15: V | B15: SP500
A16: UNH | B16: SP500
A17: XOM | B17: SP500
A18: ORCL | B18: SP500
A19: MA | B19: SP500
A20: COST | B20: SP500 | C20: NQ100
A21: PG | B21: SP500
A22: HD | B22: SP500
A23: NFLX | B23: SP500 | C23: NQ100
A24: JNJ | B24: SP500
A25: BAC | B25: SP500
A26: CRM | B26: SP500
A27: ABBV | B27: SP500
A28: CVX | B28: SP500
A29: TMUS | B29: SP500 | C29: NQ100
A30: KO | B30: SP500
A31: MRK | B31: SP500
A32: WFC | B32: SP500
A33: CSCO | B33: SP500 | C33: NQ100
A34: BX | B34: SP500
A35: ACN | B35: SP500
A36: AMD | B36: SP500 | C36: NQ100
A37: ADBE | B37: SP500 | C37: NQ100
A38: PEP | B38: SP500 | C38: NQ100
A39: LIN | B39: SP500 | C39: NQ100
A40: MS | B40: SP500
A41: NOW | B41: SP500
A42: MCD | B42: SP500
A43: DIS | B43: SP500
A44: PM | B44: SP500
A45: AXP | B45: SP500
A46: ABT | B46: SP500
A47: IBM | B47: SP500
A48: TMO | B48: SP500
A49: ISRG | B49: SP500 | C49: NQ100
A50: GE | B50: SP500
A51: GS | B51: SP500
A52: CAT | B52: SP500
A53: INTU | B53: SP500 | C53: NQ100
A54: TXN | B54: SP500 | C54: NQ100
A55: VZ | B55: SP500
A56: QCOM | B56: SP500 | C56: NQ100
A57: DHR | B57: SP500
A58: BKNG | B58: SP500 | C58: NQ100
A59: T | B59: SP500
A60: CMCSA | B60: SP500 | C60: NQ100
A61: BLK | B61: SP500
A62: RTX | B62: SP500
A63: NEE | B63: SP500
A64: SPGI | B64: SP500
A65: AMGN | B65: SP500 | C65: NQ100
A66: PGR | B66: SP500
A67: LOW | B67: SP500
A68: HON | B68: SP500 | C68: NQ100
A69: SCHW | B69: SP500
A70: SYK | B70: SP500
A71: UBER | B71: SP500
A72: ETN | B72: SP500
A73: UNP | B73: SP500
A74: PLTR | B74: SP500
A75: PFE | B75: SP500
A76: AMAT | B76: SP500 | C76: NQ100
A77: KKR | B77: SP500
A78: TJX | B78: SP500
A79: BSX | B79: SP500
A80: COP | B80: SP500
A81: C | B81: SP500
A82: PANW | B82: SP500 | C82: NQ100
A83: LMT | B83: SP500
A84: FI | B84: SP500
A85: ADP | B85: SP500 | C85: NQ100
A86: ANET | B86: SP500
A87: BMY | B87: SP500
A88: VRTX | B88: SP500 | C88: NQ100
A89: CB | B89: SP500
A90: UPS | B90: SP500
A91: SBUX | B91: SP500 | C91: NQ100
A92: GILD | B92: SP500 | C92: NQ100
A93: DE | B93: SP500
A94: BA | B94: SP500
A95: MMC | B95: SP500
A96: NKE | B96: SP500
A97: MU | B97: SP500 | C97: NQ100
A98: MDT | B98: SP500
A99: PLD | B99: SP500
A100: ADI | B100: SP500 | C100: NQ100
...

Sheet Industries
A1: Sector | B1: XLF | C1: XLE
A2: Industries | B2: Consumer Finance | C2: Oil & Gas Refining & Marketing
B3: Capital markets | C3: Integrated Oil & Gas
B4: Banks | C4: Oil & Gas Equipment & Services
B5: Financial Services | C5: Oil & Gas Exploration & Production
B6: Insurance | C6: Oil & Gas Storage & Transportation

Sheet Pivot
A1: Index | B1: (All)
A3: Row Labels | B3: Count of Ticker
A4: 1-Apr | B4: 11
A5: 2-Apr | B5: 17
A6: 3-Apr | B6: 12
A7: 4-Apr | B7: 3
A8: 7-Apr | B8: 33
A9: 8-Apr | B9: 29
A10: 9-Apr | B10: 25
A11: 10-Apr | B11: 20
A12: 11-Apr | B12: 28
A13: 14-Apr | B13: 11
A14: 15-Apr | B14: 32
A15: 16-Apr | B15: 44
... A59: Grand Total | B59: 4468

Sheet Charts

Sheet SPDR Chart
B1: % of Tot > | C1: =C2/SUM($C$2:$Q$2) -> 0.086705202 | D1: =D2/SUM($C$2:$Q$2) -> 0.17630058 | E1: =E2/SUM($C$2:$Q$2) -> 0.020231214 | F1: =F2/SUM($C$2:$Q$2) -> 0.11560694 | G1: =G2/SUM($C$2:$Q$2) -> 0.12427746 | H1: =H2/SUM($C$2:$Q$2) -> 0.037572254 | I1: =I2/SUM($C$2:$Q$2) -> 0 | J1: =J2/SUM($C$2:$Q$2) -> 0.11271676 | ... Q1: =Q2/SUM($C$2:$Q$2) -> 0.043352601 | R1: In SPY Total | S1: % | U1: % of Tot > | V1: =V2/SUM($C$2:$Q$2) -> 0.01734104 | W1: =W2/SUM($C$2:$Q$2) -> 0.011560694 | X1: =X2/SUM($C$2:$Q$2) -> 0.0028901734 | Y1: =Y2/SUM($C$2:$Q$2) -> 0.0086705202 | Z1: =Z2/SUM($C$2:$Q$2) -> 0.0057803468 | AA1: =AA2/SUM($C$2:$Q$2) -> 0 | AB1: =AB2/SUM($C$2:$Q$2) -> 0 | AC1: =AC2/SUM($C$2:$Q$2) -> 0.031791908 | ... AJ1: =AJ2/SUM($C$2:$Q$2) -> 0.083815029 | AK1: Total | AL1: %
B2: SPY # > | C2: =SUM(C4:C86) -> 30 | D2: =SUM(D4:D86) -> 61 | E2: =SUM(E4:E86) -> 7 | F2: =SUM(F4:F86) -> 40 | G2: =SUM(G4:G86) -> 43 | H2: =SUM(H4:H86) -> 13 | I2: =SUM(I4:I86) -> 0 | J2: =SUM(J4:J86) -> 39 | ... Q2: =SUM(Q4:Q86) -> 15 | U2: Not Spy# > | V2: =SUM(V4:V86) -> 6 | W2: =SUM(W4:W86) -> 4 | X2: =SUM(X4:X86) -> 1 | Y2: =SUM(Y4:Y86) -> 3 | Z2: =SUM(Z4:Z86) -> 2 | AA2: =SUM(AA4:AA86) -> 0 | AB2: =SUM(AB4:AB86) -> 0 | AC2: =SUM(AC4:AC86) -> 11 | ... AJ2: =SUM(AJ4:AJ86) -> 29
B3: Sector > | C3: XLP | D3: XLI | E3: XHB | F3: XLF | G3: XLV | H3: XLE | I3: XLRE | J3: XLY | K3: XLC | L3: XLK | M3: XLB | N3: XLU | O3: SMH | P3: INS | Q3: IGV | U3: Sector > | V3: XLP | W3: XLI | X3: XHB | Y3: XLF | Z3: XLV | AA3: XLE | AB3: XLRE | AC3: XLY | AD3: XLC | AE3: XLK | AF3: XLB | AG3: XLU | AH3: SMH | AI3: INS | AJ3: IGV
B4: 45756 | C4: =COUNTIFS('2025-Q2'!$E$4:$E$422,'SPDR Chart'!C$3,'2025-Q2'!$F$4:$F$422,'SPDR Chart'!$B4,'2025-Q2'!$D$4:$D$422,"Y") -> 1 | D4: =COUNTIFS('2025-Q2'!$E$4:$E$422,'SPDR Chart'!D$3,'2025-Q2'!$F$4:$F$422,'SPDR Chart'!$B4,'2025-Q2'!$D$4:$D$422,"Y") -> 1 | E4: =COUNTIFS('2025-Q2'!$E$4:$E$422,'SPDR Chart'!E$3,'2025-Q2'!$F$4:$F$422,'SPDR Chart'!$B4,'2025-Q2'!$D$4:$D$422,"Y") -> 0 | F4: =COUNTIFS('2025-Q2'!$E$4:$E$422,'SPDR Chart'!F$3,'2025-Q2'!$F$4:$F$422,'SPDR Chart'!$B4,'2025-Q2'!$D$4:$D$422,"Y") -> 0 | G4: =COUNTIFS('2025-Q2'!$E$4:$E$422,'SPDR Chart'!G$3,'2025-Q2'!$F$4:$F$422,'SPDR Chart'!$B4,'2025-Q2'!$D$4:$D$422,"Y") -> 0 | H4: =COUNTIFS('2025-Q2'!$E$4:$E$422,'SPDR Chart'!H$3,'2025-Q2'!$F$4:$F$422,'SPDR Chart'!$B4,'2025-Q2'!$D$4:$D$422,"Y") -> 0 | I4: =COUNTIFS('2025-Q2'!$E$4:$E$422,'SPDR Chart'!I$3,'2025-Q2'!$F$4:$F$422,'SPDR Chart'!$B4,'2025-Q2'!$D$4:$D$422,"Y") -> 0 | J4: =COUNTIFS('2025-Q2'!$E$4:$E$422,'SPDR Chart'!J$3,'2025-Q2'!$F$4:$F$422,'SPDR Chart'!$B4,'2025-Q2'!$D$4:$D$422,"Y") -> 0 | ... Q4: =COUNTIFS('2025-Q2'!$E$4:$E$422,'SPDR Chart'!Q$3,'2025-Q2'!$F$4:$F$422,'SPDR Chart'!$B4,'2025-Q2'!$D$4:$D$422,"Y") -> 0 | R4: =SUM(C4:Q4) -> 2 | S4: =SUM($R$4:R4)/SUM($R$4:$R$86) -> 0.0057803468 | U4: 45756 | V4: =COUNTIFS('2025-Q2'!$E$4:$E$422,'SPDR Chart'!V$3,'2025-Q2'!$F$4:$F$422,'SPDR Chart'!$B4,'2025-Q2'!$D$4:$D$422,"N") -> 0 | W4: =COUNTIFS('2025-Q2'!$E$4:$E$422,'SPDR Chart'!W$3,'2025-Q2'!$F$4:$F$422,'SPDR Chart'!$B4,'2025-Q2'!$D$4:$D$422,"N") -> 0 | X4: =COUNTIFS('2025-Q2'!$E$4:$E$422,'SPDR Chart'!X$3,'2025-Q2'!$F$4:$F$422,'SPDR Chart'!$B4,'2025-Q2'!$D$4:$D$422,"N") -> 0 | Y4: =COUNTIFS('2025-Q2'!$E$4:$E$422,'SPDR Chart'!Y$3,'2025-Q2'!$F$4:$F$422,'SPDR Chart'!$B4,'2025-Q2'!$D$4:$D$422,"N") -> 0 | Z4: =COUNTIFS('2025-Q2'!$E$4:$E$422,'SPDR Chart'!Z$3,'2025-Q2'!$F$4:$F$422,'SPDR Chart'!$B4,'2025-Q2'!$D$4:$D$422,"N") -> 0 | AA4: =COUNTIFS('2025-Q2'!$E$4:$E$422,'SPDR Chart'!AA$3,'2025-Q2'!$F$4:$F$422,'SPDR Chart'!$B4,'2025-Q2'!$D$4:$D$422,"N") -> 0 | AB4: =COUNTIFS('2025-Q2'!$E$4:$E$422,'SPDR Chart'!AB$3,'2025-Q2'!$F$4:$F$422,'SPDR Chart'!$B4,'2025-Q2'!$D$4:$D$422,"N") -> 0 | AC4: =COUNTIFS('2025-Q2'!$E$4:$E$422,'SPDR Chart'!AC$3,'2025-Q2'!$F$4:$F$422,'SPDR Chart'!$B4,'2025-Q2'!$D$4:$D$422,"N") -> 0 | ... AJ4: =COUNTIFS('2025-Q2'!$E$4:$E$422,'SPDR Chart'!AJ$3,'2025-Q2'!$F$4:$F$422,'SPDR Chart'!$B4,'2025-Q2'!$D$4:$D$422,"N") -> 0 | AK4: =SUM(V4:AJ4) -> 0 | AL4: =SUM($AK$4:AK4)/SUM($AK$4:$AK$86) -> 0
B5: 45757 | C5: =COUNTIFS('2025-Q2'!$E$4:$E$422,'SPDR Chart'!C$3,'2025-Q2'!$F$4:$F$422,'SPDR Chart'!$B5,'2025-Q2'!$D$4:$D$422,"Y") -> 0 | D5: =COUNTIFS('2025-Q2'!$E$4:$E$422,'SPDR Chart'!D$3,'2025-Q2'!$F$4:$F$422,'SPDR Chart'!$B5,'2025-Q2'!$D$4:$D$422,"Y") -> 0 | E5: =COUNTIFS('2025-Q2'!$E$4:$E$422,'SPDR Chart'!E$3,'2025-Q2'!$F$4:$F$422,'SPDR Chart'!$B5,'2025-Q2'!$D$4:$D$422,"Y") -> 0 | F5: =COUNTIFS('2025-Q2'!$E$4:$E$422,'SPDR Chart'!F$3,'2025-Q2'!$F$4:$F$422,'SPDR Chart'!$B5,'2025-Q2'!$D$4:$D$422,"Y") -> 0 | G5: =COUNTIFS('2025-Q2'!$E$4:$E$422,'SPDR Chart'!G$3,'2025-Q2'!$F$4:$F$422,'SPDR Chart'!$B5,'2025-Q2'!$D$4:$D$422,"Y") -> 0 | H5: =COUNTIFS('2025-Q2'!$E$4:$E$422,'SPDR Chart'!H$3,'2025-Q2'!$F$4:$F$422,'SPDR Chart'!$B5,'2025-Q2'!$D$4:$D$422,"Y") -> 0 | I5: =COUNTIFS('2025-Q2'!$E$4:$E$422,'SPDR Chart'!I$3,'2025-Q2'!$F$4:$F$422,'SPDR Chart'!$B5,'2025-Q2'!$D$4:$D$422,"Y") -> 0 | J5: =COUNTIFS('2025-Q2'!$E$4:$E$422,'SPDR Chart'!J$3,'2025-Q2'!$F$4:$F$422,'SPDR Chart'!$B5,'2025-Q2'!$D$4:$D$422,"Y") -> 0 | ... Q5: =COUNTIFS('2025-Q2'!$E$4:$E$422,'SPDR Chart'!Q$3,'2025-Q2'!$F$4:$F$422,'SPDR Chart'!$B5,'2025-Q2'!$D$4:$D$422,"Y") -> 0 | R5: =SUM(C5:Q5) -> 0 | S5: =SUM($R$4:R5)/SUM($R$4:$R$86) -> 0.0057803468 | U5: 45757 | V5: =COUNTIFS('2025-Q2'!$E$4:$E$422,'SPDR Chart'!V$3,'2025-Q2'!$F$4:$F$422,'SPDR Chart'!$B5,'2025-Q2'!$D$4:$D$422,"N") -> 0 | W5: =COUNTIFS('2025-Q2'!$E$4:$E$422,'SPDR Chart'!W$3,'2025-Q2'!$F$4:$F$422,'SPDR Chart'!$B5,'2025-Q2'!$D$4:$D$422,"N") -> 0 | X5: =COUNTIFS('2025-Q2'!$E$4:$E$422,'SPDR Chart'!X$3,'2025-Q2'!$F$4:$F$422,'SPDR Chart'!$B5,'2025-Q2'!$D$4:$D$422,"N") -> 0 | Y5: =COUNTIFS('2025-Q2'!$E$4:$E$422,'SPDR Chart'!Y$3,'2025-Q2'!$F$4:$F$422,'SPDR Chart'!$B5,'2025-Q2'!$D$4:$D$422,"N") -> 0 | Z5: =COUNTIFS('2025-Q2'!$E$4:$E$422,'SPDR Chart'!Z$3,'2025-Q2'!$F$4:$F$422,'SPDR Chart'!$B5,'2025-Q2'!$D$4:$D$422,"N") -> 0 | AA5: =COUNTIFS('2025-Q2'!$E$4:$E$422,'SPDR Chart'!AA$3,'2025-Q2'!$F$4:$F$422,'SPDR Chart'!$B5,'2025-Q2'!$D$4:$D$422,"N") -> 0 | AB5: =COUNTIFS('2025-Q2'!$E$4:$E$422,'SPDR Chart'!AB$3,'2025-Q2'!$F$4:$F$422,'SPDR Chart'!$B5,'2025-Q2'!$D$4:$D$422,"N") -> 0 | AC5: =COUNTIFS('2025-Q2'!$E$4:$E$422,'SPDR Chart'!AC$3,'2025-Q2'!$F$4:$F$422,'SPDR Chart'!$B5,'2025-Q2'!$D$4:$D$422,"N") -> 0 | ... AJ5: =COUNTIFS('2025-Q2'!$E$4:$E$422,'SPDR Chart'!AJ$3,'2025-Q2'!$F$4:$F$422,'SPDR Chart'!$B5,'2025-Q2'!$D$4:$D$422,"N") -> 0 | AK5: =SUM(V5:AJ5) -> 0 | AL5: =SUM($AK$4:AK5)/SUM($AK$4:$AK$86) -> 0
B6: 45758 | C6: =COUNTIFS('2025-Q2'!$E$4:$E$422,'SPDR Chart'!C$3,'2025-Q2'!$F$4:$F$422,'SPDR Chart'!$B6,'2025-Q2'!$D$4:$D$422,"Y") -> 0 | D6: =COUNTIFS('2025-Q2'!$E$4:$E$422,'SPDR Chart'!D$3,'2025-Q2'!$F$4:$F$422,'SPDR Chart'!$B6,'2025-Q2'!$D$4:$D$422,"Y") -> 1 | E6: =COUNTIFS('2025-Q2'!$E$4:$E$422,'SPDR Chart'!E$3,'2025-Q2'!$F$4:$F$422,'SPDR Chart'!$B6,'2025-Q2'!$D$4:$D$422,"Y") -> 0 | F6: =COUNTIFS('2025-Q2'!$E$4:$E$422,'SPDR Chart'!F$3,'2025-Q2'!$F$4:$F$422,'SPDR Chart'!$B6,'2025-Q2'!$D$4:$D$422,"Y") -> 5 | G6: =COUNTIFS('2025-Q2'!$E$4:$E$422,'SPDR Chart'!G$3,'2025-Q2'!$F$4:$F$422,'SPDR Chart'!$B6,'2025-Q2'!$D$4:$D$422,"Y") -> 0 | H6: =COUNTIFS('2025-Q2'!$E$4:$E$422,'SPDR Chart'!H$3,'2025-Q2'!$F$4:$F$422,'SPDR Chart'!$B6,'2025-Q2'!$D$4:$D$422,"Y") -> 0 | I6: =COUNTIFS('2025-Q2'!$E$4:$E$422,'SPDR Chart'!I$3,'2025-Q2'!$F$4:$F$422,'SPDR Chart'!$B6,'2025-Q2'!$D$4:$D$422,"Y") -> 0 | J6: =COUNTIFS('2025-Q2'!$E$4:$E$422,'SPDR Chart'!J$3,'2025-Q2'!$F$4:$F$422,'SPDR Chart'!$B6,'2025-Q2'!$D$4:$D$422,"Y") -> 0 | ... Q6: =COUNTIFS('2025-Q2'!$E$4:$E$422,'SPDR Chart'!Q$3,'2025-Q2'!$F$4:$F$422,'SPDR Chart'!$B6,'2025-Q2'!$D$4:$D$422,"Y") -> 0 | R6: =SUM(C6:Q6) -> 6 | S6: =SUM($R$4:R6)/SUM($R$4:$R$86) -> 0.023121387 | U6: 45758 | V6: =COUNTIFS('2025-Q2'!$E$4:$E$422,'SPDR Chart'!V$3,'2025-Q2'!$F$4:$F$422,'SPDR Chart'!$B6,'2025-Q2'!$D$4:$D$422,"N") -> 0 | W6: =COUNTIFS('2025-Q2'!$E$4:$E$422,'SPDR Chart'!W$3,'2025-Q2'!$F$4:$F$422,'SPDR Chart'!$B6,'2025-Q2'!$D$4:$D$422,"N") -> 0 | X6: =COUNTIFS('2025-Q2'!$E$4:$E$422,'SPDR Chart'!X$3,'2025-Q2'!$F$4:$F$422,'SPDR Chart'!$B6,'2025-Q2'!$D$4:$D$422,"N") -> 0 | Y6: =COUNTIFS('2025-Q2'!$E$4:$E$422,'SPDR Chart'!Y$3,'2025-Q2'!$F$4:$F$422,'SPDR Chart'!$B6,'2025-Q2'!$D$4:$D$422,"N") -> 0 | Z6: =COUNTIFS('2025-Q2'!$E$4:$E$422,'SPDR Chart'!Z$3,'2025-Q2'!$F$4:$F$422,'SPDR Chart'!$B6,'2025-Q2'!$D$4:$D$422,"N") -> 0 | AA6: =COUNTIFS('2025-Q2'!$E$4:$E$422,'SPDR Chart'!AA$3,'2025-Q2'!$F$4:$F$422,'SPDR Chart'!$B6,'2025-Q2'!$D$4:$D$422,"N") -> 0 | AB6: =COUNTIFS('2025-Q2'!$E$4:$E$422,'SPDR Chart'!AB$3,'2025-Q2'!$F$4:$F$422,'SPDR Chart'!$B6,'2025-Q2'!$D$4:$D$422,"N") -> 0 | AC6: =COUNTIFS('2025-Q2'!$E$4:$E$422,'SPDR Chart'!AC$3,'2025-Q2'!$F$4:$F$422,'SPDR Chart'!$B6,'2025-Q2'!$D$4:$D$422,"N") -> 0 | ... AJ6: =COUNTIFS('2025-Q2'!$E$4:$E$422,'SPDR Chart'!AJ$3,'2025-Q2'!$F$4:$F$422,'SPDR Chart'!$B6,'2025-Q2'!$D$4:$D$422,"N") -> 0 | AK6: =SUM(V6:AJ6) -> 0 | AL6: =SUM($AK$4:AK6)/SUM($AK$4:$AK$86) -> 0
B7: 45759 | C7: =COUNTIFS('2025-Q2'!$E$4:$E$422,'SPDR Chart'!C$3,'2025-Q2'!$F$4:$F$422,'SPDR Chart'!$B7,'2025-Q2'!$D$4:$D$422,"Y") -> 0 | D7: =COUNTIFS('2025-Q2'!$E$4:$E$422,'SPDR Chart'!D$3,'2025-Q2'!$F$4:$F$422,'SPDR Chart'!$B7,'2025-Q2'!$D$4:$D$422,"Y") -> 0 | E7: =COUNTIFS('2025-Q2'!$E$4:$E$422,'SPDR Chart'!E$3,'2025-Q2'!$F$4:$F$422,'SPDR Chart'!$B7,'2025-Q2'!$D$4:$D$422,"Y") -> 0 | F7: =COUNTIFS('2025-Q2'!$E$4:$E$422,'SPDR Chart'!F$3,'2025-Q2'!$F$4:$F$422,'SPDR Chart'!$B7,'2025-Q2'!$D$4:$D$422,"Y") -> 0 | G7: =COUNTIFS('2025-Q2'!$E$4:$E$422,'SPDR Chart'!G$3,'2025-Q2'!$F$4:$F$422,'SPDR Chart'!$B7,'2025-Q2'!$D$4:$D$422,"Y") -> 0 | H7: =COUNTIFS('2025-Q2'!$E$4:$E$422,'SPDR Chart'!H$3,'2025-Q2'!$F$4:$F$422,'SPDR Chart'!$B7,'2025-Q2'!$D$4:$D$422,"Y") -> 0 | I7: =COUNTIFS('2025-Q2'!$E$4:$E$422,'SPDR Chart'!I$3,'2025-Q2'!$F$4:$F$422,'SPDR Chart'!$B7,'2025-Q2'!$D$4:$D$422,"Y") -> 0 | J7: =COUNTIFS('2025-Q2'!$E$4:$E$422,'SPDR Chart'!J$3,'2025-Q2'!$F$4:$F$422,'SPDR Chart'!$B7,'2025-Q2'!$D$4:$D$422,"Y") -> 0 | ... Q7: =COUNTIFS('2025-Q2'!$E$4:$E$422,'SPDR Chart'!Q$3,'2025-Q2'!$F$4:$F$422,'SPDR Chart'!$B7,'2025-Q2'!$D$4:$D$422,"Y") -> 0 | R7: =SUM(C7:Q7) -> 0 | S7: =SUM($R$4:R7)/SUM($R$4:$R$86) -> 0.023121387 | U7: 45759 | V7: =COUNTIFS('2025-Q2'!$E$4:$E$422,'SPDR Chart'!V$3,'2025-Q2'!$F$4:$F$422,'SPDR Chart'!$B7,'2025-Q2'!$D$4:$D$422,"N") -> 0 | W7: =COUNTIFS('2025-Q2'!$E$4:$E$422,'SPDR Chart'!W$3,'2025-Q2'!$F$4:$F$422,'SPDR Chart'!$B7,'2025-Q2'!$D$4:$D$422,"N") -> 0 | X7: =COUNTIFS('2025-Q2'!$E$4:$E$422,'SPDR Chart'!X$3,'2025-Q2'!$F$4:$F$422,'SPDR Chart'!$B7,'2025-Q2'!$D$4:$D$422,"N") -> 0 | Y7: =COUNTIFS('2025-Q2'!$E$4:$E$422,'SPDR Chart'!Y$3,'2025-Q2'!$F$4:$F$422,'SPDR Chart'!$B7,'2025-Q2'!$D$4:$D$422,"N") -> 0 | Z7: =COUNTIFS('2025-Q2'!$E$4:$E$422,'SPDR Chart'!Z$3,'2025-Q2'!$F$4:$F$422,'SPDR Chart'!$B7,'2025-Q2'!$D$4:$D$422,"N") -> 0 | AA7: =COUNTIFS('2025-Q2'!$E$4:$E$422,'SPDR Chart'!AA$3,'2025-Q2'!$F$4:$F$422,'SPDR Chart'!$B7,'2025-Q2'!$D$4:$D$422,"N") -> 0 | AB7: =COUNTIFS('2025-Q2'!$E$4:$E$422,'SPDR Chart'!AB$3,'2025-Q2'!$F$4:$F$422,'SPDR Chart'!$B7,'2025-Q2'!$D$4:$D$422,"N") -> 0 | AC7: =COUNTIFS('2025-Q2'!$E$4:$E$422,'SPDR Chart'!AC$3,'2025-Q2'!$F$4:$F$422,'SPDR Chart'!$B7,'2025-Q2'!$D$4:$D$422,"N") -> 0 | ... AJ7: =COUNTIFS('2025-Q2'!$E$4:$E$422,'SPDR Chart'!AJ$3,'2025-Q2'!$F$4:$F$422,'SPDR Chart'!$B7,'2025-Q2'!$D$4:$D$422,"N") -> 0 | AK7: =SUM(V7:AJ7) -> 0 | AL7: =SUM($AK$4:AK7)/SUM($AK$4:$AK$86) -> 0
B8: 45760 | C8: =COUNTIFS('2025-Q2'!$E$4:$E$422,'SPDR Chart'!C$3,'2025-Q2'!$F$4:$F$422,'SPDR Chart'!$B8,'2025-Q2'!$D$4:$D$422,"Y") -> 0 | D8: =COUNTIFS('2025-Q2'!$E$4:$E$422,'SPDR Chart'!D$3,'2025-Q2'!$F$4:$F$422,'SPDR Chart'!$B8,'2025-Q2'!$D$4:$D$422,"Y") -> 0 | E8: =COUNTIFS('2025-Q2'!$E$4:$E$422,'SPDR Chart'!E$3,'2025-Q2'!$F$4:$F$422,'SPDR Chart'!$B8,'2025-Q2'!$D$4:$D$422,"Y") -> 0 | F8: =COUNTIFS('2025-Q2'!$E$4:$E$422,'SPDR Chart'!F$3,'2025-Q2'!$F$4:$F$422,'SPDR Chart'!$B8,'2025-Q2'!$D$4:$D$422,"Y") -> 0 | G8: =COUNTIFS('2025-Q2'!$E$4:$E$422,'SPDR Chart'!G$3,'2025-Q2'!$F$4:$F$422,'SPDR Chart'!$B8,'2025-Q2'!$D$4:$D$422,"Y") -> 0 | H8: =COUNTIFS('2025-Q2'!$E$4:$E$422,'SPDR Chart'!H$3,'2025-Q2'!$F$4:$F$422,'SPDR Chart'!$B8,'2025-Q2'!$D$4:$D$422,"Y") -> 0 | I8: =COUNTIFS('2025-Q2'!$E$4:$E$422,'SPDR Chart'!I$3,'2025-Q2'!$F$4:$F$422,'SPDR Chart'!$B8,'2025-Q2'!$D$4:$D$422,"Y") -> 0 | J8: =COUNTIFS('2025-Q2'!$E$4:$E$422,'SPDR Chart'!J$3,'2025-Q2'!$F$4:$F$422,'SPDR Chart'!$B8,'2025-Q2'!$D$4:$D$422,"Y") -> 0 | ... Q8: =COUNTIFS('2025-Q2'!$E$4:$E$422,'SPDR Chart'!Q$3,'2025-Q2'!$F$4:$F$422,'SPDR Chart'!$B8,'2025-Q2'!$D$4:$D$422,"Y") -> 0 | R8: =SUM(C8:Q8) -> 0 | S8: =SUM($R$4:R8)/SUM($R$4:$R$86) -> 0.023121387 | U8: 45760 | V8: =COUNTIFS('2025-Q2'!$E$4:$E$422,'SPDR Chart'!V$3,'2025-Q2'!$F$4:$F$422,'SPDR Chart'!$B8,'2025-Q2'!$D$4:$D$422,"N") -> 0 | W8: =COUNTIFS('2025-Q2'!$E$4:$E$422,'SPDR Chart'!W$3,'2025-Q2'!$F$4:$F$422,'SPDR Chart'!$B8,'2025-Q2'!$D$4:$D$422,"N") -> 0 | X8: =COUNTIFS('2025-Q2'!$E$4:$E$422,'SPDR Chart'!X$3,'2025-Q2'!$F$4:$F$422,'SPDR Chart'!$B8,'2025-Q2'!$D$4:$D$422,"N") -> 0 | Y8: =COUNTIFS('2025-Q2'!$E$4:$E$422,'SPDR Chart'!Y$3,'2025-Q2'!$F$4:$F$422,'SPDR Chart'!$B8,'2025-Q2'!$D$4:$D$422,"N") -> 0 | Z8: =COUNTIFS('2025-Q2'!$E$4:$E$422,'SPDR Chart'!Z$3,'2025-Q2'!$F$4:$F$422,'SPDR Chart'!$B8,'2025-Q2'!$D$4:$D$422,"N") -> 0 | AA8: =COUNTIFS('2025-Q2'!$E$4:$E$422,'SPDR Chart'!AA$3,'2025-Q2'!$F$4:$F$422,'SPDR Chart'!$B8,'2025-Q2'!$D$4:$D$422,"N") -> 0 | AB8: =COUNTIFS('2025-Q2'!$E$4:$E$422,'SPDR Chart'!AB$3,'2025-Q2'!$F$4:$F$422,'SPDR Chart'!$B8,'2025-Q2'!$D$4:$D$422,"N") -> 0 | AC8: =COUNTIFS('2025-Q2'!$E$4:$E$422,'SPDR Chart'!AC$3,'2025-Q2'!$F$4:$F$422,'SPDR Chart'!$B8,'2025-Q2'!$D$4:$D$422,"N") -> 0 | ... AJ8: =COUNTIFS('2025-Q2'!$E$4:$E$422,'SPDR Chart'!AJ$3,'2025-Q2'!$F$4:$F$422,'SPDR Chart'!$B8,'2025-Q2'!$D$4:$D$422,"N") -> 0 | AK8: =SUM(V8:AJ8) -> 0 | AL8: =SUM($AK$4:AK8)/SUM($AK$4:$AK$86) -> 0
B9: 45761 | C9: =COUNTIFS('2025-Q2'!$E$4:$E$422,'SPDR Chart'!C$3,'2025-Q2'!$F$4:$F$422,'SPDR Chart'!$B9,'2025-Q2'!$D$4:$D$422,"Y") -> 0 | D9: =COUNTIFS('2025-Q2'!$E$4:$E$422,'SPDR Chart'!D$3,'2025-Q2'!$F$4:$F$422,'SPDR Chart'!$B9,'2025-Q2'!$D$4:$D$422,"Y") -> 0 | E9: =COUNTIFS('2025-Q2'!$E$4:$E$422,'SPDR Chart'!E$3,'2025-Q2'!$F$4:$F$422,'SPDR Chart'!$B9,'2025-Q2'!$D$4:$D$422,"Y") -> 0 | F9: =COUNTIFS('2025-Q2'!$E$4:$E$422,'SPDR Chart'!F$3,'2025-Q2'!$F$4:$F$422,'SPDR Chart'!$B9,'2025-Q2'!$D$4:$D$422,"Y") -> 2 | G9: =COUNTIFS('2025-Q2'!$E$4:$E$422,'SPDR Chart'!G$3,'2025-Q2'!$F$4:$F$422,'SPDR Chart'!$B9,'2025-Q2'!$D$4:$D$422,"Y") -> 0 | H9: =COUNTIFS('2025-Q2'!$E$4:$E$422,'SPDR Chart'!H$3,'2025-Q2'!$F$4:$F$422,'SPDR Chart'!$B9,'2025-Q2'!$D$4:$D$422,"Y") -> 0 | I9: =COUNTIFS('2025-Q2'!$E$4:$E$422,'SPDR Chart'!I$3,'2025-Q2'!$F$4:$F$422,'SPDR Chart'!$B9,'2025-Q2'!$D$4:$D$422,"Y") -> 0 | J9: =COUNTIFS('2025-Q2'!$E$4:$E$422,'SPDR Chart'!J$3,'2025-Q2'!$F$4:$F$422,'SPDR Chart'!$B9,'2025-Q2'!$D$4:$D$422,"Y") -> 0 | ... Q9: =COUNTIFS('2025-Q2'!$E$4:$E$422,'SPDR Chart'!Q$3,'2025-Q2'!$F$4:$F$422,'SPDR Chart'!$B9,'2025-Q2'!$D$4:$D$422,"Y") -> 0 | R9: =SUM(C9:Q9) -> 2 | S9: =SUM($R$4:R9)/SUM($R$4:$R$86) -> 0.028901734 | U9: 45761 | V9: =COUNTIFS('2025-Q2'!$E$4:$E$422,'SPDR Chart'!V$3,'2025-Q2'!$F$4:$F$422,'SPDR Chart'!$B9,'2025-Q2'!$D$4:$D$422,"N") -> 0 | W9: =COUNTIFS('2025-Q2'!$E$4:$E$422,'SPDR Chart'!W$3,'2025-Q2'!$F$4:$F$422,'SPDR Chart'!$B9,'2025-Q2'!$D$4:$D$422,"N") -> 0 | X9: =COUNTIFS('2025-Q2'!$E$4:$E$422,'SPDR Chart'!X$3,'2025-Q2'!$F$4:$F$422,'SPDR Chart'!$B9,'2025-Q2'!$D$4:$D$422,"N") -> 0 | Y9: =COUNTIFS('2025-Q2'!$E$4:$E$422,'SPDR Chart'!Y$3,'2025-Q2'!$F$4:$F$422,'SPDR Chart'!$B9,'2025-Q2'!$D$4:$D$422,"N") -> 0 | Z9: =COUNTIFS('2025-Q2'!$E$4:$E$422,'SPDR Chart'!Z$3,'2025-Q2'!$F$4:$F$422,'SPDR Chart'!$B9,'2025-Q2'!$D$4:$D$422,"N") -> 0 | AA9: =COUNTIFS('2025-Q2'!$E$4:$E$422,'SPDR Chart'!AA$3,'2025-Q2'!$F$4:$F$422,'SPDR Chart'!$B9,'2025-Q2'!$D$4:$D$422,"N") -> 0 | AB9: =COUNTIFS('2025-Q2'!$E$4:$E$422,'SPDR Chart'!AB$3,'2025-Q2'!$F$4:$F$422,'SPDR Chart'!$B9,'2025-Q2'!$D$4:$D$422,"N") -> 0 | AC9: =COUNTIFS('2025-Q2'!$E$4:$E$422,'SPDR Chart'!AC$3,'2025-Q2'!$F$4:$F$422,'SPDR Chart'!$B9,'2025-Q2'!$D$4:$D$422,"N") -> 0 | ... AJ9: =COUNTIFS('2025-Q2'!$E$4:$E$422,'SPDR Chart'!AJ$3,'2025-Q2'!$F$4:$F$422,'SPDR Chart'!$B9,'2025-Q2'!$D$4:$D$422,"N") -> 0 | AK9: =SUM(V9:AJ9) -> 0 | AL9: =SUM($AK$4:AK9)/SUM($AK$4:$AK$86) -> 0
B10: 45762 | C10: =COUNTIFS('2025-Q2'!$E$4:$E$422,'SPDR Chart'!C$3,'2025-Q2'!$F$4:$F$422,'SPDR Chart'!$B10,'2025-Q2'!$D$4:$D$422,"Y") -> 0 | D10: =COUNTIFS('2025-Q2'!$E$4:$E$422,'SPDR Chart'!D$3,'2025-Q2'!$F$4:$F$422,'SPDR Chart'!$B10,'2025-Q2'!$D$4:$D$422,"Y") -> 2 | E10: =COUNTIFS('2025-Q2'!$E$4:$E$422,'SPDR Chart'!E$3,'2025-Q2'!$F$4:$F$422,'SPDR Chart'!$B10,'2025-Q2'!$D$4:$D$422,"Y") -> 0 | F10: =COUNTIFS('2025-Q2'!$E$4:$E$422,'SPDR Chart'!F$3,'2025-Q2'!$F$4:$F$422,'SPDR Chart'!$B10,'2025-Q2'!$D$4:$D$422,"Y") -> 3 | G10: =COUNTIFS('2025-Q2'!$E$4:$E$422,'SPDR Chart'!G$3,'2025-Q2'!$F$4:$F$422,'SPDR Chart'!$B10,'2025-Q2'!$D$4:$D$422,"Y") -> 1 | H10: =COUNTIFS('2025-Q2'!$E$4:$E$422,'SPDR Chart'!H$3,'2025-Q2'!$F$4:$F$422,'SPDR Chart'!$B10,'2025-Q2'!$D$4:$D$422,"Y") -> 0 | I10: =COUNTIFS('2025-Q2'!$E$4:$E$422,'SPDR Chart'!I$3,'2025-Q2'!$F$4:$F$422,'SPDR Chart'!$B10,'2025-Q2'!$D$4:$D$422,"Y") -> 0 | J10: =COUNTIFS('2025-Q2'!$E$4:$E$422,'SPDR Chart'!J$3,'2025-Q2'!$F$4:$F$422,'SPDR Chart'!$B10,'2025-Q2'!$D$4:$D$422,"Y") -> 0 | ... Q10: =COUNTIFS('2025-Q2'!$E$4:$E$422,'SPDR Chart'!Q$3,'2025-Q2'!$F$4:$F$422,'SPDR Chart'!$B10,'2025-Q2'!$D$4:$D$422,"Y") -> 0 | R10: =SUM(C10:Q10) -> 7 | S10: =SUM($R$4:R10)/SUM($R$4:$R$86) -> 0.049132948 | U10: 45762 | V10: =COUNTIFS('2025-Q2'!$E$4:$E$422,'SPDR Chart'!V$3,'2025-Q2'!$F$4:$F$422,'SPDR Chart'!$B10,'2025-Q2'!$D$4:$D$422,"N") -> 0 | W10: =COUNTIFS('2025-Q2'!$E$4:$E$422,'SPDR Chart'!W$3,'2025-Q2'!$F$4:$F$422,'SPDR Chart'!$B10,'2025-Q2'!$D$4:$D$422,"N") -> 0 | X10: =COUNTIFS('2025-Q2'!$E$4:$E$422,'SPDR Chart'!X$3,'2025-Q2'!$F$4:$F$422,'SPDR Chart'!$B10,'2025-Q2'!$D$4:$D$422,"N") -> 0 | Y10: =COUNTIFS('2025-Q2'!$E$4:$E$422,'SPDR Chart'!Y$3,'2025-Q2'!$F$4:$F$422,'SPDR Chart'!$B10,'2025-Q2'!$D$4:$D$422,"N") -> 0 | Z10: =COUNTIFS('2025-Q2'!$E$4:$E$422,'SPDR Chart'!Z$3,'2025-Q2'!$F$4:$F$422,'SPDR Chart'!$B10,'2025-Q2'!$D$4:$D$422,"N") -> 0 | AA10: =COUNTIFS('2025-Q2'!$E$4:$E$422,'SPDR Chart'!AA$3,'2025-Q2'!$F$4:$F$422,'SPDR Chart'!$B10,'2025-Q2'!$D$4:$D$422,"N") -> 0 | AB10: =COUNTIFS('2025-Q2'!$E$4:$E$422,'SPDR Chart'!AB$3,'2025-Q2'!$F$4:$F$422,'SPDR Chart'!$B10,'2025-Q2'!$D$4:$D$422,"N") -> 0 | AC10: =COUNTIFS('2025-Q2'!$E$4:$E$422,'SPDR Chart'!AC$3,'2025-Q2'!$F$4:$F$422,'SPDR Chart'!$B10,'2025-Q2'!$D$4:$D$422,"N") -> 0 | ... AJ10: =COUNTIFS('2025-Q2'!$E$4:$E$422,'SPDR Chart'!AJ$3,'2025-Q2'!$F$4:$F$422,'SPDR Chart'!$B10,'2025-Q2'!$D$4:$D$422,"N") -> 0 | AK10: =SUM(V10:AJ10) -> 0 | AL10: =SUM($AK$4:AK10)/SUM($AK$4:$AK$86) -> 0
B11: 45763 | C11: =COUNTIFS('2025-Q2'!$E$4:$E$422,'SPDR Chart'!C$3,'2025-Q2'!$F$4:$F$422,'SPDR Chart'!$B11,'2025-Q2'!$D$4:$D$422,"Y") -> 0 | D11: =COUNTIFS('2025-Q2'!$E$4:$E$422,'SPDR Chart'!D$3,'2025-Q2'!$F$4:$F$422,'SPDR Chart'!$B11,'2025-Q2'!$D$4:$D$422,"Y") -> 1 | E11: =COUNTIFS('2025-Q2'!$E$4:$E$422,'SPDR Chart'!E$3,'2025-Q2'!$F$4:$F$422,'SPDR Chart'!$B11,'2025-Q2'!$D$4:$D$422,"Y") -> 0 | F11: =COUNTIFS('2025-Q2'!$E$4:$E$422,'SPDR Chart'!F$3,'2025-Q2'!$F$4:$F$422,'SPDR Chart'!$B11,'2025-Q2'!$D$4:$D$422,"Y") -> 2 | G11: =COUNTIFS('2025-Q2'!$E$4:$E$422,'SPDR Chart'!G$3,'2025-Q2'!$F$4:$F$422,'SPDR Chart'!$B11,'2025-Q2'!$D$4:$D$422,"Y") -> 1 | H11: =COUNTIFS('2025-Q2'!$E$4:$E$422,'SPDR Chart'!H$3,'2025-Q2'!$F$4:$F$422,'SPDR Chart'!$B11,'2025-Q2'!$D$4:$D$422,"Y") -> 1 | I11: =COUNTIFS('2025-Q2'!$E$4:$E$422,'SPDR Chart'!I$3,'2025-Q2'!$F$4:$F$422,'SPDR Chart'!$B11,'2025-Q2'!$D$4:$D$422,"Y") -> 0 | J11: =COUNTIFS('2025-Q2'!$E$4:$E$422,'SPDR Chart'!J$3,'2025-Q2'!$F$4:$F$422,'SPDR Chart'!$B11,'2025-Q2'!$D$4:$D$422,"Y") -> 0 | ... Q11: =COUNTIFS('2025-Q2'!$E$4:$E$422,'SPDR Chart'!Q$3,'2025-Q2'!$F$4:$F$422,'SPDR Chart'!$B11,'2025-Q2'!$D$4:$D$422,"Y") -> 0 | R11: =SUM(C11:Q11) -> 7 | S11: =SUM($R$4:R11)/SUM($R$4:$R$86) -> 0.069364162 | U11: 45763 | V11: =COUNTIFS('2025-Q2'!$E$4:$E$422,'SPDR Chart'!V$3,'2025-Q2'!$F$4:$F$422,'SPDR Chart'!$B11,'2025-Q2'!$D$4:$D$422,"N") -> 0 | W11: =COUNTIFS('2025-Q2'!$E$4:$E$422,'SPDR Chart'!W$3,'2025-Q2'!$F$4:$F$422,'SPDR Chart'!$B11,'2025-Q2'!$D$4:$D$422,"N") -> 0 | X11: =COUNTIFS('2025-Q2'!$E$4:$E$422,'SPDR Chart'!X$3,'2025-Q2'!$F$4:$F$422,'SPDR Chart'!$B11,'2025-Q2'!$D$4:$D$422,"N") -> 0 | Y11: =COUNTIFS('2025-Q2'!$E$4:$E$422,'SPDR Chart'!Y$3,'2025-Q2'!$F$4:$F$422,'SPDR Chart'!$B11,'2025-Q2'!$D$4:$D$422,"N") -> 0 | Z11: =COUNTIFS('2025-Q2'!$E$4:$E$422,'SPDR Chart'!Z$3,'2025-Q2'!$F$4:$F$422,'SPDR Chart'!$B11,'2025-Q2'!$D$4:$D$422,"N") -> 0 | AA11: =COUNTIFS('2025-Q2'!$E$4:$E$422,'SPDR Chart'!AA$3,'2025-Q2'!$F$4:$F$422,'SPDR Chart'!$B11,'2025-Q2'!$D$4:$D$422,"N") -> 0 | AB11: =COUNTIFS('2025-Q2'!$E$4:$E$422,'SPDR Chart'!AB$3,'2025-Q2'!$F$4:$F$422,'SPDR Chart'!$B11,'2025-Q2'!$D$4:$D$422,"N") -> 0 | AC11: =COUNTIFS('2025-Q2'!$E$4:$E$422,'SPDR Chart'!AC$3,'2025-Q2'!$F$4:$F$422,'SPDR Chart'!$B11,'2025-Q2'!$D$4:$D$422,"N") -> 0 | ... AJ11: =COUNTIFS('2025-Q2'!$E$4:$E$422,'SPDR Chart'!AJ$3,'2025-Q2'!$F$4:$F$422,'SPDR Chart'!$B11,'2025-Q2'!$D$4:$D$422,"N") -> 0 | AK11: =SUM(V11:AJ11) -> 0 | AL11: =SUM($AK$4:AK11)/SUM($AK$4:$AK$86) -> 0
B12: 45764 | C12: =COUNTIFS('2025-Q2'!$E$4:$E$422,'SPDR Chart'!C$3,'2025-Q2'!$F$4:$F$422,'SPDR Chart'!$B12,'2025-Q2'!$D$4:$D$422,"Y") -> 0 | D12: =COUNTIFS('2025-Q2'!$E$4:$E$422,'SPDR Chart'!D$3,'2025-Q2'!$F$4:$F$422,'SPDR Chart'!$B12,'2025-Q2'!$D$4:$D$422,"Y") -> 1 | E12: =COUNTIFS('2025-Q2'!$E$4:$E$422,'SPDR Chart'!E$3,'2025-Q2'!$F$4:$F$422,'SPDR Chart'!$B12,'2025-Q2'!$D$4:$D$422,"Y") -> 1 | F12: =COUNTIFS('2025-Q2'!$E$4:$E$422,'SPDR Chart'!F$3,'2025-Q2'!$F$4:$F$422,'SPDR Chart'!$B12,'2025-Q2'!$D$4:$D$422,"Y") -> 9 | G12: =COUNTIFS('2025-Q2'!$E$4:$E$422,'SPDR Chart'!G$3,'2025-Q2'!$F$4:$F$422,'SPDR Chart'!$B12,'2025-Q2'!$D$4:$D$422,"Y") -> 0 | H12: =COUNTIFS('2025-Q2'!$E$4:$E$422,'SPDR Chart'!H$3,'2025-Q2'!$F$4:$F$422,'SPDR Chart'!$B12,'2025-Q2'!$D$4:$D$422,"Y") -> 0 | I12: =COUNTIFS('2025-Q2'!$E$4:$E$422,'SPDR Chart'!I$3,'2025-Q2'!$F$4:$F$422,'SPDR Chart'!$B12,'2025-Q2'!$D$4:$D$422,"Y") -> 0 | J12: =COUNTIFS('2025-Q2'!$E$4:$E$422,'SPDR Chart'!J$3,'2025-Q2'!$F$4:$F$422,'SPDR Chart'!$B12,'2025-Q2'!$D$4:$D$422,"Y") -> 0 | ... Q12: =COUNTIFS('2025-Q2'!$E$4:$E$422,'SPDR Chart'!Q$3,'2025-Q2'!$F$4:$F$422,'SPDR Chart'!$B12,'2025-Q2'!$D$4:$D$422,"Y") -> 0 | R12: =SUM(C12:Q12) -> 13 | S12: =SUM($R$4:R12)/SUM($R$4:$R$86) -> 0.10693642 | U12: 45764 | V12: =COUNTIFS('2025-Q2'!$E$4:$E$422,'SPDR Chart'!V$3,'2025-Q2'!$F$4:$F$422,'SPDR Chart'!$B12,'2025-Q2'!$D$4:$D$422,"N") -> 0 | W12: =COUNTIFS('2025-Q2'!$E$4:$E$422,'SPDR Chart'!W$3,'2025-Q2'!$F$4:$F$422,'SPDR Chart'!$B12,'2025-Q2'!$D$4:$D$422,"N") -> 0 | X12: =COUNTIFS('2025-Q2'!$E$4:$E$422,'SPDR Chart'!X$3,'2025-Q2'!$F$4:$F$422,'SPDR Chart'!$B12,'2025-Q2'!$D$4:$D$422,"N") -> 0 | Y12: =COUNTIFS('2025-Q2'!$E$4:$E$422,'SPDR Chart'!Y$3,'2025-Q2'!$F$4:$F$422,'SPDR Chart'!$B12,'2025-Q2'!$D$4:$D$422,"N") -> 1 | Z12: =COUNTIFS('2025-Q2'!$E$4:$E$422,'SPDR Chart'!Z$3,'2025-Q2'!$F$4:$F$422,'SPDR Chart'!$B12,'2025-Q2'!$D$4:$D$422,"N") -> 0 | AA12: =COUNTIFS('2025-Q2'!$E$4:$E$422,'SPDR Chart'!AA$3,'2025-Q2'!$F$4:$F$422,'SPDR Chart'!$B12,'2025-Q2'!$D$4:$D$422,"N") -> 0 | AB12: =COUNTIFS('2025-Q2'!$E$4:$E$422,'SPDR Chart'!AB$3,'2025-Q2'!$F$4:$F$422,'SPDR Chart'!$B12,'2025-Q2'!$D$4:$D$422,"N") -> 0 | AC12: =COUNTIFS('2025-Q2'!$E$4:$E$422,'SPDR Chart'!AC$3,'2025-Q2'!$F$4:$F$422,'SPDR Chart'!$B12,'2025-Q2'!$D$4:$D$422,"N") -> 0 | ... AJ12: =COUNTIFS('2025-Q2'!$E$4:$E$422,'SPDR Chart'!AJ$3,'2025-Q2'!$F$4:$F$422,'SPDR Chart'!$B12,'2025-Q2'!$D$4:$D$422,"N") -> 0 | AK12: =SUM(V12:AJ12) -> 1 | AL12: =SUM($AK$4:AK12)/SUM($AK$4:$AK$86) -> 0.014925373
B13: 45765 | C13: =COUNTIFS('2025-Q2'!$E$4:$E$422,'SPDR Chart'!C$3,'2025-Q2'!$F$4:$F$422,'SPDR Chart'!$B13,'2025-Q2'!$D$4:$D$422,"Y") -> 0 | D13: =COUNTIFS('2025-Q2'!$E$4:$E$422,'SPDR Chart'!D$3,'2025-Q2'!$F$4:$F$422,'SPDR Chart'!$B13,'2025-Q2'!$D$4:$D$422,"Y") -> 0 | E13: =COUNTIFS('2025-Q2'!$E$4:$E$422,'SPDR Chart'!E$3,'2025-Q2'!$F$4:$F$422,'SPDR Chart'!$B13,'2025-Q2'!$D$4:$D$422,"Y") -> 0 | F13: =COUNTIFS('2025-Q2'!$E$4:$E$422,'SPDR Chart'!F$3,'2025-Q2'!$F$4:$F$422,'SPDR Chart'!$B13,'2025-Q2'!$D$4:$D$422,"Y") -> 0 | G13: =COUNTIFS('2025-Q2'!$E$4:$E$422,'SPDR Chart'!G$3,'2025-Q2'!$F$4:$F$422,'SPDR Chart'!$B13,'2025-Q2'!$D$4:$D$422,"Y") -> 0 | H13: =COUNTIFS('2025-Q2'!$E$4:$E$422,'SPDR Chart'!H$3,'2025-Q2'!$F$4:$F$422,'SPDR Chart'!$B13,'2025-Q2'!$D$4:$D$422,"Y") -> 0 | I13: =COUNTIFS('2025-Q2'!$E$4:$E$422,'SPDR Chart'!I$3,'2025-Q2'!$F$4:$F$422,'SPDR Chart'!$B13,'2025-Q2'!$D$4:$D$422,"Y") -> 0 | J13: =COUNTIFS('2025-Q2'!$E$4:$E$422,'SPDR Chart'!J$3,'2025-Q2'!$F$4:$F$422,'SPDR Chart'!$B13,'2025-Q2'!$D$4:$D$422,"Y") -> 0 | ... Q13: =COUNTIFS('2025-Q2'!$E$4:$E$422,'SPDR Chart'!Q$3,'2025-Q2'!$F$4:$F$422,'SPDR Chart'!$B13,'2025-Q2'!$D$4:$D$422,"Y") -> 0 | R13: =SUM(C13:Q13) -> 0 | S13: =SUM($R$4:R13)/SUM($R$4:$R$86) -> 0.10693642 | U13: 45765 | V13: =COUNTIFS('2025-Q2'!$E$4:$E$422,'SPDR Chart'!V$3,'2025-Q2'!$F$4:$F$422,'SPDR Chart'!$B13,'2025-Q2'!$D$4:$D$422,"N") -> 0 | W13: =COUNTIFS('2025-Q2'!$E$4:$E$422,'SPDR Chart'!W$3,'2025-Q2'!$F$4:$F$422,'SPDR Chart'!$B13,'2025-Q2'!$D$4:$D$422,"N") -> 0 | X13: =COUNTIFS('2025-Q2'!$E$4:$E$422,'SPDR Chart'!X$3,'2025-Q2'!$F$4:$F$422,'SPDR Chart'!$B13,'2025-Q2'!$D$4:$D$422,"N") -> 0 | Y13: =COUNTIFS('2025-Q2'!$E$4:$E$422,'SPDR Chart'!Y$3,'2025-Q2'!$F$4:$F$422,'SPDR Chart'!$B13,'2025-Q2'!$D$4:$D$422,"N") -> 0 | Z13: =COUNTIFS('2025-Q2'!$E$4:$E$422,'SPDR Chart'!Z$3,'2025-Q2'!$F$4:$F$422,'SPDR Chart'!$B13,'2025-Q2'!$D$4:$D$422,"N") -> 0 | AA13: =COUNTIFS('2025-Q2'!$E$4:$E$422,'SPDR Chart'!AA$3,'2025-Q2'!$F$4:$F$422,'SPDR Chart'!$B13,'2025-Q2'!$D$4:$D$422,"N") -> 0 | AB13: =COUNTIFS('2025-Q2'!$E$4:$E$422,'SPDR Chart'!AB$3,'2025-Q2'!$F$4:$F$422,'SPDR Chart'!$B13,'2025-Q2'!$D$4:$D$422,"N") -> 0 | AC13: =COUNTIFS('2025-Q2'!$E$4:$E$422,'SPDR Chart'!AC$3,'2025-Q2'!$F$4:$F$422,'SPDR Chart'!$B13,'2025-Q2'!$D$4:$D$422,"N") -> 0 | ... AJ13: =COUNTIFS('2025-Q2'!$E$4:$E$422,'SPDR Chart'!AJ$3,'2025-Q2'!$F$4:$F$422,'SPDR Chart'!$B13,'2025-Q2'!$D$4:$D$422,"N") -> 0 | AK13: =SUM(V13:AJ13) -> 0 | AL13: =SUM($AK$4:AK13)/SUM($AK$4:$AK$86) -> 0.014925373
B14: 45766 | C14: =COUNTIFS('2025-Q2'!$E$4:$E$422,'SPDR Chart'!C$3,'2025-Q2'!$F$4:$F$422,'SPDR Chart'!$B14,'2025-Q2'!$D$4:$D$422,"Y") -> 0 | D14: =COUNTIFS('2025-Q2'!$E$4:$E$422,'SPDR Chart'!D$3,'2025-Q2'!$F$4:$F$422,'SPDR Chart'!$B14,'2025-Q2'!$D$4:$D$422,"Y") -> 0 | E14: =COUNTIFS('2025-Q2'!$E$4:$E$422,'SPDR Chart'!E$3,'2025-Q2'!$F$4:$F$422,'SPDR Chart'!$B14,'2025-Q2'!$D$4:$D$422,"Y") -> 0 | F14: =COUNTIFS('2025-Q2'!$E$4:$E$422,'SPDR Chart'!F$3,'2025-Q2'!$F$4:$F$422,'SPDR Chart'!$B14,'2025-Q2'!$D$4:$D$422,"Y") -> 0 | G14: =COUNTIFS('2025-Q2'!$E$4:$E$422,'SPDR Chart'!G$3,'2025-Q2'!$F$4:$F$422,'SPDR Chart'!$B14,'2025-Q2'!$D$4:$D$422,"Y") -> 0 | H14: =COUNTIFS('2025-Q2'!$E$4:$E$422,'SPDR Chart'!H$3,'2025-Q2'!$F$4:$F$422,'SPDR Chart'!$B14,'2025-Q2'!$D$4:$D$422,"Y") -> 0 | I14: =COUNTIFS('2025-Q2'!$E$4:$E$422,'SPDR Chart'!I$3,'2025-Q2'!$F$4:$F$422,'SPDR Chart'!$B14,'2025-Q2'!$D$4:$D$422,"Y") -> 0 | J14: =COUNTIFS('2025-Q2'!$E$4:$E$422,'SPDR Chart'!J$3,'2025-Q2'!$F$4:$F$422,'SPDR Chart'!$B14,'2025-Q2'!$D$4:$D$422,"Y") -> 0 | ... Q14: =COUNTIFS('2025-Q2'!$E$4:$E$422,'SPDR Chart'!Q$3,'2025-Q2'!$F$4:$F$422,'SPDR Chart'!$B14,'2025-Q2'!$D$4:$D$422,"Y") -> 0 | R14: =SUM(C14:Q14) -> 0 | S14: =SUM($R$4:R14)/SUM($R$4:$R$86) -> 0.10693642 | U14: 45766 | V14: =COUNTIFS('2025-Q2'!$E$4:$E$422,'SPDR Chart'!V$3,'2025-Q2'!$F$4:$F$422,'SPDR Chart'!$B14,'2025-Q2'!$D$4:$D$422,"N") -> 0 | W14: =COUNTIFS('2025-Q2'!$E$4:$E$422,'SPDR Chart'!W$3,'2025-Q2'!$F$4:$F$422,'SPDR Chart'!$B14,'2025-Q2'!$D$4:$D$422,"N") -> 0 | X14: =COUNTIFS('2025-Q2'!$E$4:$E$422,'SPDR Chart'!X$3,'2025-Q2'!$F$4:$F$422,'SPDR Chart'!$B14,'2025-Q2'!$D$4:$D$422,"N") -> 0 | Y14: =COUNTIFS('2025-Q2'!$E$4:$E$422,'SPDR Chart'!Y$3,'2025-Q2'!$F$4:$F$422,'SPDR Chart'!$B14,'2025-Q2'!$D$4:$D$422,"N") -> 0 | Z14: =COUNTIFS('2025-Q2'!$E$4:$E$422,'SPDR Chart'!Z$3,'2025-Q2'!$F$4:$F$422,'SPDR Chart'!$B14,'2025-Q2'!$D$4:$D$422,"N") -> 0 | AA14: =COUNTIFS('2025-Q2'!$E$4:$E$422,'SPDR Chart'!AA$3,'2025-Q2'!$F$4:$F$422,'SPDR Chart'!$B14,'2025-Q2'!$D$4:$D$422,"N") -> 0 | AB14: =COUNTIFS('2025-Q2'!$E$4:$E$422,'SPDR Chart'!AB$3,'2025-Q2'!$F$4:$F$422,'SPDR Chart'!$B14,'2025-Q2'!$D$4:$D$422,"N") -> 0 | AC14: =COUNTIFS('2025-Q2'!$E$4:$E$422,'SPDR Chart'!AC$3,'2025-Q2'!$F$4:$F$422,'SPDR Chart'!$B14,'2025-Q2'!$D$4:$D$422,"N") -> 0 | ... AJ14: =COUNTIFS('2025-Q2'!$E$4:$E$422,'SPDR Chart'!AJ$3,'2025-Q2'!$F$4:$F$422,'SPDR Chart'!$B14,'2025-Q2'!$D$4:$D$422,"N") -> 0 | AK14: =SUM(V14:AJ14) -> 0 | AL14: =SUM($AK$4:AK14)/SUM($AK$4:$AK$86) -> 0.014925373
B15: 45767 | C15: =COUNTIFS('2025-Q2'!$E$4:$E$422,'SPDR Chart'!C$3,'2025-Q2'!$F$4:$F$422,'SPDR Chart'!$B15,'2025-Q2'!$D$4:$D$422,"Y") -> 0 | D15: =COUNTIFS('2025-Q2'!$E$4:$E$422,'SPDR Chart'!D$3,'2025-Q2'!$F$4:$F$422,'SPDR Chart'!$B15,'2025-Q2'!$D$4:$D$422,"Y") -> 0 | E15: =COUNTIFS('2025-Q2'!$E$4:$E$422,'SPDR Chart'!E$3,'2025-Q2'!$F$4:$F$422,'SPDR Chart'!$B15,'2025-Q2'!$D$4:$D$422,"Y") -> 0 | F15: =COUNTIFS('2025-Q2'!$E$4:$E$422,'SPDR Chart'!F$3,'2025-Q2'!$F$4:$F$422,'SPDR Chart'!$B15,'2025-Q2'!$D$4:$D$422,"Y") -> 0 | G15: =COUNTIFS('2025-Q2'!$E$4:$E$422,'SPDR Chart'!G$3,'2025-Q2'!$F$4:$F$422,'SPDR Chart'!$B15,'2025-Q2'!$D$4:$D$422,"Y") -> 0 | H15: =COUNTIFS('2025-Q2'!$E$4:$E$422,'SPDR Chart'!H$3,'2025-Q2'!$F$4:$F$422,'SPDR Chart'!$B15,'2025-Q2'!$D$4:$D$422,"Y") -> 0 | I15: =COUNTIFS('2025-Q2'!$E$4:$E$422,'SPDR Chart'!I$3,'2025-Q2'!$F$4:$F$422,'SPDR Chart'!$B15,'2025-Q2'!$D$4:$D$422,"Y") -> 0 | J15: =COUNTIFS('2025-Q2'!$E$4:$E$422,'SPDR Chart'!J$3,'2025-Q2'!$F$4:$F$422,'SPDR Chart'!$B15,'2025-Q2'!$D$4:$D$422,"Y") -> 0 | ... Q15: =COUNTIFS('2025-Q2'!$E$4:$E$422,'SPDR Chart'!Q$3,'2025-Q2'!$F$4:$F$422,'SPDR Chart'!$B15,'2025-Q2'!$D$4:$D$422,"Y") -> 0 | R15: =SUM(C15:Q15) -> 0 | S15: =SUM($R$4:R15)/SUM($R$4:$R$86) -> 0.10693642 | U15: 45767 | V15: =COUNTIFS('2025-Q2'!$E$4:$E$422,'SPDR Chart'!V$3,'2025-Q2'!$F$4:$F$422,'SPDR Chart'!$B15,'2025-Q2'!$D$4:$D$422,"N") -> 0 | W15: =COUNTIFS('2025-Q2'!$E$4:$E$422,'SPDR Chart'!W$3,'2025-Q2'!$F$4:$F$422,'SPDR Chart'!$B15,'2025-Q2'!$D$4:$D$422,"N") -> 0 | X15: =COUNTIFS('2025-Q2'!$E$4:$E$422,'SPDR Chart'!X$3,'2025-Q2'!$F$4:$F$422,'SPDR Chart'!$B15,'2025-Q2'!$D$4:$D$422,"N") -> 0 | Y15: =COUNTIFS('2025-Q2'!$E$4:$E$422,'SPDR Chart'!Y$3,'2025-Q2'!$F$4:$F$422,'SPDR Chart'!$B15,'2025-Q2'!$D$4:$D$422,"N") -> 0 | Z15: =COUNTIFS('2025-Q2'!$E$4:$E$422,'SPDR Chart'!Z$3,'2025-Q2'!$F$4:$F$422,'SPDR Chart'!$B15,'2025-Q2'!$D$4:$D$422,"N") -> 0 | AA15: =COUNTIFS('2025-Q2'!$E$4:$E$422,'SPDR Chart'!AA$3,'2025-Q2'!$F$4:$F$422,'SPDR Chart'!$B15,'2025-Q2'!$D$4:$D$422,"N") -> 0 | AB15: =COUNTIFS('2025-Q2'!$E$4:$E$422,'SPDR Chart'!AB$3,'2025-Q2'!$F$4:$F$422,'SPDR Chart'!$B15,'2025-Q2'!$D$4:$D$422,"N") -> 0 | AC15: =COUNTIFS('2025-Q2'!$E$4:$E$422,'SPDR Chart'!AC$3,'2025-Q2'!$F$4:$F$422,'SPDR Chart'!$B15,'2025-Q2'!$D$4:$D$422,"N") -> 0 | ... AJ15: =COUNTIFS('2025-Q2'!$E$4:$E$422,'SPDR Chart'!AJ$3,'2025-Q2'!$F$4:$F$422,'SPDR Chart'!$B15,'2025-Q2'!$D$4:$D$422,"N") -> 0 | AK15: =SUM(V15:AJ15) -> 0 | AL15: =SUM($AK$4:AK15)/SUM($AK$4:$AK$86) -> 0.014925373
... B86: 45838 | C86: =COUNTIFS('2025-Q2'!$E$4:$E$422,'SPDR Chart'!C$3,'2025-Q2'!$F$4:$F$422,'SPDR Chart'!$B86,'2025-Q2'!$D$4:$D$422,"Y") -> 0 | D86: =COUNTIFS('2025-Q2'!$E$4:$E$422,'SPDR Chart'!D$3,'2025-Q2'!$F$4:$F$422,'SPDR Chart'!$B86,'2025-Q2'!$D$4:$D$422,"Y") -> 0 | E86: =COUNTIFS('2025-Q2'!$E$4:$E$422,'SPDR Chart'!E$3,'2025-Q2'!$F$4:$F$422,'SPDR Chart'!$B86,'2025-Q2'!$D$4:$D$422,"Y") -> 0 | F86: =COUNTIFS('2025-Q2'!$E$4:$E$422,'SPDR Chart'!F$3,'2025-Q2'!$F$4:$F$422,'SPDR Chart'!$B86,'2025-Q2'!$D$4:$D$422,"Y") -> 0 | G86: =COUNTIFS('2025-Q2'!$E$4:$E$422,'SPDR Chart'!G$3,'2025-Q2'!$F$4:$F$422,'SPDR Chart'!$B86,'2025-Q2'!$D$4:$D$422,"Y") -> 0 | H86: =COUNTIFS('2025-Q2'!$E$4:$E$422,'SPDR Chart'!H$3,'2025-Q2'!$F$4:$F$422,'SPDR Chart'!$B86,'2025-Q2'!$D$4:$D$422,"Y") -> 0 | I86: =COUNTIFS('2025-Q2'!$E$4:$E$422,'SPDR Chart'!I$3,'2025-Q2'!$F$4:$F$422,'SPDR Chart'!$B86,'2025-Q2'!$D$4:$D$422,"Y") -> 0 | J86: =COUNTIFS('2025-Q2'!$E$4:$E$422,'SPDR Chart'!J$3,'2025-Q2'!$F$4:$F$422,'SPDR Chart'!$B86,'2025-Q2'!$D$4:$D$422,"Y") -> 0 | ... Q86: =COUNTIFS('2025-Q2'!$E$4:$E$422,'SPDR Chart'!Q$3,'2025-Q2'!$F$4:$F$422,'SPDR Chart'!$B86,'2025-Q2'!$D$4:$D$422,"Y") -> 0 | R86: =SUM(C86:Q86) -> 0 | S86: =SUM($R$4:R86)/SUM($R$4:$R$86) -> 1 | U86: 45838 | V86: =COUNTIFS('2025-Q2'!$E$4:$E$422,'SPDR Chart'!V$3,'2025-Q2'!$F$4:$F$422,'SPDR Chart'!$B86,'2025-Q2'!$D$4:$D$422,"N") -> 0 | W86: =COUNTIFS('2025-Q2'!$E$4:$E$422,'SPDR Chart'!W$3,'2025-Q2'!$F$4:$F$422,'SPDR Chart'!$B86,'2025-Q2'!$D$4:$D$422,"N") -> 0 | X86: =COUNTIFS('2025-Q2'!$E$4:$E$422,'SPDR Chart'!X$3,'2025-Q2'!$F$4:$F$422,'SPDR Chart'!$B86,'2025-Q2'!$D$4:$D$422,"N") -> 0 | Y86: =COUNTIFS('2025-Q2'!$E$4:$E$422,'SPDR Chart'!Y$3,'2025-Q2'!$F$4:$F$422,'SPDR Chart'!$B86,'2025-Q2'!$D$4:$D$422,"N") -> 0 | Z86: =COUNTIFS('2025-Q2'!$E$4:$E$422,'SPDR Chart'!Z$3,'2025-Q2'!$F$4:$F$422,'SPDR Chart'!$B86,'2025-Q2'!$D$4:$D$422,"N") -> 0 | AA86: =COUNTIFS('2025-Q2'!$E$4:$E$422,'SPDR Chart'!AA$3,'2025-Q2'!$F$4:$F$422,'SPDR Chart'!$B86,'2025-Q2'!$D$4:$D$422,"N") -> 0 | AB86: =COUNTIFS('2025-Q2'!$E$4:$E$422,'SPDR Chart'!AB$3,'2025-Q2'!$F$4:$F$422,'SPDR Chart'!$B86,'2025-Q2'!$D$4:$D$422,"N") -> 0 | AC86: =COUNTIFS('2025-Q2'!$E$4:$E$422,'SPDR Chart'!AC$3,'2025-Q2'!$F$4:$F$422,'SPDR Chart'!$B86,'2025-Q2'!$D$4:$D$422,"N") -> 0 | ... AJ86: =COUNTIFS('2025-Q2'!$E$4:$E$422,'SPDR Chart'!AJ$3,'2025-Q2'!$F$4:$F$422,'SPDR Chart'!$B86,'2025-Q2'!$D$4:$D$422,"N") -> 0 | AK86: =SUM(V86:AJ86) -> 0 | AL86: =SUM($AK$4:AK86)/SUM($AK$4:$AK$86) -> 1

Sheet Summary Data
B1: % in SPY | C1: Total | D1: # in Up | E1: % in Up | F1: # in Dwn | G1: % in Dwn | H1: # in SW | I1: % in SW
B2: =COUNTIF('2025-Q2'!$D$4:$D$422,"Y")/C2 -> 0.82816229 | C2: =COUNTA('2025-Q2'!$D$4:$D$422) -> 419 | D2: =COUNTIF('2025-Q2'!$S$4:$S$422,"Up") -> 51 | E2: =D2/$C$2 -> 0.12171838 | F2: =COUNTIF('2025-Q2'!$S$4:$S$422,"Dwn") -> 166 | G2: =F2/$C$2 -> 0.39618138 | H2: =COUNTIF('2025-Q2'!$S$4:$S$422,"Sw") -> 202 | I2: =H2/$C$2 -> 0.48210024
D3: Up: R | F3: Down: R | H3: SW: R | J3: All: R
D4: =SUM('2025-Q2'!$CC$4:$CC$422) -> -8.3953557 | F4: =SUM('2025-Q2'!$CE$4:$CE$422) -> 10.963955 | H4: =SUM('2025-Q2'!$CG$4:$CG$422) -> 9.9627467 | J4: =D4+F4+H4 -> 12.531346
B8: Risk Units | C8: Expectancy
A9: Up | B9: =D4 -> -8.3953557 | C9: =Expectancy!Q3 -> -0.16461482
A10: Down | B10: =F4 -> 10.963955 | C10: =Expectancy!R3 -> 0.066047922
A11: SW | B11: =H4 -> 9.9627467 | C11: =Expectancy!S3 -> 0.049320528

Sheet Summary
A1: 2025 -- Q1
A3: Executive Summary:
A4: =_xlfn.CONCAT(" For the ",A1," earnings season, ", TEXT('Stats Roll Up'!R4,"###")& " earnings trades were taken, ",TEXT('Summary Data'!B2,"00%")," were stocks from the S&P 500.") -> For the 2025 -- Q1 earnings season, 413 earnings trades were taken, 83% were stocks from the S&P 500.
A5: ● | B5: =CONCATENATE("Overall, the three pillars of the strategy producted: ") -> Overall, the three pillars of the strategy producted: | O5: =TEXT('Summary Data'!J$4,"0") -> 13 | Q5: risk units.
A6: Up Trending Stocks:
A7: ● | B7: =_xlfn.CONCAT('Summary Data'!$D$2," of the trades were stocks in an up trend."," This is ", TEXT('Summary Data'!$E$2,"##%")," of all trades.") -> 51 of the trades were stocks in an up trend. This is 12% of all trades.
A8: ● | B8: =_xlfn.CONCAT(TEXT('Stats Roll Up'!$G$4,"00.0%")," of the up trendng stocks opened higher after earnings. The average gap higher was ",TEXT('Stats Roll Up'!$D$4,"0.0%"),".") -> 47.1% of the up trendng stocks opened higher after earnings. The average gap higher was 4.6%.
A9: ● | B9: =_xlfn.CONCAT(TEXT('Stats Roll Up'!$AC$4,"00.0%")," of the up trendng stocks opened lower after earnings. The average gap down from an up trend was ",TEXT('Stats Roll Up'!$AE$4,"0.0%"),".") -> 52.9% of the up trendng stocks opened lower after earnings. The average gap down from an up trend was 5.2%.
A10: ● | B10: =CONCATENATE("For up trends, the strategy produced: ") -> For up trends, the strategy produced: | M10: ='Summary Data'!$D$4 -> -8.3953557 | N10: risk units.
A11: ● | B11: Up trends had an expectancy of: | K11: =Expectancy!$Q$3 -> -0.16461482 | M11: risk units per trade.
A13: Down Trending Stocks:
A14: ● | B14: =_xlfn.CONCAT('Summary Data'!$F$2," of the trades were stocks in an down trend."," This is ", TEXT('Summary Data'!$G$2,"##%")," of all trades.") -> 166 of the trades were stocks in an down trend. This is 40% of all trades.
A15: ● | B15: =_xlfn.CONCAT(TEXT('Stats Roll Up'!$Y$4,"00.0%")," of the down trendng stocks opened lower after earnings. The average gap down was ",TEXT('Stats Roll Up'!$AA$4,"0.0%"),".") -> 55.4% of the down trendng stocks opened lower after earnings. The average gap down was 4.1%.
A16: ● | B16: =_xlfn.CONCAT(TEXT('Stats Roll Up'!$K$4,"00.0%")," of the down trendng stocks opened higher after earnings. The average gap up from a down trend was ",TEXT('Stats Roll Up'!$M$4,"0.0%"),".") -> 44.6% of the down trendng stocks opened higher after earnings. The average gap up from a down trend was 4.3%.
A17: ● | B17: =CONCATENATE("For down trends, the strategy produced: ") -> For down trends, the strategy produced: | N17: ='Summary Data'!$F$4 -> 10.963955 | O17: =_xlfn.CONCAT("risk units.") -> risk units.
A18: ● | B18: Down trends had an expectancy of: | L18: =Expectancy!$R$3 -> 0.066047922 | N18: risk units per trade.
A20: Sideways Trending Stocks:
A21: ● | B21: =_xlfn.CONCAT('Summary Data'!$H$2," of the trades were stocks in a sideways trend."," This is ", TEXT('Summary Data'!$I$2,"00%")," of all trades.") -> 202 of the trades were stocks in a sideways trend. This is 48% of all trades.
A22: ● | B22: =_xlfn.CONCAT(TEXT('Stats Roll Up'!$O$4,"00.0%")," of the sideways stocks opened higher after earnings. The average gap up was ",TEXT('Stats Roll Up'!$Q$4,"0.0%"),".") -> 50.5% of the sideways stocks opened higher after earnings. The average gap up was 5.1%.
A23: ● | B23: =_xlfn.CONCAT(TEXT('Stats Roll Up'!$AG$4,"00.0%")," of the sideways stocks opened lower after earnings. The average gap down from a sideways trend was ",TEXT('Stats Roll Up'!$AI$4,"0.0%"),".") -> 48.5% of the sideways stocks opened lower after earnings. The average gap down from a sideways trend was 4.7%.
A24: ● | B24: =CONCATENATE("For sideways trends, the strategy produced: ") -> For sideways trends, the strategy produced: | N24: ='Summary Data'!$H$4 -> 9.9627467 | O24: =_xlfn.CONCAT("risk units.") -> risk units.
A25: ● | B25: Sideways trends had an expectancy of: | M25: =Expectancy!$S$3 -> 0.049320528 | O25: risk units per trade.
A44: 2025 -- Q1
A46: Sector Performance:
A47: Up Trending Stocks, Risk Units by Sector:
A61: Down Trending Stocks, Risk Units by Sector:
A75: Sideways Trending Stocks:
A89: 2025 -- Q2
A91: Sector Performance, continued:
A92: Total Risk Units by Sector, w/ Expectancy:

Sheet Earnings
A1: Date/Time | B1: Ticker | C1: When | D1: Index
A2: 45778.024 | B2: BVN | C2: on 5/1/25, 2:35 AM Before Market Eastern Standard Time | D2: =_xlfn.XLOOKUP(B2,Indices!$A$2:$A$2676,Indices!$B$2:$B$2676,"")
A3: 45778.167 | B3: WCC | C3: on 5/1/25, 6:00 AM Before Market Eastern Standard Time | D3: =_xlfn.XLOOKUP(B3,Indices!$A$2:$A$2676,Indices!$B$2:$B$2676,"") -> S&P Mid
A4: 45778.167 | B4: LXP | C4: on 5/1/25, 6:00 AM Before Market Eastern Standard Time | D4: =_xlfn.XLOOKUP(B4,Indices!$A$2:$A$2676,Indices!$B$2:$B$2676,"") -> IWM
A5: 45778.167 | B5: APD | C5: on 5/1/25, 6:00 AM Before Market Eastern Standard Time | D5: =_xlfn.XLOOKUP(B5,Indices!$A$2:$A$2676,Indices!$B$2:$B$2676,"") -> SP500
A6: 45778.167 | B6: ECVT | C6: on 5/1/25, 6:00 AM Before Market Eastern Standard Time | D6: =_xlfn.XLOOKUP(B6,Indices!$A$2:$A$2676,Indices!$B$2:$B$2676,"") -> IWM
A7: 45778.167 | B7: TRGP | C7: on 5/1/25, 6:00 AM Before Market Eastern Standard Time | D7: =_xlfn.XLOOKUP(B7,Indices!$A$2:$A$2676,Indices!$B$2:$B$2676,"") -> SP500
A8: 45778.167 | B8: OCSL | C8: on 5/1/25, 6:00 AM Before Market Eastern Standard Time | D8: =_xlfn.XLOOKUP(B8,Indices!$A$2:$A$2676,Indices!$B$2:$B$2676,"")
A9: 45778.167 | B9: WD | C9: on 5/1/25, 6:00 AM Before Market Eastern Standard Time | D9: =_xlfn.XLOOKUP(B9,Indices!$A$2:$A$2676,Indices!$B$2:$B$2676,"") -> IWM
A10: 45778.167 | B10: EL | C10: on 5/1/25, 6:00 AM Before Market Eastern Standard Time | D10: =_xlfn.XLOOKUP(B10,Indices!$A$2:$A$2676,Indices!$B$2:$B$2676,"") -> SP500
A11: 45778.167 | B11: CCO | C11: on 5/1/25, 6:00 AM Before Market Eastern Standard Time | D11: =_xlfn.XLOOKUP(B11,Indices!$A$2:$A$2676,Indices!$B$2:$B$2676,"") -> IWM
A12: 45778.167 | B12: XFOR | C12: on 5/1/25, 6:01 AM Before Market Eastern Standard Time | D12: =_xlfn.XLOOKUP(B12,Indices!$A$2:$A$2676,Indices!$B$2:$B$2676,"")
A13: 45778.188 | B13: AGIO | C13: on 5/1/25, 6:30 AM Before Market Eastern Standard Time | D13: =_xlfn.XLOOKUP(B13,Indices!$A$2:$A$2676,Indices!$B$2:$B$2676,"") -> IWM
... A440: 45782.59 | B440: GBDC | C440: on 5/5/25, 4:10 PM After Market Eastern Standard Time | D440: =_xlfn.XLOOKUP(B440,Indices!$A$2:$A$2676,Indices!$B$2:$B$2676,"")
A441: 45782.592 | B441: TRUE | C441: on 5/5/25, 4:13 PM After Market Eastern Standard Time | D441: =_xlfn.XLOOKUP(B441,Indices!$A$2:$A$2676,Indices!$B$2:$B$2676,"")
A442: 45782.594 | B442: MYPS | C442: on 5/5/25, 4:15 PM After Market Eastern Standard Time | D442: =_xlfn.XLOOKUP(B442,Indices!$A$2:$A$2676,Indices!$B$2:$B$2676,"")
A443: 45782.594 | B443: WMB | C443: on 5/5/25, 4:15 PM After Market Eastern Standard Time | D443: =_xlfn.XLOOKUP(B443,Indices!$A$2:$A$2676,Indices!$B$2:$B$2676,"") -> SP500
A444: 45782.594 | B444: AESI | C444: on 5/5/25, 4:15 PM After Market Eastern Standard Time | D444: =_xlfn.XLOOKUP(B444,Indices!$A$2:$A$2676,Indices!$B$2:$B$2676,"") -> IWM
A445: 45782.594 | B445: SPNT | C445: on 5/5/25, 4:15 PM After Market Eastern Standard Time | D445: =_xlfn.XLOOKUP(B445,Indices!$A$2:$A$2676,Indices!$B$2:$B$2676,"") -> IWM
A446: 45782.594 | B446: GECC | C446: on 5/5/25, 4:15 PM After Market Eastern Standard Time | D446: =_xlfn.XLOOKUP(B446,Indices!$A$2:$A$2676,Indices!$B$2:$B$2676,"")
A447: 45782.594 | B447: ACEL | C447: on 5/5/25, 4:15 PM After Market Eastern Standard Time | D447: =_xlfn.XLOOKUP(B447,Indices!$A$2:$A$2676,Indices!$B$2:$B$2676,"") -> IWM
A448: 45782.594 | B448: ANAB | C448: on 5/5/25, 4:15 PM After Market Eastern Standard Time | D448: =_xlfn.XLOOKUP(B448,Indices!$A$2:$A$2676,Indices!$B$2:$B$2676,"") -> IWM
A449: 45782.594 | B449: IPAR | C449: on 5/5/25, 4:15 PM After Market Eastern Standard Time | D449: =_xlfn.XLOOKUP(B449,Indices!$A$2:$A$2676,Indices!$B$2:$B$2676,"") -> IWM
A450: 45782.594 | B450: CRD/B | C450: on 5/5/25, 4:15 PM After Market Eastern Standard Time | D450: =_xlfn.XLOOKUP(B450,Indices!$A$2:$A$2676,Indices!$B$2:$B$2676,"")
A451: 45782.594 | B451: LTC | C451: on 5/5/25, 4:15 PM After Market Eastern Standard Time | D451: =_xlfn.XLOOKUP(B451,Indices!$A$2:$A$2676,Indices!$B$2:$B$2676,"") -> IWM
A452: 45782.594 | B452: NGVT | C452: on 5/5/25, 4:15 PM After Market Eastern Standard Time | D452: =_xlfn.XLOOKUP(B452,Indices!$A$2:$A$2676,Indices!$B$2:$B$2676,"") -> IWM
A453: 45782.594 | B453: CRBG | C453: on 5/5/25, 4:15 PM After Market Eastern Standard Time | D453: =_xlfn.XLOOKUP(B453,Indices!$A$2:$A$2676,Indices!$B$2:$B$2676,"")
... A3326: 45838.625 | B3326: ELTP | C3326: on 6/30/25 After Market Eastern Standard Time | D3326: =_xlfn.XLOOKUP(B3326,Indices!$A$2:$A$2676,Indices!$B$2:$B$2676,"")
D3327: =_xlfn.XLOOKUP(B3327,Indices!$A$2:$A$2676,Indices!$B$2:$B$2676,"")
D3328: =_xlfn.XLOOKUP(B3328,Indices!$A$2:$A$2676,Indices!$B$2:$B$2676,"")
D3329: =_xlfn.XLOOKUP(B3329,Indices!$A$2:$A$2676,Indices!$B$2:$B$2676,"")
D3330: =_xlfn.XLOOKUP(B3330,Indices!$A$2:$A$2676,Indices!$B$2:$B$2676,"")
D3331: =_xlfn.XLOOKUP(B3331,Indices!$A$2:$A$2676,Indices!$B$2:$B$2676,"")
D3332: =_xlfn.XLOOKUP(B3332,Indices!$A$2:$A$2676,Indices!$B$2:$B$2676,"")
D3333: =_xlfn.XLOOKUP(B3333,Indices!$A$2:$A$2676,Indices!$B$2:$B$2676,"")
D3334: =_xlfn.XLOOKUP(B3334,Indices!$A$2:$A$2676,Indices!$B$2:$B$2676,"")
D3335: =_xlfn.XLOOKUP(B3335,Indices!$A$2:$A$2676,Indices!$B$2:$B$2676,"")
D3336: =_xlfn.XLOOKUP(B3336,Indices!$A$2:$A$2676,Indices!$B$2:$B$2676,"")
D3337: =_xlfn.XLOOKUP(B3337,Indices!$A$2:$A$2676,Indices!$B$2:$B$2676,"")
D3338: =_xlfn.XLOOKUP(B3338,Indices!$A$2:$A$2676,Indices!$B$2:$B$2676,"")
... D4734: =_xlfn.XLOOKUP(B4734,Indices!$A$2:$A$2676,Indices!$B$2:$B$2676,"")

Sheet 2025-Q2
A1: Formulas --> | B1: {=IFERROR(_xlfn.XLOOKUP(A4,Earnings!$B$2:$B$9984,LEFT(Earnings!$C$2:$C$9984,37)),"Can't Find Date***")} -> Can't Find Date*** | E1: =_xlfn.XLOOKUP(A1,[1]SP500!$A$2:$A$655,[1]SP500!$B$2:$B$655) -> #N/A | F1: =IFERROR(TRIM(MID(B1,FIND("/",B1,1)-2,8)),"") | I1: ------------ Gap Data ------------ | N1: ------- Strategy P&L ------- | S1: --- Trend Data --- | U1: ---------- Entry ---------- | Y1: Exit at Open, or Other Exit | AA1: Mkt at Open, or, Other Exit | AB1: -------- Market on Close Stats -------- | AH1: ---------- Actual P&L ---------- | AO1: Market on Close Comparison Data | BC1: Key Strategy Flags | BK1: Expectancy Update with row del | BO1: ---- % Gapping Up ----- | BW1: Hide These these columns track the strategies three pillars per trade and cumulatively | CC1: Hide These these columns track the strategies three pillars per trade and cumulatively | CI1: Hide These (Sector 3 Pillars) these columns track the strategies three pillars per trade and cumulatively | CP1: Hide These (Sector 3 Pillars) these columns track the strategies three pillars per trade and cumulatively | CW1: Hide These (Sector 3 Pillars) these columns track the strategies three pillars per trade and cumulatively | DD1: Hide These (Sector 3 Pillars) these columns track the strategies three pillars per trade and cumulatively | DK1: Hide These (Sector 3 Pillars) these columns track the strategies three pillars per trade and cumulatively | DR1: Hide These (Sector 3 Pillars) these columns track the strategies three pillars per trade and cumulatively | DY1: Hide These (Sector 3 Pillars) these columns track the strategies three pillars per trade and cumulatively | EF1: Hide These (Sector 3 Pillars) these columns track the strategies three pillars per trade and cumulatively | EM1: Hide These (Sector 3 Pillars) these columns track the strategies three pillars per trade and cumulatively | ET1: Hide These (Sector 3 Pillars) these columns track the strategies three pillars per trade and cumulatively | FA1: Hide These (Sector 3 Pillars) these columns track the strategies three pillars per trade and cumulatively | FH1: Hide These (Sector 3 Pillars) these columns track the strategies three pillars per trade and cumulatively | FO1: Hide These (Sector 3 Pillars) these columns track the strategies three pillars per trade and cumulatively | FV1: Hide These (Sector 3 Pillars) these columns track the strategies three pillars per trade and cumulatively | GC1: Hide These (Sector 3 Pillars) these columns track the strategies three pillars per trade and cumulatively | GJ1: Hide These (Sector 3 Pillars) these columns track the strategies three pillars per trade and cumulatively
A2: Cheat -> | B2: hide | C2: hide | E2: ● | F2: ● | G2: ● | H2: ● | I2: ↓ | J2: ↓ | K2: ● | L2: ● | M2: ● | N2: ● | O2: ● | P2: ● | Q2: ● | R2: ● | S2: ● | T2: ↓ | U2: ● | V2: ↓ | W2: ↓ | X2: ● | Y2: ● | Z2: ↓ | AA2: ● | AB2: ● | AC2: ↓ | AD2: ● | AE2: ● | AF2: ● | AG2: ● | AH2: ↓ | AI2: ● | AJ2: ● | AK2: ● | AL2: ● | AO2: Risk Units | AU2: P & L | BC2: =SUM(BC4:BC422) -> 24 | BD2: =SUM(BD4:BD422) -> 74 | BE2: =SUM(BE4:BE422) -> 102 | BF2: =(BC2+BE2+BG2)/(BC2+BE2+BG2+BD2+BH2+BI2) -> 0.52278177 | BG2: =SUM(BG4:BG422) -> 92 | BH2: =SUM(BH4:BH422) -> 27 | BI2: =SUM(BI4:BI422) -> 98 | BO2: form | BP2: form | BQ2: form | BR2: form | BS2: form | BT2: form | BU2: form | BV2: form | BW2: form | BX2: form | BY2: form | BZ2: form | CA2: form | CB2: form | CC2: form | CD2: form | CE2: form | CF2: form | CG2: form | CH2: form | CI2: XLK | CJ2: form | CK2: form | CL2: form | CM2: form | CN2: form | CO2: form | CP2: IGV | CQ2: form | CR2: form | CS2: form | CT2: form | CU2: form | CV2: form | CW2: XLY | CX2: form | CY2: form | CZ2: form | DA2: form | DB2: form | DC2: form | DD2: XLP | DE2: form | DF2: form | DG2: form | DH2: form | DI2: form | DJ2: form | DK2: XLC | DL2: form | DM2: form | DN2: form | DO2: form | DP2: form | DQ2: form | DR2: XLF | DS2: form | DT2: form | DU2: form | DV2: form | DW2: form | DX2: form | DY2: XLI | DZ2: form | EA2: form | EB2: form | EC2: form | ED2: form | EE2: form | EF2: XLV | EG2: form | EH2: form | EI2: form | EJ2: form | EK2: form | EL2: form | EM2: XLB | EN2: form | EO2: form | EP2: form | EQ2: form | ER2: form | ES2: form | ET2: SMH | EU2: form | EV2: form | EW2: form | EX2: form | EY2: form | EZ2: form | FA2: XLE | FB2: form | FC2: form | FD2: form | FE2: form | FF2: form | FG2: form | FH2: XLU | FI2: form | FJ2: form | FK2: form | FL2: form | FM2: form | FN2: form | FO2: XLRE | FP2: form | FQ2: form | FR2: form | FS2: form | FT2: form | FU2: form | FV2: INS | FW2: form | FX2: form | FY2: form | FZ2: form | GA2: form | GB2: form | GC2: H-INS | GD2: form | GE2: form | GF2: form | GG2: form | GH2: form | GI2: form | GJ2: XHB | GK2: form | GL2: form | GM2: form | GN2: form | GO2: form | GP2: form | GS2: SPY | GT2: SPY | GU2: SPY | GV2: SPY | GW2: SPY | GX2: SPY | GY2: SPY | GZ2: SPY | HA2: Not Spy | HB2: Not Spy | HC2: Not Spy | HD2: Not Spy | HE2: Not Spy | HF2: Not Spy | HG2: Not Spy | HH2: Not Spy | HI2: Gap ↓ from Dwn Tr | HK2: Gap ↑ from Dwn Tr | HM2: Gap ↑ from Up Tr | HO2: Gap ↓ from Up Tr | HQ2: Gap ↑ from Sw Tr | HS2: Gap ↓ from Sw Tr | HU2: hide | HV2: hide
A3: Stock | B3: Earnings Date | C3: TrCh | D3: In SPY? | E3: Sector | F3: Date | G3: AMO, BMO | H3: S/O | I3: Close [entry] | J3: Open | K3: Gap % | L3: Gap P/L | M3: P&L Var. from Slippage | N3: P/L per Trade | O3: P/L Total | P3: R per Trade | Q3: R Total | R3: Total Var Act v. Strat | S3: Trend | T3: Trend Y/N | U3: Entry Price: | V3: L / S | W3: Entry Shares | X3: Cost to Play | Y3: Exit Shares | Z3: Exit at Open or "Other" | AA3: P&L | AB3: Actual: MOC P / L | AC3: Exit Using MOC | AD3: Strategy: MOC P / L | AE3: Strategy: MOC R | AF3: Strategy P/L MOC Total | AG3: Var vs. Strategy | AH3: Exit Type | AI3: R per Trade | AJ3: R Total | AK3: P/L per Trade | AL3: P/L Total | AO3: Sw Trends MOC R | AP3: Total Sw Trends MOC R | AQ3: UP Trends MOC R | AR3: Total UP Trends MOC R | AS3: Dwn Trends MOC R | AT3: Total Dwn Trends MOC R | AU3: Sw Trends MOC P/L | AV3: Total Sw Trends MOC P/L | AW3: UP Trends MOC P/L | AX3: Total UP Trends MOC P/L | AY3: Dwn Trends MOC P/L | AZ3: Total Dwn Trends MOC P/L | BA3: Total MOC P/L | BC3: Gap Ups with trend | BD3: Gap Ups Against Trend | BE3: Gap Ups SW | BF3: Strategy Direction | BG3: Gap Downs with trend | BH3: Gap Dns Against Trend | BI3: Gap Downs SW | BK3: Exp 50-ma | BL3: Exp 25-ma | BM3: Overall Strategy Exp. | BO3: % of SW Gapping Up | BP3: % of DWN Gapping D | BQ3: % of UP Gapping Up | BR3: % Gapping Up | BS3: Long Wins | BT3: Long Losses | BU3: Short Wins | BV3: Short Losses | BW3: Playing Up Trends Long | BX3: Cumulative Playing Up Trends Long | BY3: Playing Down Trends Short | BZ3: Cumulative Playing Dwn Trends Short | CA3: Playing Sideways Trends Long | CB3: Cumulative Playing SW Trends Long | CC3: R, Playing Up Trends Long | CD3: Cumulative Playing Up Trends Long | CE3: R, Playing Down Trends Short | CF3: Cumulative Playing Dwn Trends Short | CG3: R, Playing Sideways Trends Long | CH3: Cumulative Playing SW Trends Long | CI3: Playing Up Trends Long | CJ3: Cumulative Playing Up Trends Long | CK3: Playing Down Trends Short | CL3: Cumulative Playing Dwn Trends Short | CM3: Playing Sideways Trends Long | CN3: Cumulative Playing SW Trends Long | CO3: TOTAL of Three Pillars | CP3: Playing Up Trends Long | CQ3: Cumulative Playing Up Trends Long | CR3: Playing Down Trends Short | CS3: Cumulative Playing Dwn Trends Short | CT3: Playing Sideways Trends Long | CU3: Cumulative Playing SW Trends Long | CV3: TOTAL of Three Pillars | CW3: Playing Up Trends Long | CX3: Cumulative Playing Up Trends Long | CY3: Playing Down Trends Short | CZ3: Cumulative Playing Dwn Trends Short | DA3: Playing Sideways Trends Long | DB3: Cumulative Playing SW Trends Long | DC3: TOTAL of Three Pillars | DD3: Playing Up Trends Long | DE3: Cumulative Playing Up Trends Long | DF3: Playing Down Trends Short | DG3: Cumulative Playing Dwn Trends Short | DH3: Playing Sideways Trends Long | DI3: Cumulative Playing SW Trends Long | DJ3: TOTAL of Three Pillars | DK3: Playing Up Trends Long | DL3: Cumulative Playing Up Trends Long | DM3: Playing Down Trends Short | DN3: Cumulative Playing Dwn Trends Short | DO3: Playing Sideways Trends Long | DP3: Cumulative Playing SW Trends Long | DQ3: TOTAL of Three Pillars | DR3: Playing Up Trends Long | DS3: Cumulative Playing Up Trends Long | DT3: Playing Down Trends Short | DU3: Cumulative Playing Dwn Trends Short | DV3: Playing Sideways Trends Long | DW3: Cumulative Playing SW Trends Long | DX3: TOTAL of Three Pillars | DY3: Playing Up Trends Long | DZ3: Cumulative Playing Up Trends Long | EA3: Playing Down Trends Short | EB3: Cumulative Playing Dwn Trends Short | EC3: Playing Sideways Trends Long | ED3: Cumulative Playing SW Trends Long | EE3: TOTAL of Three Pillars | EF3: Playing Up Trends Long | EG3: Cumulative Playing Up Trends Long | EH3: Playing Down Trends Short | EI3: Cumulative Playing Dwn Trends Short | EJ3: Playing Sideways Trends Long | EK3: Cumulative Playing SW Trends Long | EL3: TOTAL of Three Pillars | EM3: Playing Up Trends Long | EN3: Cumulative Playing Up Trends Long | EO3: Playing Down Trends Short | EP3: Cumulative Playing Dwn Trends Short | EQ3: Playing Sideways Trends Long | ER3: Cumulative Playing SW Trends Long | ES3: TOTAL of Three Pillars | ET3: Playing Up Trends Long | EU3: Cumulative Playing Up Trends Long | EV3: Playing Down Trends Short | EW3: Cumulative Playing Dwn Trends Short | EX3: Playing Sideways Trends Long | EY3: Cumulative Playing SW Trends Long | EZ3: TOTAL of Three Pillars | FA3: Playing Up Trends Long | FB3: Cumulative Playing Up Trends Long | FC3: Playing Down Trends Short | FD3: Cumulative Playing Dwn Trends Short | FE3: Playing Sideways Trends Long | FF3: Cumulative Playing SW Trends Long | FG3: TOTAL of Three Pillars | FH3: Playing Up Trends Long | FI3: Cumulative Playing Up Trends Long | FJ3: Playing Down Trends Short | FK3: Cumulative Playing Dwn Trends Short | FL3: Playing Sideways Trends Long | FM3: Cumulative Playing SW Trends Long | FN3: TOTAL of Three Pillars | FO3: Playing Up Trends Long | FP3: Cumulative Playing Up Trends Long | FQ3: Playing Down Trends Short | FR3: Cumulative Playing Dwn Trends Short | FS3: Playing Sideways Trends Long | FT3: Cumulative Playing SW Trends Long | FU3: TOTAL of Three Pillars | FV3: Playing Up Trends Long | FW3: Cumulative Playing Up Trends Long | FX3: Playing Down Trends Short | FY3: Cumulative Playing Dwn Trends Short | FZ3: Playing Sideways Trends Long | GA3: Cumulative Playing SW Trends Long | GB3: TOTAL of Three Pillars | GC3: Playing Up Trends Long | GD3: Cumulative Playing Up Trends Long | GE3: Playing Down Trends Short | GF3: Cumulative Playing Dwn Trends Short | GG3: Playing Sideways Trends Long | GH3: Cumulative Playing SW Trends Long | GI3: TOTAL of Three Pillars | GJ3: Playing Up Trends Long | GK3: Cumulative Playing Up Trends Long | GL3: Playing Down Trends Short | GM3: Cumulative Playing Dwn Trends Short | GN3: Playing Sideways Trends Long | GO3: Cumulative Playing SW Trends Long | GP3: TOTAL of Three Pillars | GS3: R per Trade | GT3: R Total | GU3: R per Trade Up | GV3: R Total Up Trends | GW3: R per Trade SW | GX3: R Total SW Trends | GY3: R per Trade Dwn | GZ3: R Total Dwn Trends | HA3: R per Trade | HB3: R Total | HC3: R per Trade Up | HD3: R Total Up Trends | HE3: R per Trade SW | HF3: R Total SW Trends | HG3: R per Trade Dwn | HH3: R Total Dwn Trends | HI3: R Dwn per Trade MOC | HJ3: R Dwn MOC Total | HK3: R Dwn per Trade MOC | HL3: R Dwn MOC Total | HM3: R per Trade MOC | HN3: R MOC Total | HO3: R Dwn per Trade MOC | HP3: R Dwn MOC Total | HQ3: R per Trade MOC | HR3: R MOC Total | HS3: R Dwn per Trade MOC | HT3: R Dwn MOC Total | HU3: R per Trade MOC | HV3: R MOC Total
A4: DAL | B4: on 4/9/25 Before Market Eastern Stand | C4: =IF(S4="Dwn",2,IF(S4="Up",1,IF(S4="SW",3,"x"))) -> 2 | D4: =_xlfn.XLOOKUP(A4,[1]SP500!$A$2:$A$502,[1]SP500!$D$2:$D$502,"N") -> Y | E4: =IFERROR(_xlfn.XLOOKUP(A4,[1]SP500!$A$2:$A$655,[1]SP500!$B$2:$B$655),"") -> XLI | F4: 45756 | G4: =IF(ISNUMBER(FIND("After",B4,1)),"AMC",IF(ISNUMBER(FIND("Before",B4,1)),"BMO","err")) -> BMO | H4: =IF(AH4="Skip","sk",IF(OR(S4="",V4=""),"",IF(AND(S4="Dwn",V4="Short"),"s",IF(AND(S4="Up",V4="Long"),"s",IF(AND(S4="SW",V4="Long"),"s","o"))))) -> s | I4: 35.88 | J4: 36.91 | K4: =IF(J4="","",(J4-I4)/I4) -> 0.0287068 | L4: =IF(OR($Y4="",J4=""),"",IF($V4="Long",(($J4*$Y4)-$X4),($X4-($J4*$Y4)))) -> -30.9 | M4: =IF(L4="","",IF(AK4="",#N/A,IF(AH4="Open",AK4-L4,#N/A))) -> -6.3 | N4: =IF(OR($Y4="",L4=""),"",IF($BF4="Long",(($J4*$Y4)-$X4),($X4-($J4*$Y4)))) -> -30.9 | O4: =IF(N4="",#N/A,SUM($N$4:N4)) -> -30.9 | P4: =IF(OR($Y4="",$L4=""),"",IF($BF4="Long",(($J4*$Y4)-$X4)/($X4*0.06),($X4-($J4*$Y4))/($X4*0.06))) -> -0.47844667 | Q4: =IF($N4="",#N/A,SUM($P$4:P4)) -> -0.47844667 | R4: =IF(AND(AH4="MOC",AC4=""),#N/A,IFERROR(Q4-AJ4,Q4-0)) -> 0.09754738 | S4: =IF(T4="Down","Dwn",IF(T4="Up","Up",IF(AND(T4="",K4=""),"",IF(AND(K4<0,T4="Yes"),"Dwn",IF(AND(K4>0,T4="Yes"),"Up",IF(AND(K4<0,T4="No"),"Up",IF(AND(K4>0,T4="No"),"Dwn",IF(T4="NA","SW","err")))))))) -> Dwn | T4: No | U4: =I4 -> 35.88 | V4: Short | W4: 30 | X4: =IF(W4="","",U4*W4) -> 1076.4 | Y4: =IF(W4="","",W4) -> 30 | Z4: 37.12 | AA4: =IF($Z4="","",IF($V4="Long",(($Z4*$Y4)-$X4),($X4-($Z4*$Y4)))) -> -37.2 | AB4: =IF($AC4="","",IF($V4="Long",(($AC4*$Y4)-$X4),($X4-($AC4*$Y4)))) -> -254.7 | AC4: 44.37 | AD4: =IF(AC4="","",IF(OR($Y4="",CV4=""),"",IF($BF4="Long",(($AC4*$Y4)-$X4),($X4-($AC4*$Y4))))) -> -254.7 | AE4: =IF(OR($Y4="",$AD4=""),"",IF($BF4="Long",(($AC4*$Y4)-$X4)/($X4*0.06),($X4-($AC4*$Y4))/($X4*0.06))) -> -3.9437012 | AF4: =IF($AC4="",#N/A,SUM(AD$4:AD4)) -> -254.7 | AG4: =IF(OR(AD4="",AC4=""),"",AD4-N4) -> -223.8 | AH4: Open | AI4: =IF(AND(AH4="MOC",AC4=""),"",IF(Z4="","",IF(AH4="Skip",0,IF(AK4=0,0,AK4/(X4*0.06))))) -> -0.57599405 | AJ4: =IF(AI4="",#N/A,SUM($AI$4:AI4)) -> -0.57599405 | AK4: =IF(AH4="","",IF(AH4="Skip","",IF(OR(AH4="open",AH4="Other"),AA4,IF(AH4="MOC",AB4,"Err")))) -> -37.2 | AL4: =IF(AI4="",#N/A,IF(AH4="Skip",SUM($AK$4:AK4),SUM($AK$4:AK4))) -> -37.2 | AM4: =IF(OR($Y4="",$L4=""),"",IF($BF4="Long",(($AC4*$Y4)-$X4)/($X4*0.06),($X4-($AC4*$Y4))/($X4*0.06))) -> -3.9437012 | AO4: =IF(AND($S4="SW",$BF4="Long"),$HU4,"") | AP4: =IF($AC4="",#N/A,SUM(AO$4:AO4)) -> 0 | AQ4: =IF(AND($S4="UP",$BF4="Long"),$HU4,"") | AR4: =IF($AC4="",#N/A,SUM(AQ$4:AQ4)) -> 0 | AS4: =IF(AND($S4="Dwn",$BF4="Short"),$HU4,"") -> -3.9437012 | AT4: =IF($AC4="",#N/A,SUM(AS$4:AS4)) -> -3.9437012 | AU4: =IF(AND(S4="SW",BF4="Long"),$AD4,"") | AV4: =IF($AC4="",#N/A,SUM(AU$4:AU4)) -> 0 | AW4: =IF(AND(S4="UP",BF4="Long"),$AD4,"") | AX4: =IF($AC4="",#N/A,SUM(AW$4:AW4)) -> 0 | AY4: =IF(AND(S4="Dwn",BF4="Short"),$AD4,"") -> -254.7 | AZ4: =IF($AC4="",#N/A,SUM(AY$4:AY4)) -> -254.7 | BA4: =IF(AD4="",#N/A,SUM($AD$4:AD4)) -> -254.7 | BC4: =IF(K4="","",IF(AND(K4>0,T4="Yes"),1,"")) | BD4: =IF(K4="","",IF(AND($K4>0,$T4="No"),1,"")) -> 1 | BE4: =IF(K4="","",IF(AND($K4>0,$T4="NA"),1,"")) | BF4: =IF(S4="Dwn","Short","Long") -> Short | BG4: =IF(K4="","",IF(AND($K4<0,$T4="Yes"),1,"")) | BH4: =IF(K4="","",IF(AND($K4<0,$T4="No"),1,"")) | BI4: =IF(K4="","",IF(AND($K4<0,$T4="NA"),1,"")) | BO4: =IF($J4="",#N/A,IF($S4="SW",(COUNTIFS($K$4:$K4,">0",$S$4:$S4,"SW")/COUNTIF($S$4:$S4,"SW")),#N/A)) -> #N/A | BP4: =IF($J4="",#N/A,IF($S4="DWN",(COUNTIFS($K$4:$K4,"<0",$S$4:$S4,"DWN")/COUNTIF($S$4:$S4,"DWN")),#N/A)) -> 0 | BQ4: =IF($J4="",#N/A,IF($S4="UP",(COUNTIFS($K$4:$K4,">0",$S$4:$S4,"UP")/COUNTIF($S$4:$S4,"UP")),#N/A)) -> #N/A | BR4: =IF(J4="",#N/A,COUNTIF($K$4:K4,">0")/COUNT($J$4:J4)) -> 1 | BS4: =IF($AH4="Skip","",IF($J4="","",IF(AND($V4="Long",$L4>0),$P4,""))) | BT4: =IF($AH4="Skip","",IF($J4="","",IF(AND($V4="Long",$L4<0),$P4,""))) | BU4: =IF($AH4="Skip","",IF($J4="","",IF(AND($V4="Short",$L4>0),$P4,""))) | BV4: =IF($AH4="Skip","",IF($J4="","",IF(AND($V4="Short",$L4<0),$P4,""))) -> -0.47844667 | BW4: =IF(AND($S4="Up",$BF4="Long"),$N4,"") | BX4: =IF($J4="",#N/A,SUM($BW$4:BW4)) -> 0 | BY4: =IF(AND($S4="Dwn",$BF4="Short"),$N4,"") -> -30.9 | BZ4: =IF($J4="",#N/A,SUM($BY$4:BY4)) -> -30.9 | CA4: =IF(AND($S4="SW",$BF4="Long"),$N4,"") | CB4: =IF($J4="",#N/A,SUM($CA$4:CA4)) -> 0 | CC4: =IF(AND($S4="Up",$BF4="Long"),$P4,"") | CD4: =IF($J4="",#N/A,SUM($CC$4:CC4)) -> 0 | CE4: =IF(AND($S4="Dwn",$BF4="Short"),$P4,"") -> -0.47844667 | CF4: =IF($J4="",#N/A,SUM($CE$4:CE4)) -> -0.47844667 | CG4: =IF(AND($S4="SW",$BF4="Long"),$P4,"") | CH4: =IF($J4="",#N/A,SUM($CG$4:CG4)) -> 0 | CI4: =IF(AND($S4="Up",$BF4="Long",$E4=CI$2),$P4,"") | CJ4: =IF($J4="",#N/A,SUM(CI$4:CI4)) -> 0 | CK4: =IF(AND($S4="Dwn",$BF4="Short",$E4=CI$2),$P4,"") | CL4: =IF($J4="",#N/A,SUM(CK$4:CK4)) -> 0 | CM4: =IF(AND($S4="SW",$BF4="Long",$E4=CI$2),$P4,"") | CN4: =IF($J4="",#N/A,SUM(CM$4:CM4)) -> 0 | CO4: =IF($J4="",#N/A,SUM(CM$4:CM4,CK$4:CK4,CI$4:CI4)) -> 0 | CP4: =IF(AND($S4="Up",$BF4="Long",$E4=CP$2),$P4,"") | CQ4: =IF($J4="",#N/A,SUM(CP$4:CP4)) -> 0 | CR4: =IF(AND($S4="Dwn",$BF4="Short",$E4=CP$2),$P4,"") | CS4: =IF($J4="",#N/A,SUM(CR$4:CR4)) -> 0 | CT4: =IF(AND($S4="SW",$BF4="Long",$E4=CP$2),$P4,"") | CU4: =IF($J4="",#N/A,SUM(CT$4:CT4)) -> 0 | CV4: =IF($J4="",#N/A,SUM(CT$4:CT4,CR$4:CR4,CP$4:CP4)) -> 0 | CW4: =IF(AND($S4="Up",$BF4="Long",$E4=CW$2),$P4,"") | CX4: =IF($J4="",#N/A,SUM(CW$4:CW4)) -> 0 | CY4: =IF(AND($S4="Dwn",$BF4="Short",$E4=CW$2),$P4,"") | CZ4: =IF($J4="",#N/A,SUM(CY$4:CY4)) -> 0 | DA4: =IF(AND($S4="SW",$BF4="Long",$E4=CW$2),$P4,"") | DB4: =IF($J4="",#N/A,SUM(DA$4:DA4)) -> 0 | DC4: =IF($J4="",#N/A,SUM(DA$4:DA4,CY$4:CY4,CW$4:CW4)) -> 0 | DD4: =IF(AND($S4="Up",$BF4="Long",$E4=DD$2),$P4,"") | DE4: =IF($J4="",#N/A,SUM(DD$4:DD4)) -> 0 | DF4: =IF(AND($S4="Dwn",$BF4="Short",$E4=DD$2),$P4,"") | DG4: =IF($J4="",#N/A,SUM(DF$4:DF4)) -> 0 | DH4: =IF(AND($S4="SW",$BF4="Long",$E4=DD$2),$P4,"") | DI4: =IF($J4="",#N/A,SUM(DH$4:DH4)) -> 0 | DJ4: =IF($J4="",#N/A,SUM(DH$4:DH4,DF$4:DF4,DD$4:DD4)) -> 0 | DK4: =IF(AND($S4="Up",$BF4="Long",$E4=DK$2),$P4,"") | DL4: =IF($J4="",#N/A,SUM(DK$4:DK4)) -> 0 | DM4: =IF(AND($S4="Dwn",$BF4="Short",$E4=DK$2),$P4,"") | DN4: =IF($J4="",#N/A,SUM(DM$4:DM4)) -> 0 | DO4: =IF(AND($S4="SW",$BF4="Long",$E4=DK$2),$P4,"") | DP4: =IF($J4="",#N/A,SUM(DO$4:DO4)) -> 0 | DQ4: =IF($J4="",#N/A,SUM(DO$4:DO4,DM$4:DM4,DK$4:DK4)) -> 0 | DR4: =IF(AND($S4="Up",$BF4="Long",$E4=DR$2),$P4,"") | DS4: =IF($J4="",#N/A,SUM(DR$4:DR4)) -> 0 | DT4: =IF(AND($S4="Dwn",$BF4="Short",$E4=DR$2),$P4,"") | DU4: =IF($J4="",#N/A,SUM(DT$4:DT4)) -> 0 | DV4: =IF(AND($S4="SW",$BF4="Long",$E4=DR$2),$P4,"") | DW4: =IF($J4="",#N/A,SUM(DV$4:DV4)) -> 0 | DX4: =IF($J4="",#N/A,SUM(DV$4:DV4,DT$4:DT4,DR$4:DR4)) -> 0 | DY4: =IF(AND($S4="Up",$BF4="Long",$E4=DY$2),$P4,"") | DZ4: =IF($J4="",#N/A,SUM(DY$4:DY4)) -> 0 | EA4: =IF(AND($S4="Dwn",$BF4="Short",$E4=DY$2),$P4,"") -> -0.47844667 | EB4: =IF($J4="",#N/A,SUM(EA$4:EA4)) -> -0.47844667 | EC4: =IF(AND($S4="SW",$BF4="Long",$E4=DY$2),$P4,"") | ED4: =IF($J4="",#N/A,SUM(EC$4:EC4)) -> 0 | EE4: =IF($J4="",#N/A,SUM(EC$4:EC4,EA$4:EA4,DY$4:DY4)) -> -0.47844667 | EF4: =IF(AND($S4="Up",$BF4="Long",$E4=EF$2),$P4,"") | EG4: =IF($J4="",#N/A,SUM(EF$4:EF4)) -> 0 | EH4: =IF(AND($S4="Dwn",$BF4="Short",$E4=EF$2),$P4,"") | EI4: =IF($J4="",#N/A,SUM(EH$4:EH4)) -> 0 | EJ4: =IF(AND($S4="SW",$BF4="Long",$E4=EF$2),$P4,"") | EK4: =IF($J4="",#N/A,SUM(EJ$4:EJ4)) -> 0 | EL4: =IF($J4="",#N/A,SUM(EJ$4:EJ4,EH$4:EH4,EF$4:EF4)) -> 0 | EM4: =IF(AND($S4="Up",$BF4="Long",$E4=EM$2),$P4,"") | EN4: =IF($J4="",#N/A,SUM(EM$4:EM4)) -> 0 | EO4: =IF(AND($S4="Dwn",$BF4="Short",$E4=EM$2),$P4,"") | EP4: =IF($J4="",#N/A,SUM(EO$4:EO4)) -> 0 | EQ4: =IF(AND($S4="SW",$BF4="Long",$E4=EM$2),$P4,"") | ER4: =IF($J4="",#N/A,SUM(EQ$4:EQ4)) -> 0 | ES4: =IF($J4="",#N/A,SUM(EQ$4:EQ4,EO$4:EO4,EM$4:EM4)) -> 0 | ET4: =IF(AND($S4="Up",$BF4="Long",$E4=ET$2),$P4,"") | EU4: =IF($J4="",#N/A,SUM(ET$4:ET4)) -> 0 | EV4: =IF(AND($S4="Dwn",$BF4="Short",$E4=ET$2),$P4,"") | EW4: =IF($J4="",#N/A,SUM(EV$4:EV4)) -> 0 | EX4: =IF(AND($S4="SW",$BF4="Long",$E4=ET$2),$P4,"") | EY4: =IF($J4="",#N/A,SUM(EX$4:EX4)) -> 0 | EZ4: =IF($J4="",#N/A,SUM(EX$4:EX4,EV$4:EV4,ET$4:ET4)) -> 0 | FA4: =IF(AND($S4="Up",$BF4="Long",$E4=FA$2),$P4,"") | FB4: =IF($J4="",#N/A,SUM(FA$4:FA4)) -> 0 | FC4: =IF(AND($S4="Dwn",$BF4="Short",$E4=FA$2),$P4,"") | FD4: =IF($J4="",#N/A,SUM(FC$4:FC4)) -> 0 | FE4: =IF(AND($S4="SW",$BF4="Long",$E4=FA$2),$P4,"") | FF4: =IF($J4="",#N/A,SUM(FE$4:FE4)) -> 0 | FG4: =IF($J4="",#N/A,SUM(FE$4:FE4,FC$4:FC4,FA$4:FA4)) -> 0 | FH4: =IF(AND($S4="Up",$BF4="Long",$E4=FH$2),$P4,"") | FI4: =IF($J4="",#N/A,SUM(FH$4:FH4)) -> 0 | FJ4: =IF(AND($S4="Dwn",$BF4="Short",$E4=FH$2),$P4,"") | FK4: =IF($J4="",#N/A,SUM(FJ$4:FJ4)) -> 0 | FL4: =IF(AND($S4="SW",$BF4="Long",$E4=FH$2),$P4,"") | FM4: =IF($J4="",#N/A,SUM(FL$4:FL4)) -> 0 | FN4: =IF($J4="",#N/A,SUM(FL$4:FL4,FJ$4:FJ4,FH$4:FH4)) -> 0 | FO4: =IF(AND($S4="Up",$BF4="Long",$E4=FO$2),$P4,"") | FP4: =IF($J4="",#N/A,SUM(FO$4:FO4)) -> 0 | FQ4: =IF(AND($S4="Dwn",$BF4="Short",$E4=FO$2),$P4,"") | FR4: =IF($J4="",#N/A,SUM(FQ$4:FQ4)) -> 0 | FS4: =IF(AND($S4="SW",$BF4="Long",$E4=FO$2),$P4,"") | FT4: =IF($J4="",#N/A,SUM(FS$4:FS4)) -> 0 | FU4: =IF($J4="",#N/A,SUM(FS$4:FS4,FQ$4:FQ4,FO$4:FO4)) -> 0 | FV4: =IF(AND($S4="Up",$BF4="Long",$E4=FV$2),$P4,"") | FW4: =IF($J4="",#N/A,SUM(FV$4:FV4)) -> 0 | FX4: =IF(AND($S4="Dwn",$BF4="Short",$E4=FV$2),$P4,"") | FY4: =IF($J4="",#N/A,SUM(FX$4:FX4)) -> 0 | FZ4: =IF(AND($S4="SW",$BF4="Long",$E4=FV$2),$P4,"") | GA4: =IF($J4="",#N/A,SUM(FZ$4:FZ4)) -> 0 | GB4: =IF($J4="",#N/A,SUM(FZ$4:FZ4,FX$4:FX4,FV$4:FV4)) -> 0 | GC4: =IF(AND($S4="Up",$BF4="Long",$E4=GC$2),$P4,"") | GD4: =IF($J4="",#N/A,SUM(GC$4:GC4)) -> 0 | GE4: =IF(AND($S4="Dwn",$BF4="Short",$E4=GC$2),$P4,"") | GF4: =IF($J4="",#N/A,SUM(GE$4:GE4)) -> 0 | GG4: =IF(AND($S4="SW",$BF4="Long",$E4=GC$2),$P4,"") | GH4: =IF($J4="",#N/A,SUM(GG$4:GG4)) -> 0 | GI4: =IF($J4="",#N/A,SUM(GG$4:GG4,GE$4:GE4,GC$4:GC4)) -> 0 | GJ4: =IF(AND($S4="Up",$BF4="Long",$E4=GJ$2),$P4,"") | GK4: =IF($J4="",#N/A,SUM(GJ$4:GJ4)) -> 0 | GL4: =IF(AND($S4="Dwn",$BF4="Short",$E4=GJ$2),$P4,"") | GM4: =IF($J4="",#N/A,SUM(GL$4:GL4)) -> 0 | GN4: =IF(AND($S4="SW",$BF4="Long",$E4=GJ$2),$P4,"") | GO4: =IF($J4="",#N/A,SUM(GN$4:GN4)) -> 0 | GP4: =IF($J4="",#N/A,SUM(GN$4:GN4,GL$4:GL4,GJ$4:GJ4)) -> 0 | GS4: =IF(J4="","",IF(D4="Y",P4,"")) -> -0.47844667 | GT4: =IF(GS4="",NA(),SUM($GS$4:GS4)) -> -0.47844667 | GU4: =IF(AND($S4="Up",$BF4="Long",$D4="Y"),$GS4,"") | GV4: =IF(GU4="",NA(),SUM($GU$4:GU4)) -> #N/A | GW4: =IF(AND($S4="SW",$BF4="Long",$D4="Y"),$GS4,"") | GX4: =IF(GW4="",NA(),SUM($GW$4:GW4)) -> #N/A | GY4: =IF(AND($S4="Dwn",$BF4="Short",$D4="Y"),$GS4,"") -> -0.47844667 | GZ4: =IF(GY4="",NA(),SUM($GY$4:GY4)) -> -0.47844667 | HA4: =IF($J4="","",IF($D4="N",$P4,"")) | HB4: =IF(HA4="",NA(),SUM($HA$4:HA4)) -> #N/A | HC4: =IF(AND($S4="Up",$BF4="Long",$D4="N"),$HA4,"") | HD4: =IF(HC4="",NA(),SUM($HC$4:HC4)) -> #N/A | HE4: =IF(AND($S4="SW",$BF4="Long",$D4="N"),$HA4,"") | HF4: =IF(HE4="",NA(),SUM($HE$4:HE4)) -> #N/A | HG4: =IF(AND($S4="Dwn",$BF4="Short",$D4="N"),$HA4,"") | HH4: =IF(HG4="",NA(),SUM($HG$4:HG4)) -> #N/A | HI4: =IF($AC4="","",IF(AND($S4="Dwn",$K4<0),$HU4-P4,"")) | HJ4: =IF($J4="",#N/A,SUM(HI$4:$HI4)) -> 0 | HK4: =IF($AC4="","",IF(AND($S4="Dwn",$K4>0),$HU4-$P4,"")) -> -3.4652546 | HL4: =IF($J4="",#N/A,SUM($HK$4:HK4)) -> -3.4652546 | HM4: =IF($AC4="","",IF(AND($S4="Up",$K4>0),$HU4-$P4,"")) | HN4: =IF($J4="",#N/A,SUM($HM$4:HM4)) -> 0 | HO4: =IF($AC4="","",IF(AND($S4="Up",$K4<0),$HU4-$P4,"")) | HP4: =IF($J4="",#N/A,SUM($HO$4:HO4)) -> 0 | HQ4: =IF($AC4="","",IF(AND($S4="SW",$K4>0),$HU4-$P4,"")) | HR4: =IF($J4="",#N/A,SUM($HQ$4:HQ4)) -> 0 | HS4: =IF($AC4="","",IF(AND($S4="SW",$K4<0),$HU4-$P4,"")) | HT4: =IF($J4="",#N/A,SUM($HS$4:HS4)) -> 0 | HU4: =IF(OR($Y4="",$AC4=""),"",IF($BF4="Long",(($AC4*$Y4)-$X4)/($X4*0.06),($X4-($AC4*$Y4))/($X4*0.06))) -> -3.9437012 | HV4: =IF($J4="",#N/A,SUM(HU$4:$HU4)) -> -3.9437012
A5: STZ | B5: on 4/9/25 After Market Eastern Standa | C5: =IF(S5="Dwn",2,IF(S5="Up",1,IF(S5="SW",3,"x"))) -> 2 | D5: =_xlfn.XLOOKUP(A5,[1]SP500!$A$2:$A$502,[1]SP500!$D$2:$D$502,"N") -> Y | E5: =IFERROR(_xlfn.XLOOKUP(A5,[1]SP500!$A$2:$A$655,[1]SP500!$B$2:$B$655),"") -> XLP | F5: 45756 | G5: =IF(ISNUMBER(FIND("After",B5,1)),"AMC",IF(ISNUMBER(FIND("Before",B5,1)),"BMO","err")) -> AMC | H5: =IF(AH5="Skip","sk",IF(OR(S5="",V5=""),"",IF(AND(S5="Dwn",V5="Short"),"s",IF(AND(S5="Up",V5="Long"),"s",IF(AND(S5="SW",V5="Long"),"s","o"))))) -> s | I5: 183.4 | J5: 175.93 | K5: =IF(J5="","",(J5-I5)/I5) -> -0.040730643 | L5: =IF(OR($Y5="",J5=""),"",IF($V5="Long",(($J5*$Y5)-$X5),($X5-($J5*$Y5)))) -> 44.82 | M5: =IF(L5="","",IF(AK5="",#N/A,IF(AH5="Open",AK5-L5,#N/A))) -> 2.58 | N5: =IF(OR($Y5="",L5=""),"",IF($BF5="Long",(($J5*$Y5)-$X5),($X5-($J5*$Y5)))) -> 44.82 | O5: =IF($N5="",#N/A,SUM($N$4:N5)) -> 13.92 | P5: =IF(OR($Y5="",L5=""),"",IF($BF5="Long",(($J5*$Y5)-$X5)/(X5*0.06),($X5-($J5*$Y5))/(X5*0.06))) -> 0.67884406 | Q5: =IF($N5="",#N/A,SUM($P$4:P5)) -> 0.20039738 | R5: =IF(AND(AH5="MOC",AC5=""),#N/A,IFERROR(Q5-AJ5,Q5-0)) -> 0.058470681 | S5: =IF(T5="Down","Dwn",IF(T5="Up","Up",IF(AND(T5="",K5=""),"",IF(AND(K5<0,T5="Yes"),"Dwn",IF(AND(K5>0,T5="Yes"),"Up",IF(AND(K5<0,T5="No"),"Up",IF(AND(K5>0,T5="No"),"Dwn",IF(T5="NA","SW","err")))))))) -> Dwn | T5: Yes | U5: =I5 -> 183.4 | V5: Short | W5: 6 | X5: =IF(W5="","",U5*W5) -> 1100.4 | Y5: =IF(W5="","",W5) -> 6 | Z5: 175.5 | AA5: =IF($Z5="","",IF($V5="Long",(($Z5*$Y5)-$X5),($X5-($Z5*$Y5)))) -> 47.4 | AB5: =IF($AC5="","",IF($V5="Long",(($AC5*$Y5)-$X5),($X5-($AC5*$Y5)))) -> -8.1 | AC5: 184.75 | AD5: =IF(AC5="","",IF(OR($Y5="",CV5=""),"",IF($BF5="Long",(($AC5*$Y5)-$X5),($X5-($AC5*$Y5))))) -> -8.1 | AE5: =IF(OR($Y5="",$AD5=""),"",IF($BF5="Long",(($AC5*$Y5)-$X5)/($X5*0.06),($X5-($AC5*$Y5))/($X5*0.06))) -> -0.12268266 | AF5: =IF($AC5="",#N/A,SUM(AD$4:AD5)) -> -262.8 | AG5: =IF(OR(AD5="",AC5=""),"",AD5-N5) -> -52.92 | AH5: Open | AI5: =IF(AND(AH5="MOC",AC5=""),"",IF(Z5="","",IF(AH5="Skip",0,IF(AK5=0,0,AK5/(X5*0.06))))) -> 0.71792076 | AJ5: =IF(AI5="",#N/A,SUM($AI$4:AI5)) -> 0.1419267 | AK5: =IF(AH5="","",IF(AH5="Skip","",IF(OR(AH5="open",AH5="Other"),AA5,IF(AH5="MOC",AB5,"Err")))) -> 47.4 | AL5: =IF(AI5="",#N/A,IF(AH5="Skip",SUM($AK$4:AK5),SUM($AK$4:AK5))) -> 10.2 | AM5: =IF(OR($Y5="",$L5=""),"",IF($BF5="Long",(($AC5*$Y5)-$X5)/($X5*0.06),($X5-($AC5*$Y5))/($X5*0.06))) -> -0.12268266 | AO5: =IF(AND($S5="SW",$BF5="Long"),$HU5,"") | AP5: =IF($AC5="",#N/A,SUM(AO$4:AO5)) -> 0 | AQ5: =IF(AND($S5="UP",$BF5="Long"),$HU5,"") | AR5: =IF($AC5="",#N/A,SUM(AQ$4:AQ5)) -> 0 | AS5: =IF(AND($S5="Dwn",$BF5="Short"),$HU5,"") -> -0.12268266 | AT5: =IF($AC5="",#N/A,SUM(AS$4:AS5)) -> -4.0663839 | AU5: =IF(AND($S5="SW",$BF5="Long"),$AD5,"") | AV5: =IF($AC5="",#N/A,SUM(AU$4:AU5)) -> 0 | AW5: =IF(AND($S5="UP",$BF5="Long"),$AD5,"") | AX5: =IF($AC5="",#N/A,SUM(AW$4:AW5)) -> 0 | AY5: =IF(AND($S5="Dwn",$BF5="Short"),$AD5,"") -> -8.1 | AZ5: =IF($AC5="",#N/A,SUM(AY$4:AY5)) -> -262.8 | BA5: =IF($AD5="",#N/A,SUM($AD$4:$AD5)) -> -262.8 | BC5: =IF(K5="","",IF(AND(K5>0,T5="Yes"),1,"")) | BD5: =IF(K5="","",IF(AND($K5>0,$T5="No"),1,"")) | BE5: =IF(K5="","",IF(AND($K5>0,$T5="NA"),1,"")) | BF5: =IF(S5="Dwn","Short","Long") -> Short | BG5: =IF(K5="","",IF(AND($K5<0,$T5="Yes"),1,"")) -> 1 | BH5: =IF(K5="","",IF(AND($K5<0,$T5="No"),1,"")) | BI5: =IF(K5="","",IF(AND($K5<0,$T5="NA"),1,"")) | BO5: =IF(J5="",#N/A,IF(S5="SW",(COUNTIFS(K$4:$K5,">0",S$4:$S5,"SW")/COUNTIF(S$4:$S5,"SW")),#N/A)) -> #N/A | BP5: =IF($J5="",#N/A,IF($S5="DWN",(COUNTIFS($K$4:$K5,"<0",$S$4:$S5,"DWN")/COUNTIF($S$4:$S5,"DWN")),#N/A)) -> 0.5 | BQ5: =IF($J5="",#N/A,IF($S5="UP",(COUNTIFS($K$4:$K5,">0",$S$4:$S5,"UP")/COUNTIF($S$4:$S5,"UP")),#N/A)) -> #N/A | BR5: =IF(J5="",#N/A,COUNTIF($K$4:K5,">0")/COUNT($J$4:J5)) -> 0.5 | BS5: =IF($AH5="Skip","",IF($J5="","",IF(AND($V5="Long",$L5>0),$P5,""))) | BT5: =IF($AH5="Skip","",IF($J5="","",IF(AND($V5="Long",$L5<0),$P5,""))) | BU5: =IF($AH5="Skip","",IF($J5="","",IF(AND($V5="Short",$L5>0),$P5,""))) -> 0.67884406 | BV5: =IF($AH5="Skip","",IF($J5="","",IF(AND($V5="Short",$L5<0),$P5,""))) | BW5: =IF(AND($S5="Up",$BF5="Long"),$N5,"") | BX5: =IF($J5="",#N/A,SUM(BW$4:BW5)) -> 0 | BY5: =IF(AND($S5="Dwn",$BF5="Short"),$N5,"") -> 44.82 | BZ5: =IF($J5="",#N/A,SUM(BY$4:BY5)) -> 13.92 | CA5: =IF(AND($S5="SW",$BF5="Long"),$N5,"") | CB5: =IF($J5="",#N/A,SUM(CA$4:CA5)) -> 0 | CC5: =IF(AND($S5="Up",$BF5="Long"),$P5,"") | CD5: =IF($J5="",#N/A,SUM(CC$4:CC5)) -> 0 | CE5: =IF(AND($S5="Dwn",$BF5="Short"),$P5,"") -> 0.67884406 | CF5: =IF($J5="",#N/A,SUM(CE$4:CE5)) -> 0.20039738 | CG5: =IF(AND($S5="SW",$BF5="Long"),$P5,"") | CH5: =IF($J5="",#N/A,SUM(CG$4:CG5)) -> 0 | CI5: =IF(AND($S5="Up",$BF5="Long",$E5=CI$2),$P5,"") | CJ5: =IF($J5="",#N/A,SUM(CI$4:CI5)) -> 0 | CK5: =IF(AND($S5="Dwn",$BF5="Short",$E5=CI$2),$P5,"") | CL5: =IF($J5="",#N/A,SUM(CK$4:CK5)) -> 0 | CM5: =IF(AND($S5="SW",$BF5="Long",$E5=CI$2),$P5,"") | CN5: =IF($J5="",#N/A,SUM(CM$4:CM5)) -> 0 | CO5: =IF($J5="",#N/A,SUM(CM$4:CM5,CK$4:CK5,CI$4:CI5)) -> 0 | CP5: =IF(AND($S5="Up",$BF5="Long",$E5=CP$2),$P5,"") | CQ5: =IF($J5="",#N/A,SUM(CP$4:CP5)) -> 0 | CR5: =IF(AND($S5="Dwn",$BF5="Short",$E5=CP$2),$P5,"") | CS5: =IF($J5="",#N/A,SUM(CR$4:CR5)) -> 0 | CT5: =IF(AND($S5="SW",$BF5="Long",$E5=CP$2),$P5,"") | CU5: =IF($J5="",#N/A,SUM(CT$4:CT5)) -> 0 | CV5: =IF($J5="",#N/A,SUM(CT$4:CT5,CR$4:CR5,CP$4:CP5)) -> 0 | CW5: =IF(AND($S5="Up",$BF5="Long",$E5=CW$2),$P5,"") | CX5: =IF($J5="",#N/A,SUM(CW$4:CW5)) -> 0 | CY5: =IF(AND($S5="Dwn",$BF5="Short",$E5=CW$2),$P5,"") | CZ5: =IF($J5="",#N/A,SUM(CY$4:CY5)) -> 0 | DA5: =IF(AND($S5="SW",$BF5="Long",$E5=CW$2),$P5,"") | DB5: =IF($J5="",#N/A,SUM(DA$4:DA5)) -> 0 | DC5: =IF($J5="",#N/A,SUM(DA$4:DA5,CY$4:CY5,CW$4:CW5)) -> 0 | DD5: =IF(AND($S5="Up",$BF5="Long",$E5=DD$2),$P5,"") | DE5: =IF($J5="",#N/A,SUM(DD$4:DD5)) -> 0 | DF5: =IF(AND($S5="Dwn",$BF5="Short",$E5=DD$2),$P5,"") -> 0.67884406 | DG5: =IF($J5="",#N/A,SUM(DF$4:DF5)) -> 0.67884406 | DH5: =IF(AND($S5="SW",$BF5="Long",$E5=DD$2),$P5,"") | DI5: =IF($J5="",#N/A,SUM(DH$4:DH5)) -> 0 | DJ5: =IF($J5="",#N/A,SUM(DH$4:DH5,DF$4:DF5,DD$4:DD5)) -> 0.67884406 | DK5: =IF(AND($S5="Up",$BF5="Long",$E5=DK$2),$P5,"") | DL5: =IF($J5="",#N/A,SUM(DK$4:DK5)) -> 0 | DM5: =IF(AND($S5="Dwn",$BF5="Short",$E5=DK$2),$P5,"") | DN5: =IF($J5="",#N/A,SUM(DM$4:DM5)) -> 0 | DO5: =IF(AND($S5="SW",$BF5="Long",$E5=DK$2),$P5,"") | DP5: =IF($J5="",#N/A,SUM(DO$4:DO5)) -> 0 | DQ5: =IF($J5="",#N/A,SUM(DO$4:DO5,DM$4:DM5,DK$4:DK5)) -> 0 | DR5: =IF(AND($S5="Up",$BF5="Long",$E5=DR$2),$P5,"") | DS5: =IF($J5="",#N/A,SUM(DR$4:DR5)) -> 0 | DT5: =IF(AND($S5="Dwn",$BF5="Short",$E5=DR$2),$P5,"") | DU5: =IF($J5="",#N/A,SUM(DT$4:DT5)) -> 0 | DV5: =IF(AND($S5="SW",$BF5="Long",$E5=DR$2),$P5,"") | DW5: =IF($J5="",#N/A,SUM(DV$4:DV5)) -> 0 | DX5: =IF($J5="",#N/A,SUM(DV$4:DV5,DT$4:DT5,DR$4:DR5)) -> 0 | DY5: =IF(AND($S5="Up",$BF5="Long",$E5=DY$2),$P5,"") | DZ5: =IF($J5="",#N/A,SUM(DY$4:DY5)) -> 0 | EA5: =IF(AND($S5="Dwn",$BF5="Short",$E5=DY$2),$P5,"") | EB5: =IF($J5="",#N/A,SUM(EA$4:EA5)) -> -0.47844667 | EC5: =IF(AND($S5="SW",$BF5="Long",$E5=DY$2),$P5,"") | ED5: =IF($J5="",#N/A,SUM(EC$4:EC5)) -> 0 | EE5: =IF($J5="",#N/A,SUM(EC$4:EC5,EA$4:EA5,DY$4:DY5)) -> -0.47844667 | EF5: =IF(AND($S5="Up",$BF5="Long",$E5=EF$2),$P5,"") | EG5: =IF($J5="",#N/A,SUM(EF$4:EF5)) -> 0 | EH5: =IF(AND($S5="Dwn",$BF5="Short",$E5=EF$2),$P5,"") | EI5: =IF($J5="",#N/A,SUM(EH$4:EH5)) -> 0 | EJ5: =IF(AND($S5="SW",$BF5="Long",$E5=EF$2),$P5,"") | EK5: =IF($J5="",#N/A,SUM(EJ$4:EJ5)) -> 0 | EL5: =IF($J5="",#N/A,SUM(EJ$4:EJ5,EH$4:EH5,EF$4:EF5)) -> 0 | EM5: =IF(AND($S5="Up",$BF5="Long",$E5=EM$2),$P5,"") | EN5: =IF($J5="",#N/A,SUM(EM$4:EM5)) -> 0 | EO5: =IF(AND($S5="Dwn",$BF5="Short",$E5=EM$2),$P5,"") | EP5: =IF($J5="",#N/A,SUM(EO$4:EO5)) -> 0 | EQ5: =IF(AND($S5="SW",$BF5="Long",$E5=EM$2),$P5,"") | ER5: =IF($J5="",#N/A,SUM(EQ$4:EQ5)) -> 0 | ES5: =IF($J5="",#N/A,SUM(EQ$4:EQ5,EO$4:EO5,EM$4:EM5)) -> 0 | ET5: =IF(AND($S5="Up",$BF5="Long",$E5=ET$2),$P5,"") | EU5: =IF($J5="",#N/A,SUM(ET$4:ET5)) -> 0 | EV5: =IF(AND($S5="Dwn",$BF5="Short",$E5=ET$2),$P5,"") | EW5: =IF($J5="",#N/A,SUM(EV$4:EV5)) -> 0 | EX5: =IF(AND($S5="SW",$BF5="Long",$E5=ET$2),$P5,"") | EY5: =IF($J5="",#N/A,SUM(EX$4:EX5)) -> 0 | EZ5: =IF($J5="",#N/A,SUM(EX$4:EX5,EV$4:EV5,ET$4:ET5)) -> 0 | FA5: =IF(AND($S5="Up",$BF5="Long",$E5=FA$2),$P5,"") | FB5: =IF($J5="",#N/A,SUM(FA$4:FA5)) -> 0 | FC5: =IF(AND($S5="Dwn",$BF5="Short",$E5=FA$2),$P5,"") | FD5: =IF($J5="",#N/A,SUM(FC$4:FC5)) -> 0 | FE5: =IF(AND($S5="SW",$BF5="Long",$E5=FA$2),$P5,"") | FF5: =IF($J5="",#N/A,SUM(FE$4:FE5)) -> 0 | FG5: =IF($J5="",#N/A,SUM(FE$4:FE5,FC$4:FC5,FA$4:FA5)) -> 0 | FH5: =IF(AND($S5="Up",$BF5="Long",$E5=FH$2),$P5,"") | FI5: =IF($J5="",#N/A,SUM(FH$4:FH5)) -> 0 | FJ5: =IF(AND($S5="Dwn",$BF5="Short",$E5=FH$2),$P5,"") | FK5: =IF($J5="",#N/A,SUM(FJ$4:FJ5)) -> 0 | FL5: =IF(AND($S5="SW",$BF5="Long",$E5=FH$2),$P5,"") | FM5: =IF($J5="",#N/A,SUM(FL$4:FL5)) -> 0 | FN5: =IF($J5="",#N/A,SUM(FL$4:FL5,FJ$4:FJ5,FH$4:FH5)) -> 0 | FO5: =IF(AND($S5="Up",$BF5="Long",$E5=FO$2),$P5,"") | FP5: =IF($J5="",#N/A,SUM(FO$4:FO5)) -> 0 | FQ5: =IF(AND($S5="Dwn",$BF5="Short",$E5=FO$2),$P5,"") | FR5: =IF($J5="",#N/A,SUM(FQ$4:FQ5)) -> 0 | FS5: =IF(AND($S5="SW",$BF5="Long",$E5=FO$2),$P5,"") | FT5: =IF($J5="",#N/A,SUM(FS$4:FS5)) -> 0 | FU5: =IF($J5="",#N/A,SUM(FS$4:FS5,FQ$4:FQ5,FO$4:FO5)) -> 0 | FV5: =IF(AND($S5="Up",$BF5="Long",$E5=FV$2),$P5,"") | FW5: =IF($J5="",#N/A,SUM(FV$4:FV5)) -> 0 | FX5: =IF(AND($S5="Dwn",$BF5="Short",$E5=FV$2),$P5,"") | FY5: =IF($J5="",#N/A,SUM(FX$4:FX5)) -> 0 | FZ5: =IF(AND($S5="SW",$BF5="Long",$E5=FV$2),$P5,"") | GA5: =IF($J5="",#N/A,SUM(FZ$4:FZ5)) -> 0 | GB5: =IF($J5="",#N/A,SUM(FZ$4:FZ5,FX$4:FX5,FV$4:FV5)) -> 0 | GC5: =IF(AND($S5="Up",$BF5="Long",$E5=GC$2),$P5,"") | GD5: =IF($J5="",#N/A,SUM(GC$4:GC5)) -> 0 | GE5: =IF(AND($S5="Dwn",$BF5="Short",$E5=GC$2),$P5,"") | GF5: =IF($J5="",#N/A,SUM(GE$4:GE5)) -> 0 | GG5: =IF(AND($S5="SW",$BF5="Long",$E5=GC$2),$P5,"") | GH5: =IF($J5="",#N/A,SUM(GG$4:GG5)) -> 0 | GI5: =IF($J5="",#N/A,SUM(GG$4:GG5,GE$4:GE5,GC$4:GC5)) -> 0 | GJ5: =IF(AND($S5="Up",$BF5="Long",$E5=GJ$2),$P5,"") | GK5: =IF($J5="",#N/A,SUM(GJ$4:GJ5)) -> 0 | GL5: =IF(AND($S5="Dwn",$BF5="Short",$E5=GJ$2),$P5,"") | GM5: =IF($J5="",#N/A,SUM(GL$4:GL5)) -> 0 | GN5: =IF(AND($S5="SW",$BF5="Long",$E5=GJ$2),$P5,"") | GO5: =IF($J5="",#N/A,SUM(GN$4:GN5)) -> 0 | GP5: =IF($J5="",#N/A,SUM(GN$4:GN5,GL$4:GL5,GJ$4:GJ5)) -> 0 | GS5: =IF($J5="","",IF($D5="Y",$P5,"")) -> 0.67884406 | GT5: =IF(GS5="",NA(),SUM($GS$4:GS5)) -> 0.20039738 | GU5: =IF(AND($S5="Up",$BF5="Long",$D5="Y"),$GS5,"") | GV5: =IF(GU5="",NA(),SUM($GU$4:GU5)) -> #N/A | GW5: =IF(AND($S5="SW",$BF5="Long",$D5="Y"),$GS5,"") | GX5: =IF(GW5="",NA(),SUM($GW$4:GW5)) -> #N/A | GY5: =IF(AND($S5="Dwn",$BF5="Short",$D5="Y"),$GS5,"") -> 0.67884406 | GZ5: =IF(GY5="",NA(),SUM($GY$4:GY5)) -> 0.20039738 | HA5: =IF($J5="","",IF($D5="N",$P5,"")) | HB5: =IF(HA5="",NA(),SUM($HA$4:HA5)) -> #N/A | HC5: =IF(AND($S5="Up",$BF5="Long",$D5="N"),$HA5,"") | HD5: =IF(HC5="",NA(),SUM($HC$4:HC5)) -> #N/A | HE5: =IF(AND($S5="SW",$BF5="Long",$D5="N"),$HA5,"") | HF5: =IF(HE5="",NA(),SUM($HE$4:HE5)) -> #N/A | HG5: =IF(AND($S5="Dwn",$BF5="Short",$D5="N"),$HA5,"") | HH5: =IF(HG5="",NA(),SUM($HG$4:HG5)) -> #N/A | HI5: =IF($AC5="","",IF(AND($S5="Dwn",$K5<0),$HU5-$P5,"")) -> -0.80152672 | HJ5: =IF($J5="",#N/A,SUM(HI$4:$HI5)) -> -0.80152672 | HK5: =IF($AC5="","",IF(AND($S5="Dwn",$K5>0),$HU5-$P5,"")) | HL5: =IF($J5="",#N/A,SUM($HK$4:HK5)) -> -3.4652546 | HM5: =IF($AC5="","",IF(AND($S5="Up",$K5>0),$HU5-$P5,"")) | HN5: =IF($J5="",#N/A,SUM($HM$4:HM5)) -> 0 | HO5: =IF($AC5="","",IF(AND($S5="Up",$K5<0),$HU5-$P5,"")) | HP5: =IF($J5="",#N/A,SUM($HO$4:HO5)) -> 0 | HQ5: =IF($AC5="","",IF(AND($S5="SW",$K5>0),$HU5-$P5,"")) | HR5: =IF($J5="",#N/A,SUM($HQ$4:HQ5)) -> 0 | HS5: =IF($AC5="","",IF(AND($S5="SW",$K5<0),$HU5-$P5,"")) | HT5: =IF($J5="",#N/A,SUM($HS$4:HS5)) -> 0 | HU5: =IF(OR($Y5="",$AC5=""),"",IF($BF5="Long",(($AC5*$Y5)-$X5)/($X5*0.06),($X5-($AC5*$Y5))/($X5*0.06))) -> -0.12268266 | HV5: =IF($J5="",#N/A,SUM(HU$4:$HU5)) -> -4.0663839
A6: JPM | B6: on 4/11/25 Before Market Eastern Stan | C6: =IF(S6="Dwn",2,IF(S6="Up",1,IF(S6="SW",3,"x"))) -> 3 | D6: =_xlfn.XLOOKUP(A6,[1]SP500!$A$2:$A$502,[1]SP500!$D$2:$D$502,"N") -> Y | E6: =IFERROR(_xlfn.XLOOKUP(A6,[1]SP500!$A$2:$A$655,[1]SP500!$B$2:$B$655),"") -> XLF | F6: 45758 | G6: =IF(ISNUMBER(FIND("After",B6,1)),"AMC",IF(ISNUMBER(FIND("Before",B6,1)),"BMO","err")) -> BMO | H6: =IF(AH6="Skip","sk",IF(OR(S6="",V6=""),"",IF(AND(S6="Dwn",V6="Short"),"s",IF(AND(S6="Up",V6="Long"),"s",IF(AND(S6="SW",V6="Long"),"s","o"))))) -> s | I6: 227.11 | J6: 226.31 | K6: =IF(J6="","",(J6-I6)/I6) -> -0.0035225221 | L6: =IF(OR($Y6="",J6=""),"",IF($V6="Long",(($J6*$Y6)-$X6),($X6-($J6*$Y6)))) -> -4 | M6: =IF(L6="","",IF(AK6="",#N/A,IF(AH6="Open",AK6-L6,#N/A))) -> 0 | N6: =IF(OR($Y6="",L6=""),"",IF($BF6="Long",(($J6*$Y6)-$X6),($X6-($J6*$Y6)))) -> -4 | O6: =IF(N6="",#N/A,SUM($N$4:N6)) -> 9.92 | P6: =IF(OR($Y6="",L6=""),"",IF($BF6="Long",(($J6*$Y6)-$X6)/(X6*0.06),($X6-($J6*$Y6))/(X6*0.06))) -> -0.058708702 | Q6: =IF($N6="",#N/A,SUM($P$4:P6)) -> 0.14168868 | R6: =IF(AND(AH6="MOC",AC6=""),#N/A,IFERROR(Q6-AJ6,Q6-0)) -> 0.058470681 | S6: =IF(T6="Down","Dwn",IF(T6="Up","Up",IF(AND(T6="",K6=""),"",IF(AND(K6<0,T6="Yes"),"Dwn",IF(AND(K6>0,T6="Yes"),"Up",IF(AND(K6<0,T6="No"),"Up",IF(AND(K6>0,T6="No"),"Dwn",IF(T6="NA","SW","err")))))))) -> SW | T6: NA | U6: =I6 -> 227.11 | V6: Long | W6: 5 | X6: =IF(W6="","",U6*W6) -> 1135.55 | Y6: =IF(W6="","",W6) -> 5 | Z6: 226.31 | AA6: =IF($Z6="","",IF($V6="Long",(($Z6*$Y6)-$X6),($X6-($Z6*$Y6)))) -> -4 | AB6: =IF($AC6="","",IF($V6="Long",(($AC6*$Y6)-$X6),($X6-($AC6*$Y6)))) -> 45.45 | AC6: 236.2 | AD6: =IF(AC6="","",IF(OR($Y6="",CV6=""),"",IF($BF6="Long",(($AC6*$Y6)-$X6),($X6-($AC6*$Y6))))) -> 45.45 | AE6: =IF(OR($Y6="",$AD6=""),"",IF($BF6="Long",(($AC6*$Y6)-$X6)/($X6*0.06),($X6-($AC6*$Y6))/($X6*0.06))) -> 0.66707763 | AF6: =IF($AC6="",#N/A,SUM(AD$4:AD6)) -> -217.35 | AG6: =IF(OR(AD6="",AC6=""),"",AD6-N6) -> 49.45 | AH6: Open | AI6: =IF(AND(AH6="MOC",AC6=""),"",IF(Z6="","",IF(AH6="Skip",0,IF(AK6=0,0,AK6/(X6*0.06))))) -> -0.058708702 | AJ6: =IF(AI6="",#N/A,SUM($AI$4:AI6)) -> 0.083218 | AK6: =IF(AH6="","",IF(AH6="Skip","",IF(OR(AH6="open",AH6="Other"),AA6,IF(AH6="MOC",AB6,"Err")))) -> -4 | AL6: =IF(AI6="",#N/A,IF(AH6="Skip",SUM($AK$4:AK6),SUM($AK$4:AK6))) -> 6.2 | AM6: =IF(OR($Y6="",$L6=""),"",IF($BF6="Long",(($AC6*$Y6)-$X6)/($X6*0.06),($X6-($AC6*$Y6))/($X6*0.06))) -> 0.66707763 | AO6: =IF(AND($S6="SW",$BF6="Long"),$HU6,"") -> 0.66707763 | AP6: =IF($AC6="",#N/A,SUM(AO$4:AO6)) -> 0.66707763 | AQ6: =IF(AND($S6="UP",$BF6="Long"),$HU6,"") | AR6: =IF($AC6="",#N/A,SUM(AQ$4:AQ6)) -> 0 | AS6: =IF(AND($S6="Dwn",$BF6="Short"),$HU6,"") | AT6: =IF($AC6="",#N/A,SUM(AS$4:AS6)) -> -4.0663839 | AU6: =IF(AND(S6="SW",BF6="Long"),$AD6,"") -> 45.45 | AV6: =IF($AC6="",#N/A,SUM(AU$4:AU6)) -> 45.45 | AW6: =IF(AND(S6="UP",BF6="Long"),$AD6,"") | AX6: =IF($AC6="",#N/A,SUM(AW$4:AW6)) -> 0 | AY6: =IF(AND(S6="Dwn",BF6="Short"),$AD6,"") | AZ6: =IF($AC6="",#N/A,SUM(AY$4:AY6)) -> -262.8 | BA6: =IF(AD6="",#N/A,SUM($AD$4:AD6)) -> -217.35 | BC6: =IF(K6="","",IF(AND(K6>0,T6="Yes"),1,"")) | BD6: =IF(K6="","",IF(AND($K6>0,$T6="No"),1,"")) | BE6: =IF(K6="","",IF(AND($K6>0,$T6="NA"),1,"")) | BF6: =IF(S6="Dwn","Short","Long") -> Long | BG6: =IF(K6="","",IF(AND($K6<0,$T6="Yes"),1,"")) | BH6: =IF(K6="","",IF(AND($K6<0,$T6="No"),1,"")) | BI6: =IF(K6="","",IF(AND($K6<0,$T6="NA"),1,"")) -> 1 | BO6: =IF(J6="",#N/A,IF(S6="SW",(COUNTIFS(K$4:$K6,">0",S$4:$S6,"SW")/COUNTIF(S$4:$S6,"SW")),#N/A)) -> 0 | BP6: =IF($J6="",#N/A,IF($S6="DWN",(COUNTIFS($K$4:$K6,"<0",$S$4:$S6,"DWN")/COUNTIF($S$4:$S6,"DWN")),#N/A)) -> #N/A | BQ6: =IF($J6="",#N/A,IF($S6="UP",(COUNTIFS($K$4:$K6,">0",$S$4:$S6,"UP")/COUNTIF($S$4:$S6,"UP")),#N/A)) -> #N/A | BR6: =IF(J6="",#N/A,COUNTIF($K$4:K6,">0")/COUNT($J$4:J6)) -> 0.33333333 | BS6: =IF($AH6="Skip","",IF($J6="","",IF(AND($V6="Long",$L6>0),$P6,""))) | BT6: =IF($AH6="Skip","",IF($J6="","",IF(AND($V6="Long",$L6<0),$P6,""))) -> -0.058708702 | BU6: =IF($AH6="Skip","",IF($J6="","",IF(AND($V6="Short",$L6>0),$P6,""))) | BV6: =IF($AH6="Skip","",IF($J6="","",IF(AND($V6="Short",$L6<0),$P6,""))) | BW6: =IF(AND($S6="Up",$BF6="Long"),$N6,"") | BX6: =IF($J6="",#N/A,SUM($BW$4:BW6)) -> 0 | BY6: =IF(AND($S6="Dwn",$BF6="Short"),$N6,"") | BZ6: =IF($J6="",#N/A,SUM($BY$4:BY6)) -> 13.92 | CA6: =IF(AND($S6="SW",$BF6="Long"),$N6,"") -> -4 | CB6: =IF($J6="",#N/A,SUM($CA$4:CA6)) -> -4 | CC6: =IF(AND($S6="Up",$BF6="Long"),$P6,"") | CD6: =IF($J6="",#N/A,SUM($CC$4:CC6)) -> 0 | CE6: =IF(AND($S6="Dwn",$BF6="Short"),$P6,"") | CF6: =IF($J6="",#N/A,SUM($CE$4:CE6)) -> 0.20039738 | CG6: =IF(AND($S6="SW",$BF6="Long"),$P6,"") -> -0.058708702 | CH6: =IF($J6="",#N/A,SUM($CG$4:CG6)) -> -0.058708702 | CI6: =IF(AND($S6="Up",$BF6="Long",$E6=CI$2),$P6,"") | CJ6: =IF($J6="",#N/A,SUM(CI$4:CI6)) -> 0 | CK6: =IF(AND($S6="Dwn",$BF6="Short",$E6=CI$2),$P6,"") | CL6: =IF($J6="",#N/A,SUM(CK$4:CK6)) -> 0 | CM6: =IF(AND($S6="SW",$BF6="Long",$E6=CI$2),$P6,"") | CN6: =IF($J6="",#N/A,SUM(CM$4:CM6)) -> 0 | CO6: =IF($J6="",#N/A,SUM(CM$4:CM6,CK$4:CK6,CI$4:CI6)) -> 0 | CP6: =IF(AND($S6="Up",$BF6="Long",$E6=CP$2),$P6,"") | CQ6: =IF($J6="",#N/A,SUM(CP$4:CP6)) -> 0 | CR6: =IF(AND($S6="Dwn",$BF6="Short",$E6=CP$2),$P6,"") | CS6: =IF($J6="",#N/A,SUM(CR$4:CR6)) -> 0 | CT6: =IF(AND($S6="SW",$BF6="Long",$E6=CP$2),$P6,"") | CU6: =IF($J6="",#N/A,SUM(CT$4:CT6)) -> 0 | CV6: =IF($J6="",#N/A,SUM(CT$4:CT6,CR$4:CR6,CP$4:CP6)) -> 0 | CW6: =IF(AND($S6="Up",$BF6="Long",$E6=CW$2),$P6,"") | CX6: =IF($J6="",#N/A,SUM(CW$4:CW6)) -> 0 | CY6: =IF(AND($S6="Dwn",$BF6="Short",$E6=CW$2),$P6,"") | CZ6: =IF($J6="",#N/A,SUM(CY$4:CY6)) -> 0 | DA6: =IF(AND($S6="SW",$BF6="Long",$E6=CW$2),$P6,"") | DB6: =IF($J6="",#N/A,SUM(DA$4:DA6)) -> 0 | DC6: =IF($J6="",#N/A,SUM(DA$4:DA6,CY$4:CY6,CW$4:CW6)) -> 0 | DD6: =IF(AND($S6="Up",$BF6="Long",$E6=DD$2),$P6,"") | DE6: =IF($J6="",#N/A,SUM(DD$4:DD6)) -> 0 | DF6: =IF(AND($S6="Dwn",$BF6="Short",$E6=DD$2),$P6,"") | DG6: =IF($J6="",#N/A,SUM(DF$4:DF6)) -> 0.67884406 | DH6: =IF(AND($S6="SW",$BF6="Long",$E6=DD$2),$P6,"") | DI6: =IF($J6="",#N/A,SUM(DH$4:DH6)) -> 0 | DJ6: =IF($J6="",#N/A,SUM(DH$4:DH6,DF$4:DF6,DD$4:DD6)) -> 0.67884406 | DK6: =IF(AND($S6="Up",$BF6="Long",$E6=DK$2),$P6,"") | DL6: =IF($J6="",#N/A,SUM(DK$4:DK6)) -> 0 | DM6: =IF(AND($S6="Dwn",$BF6="Short",$E6=DK$2),$P6,"") | DN6: =IF($J6="",#N/A,SUM(DM$4:DM6)) -> 0 | DO6: =IF(AND($S6="SW",$BF6="Long",$E6=DK$2),$P6,"") | DP6: =IF($J6="",#N/A,SUM(DO$4:DO6)) -> 0 | DQ6: =IF($J6="",#N/A,SUM(DO$4:DO6,DM$4:DM6,DK$4:DK6)) -> 0 | DR6: =IF(AND($S6="Up",$BF6="Long",$E6=DR$2),$P6,"") | DS6: =IF($J6="",#N/A,SUM(DR$4:DR6)) -> 0 | DT6: =IF(AND($S6="Dwn",$BF6="Short",$E6=DR$2),$P6,"") | DU6: =IF($J6="",#N/A,SUM(DT$4:DT6)) -> 0 | DV6: =IF(AND($S6="SW",$BF6="Long",$E6=DR$2),$P6,"") -> -0.058708702 | DW6: =IF($J6="",#N/A,SUM(DV$4:DV6)) -> -0.058708702 | DX6: =IF($J6="",#N/A,SUM(DV$4:DV6,DT$4:DT6,DR$4:DR6)) -> -0.058708702 | DY6: =IF(AND($S6="Up",$BF6="Long",$E6=DY$2),$P6,"") | DZ6: =IF($J6="",#N/A,SUM(DY$4:DY6)) -> 0 | EA6: =IF(AND($S6="Dwn",$BF6="Short",$E6=DY$2),$P6,"") | EB6: =IF($J6="",#N/A,SUM(EA$4:EA6)) -> -0.47844667 | EC6: =IF(AND($S6="SW",$BF6="Long",$E6=DY$2),$P6,"") | ED6: =IF($J6="",#N/A,SUM(EC$4:EC6)) -> 0 | EE6: =IF($J6="",#N/A,SUM(EC$4:EC6,EA$4:EA6,DY$4:DY6)) -> -0.47844667 | EF6: =IF(AND($S6="Up",$BF6="Long",$E6=EF$2),$P6,"") | EG6: =IF($J6="",#N/A,SUM(EF$4:EF6)) -> 0 | EH6: =IF(AND($S6="Dwn",$BF6="Short",$E6=EF$2),$P6,"") | EI6: =IF($J6="",#N/A,SUM(EH$4:EH6)) -> 0 | EJ6: =IF(AND($S6="SW",$BF6="Long",$E6=EF$2),$P6,"") | EK6: =IF($J6="",#N/A,SUM(EJ$4:EJ6)) -> 0 | EL6: =IF($J6="",#N/A,SUM(EJ$4:EJ6,EH$4:EH6,EF$4:EF6)) -> 0 | EM6: =IF(AND($S6="Up",$BF6="Long",$E6=EM$2),$P6,"") | EN6: =IF($J6="",#N/A,SUM(EM$4:EM6)) -> 0 | EO6: =IF(AND($S6="Dwn",$BF6="Short",$E6=EM$2),$P6,"") | EP6: =IF($J6="",#N/A,SUM(EO$4:EO6)) -> 0 | EQ6: =IF(AND($S6="SW",$BF6="Long",$E6=EM$2),$P6,"") | ER6: =IF($J6="",#N/A,SUM(EQ$4:EQ6)) -> 0 | ES6: =IF($J6="",#N/A,SUM(EQ$4:EQ6,EO$4:EO6,EM$4:EM6)) -> 0 | ET6: =IF(AND($S6="Up",$BF6="Long",$E6=ET$2),$P6,"") | EU6: =IF($J6="",#N/A,SUM(ET$4:ET6)) -> 0 | EV6: =IF(AND($S6="Dwn",$BF6="Short",$E6=ET$2),$P6,"") | EW6: =IF($J6="",#N/A,SUM(EV$4:EV6)) -> 0 | EX6: =IF(AND($S6="SW",$BF6="Long",$E6=ET$2),$P6,"") | EY6: =IF($J6="",#N/A,SUM(EX$4:EX6)) -> 0 | EZ6: =IF($J6="",#N/A,SUM(EX$4:EX6,EV$4:EV6,ET$4:ET6)) -> 0 | FA6: =IF(AND($S6="Up",$BF6="Long",$E6=FA$2),$P6,"") | FB6: =IF($J6="",#N/A,SUM(FA$4:FA6)) -> 0 | FC6: =IF(AND($S6="Dwn",$BF6="Short",$E6=FA$2),$P6,"") | FD6: =IF($J6="",#N/A,SUM(FC$4:FC6)) -> 0 | FE6: =IF(AND($S6="SW",$BF6="Long",$E6=FA$2),$P6,"") | FF6: =IF($J6="",#N/A,SUM(FE$4:FE6)) -> 0 | FG6: =IF($J6="",#N/A,SUM(FE$4:FE6,FC$4:FC6,FA$4:FA6)) -> 0 | FH6: =IF(AND($S6="Up",$BF6="Long",$E6=FH$2),$P6,"") | FI6: =IF($J6="",#N/A,SUM(FH$4:FH6)) -> 0 | FJ6: =IF(AND($S6="Dwn",$BF6="Short",$E6=FH$2),$P6,"") | FK6: =IF($J6="",#N/A,SUM(FJ$4:FJ6)) -> 0 | FL6: =IF(AND($S6="SW",$BF6="Long",$E6=FH$2),$P6,"") | FM6: =IF($J6="",#N/A,SUM(FL$4:FL6)) -> 0 | FN6: =IF($J6="",#N/A,SUM(FL$4:FL6,FJ$4:FJ6,FH$4:FH6)) -> 0 | FO6: =IF(AND($S6="Up",$BF6="Long",$E6=FO$2),$P6,"") | FP6: =IF($J6="",#N/A,SUM(FO$4:FO6)) -> 0 | FQ6: =IF(AND($S6="Dwn",$BF6="Short",$E6=FO$2),$P6,"") | FR6: =IF($J6="",#N/A,SUM(FQ$4:FQ6)) -> 0 | FS6: =IF(AND($S6="SW",$BF6="Long",$E6=FO$2),$P6,"") | FT6: =IF($J6="",#N/A,SUM(FS$4:FS6)) -> 0 | FU6: =IF($J6="",#N/A,SUM(FS$4:FS6,FQ$4:FQ6,FO$4:FO6)) -> 0 | FV6: =IF(AND($S6="Up",$BF6="Long",$E6=FV$2),$P6,"") | FW6: =IF($J6="",#N/A,SUM(FV$4:FV6)) -> 0 | FX6: =IF(AND($S6="Dwn",$BF6="Short",$E6=FV$2),$P6,"") | FY6: =IF($J6="",#N/A,SUM(FX$4:FX6)) -> 0 | FZ6: =IF(AND($S6="SW",$BF6="Long",$E6=FV$2),$P6,"") | GA6: =IF($J6="",#N/A,SUM(FZ$4:FZ6)) -> 0 | GB6: =IF($J6="",#N/A,SUM(FZ$4:FZ6,FX$4:FX6,FV$4:FV6)) -> 0 | GC6: =IF(AND($S6="Up",$BF6="Long",$E6=GC$2),$P6,"") | GD6: =IF($J6="",#N/A,SUM(GC$4:GC6)) -> 0 | GE6: =IF(AND($S6="Dwn",$BF6="Short",$E6=GC$2),$P6,"") | GF6: =IF($J6="",#N/A,SUM(GE$4:GE6)) -> 0 | GG6: =IF(AND($S6="SW",$BF6="Long",$E6=GC$2),$P6,"") | GH6: =IF($J6="",#N/A,SUM(GG$4:GG6)) -> 0 | GI6: =IF($J6="",#N/A,SUM(GG$4:GG6,GE$4:GE6,GC$4:GC6)) -> 0 | GJ6: =IF(AND($S6="Up",$BF6="Long",$E6=GJ$2),$P6,"") | GK6: =IF($J6="",#N/A,SUM(GJ$4:GJ6)) -> 0 | GL6: =IF(AND($S6="Dwn",$BF6="Short",$E6=GJ$2),$P6,"") | GM6: =IF($J6="",#N/A,SUM(GL$4:GL6)) -> 0 | GN6: =IF(AND($S6="SW",$BF6="Long",$E6=GJ$2),$P6,"") | GO6: =IF($J6="",#N/A,SUM(GN$4:GN6)) -> 0 | GP6: =IF($J6="",#N/A,SUM(GN$4:GN6,GL$4:GL6,GJ$4:GJ6)) -> 0 | GS6: =IF(J6="","",IF(D6="Y",P6,"")) -> -0.058708702 | GT6: =IF(GS6="",NA(),SUM($GS$4:GS6)) -> 0.14168868 | GU6: =IF(AND($S6="Up",$BF6="Long",$D6="Y"),$GS6,"") | GV6: =IF(GU6="",NA(),SUM($GU$4:GU6)) -> #N/A | GW6: =IF(AND($S6="SW",$BF6="Long",$D6="Y"),$GS6,"") -> -0.058708702 | GX6: =IF(GW6="",NA(),SUM($GW$4:GW6)) -> -0.058708702 | GY6: =IF(AND($S6="Dwn",$BF6="Short",$D6="Y"),$GS6,"") | GZ6: =IF(GY6="",NA(),SUM($GY$4:GY6)) -> #N/A | HA6: =IF($J6="","",IF($D6="N",$P6,"")) | HB6: =IF(HA6="",NA(),SUM($HA$4:HA6)) -> #N/A | HC6: =IF(AND($S6="Up",$BF6="Long",$D6="N"),$HA6,"") | HD6: =IF(HC6="",NA(),SUM($HC$4:HC6)) -> #N/A | HE6: =IF(AND($S6="SW",$BF6="Long",$D6="N"),$HA6,"") | HF6: =IF(HE6="",NA(),SUM($HE$4:HE6)) -> #N/A | HG6: =IF(AND($S6="Dwn",$BF6="Short",$D6="N"),$HA6,"") | HH6: =IF(HG6="",NA(),SUM($HG$4:HG6)) -> #N/A | HI6: =IF($AC6="","",IF(AND($S6="Dwn",$K6<0),$HU6-P6,"")) | HJ6: =IF($J6="",#N/A,SUM(HI$4:$HI6)) -> -0.80152672 | HK6: =IF($AC6="","",IF(AND($S6="Dwn",$K6>0),$HU6-$P6,"")) | HL6: =IF($J6="",#N/A,SUM($HK$4:HK6)) -> -3.4652546 | HM6: =IF($AC6="","",IF(AND($S6="Up",$K6>0),$HU6-$P6,"")) | HN6: =IF($J6="",#N/A,SUM($HM$4:HM6)) -> 0 | HO6: =IF($AC6="","",IF(AND($S6="Up",$K6<0),$HU6-$P6,"")) | HP6: =IF($J6="",#N/A,SUM($HO$4:HO6)) -> 0 | HQ6: =IF($AC6="","",IF(AND($S6="SW",$K6>0),$HU6-$P6,"")) | HR6: =IF($J6="",#N/A,SUM($HQ$4:HQ6)) -> 0 | HS6: =IF($AC6="","",IF(AND($S6="SW",$K6<0),$HU6-$P6,"")) -> 0.72578633 | HT6: =IF($J6="",#N/A,SUM($HS$4:HS6)) -> 0.72578633 | HU6: =IF(OR($Y6="",$AC6=""),"",IF($BF6="Long",(($AC6*$Y6)-$X6)/($X6*0.06),($X6-($AC6*$Y6))/($X6*0.06))) -> 0.66707763 | HV6: =IF($J6="",#N/A,SUM(HU$4:$HU6)) -> -3.3993063
A7: WFC | B7: on 4/11/25 Before Market Eastern Stan | C7: =IF(S7="Dwn",2,IF(S7="Up",1,IF(S7="SW",3,"x"))) -> 3 | D7: =_xlfn.XLOOKUP(A7,[1]SP500!$A$2:$A$502,[1]SP500!$D$2:$D$502,"N") -> Y | E7: =IFERROR(_xlfn.XLOOKUP(A7,[1]SP500!$A$2:$A$655,[1]SP500!$B$2:$B$655),"") -> XLF | F7: 45758 | G7: =IF(ISNUMBER(FIND("After",B7,1)),"AMC",IF(ISNUMBER(FIND("Before",B7,1)),"BMO","err")) -> BMO | H7: =IF(AH7="Skip","sk",IF(OR(S7="",V7=""),"",IF(AND(S7="Dwn",V7="Short"),"s",IF(AND(S7="Up",V7="Long"),"s",IF(AND(S7="SW",V7="Long"),"s","o"))))) -> s | I7: 63.11 | J7: 61.54 | K7: =IF(J7="","",(J7-I7)/I7) -> -0.024877199 | L7: =IF(OR($Y7="",J7=""),"",IF($V7="Long",(($J7*$Y7)-$X7),($X7-($J7*$Y7)))) -> -26.69 | M7: =IF(L7="","",IF(AK7="",#N/A,IF(AH7="Open",AK7-L7,#N/A))) -> 15.98 | N7: =IF(OR($Y7="",L7=""),"",IF($BF7="Long",(($J7*$Y7)-$X7),($X7-($J7*$Y7)))) -> -26.69 | O7: =IF(N7="",#N/A,SUM($N$4:N7)) -> -16.77 | P7: =IF(OR($Y7="",L7=""),"",IF($BF7="Long",(($J7*$Y7)-$X7)/(X7*0.06),($X7-($J7*$Y7))/(X7*0.06))) -> -0.41461998 | Q7: =IF($N7="",#N/A,SUM($P$4:P7)) -> -0.2729313 | R7: =IF(AND(AH7="MOC",AC7=""),#N/A,IFERROR(Q7-AJ7,Q7-0)) -> -0.18977313 | S7: =IF(T7="Down","Dwn",IF(T7="Up","Up",IF(AND(T7="",K7=""),"",IF(AND(K7<0,T7="Yes"),"Dwn",IF(AND(K7>0,T7="Yes"),"Up",IF(AND(K7<0,T7="No"),"Up",IF(AND(K7>0,T7="No"),"Dwn",IF(T7="NA","SW","err")))))))) -> SW | T7: NA | U7: =I7 -> 63.11 | V7: Long | W7: 17 | X7: =IF(W7="","",U7*W7) -> 1072.87 | Y7: =IF(W7="","",W7) -> 17 | Z7: 62.48 | AA7: =IF($Z7="","",IF($V7="Long",(($Z7*$Y7)-$X7),($X7-($Z7*$Y7)))) -> -10.71 | AB7: =IF($AC7="","",IF($V7="Long",(($AC7*$Y7)-$X7),($X7-($AC7*$Y7)))) -> -10.2 | AC7: 62.51 | AD7: =IF(AC7="","",IF(OR($Y7="",CV7=""),"",IF($BF7="Long",(($AC7*$Y7)-$X7),($X7-($AC7*$Y7))))) -> -10.2 | AE7: =IF(OR($Y7="",$AD7=""),"",IF($BF7="Long",(($AC7*$Y7)-$X7)/($X7*0.06),($X7-($AC7*$Y7))/($X7*0.06))) -> -0.15845349 | AF7: =IF($AC7="",#N/A,SUM(AD$4:AD7)) -> -227.55 | AG7: =IF(OR(AD7="",AC7=""),"",AD7-N7) -> 16.49 | AH7: Open | AI7: =IF(AND(AH7="MOC",AC7=""),"",IF(Z7="","",IF(AH7="Skip",0,IF(AK7=0,0,AK7/(X7*0.06))))) -> -0.16637617 | AJ7: =IF(AI7="",#N/A,SUM($AI$4:AI7)) -> -0.083158169 | AK7: =IF(AH7="","",IF(AH7="Skip","",IF(OR(AH7="open",AH7="Other"),AA7,IF(AH7="MOC",AB7,"Err")))) -> -10.71 | AL7: =IF(AI7="",#N/A,IF(AH7="Skip",SUM($AK$4:AK7),SUM($AK$4:AK7))) -> -4.51 | AM7: =IF(OR($Y7="",$L7=""),"",IF($BF7="Long",(($AC7*$Y7)-$X7)/($X7*0.06),($X7-($AC7*$Y7))/($X7*0.06))) -> -0.15845349 | AO7: =IF(AND($S7="SW",$BF7="Long"),$HU7,"") -> -0.15845349 | AP7: =IF($AC7="",#N/A,SUM(AO$4:AO7)) -> 0.50862413 | AQ7: =IF(AND($S7="UP",$BF7="Long"),$HU7,"") | AR7: =IF($AC7="",#N/A,SUM(AQ$4:AQ7)) -> 0 | AS7: =IF(AND($S7="Dwn",$BF7="Short"),$HU7,"") | AT7: =IF($AC7="",#N/A,SUM(AS$4:AS7)) -> -4.0663839 | AU7: =IF(AND(S7="SW",BF7="Long"),$AD7,"") -> -10.2 | AV7: =IF($AC7="",#N/A,SUM(AU$4:AU7)) -> 35.25 | AW7: =IF(AND(S7="UP",BF7="Long"),$AD7,"") | AX7: =IF($AC7="",#N/A,SUM(AW$4:AW7)) -> 0 | AY7: =IF(AND(S7="Dwn",BF7="Short"),$AD7,"") | AZ7: =IF($AC7="",#N/A,SUM(AY$4:AY7)) -> -262.8 | BA7: =IF(AD7="",#N/A,SUM($AD$4:AD7)) -> -227.55 | BC7: =IF(K7="","",IF(AND(K7>0,T7="Yes"),1,"")) | BD7: =IF(K7="","",IF(AND($K7>0,$T7="No"),1,"")) | BE7: =IF(K7="","",IF(AND($K7>0,$T7="NA"),1,"")) | BF7: =IF(S7="Dwn","Short","Long") -> Long | BG7: =IF(K7="","",IF(AND($K7<0,$T7="Yes"),1,"")) | BH7: =IF(K7="","",IF(AND($K7<0,$T7="No"),1,"")) | BI7: =IF(K7="","",IF(AND($K7<0,$T7="NA"),1,"")) -> 1 | BO7: =IF(J7="",#N/A,IF(S7="SW",(COUNTIFS(K$4:$K7,">0",S$4:$S7,"SW")/COUNTIF(S$4:$S7,"SW")),#N/A)) -> 0 | BP7: =IF($J7="",#N/A,IF($S7="DWN",(COUNTIFS($K$4:$K7,"<0",$S$4:$S7,"DWN")/COUNTIF($S$4:$S7,"DWN")),#N/A)) -> #N/A | BQ7: =IF($J7="",#N/A,IF($S7="UP",(COUNTIFS($K$4:$K7,">0",$S$4:$S7,"UP")/COUNTIF($S$4:$S7,"UP")),#N/A)) -> #N/A | BR7: =IF(J7="",#N/A,COUNTIF($K$4:K7,">0")/COUNT($J$4:J7)) -> 0.25 | BS7: =IF($AH7="Skip","",IF($J7="","",IF(AND($V7="Long",$L7>0),$P7,""))) | BT7: =IF($AH7="Skip","",IF($J7="","",IF(AND($V7="Long",$L7<0),$P7,""))) -> -0.41461998 | BU7: =IF($AH7="Skip","",IF($J7="","",IF(AND($V7="Short",$L7>0),$P7,""))) | BV7: =IF($AH7="Skip","",IF($J7="","",IF(AND($V7="Short",$L7<0),$P7,""))) | BW7: =IF(AND($S7="Up",$BF7="Long"),$N7,"") | BX7: =IF($J7="",#N/A,SUM($BW$4:BW7)) -> 0 | BY7: =IF(AND($S7="Dwn",$BF7="Short"),$N7,"") | BZ7: =IF($J7="",#N/A,SUM($BY$4:BY7)) -> 13.92 | CA7: =IF(AND($S7="SW",$BF7="Long"),$N7,"") -> -26.69 | CB7: =IF($J7="",#N/A,SUM($CA$4:CA7)) -> -30.69 | CC7: =IF(AND($S7="Up",$BF7="Long"),$P7,"") | CD7: =IF($J7="",#N/A,SUM($CC$4:CC7)) -> 0 | CE7: =IF(AND($S7="Dwn",$BF7="Short"),$P7,"") | CF7: =IF($J7="",#N/A,SUM($CE$4:CE7)) -> 0.20039738 | CG7: =IF(AND($S7="SW",$BF7="Long"),$P7,"") -> -0.41461998 | CH7: =IF($J7="",#N/A,SUM($CG$4:CG7)) -> -0.47332868 | CI7: =IF(AND($S7="Up",$BF7="Long",$E7=CI$2),$P7,"") | CJ7: =IF($J7="",#N/A,SUM(CI$4:CI7)) -> 0 | CK7: =IF(AND($S7="Dwn",$BF7="Short",$E7=CI$2),$P7,"") | CL7: =IF($J7="",#N/A,SUM(CK$4:CK7)) -> 0 | CM7: =IF(AND($S7="SW",$BF7="Long",$E7=CI$2),$P7,"") | CN7: =IF($J7="",#N/A,SUM(CM$4:CM7)) -> 0 | CO7: =IF($J7="",#N/A,SUM(CM$4:CM7,CK$4:CK7,CI$4:CI7)) -> 0 | CP7: =IF(AND($S7="Up",$BF7="Long",$E7=CP$2),$P7,"") | CQ7: =IF($J7="",#N/A,SUM(CP$4:CP7)) -> 0 | CR7: =IF(AND($S7="Dwn",$BF7="Short",$E7=CP$2),$P7,"") | CS7: =IF($J7="",#N/A,SUM(CR$4:CR7)) -> 0 | CT7: =IF(AND($S7="SW",$BF7="Long",$E7=CP$2),$P7,"") | CU7: =IF($J7="",#N/A,SUM(CT$4:CT7)) -> 0 | CV7: =IF($J7="",#N/A,SUM(CT$4:CT7,CR$4:CR7,CP$4:CP7)) -> 0 | CW7: =IF(AND($S7="Up",$BF7="Long",$E7=CW$2),$P7,"") | CX7: =IF($J7="",#N/A,SUM(CW$4:CW7)) -> 0 | CY7: =IF(AND($S7="Dwn",$BF7="Short",$E7=CW$2),$P7,"") | CZ7: =IF($J7="",#N/A,SUM(CY$4:CY7)) -> 0 | DA7: =IF(AND($S7="SW",$BF7="Long",$E7=CW$2),$P7,"") | DB7: =IF($J7="",#N/A,SUM(DA$4:DA7)) -> 0 | DC7: =IF($J7="",#N/A,SUM(DA$4:DA7,CY$4:CY7,CW$4:CW7)) -> 0 | DD7: =IF(AND($S7="Up",$BF7="Long",$E7=DD$2),$P7,"") | DE7: =IF($J7="",#N/A,SUM(DD$4:DD7)) -> 0 | DF7: =IF(AND($S7="Dwn",$BF7="Short",$E7=DD$2),$P7,"") | DG7: =IF($J7="",#N/A,SUM(DF$4:DF7)) -> 0.67884406 | DH7: =IF(AND($S7="SW",$BF7="Long",$E7=DD$2),$P7,"") | DI7: =IF($J7="",#N/A,SUM(DH$4:DH7)) -> 0 | DJ7: =IF($J7="",#N/A,SUM(DH$4:DH7,DF$4:DF7,DD$4:DD7)) -> 0.67884406 | DK7: =IF(AND($S7="Up",$BF7="Long",$E7=DK$2),$P7,"") | DL7: =IF($J7="",#N/A,SUM(DK$4:DK7)) -> 0 | DM7: =IF(AND($S7="Dwn",$BF7="Short",$E7=DK$2),$P7,"") | DN7: =IF($J7="",#N/A,SUM(DM$4:DM7)) -> 0 | DO7: =IF(AND($S7="SW",$BF7="Long",$E7=DK$2),$P7,"") | DP7: =IF($J7="",#N/A,SUM(DO$4:DO7)) -> 0 | DQ7: =IF($J7="",#N/A,SUM(DO$4:DO7,DM$4:DM7,DK$4:DK7)) -> 0 | DR7: =IF(AND($S7="Up",$BF7="Long",$E7=DR$2),$P7,"") | DS7: =IF($J7="",#N/A,SUM(DR$4:DR7)) -> 0 | DT7: =IF(AND($S7="Dwn",$BF7="Short",$E7=DR$2),$P7,"") | DU7: =IF($J7="",#N/A,SUM(DT$4:DT7)) -> 0 | DV7: =IF(AND($S7="SW",$BF7="Long",$E7=DR$2),$P7,"") -> -0.41461998 | DW7: =IF($J7="",#N/A,SUM(DV$4:DV7)) -> -0.47332868 | DX7: =IF($J7="",#N/A,SUM(DV$4:DV7,DT$4:DT7,DR$4:DR7)) -> -0.47332868 | DY7: =IF(AND($S7="Up",$BF7="Long",$E7=DY$2),$P7,"") | DZ7: =IF($J7="",#N/A,SUM(DY$4:DY7)) -> 0 | EA7: =IF(AND($S7="Dwn",$BF7="Short",$E7=DY$2),$P7,"") | EB7: =IF($J7="",#N/A,SUM(EA$4:EA7)) -> -0.47844667 | EC7: =IF(AND($S7="SW",$BF7="Long",$E7=DY$2),$P7,"") | ED7: =IF($J7="",#N/A,SUM(EC$4:EC7)) -> 0 | EE7: =IF($J7="",#N/A,SUM(EC$4:EC7,EA$4:EA7,DY$4:DY7)) -> -0.47844667 | EF7: =IF(AND($S7="Up",$BF7="Long",$E7=EF$2),$P7,"") | EG7: =IF($J7="",#N/A,SUM(EF$4:EF7)) -> 0 | EH7: =IF(AND($S7="Dwn",$BF7="Short",$E7=EF$2),$P7,"") | EI7: =IF($J7="",#N/A,SUM(EH$4:EH7)) -> 0 | EJ7: =IF(AND($S7="SW",$BF7="Long",$E7=EF$2),$P7,"") | EK7: =IF($J7="",#N/A,SUM(EJ$4:EJ7)) -> 0 | EL7: =IF($J7="",#N/A,SUM(EJ$4:EJ7,EH$4:EH7,EF$4:EF7)) -> 0 | EM7: =IF(AND($S7="Up",$BF7="Long",$E7=EM$2),$P7,"") | EN7: =IF($J7="",#N/A,SUM(EM$4:EM7)) -> 0 | EO7: =IF(AND($S7="Dwn",$BF7="Short",$E7=EM$2),$P7,"") | EP7: =IF($J7="",#N/A,SUM(EO$4:EO7)) -> 0 | EQ7: =IF(AND($S7="SW",$BF7="Long",$E7=EM$2),$P7,"") | ER7: =IF($J7="",#N/A,SUM(EQ$4:EQ7)) -> 0 | ES7: =IF($J7="",#N/A,SUM(EQ$4:EQ7,EO$4:EO7,EM$4:EM7)) -> 0 | ET7: =IF(AND($S7="Up",$BF7="Long",$E7=ET$2),$P7,"") | EU7: =IF($J7="",#N/A,SUM(ET$4:ET7)) -> 0 | EV7: =IF(AND($S7="Dwn",$BF7="Short",$E7=ET$2),$P7,"") | EW7: =IF($J7="",#N/A,SUM(EV$4:EV7)) -> 0 | EX7: =IF(AND($S7="SW",$BF7="Long",$E7=ET$2),$P7,"") | EY7: =IF($J7="",#N/A,SUM(EX$4:EX7)) -> 0 | EZ7: =IF($J7="",#N/A,SUM(EX$4:EX7,EV$4:EV7,ET$4:ET7)) -> 0 | FA7: =IF(AND($S7="Up",$BF7="Long",$E7=FA$2),$P7,"") | FB7: =IF($J7="",#N/A,SUM(FA$4:FA7)) -> 0 | FC7: =IF(AND($S7="Dwn",$BF7="Short",$E7=FA$2),$P7,"") | FD7: =IF($J7="",#N/A,SUM(FC$4:FC7)) -> 0 | FE7: =IF(AND($S7="SW",$BF7="Long",$E7=FA$2),$P7,"") | FF7: =IF($J7="",#N/A,SUM(FE$4:FE7)) -> 0 | FG7: =IF($J7="",#N/A,SUM(FE$4:FE7,FC$4:FC7,FA$4:FA7)) -> 0 | FH7: =IF(AND($S7="Up",$BF7="Long",$E7=FH$2),$P7,"") | FI7: =IF($J7="",#N/A,SUM(FH$4:FH7)) -> 0 | FJ7: =IF(AND($S7="Dwn",$BF7="Short",$E7=FH$2),$P7,"") | FK7: =IF($J7="",#N/A,SUM(FJ$4:FJ7)) -> 0 | FL7: =IF(AND($S7="SW",$BF7="Long",$E7=FH$2),$P7,"") | FM7: =IF($J7="",#N/A,SUM(FL$4:FL7)) -> 0 | FN7: =IF($J7="",#N/A,SUM(FL$4:FL7,FJ$4:FJ7,FH$4:FH7)) -> 0 | FO7: =IF(AND($S7="Up",$BF7="Long",$E7=FO$2),$P7,"") | FP7: =IF($J7="",#N/A,SUM(FO$4:FO7)) -> 0 | FQ7: =IF(AND($S7="Dwn",$BF7="Short",$E7=FO$2),$P7,"") | FR7: =IF($J7="",#N/A,SUM(FQ$4:FQ7)) -> 0 | FS7: =IF(AND($S7="SW",$BF7="Long",$E7=FO$2),$P7,"") | FT7: =IF($J7="",#N/A,SUM(FS$4:FS7)) -> 0 | FU7: =IF($J7="",#N/A,SUM(FS$4:FS7,FQ$4:FQ7,FO$4:FO7)) -> 0 | FV7: =IF(AND($S7="Up",$BF7="Long",$E7=FV$2),$P7,"") | FW7: =IF($J7="",#N/A,SUM(FV$4:FV7)) -> 0 | FX7: =IF(AND($S7="Dwn",$BF7="Short",$E7=FV$2),$P7,"") | FY7: =IF($J7="",#N/A,SUM(FX$4:FX7)) -> 0 | FZ7: =IF(AND($S7="SW",$BF7="Long",$E7=FV$2),$P7,"") | GA7: =IF($J7="",#N/A,SUM(FZ$4:FZ7)) -> 0 | GB7: =IF($J7="",#N/A,SUM(FZ$4:FZ7,FX$4:FX7,FV$4:FV7)) -> 0 | GC7: =IF(AND($S7="Up",$BF7="Long",$E7=GC$2),$P7,"") | GD7: =IF($J7="",#N/A,SUM(GC$4:GC7)) -> 0 | GE7: =IF(AND($S7="Dwn",$BF7="Short",$E7=GC$2),$P7,"") | GF7: =IF($J7="",#N/A,SUM(GE$4:GE7)) -> 0 | GG7: =IF(AND($S7="SW",$BF7="Long",$E7=GC$2),$P7,"") | GH7: =IF($J7="",#N/A,SUM(GG$4:GG7)) -> 0 | GI7: =IF($J7="",#N/A,SUM(GG$4:GG7,GE$4:GE7,GC$4:GC7)) -> 0 | GJ7: =IF(AND($S7="Up",$BF7="Long",$E7=GJ$2),$P7,"") | GK7: =IF($J7="",#N/A,SUM(GJ$4:GJ7)) -> 0 | GL7: =IF(AND($S7="Dwn",$BF7="Short",$E7=GJ$2),$P7,"") | GM7: =IF($J7="",#N/A,SUM(GL$4:GL7)) -> 0 | GN7: =IF(AND($S7="SW",$BF7="Long",$E7=GJ$2),$P7,"") | GO7: =IF($J7="",#N/A,SUM(GN$4:GN7)) -> 0 | GP7: =IF($J7="",#N/A,SUM(GN$4:GN7,GL$4:GL7,GJ$4:GJ7)) -> 0 | GS7: =IF(J7="","",IF(D7="Y",P7,"")) -> -0.41461998 | GT7: =IF(GS7="",NA(),SUM($GS$4:GS7)) -> -0.2729313 | GU7: =IF(AND($S7="Up",$BF7="Long",$D7="Y"),$GS7,"") | GV7: =IF(GU7="",NA(),SUM($GU$4:GU7)) -> #N/A | GW7: =IF(AND($S7="SW",$BF7="Long",$D7="Y"),$GS7,"") -> -0.41461998 | GX7: =IF(GW7="",NA(),SUM($GW$4:GW7)) -> -0.47332868 | GY7: =IF(AND($S7="Dwn",$BF7="Short",$D7="Y"),$GS7,"") | GZ7: =IF(GY7="",NA(),SUM($GY$4:GY7)) -> #N/A | HA7: =IF($J7="","",IF($D7="N",$P7,"")) | HB7: =IF(HA7="",NA(),SUM($HA$4:HA7)) -> #N/A | HC7: =IF(AND($S7="Up",$BF7="Long",$D7="N"),$HA7,"") | HD7: =IF(HC7="",NA(),SUM($HC$4:HC7)) -> #N/A | HE7: =IF(AND($S7="SW",$BF7="Long",$D7="N"),$HA7,"") | HF7: =IF(HE7="",NA(),SUM($HE$4:HE7)) -> #N/A | HG7: =IF(AND($S7="Dwn",$BF7="Short",$D7="N"),$HA7,"") | HH7: =IF(HG7="",NA(),SUM($HG$4:HG7)) -> #N/A | HI7: =IF($AC7="","",IF(AND($S7="Dwn",$K7<0),$HU7-P7,"")) | HJ7: =IF($J7="",#N/A,SUM(HI$4:$HI7)) -> -0.80152672 | HK7: =IF($AC7="","",IF(AND($S7="Dwn",$K7>0),$HU7-$P7,"")) | HL7: =IF($J7="",#N/A,SUM($HK$4:HK7)) -> -3.4652546 | HM7: =IF($AC7="","",IF(AND($S7="Up",$K7>0),$HU7-$P7,"")) | HN7: =IF($J7="",#N/A,SUM($HM$4:HM7)) -> 0 | HO7: =IF($AC7="","",IF(AND($S7="Up",$K7<0),$HU7-$P7,"")) | HP7: =IF($J7="",#N/A,SUM($HO$4:HO7)) -> 0 | HQ7: =IF($AC7="","",IF(AND($S7="SW",$K7>0),$HU7-$P7,"")) | HR7: =IF($J7="",#N/A,SUM($HQ$4:HQ7)) -> 0 | HS7: =IF($AC7="","",IF(AND($S7="SW",$K7<0),$HU7-$P7,"")) -> 0.25616648 | HT7: =IF($J7="",#N/A,SUM($HS$4:HS7)) -> 0.98195281 | HU7: =IF(OR($Y7="",$AC7=""),"",IF($BF7="Long",(($AC7*$Y7)-$X7)/($X7*0.06),($X7-($AC7*$Y7))/($X7*0.06))) -> -0.15845349 | HV7: =IF($J7="",#N/A,SUM(HU$4:$HU7)) -> -3.5577598
A8: BLK | B8: on 4/11/25 Before Market Eastern Stan | C8: =IF(S8="Dwn",2,IF(S8="Up",1,IF(S8="SW",3,"x"))) -> 3 | D8: =_xlfn.XLOOKUP(A8,[1]SP500!$A$2:$A$502,[1]SP500!$D$2:$D$502,"N") -> Y | E8: =IFERROR(_xlfn.XLOOKUP(A8,[1]SP500!$A$2:$A$655,[1]SP500!$B$2:$B$655),"") -> XLF | F8: 45758 | G8: =IF(ISNUMBER(FIND("After",B8,1)),"AMC",IF(ISNUMBER(FIND("Before",B8,1)),"BMO","err")) -> BMO | H8: =IF(AH8="Skip","sk",IF(OR(S8="",V8=""),"",IF(AND(S8="Dwn",V8="Short"),"s",IF(AND(S8="Up",V8="Long"),"s",IF(AND(S8="SW",V8="Long"),"s","o"))))) -> s | I8: 858.78 | J8: 848.17 | K8: =IF(J8="","",(J8-I8)/I8) -> -0.012354736 | L8: =IF(OR($Y8="",J8=""),"",IF($V8="Long",(($J8*$Y8)-$X8),($X8-($J8*$Y8)))) -> -10.61 | M8: =IF(L8="","",IF(AK8="",#N/A,IF(AH8="Open",AK8-L8,#N/A))) -> 0 | N8: =IF(OR($Y8="",L8=""),"",IF($BF8="Long",(($J8*$Y8)-$X8),($X8-($J8*$Y8)))) -> -10.61 | O8: =IF(N8="",#N/A,SUM($N$4:N8)) -> -27.38 | P8: =IF(OR($Y8="",L8=""),"",IF($BF8="Long",(($J8*$Y8)-$X8)/(X8*0.06),($X8-($J8*$Y8))/(X8*0.06))) -> -0.20591226 | Q8: =IF($N8="",#N/A,SUM($P$4:P8)) -> -0.47884356 | R8: =IF(AND(AH8="MOC",AC8=""),#N/A,IFERROR(Q8-AJ8,Q8-0)) -> -0.18977313 | S8: =IF(T8="Down","Dwn",IF(T8="Up","Up",IF(AND(T8="",K8=""),"",IF(AND(K8<0,T8="Yes"),"Dwn",IF(AND(K8>0,T8="Yes"),"Up",IF(AND(K8<0,T8="No"),"Up",IF(AND(K8>0,T8="No"),"Dwn",IF(T8="NA","SW","err")))))))) -> SW | T8: NA | U8: =I8 -> 858.78 | V8: Long | W8: 1 | X8: =IF(W8="","",U8*W8) -> 858.78 | Y8: =IF(W8="","",W8) -> 1 | Z8: 848.17 | AA8: =IF($Z8="","",IF($V8="Long",(($Z8*$Y8)-$X8),($X8-($Z8*$Y8)))) -> -10.61 | AB8: =IF($AC8="","",IF($V8="Long",(($AC8*$Y8)-$X8),($X8-($AC8*$Y8)))) -> 20 | AC8: 878.78 | AD8: =IF(AC8="","",IF(OR($Y8="",CV8=""),"",IF($BF8="Long",(($AC8*$Y8)-$X8),($X8-($AC8*$Y8))))) -> 20 | AE8: =IF(OR($Y8="",$AD8=""),"",IF($BF8="Long",(($AC8*$Y8)-$X8)/($X8*0.06),($X8-($AC8*$Y8))/($X8*0.06))) -> 0.38814753 | AF8: =IF($AC8="",#N/A,SUM(AD$4:AD8)) -> -207.55 | AG8: =IF(OR(AD8="",AC8=""),"",AD8-N8) -> 30.61 | AH8: Open | AI8: =IF(AND(AH8="MOC",AC8=""),"",IF(Z8="","",IF(AH8="Skip",0,IF(AK8=0,0,AK8/(X8*0.06))))) -> -0.20591226 | AJ8: =IF(AI8="",#N/A,SUM($AI$4:AI8)) -> -0.28907043 | AK8: =IF(AH8="","",IF(AH8="Skip","",IF(OR(AH8="open",AH8="Other"),AA8,IF(AH8="MOC",AB8,"Err")))) -> -10.61 | AL8: =IF(AI8="",#N/A,IF(AH8="Skip",SUM($AK$4:AK8),SUM($AK$4:AK8))) -> -15.12 | AM8: =IF(OR($Y8="",$L8=""),"",IF($BF8="Long",(($AC8*$Y8)-$X8)/($X8*0.06),($X8-($AC8*$Y8))/($X8*0.06))) -> 0.38814753 | AO8: =IF(AND($S8="SW",$BF8="Long"),$HU8,"") -> 0.38814753 | AP8: =IF($AC8="",#N/A,SUM(AO$4:AO8)) -> 0.89677166 | AQ8: =IF(AND($S8="UP",$BF8="Long"),$HU8,"") | AR8: =IF($AC8="",#N/A,SUM(AQ$4:AQ8)) -> 0 | AS8: =IF(AND($S8="Dwn",$BF8="Short"),$HU8,"") | AT8: =IF($AC8="",#N/A,SUM(AS$4:AS8)) -> -4.0663839 | AU8: =IF(AND(S8="SW",BF8="Long"),$AD8,"") -> 20 | AV8: =IF($AC8="",#N/A,SUM(AU$4:AU8)) -> 55.25 | AW8: =IF(AND(S8="UP",BF8="Long"),$AD8,"") | AX8: =IF($AC8="",#N/A,SUM(AW$4:AW8)) -> 0 | AY8: =IF(AND(S8="Dwn",BF8="Short"),$AD8,"") | AZ8: =IF($AC8="",#N/A,SUM(AY$4:AY8)) -> -262.8 | BA8: =IF(AD8="",#N/A,SUM($AD$4:AD8)) -> -207.55 | BC8: =IF(K8="","",IF(AND(K8>0,T8="Yes"),1,"")) | BD8: =IF(K8="","",IF(AND($K8>0,$T8="No"),1,"")) | BE8: =IF(K8="","",IF(AND($K8>0,$T8="NA"),1,"")) | BF8: =IF(S8="Dwn","Short","Long") -> Long | BG8: =IF(K8="","",IF(AND($K8<0,$T8="Yes"),1,"")) | BH8: =IF(K8="","",IF(AND($K8<0,$T8="No"),1,"")) | BI8: =IF(K8="","",IF(AND($K8<0,$T8="NA"),1,"")) -> 1 | BO8: =IF(J8="",#N/A,IF(S8="SW",(COUNTIFS(K$4:$K8,">0",S$4:$S8,"SW")/COUNTIF(S$4:$S8,"SW")),#N/A)) -> 0 | BP8: =IF($J8="",#N/A,IF($S8="DWN",(COUNTIFS($K$4:$K8,"<0",$S$4:$S8,"DWN")/COUNTIF($S$4:$S8,"DWN")),#N/A)) -> #N/A | BQ8: =IF($J8="",#N/A,IF($S8="UP",(COUNTIFS($K$4:$K8,">0",$S$4:$S8,"UP")/COUNTIF($S$4:$S8,"UP")),#N/A)) -> #N/A | BR8: =IF(J8="",#N/A,COUNTIF($K$4:K8,">0")/COUNT($J$4:J8)) -> 0.2 | BS8: =IF($AH8="Skip","",IF($J8="","",IF(AND($V8="Long",$L8>0),$P8,""))) | BT8: =IF($AH8="Skip","",IF($J8="","",IF(AND($V8="Long",$L8<0),$P8,""))) -> -0.20591226 | BU8: =IF($AH8="Skip","",IF($J8="","",IF(AND($V8="Short",$L8>0),$P8,""))) | BV8: =IF($AH8="Skip","",IF($J8="","",IF(AND($V8="Short",$L8<0),$P8,""))) | BW8: =IF(AND($S8="Up",$BF8="Long"),$N8,"") | BX8: =IF($J8="",#N/A,SUM($BW$4:BW8)) -> 0 | BY8: =IF(AND($S8="Dwn",$BF8="Short"),$N8,"") | BZ8: =IF($J8="",#N/A,SUM($BY$4:BY8)) -> 13.92 | CA8: =IF(AND($S8="SW",$BF8="Long"),$N8,"") -> -10.61 | CB8: =IF($J8="",#N/A,SUM($CA$4:CA8)) -> -41.3 | CC8: =IF(AND($S8="Up",$BF8="Long"),$P8,"") | CD8: =IF($J8="",#N/A,SUM($CC$4:CC8)) -> 0 | CE8: =IF(AND($S8="Dwn",$BF8="Short"),$P8,"") | CF8: =IF($J8="",#N/A,SUM($CE$4:CE8)) -> 0.20039738 | CG8: =IF(AND($S8="SW",$BF8="Long"),$P8,"") -> -0.20591226 | CH8: =IF($J8="",#N/A,SUM($CG$4:CG8)) -> -0.67924094 | CI8: =IF(AND($S8="Up",$BF8="Long",$E8=CI$2),$P8,"") | CJ8: =IF($J8="",#N/A,SUM(CI$4:CI8)) -> 0 | CK8: =IF(AND($S8="Dwn",$BF8="Short",$E8=CI$2),$P8,"") | CL8: =IF($J8="",#N/A,SUM(CK$4:CK8)) -> 0 | CM8: =IF(AND($S8="SW",$BF8="Long",$E8=CI$2),$P8,"") | CN8: =IF($J8="",#N/A,SUM(CM$4:CM8)) -> 0 | CO8: =IF($J8="",#N/A,SUM(CM$4:CM8,CK$4:CK8,CI$4:CI8)) -> 0 | CP8: =IF(AND($S8="Up",$BF8="Long",$E8=CP$2),$P8,"") | CQ8: =IF($J8="",#N/A,SUM(CP$4:CP8)) -> 0 | CR8: =IF(AND($S8="Dwn",$BF8="Short",$E8=CP$2),$P8,"") | CS8: =IF($J8="",#N/A,SUM(CR$4:CR8)) -> 0 | CT8: =IF(AND($S8="SW",$BF8="Long",$E8=CP$2),$P8,"") | CU8: =IF($J8="",#N/A,SUM(CT$4:CT8)) -> 0 | CV8: =IF($J8="",#N/A,SUM(CT$4:CT8,CR$4:CR8,CP$4:CP8)) -> 0 | CW8: =IF(AND($S8="Up",$BF8="Long",$E8=CW$2),$P8,"") | CX8: =IF($J8="",#N/A,SUM(CW$4:CW8)) -> 0 | CY8: =IF(AND($S8="Dwn",$BF8="Short",$E8=CW$2),$P8,"") | CZ8: =IF($J8="",#N/A,SUM(CY$4:CY8)) -> 0 | DA8: =IF(AND($S8="SW",$BF8="Long",$E8=CW$2),$P8,"") | DB8: =IF($J8="",#N/A,SUM(DA$4:DA8)) -> 0 | DC8: =IF($J8="",#N/A,SUM(DA$4:DA8,CY$4:CY8,CW$4:CW8)) -> 0 | DD8: =IF(AND($S8="Up",$BF8="Long",$E8=DD$2),$P8,"") | DE8: =IF($J8="",#N/A,SUM(DD$4:DD8)) -> 0 | DF8: =IF(AND($S8="Dwn",$BF8="Short",$E8=DD$2),$P8,"") | DG8: =IF($J8="",#N/A,SUM(DF$4:DF8)) -> 0.67884406 | DH8: =IF(AND($S8="SW",$BF8="Long",$E8=DD$2),$P8,"") | DI8: =IF($J8="",#N/A,SUM(DH$4:DH8)) -> 0 | DJ8: =IF($J8="",#N/A,SUM(DH$4:DH8,DF$4:DF8,DD$4:DD8)) -> 0.67884406 | DK8: =IF(AND($S8="Up",$BF8="Long",$E8=DK$2),$P8,"") | DL8: =IF($J8="",#N/A,SUM(DK$4:DK8)) -> 0 | DM8: =IF(AND($S8="Dwn",$BF8="Short",$E8=DK$2),$P8,"") | DN8: =IF($J8="",#N/A,SUM(DM$4:DM8)) -> 0 | DO8: =IF(AND($S8="SW",$BF8="Long",$E8=DK$2),$P8,"") | DP8: =IF($J8="",#N/A,SUM(DO$4:DO8)) -> 0 | DQ8: =IF($J8="",#N/A,SUM(DO$4:DO8,DM$4:DM8,DK$4:DK8)) -> 0 | DR8: =IF(AND($S8="Up",$BF8="Long",$E8=DR$2),$P8,"") | DS8: =IF($J8="",#N/A,SUM(DR$4:DR8)) -> 0 | DT8: =IF(AND($S8="Dwn",$BF8="Short",$E8=DR$2),$P8,"") | DU8: =IF($J8="",#N/A,SUM(DT$4:DT8)) -> 0 | DV8: =IF(AND($S8="SW",$BF8="Long",$E8=DR$2),$P8,"") -> -0.20591226 | DW8: =IF($J8="",#N/A,SUM(DV$4:DV8)) -> -0.67924094 | DX8: =IF($J8="",#N/A,SUM(DV$4:DV8,DT$4:DT8,DR$4:DR8)) -> -0.67924094 | DY8: =IF(AND($S8="Up",$BF8="Long",$E8=DY$2),$P8,"") | DZ8: =IF($J8="",#N/A,SUM(DY$4:DY8)) -> 0 | EA8: =IF(AND($S8="Dwn",$BF8="Short",$E8=DY$2),$P8,"") | EB8: =IF($J8="",#N/A,SUM(EA$4:EA8)) -> -0.47844667 | EC8: =IF(AND($S8="SW",$BF8="Long",$E8=DY$2),$P8,"") | ED8: =IF($J8="",#N/A,SUM(EC$4:EC8)) -> 0 | EE8: =IF($J8="",#N/A,SUM(EC$4:EC8,EA$4:EA8,DY$4:DY8)) -> -0.47844667 | EF8: =IF(AND($S8="Up",$BF8="Long",$E8=EF$2),$P8,"") | EG8: =IF($J8="",#N/A,SUM(EF$4:EF8)) -> 0 | EH8: =IF(AND($S8="Dwn",$BF8="Short",$E8=EF$2),$P8,"") | EI8: =IF($J8="",#N/A,SUM(EH$4:EH8)) -> 0 | EJ8: =IF(AND($S8="SW",$BF8="Long",$E8=EF$2),$P8,"") | EK8: =IF($J8="",#N/A,SUM(EJ$4:EJ8)) -> 0 | EL8: =IF($J8="",#N/A,SUM(EJ$4:EJ8,EH$4:EH8,EF$4:EF8)) -> 0 | EM8: =IF(AND($S8="Up",$BF8="Long",$E8=EM$2),$P8,"") | EN8: =IF($J8="",#N/A,SUM(EM$4:EM8)) -> 0 | EO8: =IF(AND($S8="Dwn",$BF8="Short",$E8=EM$2),$P8,"") | EP8: =IF($J8="",#N/A,SUM(EO$4:EO8)) -> 0 | EQ8: =IF(AND($S8="SW",$BF8="Long",$E8=EM$2),$P8,"") | ER8: =IF($J8="",#N/A,SUM(EQ$4:EQ8)) -> 0 | ES8: =IF($J8="",#N/A,SUM(EQ$4:EQ8,EO$4:EO8,EM$4:EM8)) -> 0 | ET8: =IF(AND($S8="Up",$BF8="Long",$E8=ET$2),$P8,"") | EU8: =IF($J8="",#N/A,SUM(ET$4:ET8)) -> 0 | EV8: =IF(AND($S8="Dwn",$BF8="Short",$E8=ET$2),$P8,"") | EW8: =IF($J8="",#N/A,SUM(EV$4:EV8)) -> 0 | EX8: =IF(AND($S8="SW",$BF8="Long",$E8=ET$2),$P8,"") | EY8: =IF($J8="",#N/A,SUM(EX$4:EX8)) -> 0 | EZ8: =IF($J8="",#N/A,SUM(EX$4:EX8,EV$4:EV8,ET$4:ET8)) -> 0 | FA8: =IF(AND($S8="Up",$BF8="Long",$E8=FA$2),$P8,"") | FB8: =IF($J8="",#N/A,SUM(FA$4:FA8)) -> 0 | FC8: =IF(AND($S8="Dwn",$BF8="Short",$E8=FA$2),$P8,"") | FD8: =IF($J8="",#N/A,SUM(FC$4:FC8)) -> 0 | FE8: =IF(AND($S8="SW",$BF8="Long",$E8=FA$2),$P8,"") | FF8: =IF($J8="",#N/A,SUM(FE$4:FE8)) -> 0 | FG8: =IF($J8="",#N/A,SUM(FE$4:FE8,FC$4:FC8,FA$4:FA8)) -> 0 | FH8: =IF(AND($S8="Up",$BF8="Long",$E8=FH$2),$P8,"") | FI8: =IF($J8="",#N/A,SUM(FH$4:FH8)) -> 0 | FJ8: =IF(AND($S8="Dwn",$BF8="Short",$E8=FH$2),$P8,"") | FK8: =IF($J8="",#N/A,SUM(FJ$4:FJ8)) -> 0 | FL8: =IF(AND($S8="SW",$BF8="Long",$E8=FH$2),$P8,"") | FM8: =IF($J8="",#N/A,SUM(FL$4:FL8)) -> 0 | FN8: =IF($J8="",#N/A,SUM(FL$4:FL8,FJ$4:FJ8,FH$4:FH8)) -> 0 | FO8: =IF(AND($S8="Up",$BF8="Long",$E8=FO$2),$P8,"") | FP8: =IF($J8="",#N/A,SUM(FO$4:FO8)) -> 0 | FQ8: =IF(AND($S8="Dwn",$BF8="Short",$E8=FO$2),$P8,"") | FR8: =IF($J8="",#N/A,SUM(FQ$4:FQ8)) -> 0 | FS8: =IF(AND($S8="SW",$BF8="Long",$E8=FO$2),$P8,"") | FT8: =IF($J8="",#N/A,SUM(FS$4:FS8)) -> 0 | FU8: =IF($J8="",#N/A,SUM(FS$4:FS8,FQ$4:FQ8,FO$4:FO8)) -> 0 | FV8: =IF(AND($S8="Up",$BF8="Long",$E8=FV$2),$P8,"") | FW8: =IF($J8="",#N/A,SUM(FV$4:FV8)) -> 0 | FX8: =IF(AND($S8="Dwn",$BF8="Short",$E8=FV$2),$P8,"") | FY8: =IF($J8="",#N/A,SUM(FX$4:FX8)) -> 0 | FZ8: =IF(AND($S8="SW",$BF8="Long",$E8=FV$2),$P8,"") | GA8: =IF($J8="",#N/A,SUM(FZ$4:FZ8)) -> 0 | GB8: =IF($J8="",#N/A,SUM(FZ$4:FZ8,FX$4:FX8,FV$4:FV8)) -> 0 | GC8: =IF(AND($S8="Up",$BF8="Long",$E8=GC$2),$P8,"") | GD8: =IF($J8="",#N/A,SUM(GC$4:GC8)) -> 0 | GE8: =IF(AND($S8="Dwn",$BF8="Short",$E8=GC$2),$P8,"") | GF8: =IF($J8="",#N/A,SUM(GE$4:GE8)) -> 0 | GG8: =IF(AND($S8="SW",$BF8="Long",$E8=GC$2),$P8,"") | GH8: =IF($J8="",#N/A,SUM(GG$4:GG8)) -> 0 | GI8: =IF($J8="",#N/A,SUM(GG$4:GG8,GE$4:GE8,GC$4:GC8)) -> 0 | GJ8: =IF(AND($S8="Up",$BF8="Long",$E8=GJ$2),$P8,"") | GK8: =IF($J8="",#N/A,SUM(GJ$4:GJ8)) -> 0 | GL8: =IF(AND($S8="Dwn",$BF8="Short",$E8=GJ$2),$P8,"") | GM8: =IF($J8="",#N/A,SUM(GL$4:GL8)) -> 0 | GN8: =IF(AND($S8="SW",$BF8="Long",$E8=GJ$2),$P8,"") | GO8: =IF($J8="",#N/A,SUM(GN$4:GN8)) -> 0 | GP8: =IF($J8="",#N/A,SUM(GN$4:GN8,GL$4:GL8,GJ$4:GJ8)) -> 0 | GS8: =IF(J8="","",IF(D8="Y",P8,"")) -> -0.20591226 | GT8: =IF(GS8="",NA(),SUM($GS$4:GS8)) -> -0.47884356 | GU8: =IF(AND($S8="Up",$BF8="Long",$D8="Y"),$GS8,"") | GV8: =IF(GU8="",NA(),SUM($GU$4:GU8)) -> #N/A | GW8: =IF(AND($S8="SW",$BF8="Long",$D8="Y"),$GS8,"") -> -0.20591226 | GX8: =IF(GW8="",NA(),SUM($GW$4:GW8)) -> -0.67924094 | GY8: =IF(AND($S8="Dwn",$BF8="Short",$D8="Y"),$GS8,"") | GZ8: =IF(GY8="",NA(),SUM($GY$4:GY8)) -> #N/A | HA8: =IF($J8="","",IF($D8="N",$P8,"")) | HB8: =IF(HA8="",NA(),SUM($HA$4:HA8)) -> #N/A | HC8: =IF(AND($S8="Up",$BF8="Long",$D8="N"),$HA8,"") | HD8: =IF(HC8="",NA(),SUM($HC$4:HC8)) -> #N/A | HE8: =IF(AND($S8="SW",$BF8="Long",$D8="N"),$HA8,"") | HF8: =IF(HE8="",NA(),SUM($HE$4:HE8)) -> #N/A | HG8: =IF(AND($S8="Dwn",$BF8="Short",$D8="N"),$HA8,"") | HH8: =IF(HG8="",NA(),SUM($HG$4:HG8)) -> #N/A | HI8: =IF($AC8="","",IF(AND($S8="Dwn",$K8<0),$HU8-P8,"")) | HJ8: =IF($J8="",#N/A,SUM(HI$4:$HI8)) -> -0.80152672 | HK8: =IF($AC8="","",IF(AND($S8="Dwn",$K8>0),$HU8-$P8,"")) | HL8: =IF($J8="",#N/A,SUM($HK$4:HK8)) -> -3.4652546 | HM8: =IF($AC8="","",IF(AND($S8="Up",$K8>0),$HU8-$P8,"")) | HN8: =IF($J8="",#N/A,SUM($HM$4:HM8)) -> 0 | HO8: =IF($AC8="","",IF(AND($S8="Up",$K8<0),$HU8-$P8,"")) | HP8: =IF($J8="",#N/A,SUM($HO$4:HO8)) -> 0 | HQ8: =IF($AC8="","",IF(AND($S8="SW",$K8>0),$HU8-$P8,"")) | HR8: =IF($J8="",#N/A,SUM($HQ$4:HQ8)) -> 0 | HS8: =IF($AC8="","",IF(AND($S8="SW",$K8<0),$HU8-$P8,"")) -> 0.59405979 | HT8: =IF($J8="",#N/A,SUM($HS$4:HS8)) -> 1.5760126 | HU8: =IF(OR($Y8="",$AC8=""),"",IF($BF8="Long",(($AC8*$Y8)-$X8)/($X8*0.06),($X8-($AC8*$Y8))/($X8*0.06))) -> 0.38814753 | HV8: =IF($J8="",#N/A,SUM(HU$4:$HU8)) -> -3.1696122
A9: BK | B9: on 4/11/25 Before Market Eastern Stan | C9: =IF(S9="Dwn",2,IF(S9="Up",1,IF(S9="SW",3,"x"))) -> 3 | D9: =_xlfn.XLOOKUP(A9,[1]SP500!$A$2:$A$502,[1]SP500!$D$2:$D$502,"N") -> Y | E9: =IFERROR(_xlfn.XLOOKUP(A9,[1]SP500!$A$2:$A$655,[1]SP500!$B$2:$B$655),"") -> XLF | F9: 45758 | G9: =IF(ISNUMBER(FIND("After",B9,1)),"AMC",IF(ISNUMBER(FIND("Before",B9,1)),"BMO","err")) -> BMO | H9: =IF(AH9="Skip","sk",IF(OR(S9="",V9=""),"",IF(AND(S9="Dwn",V9="Short"),"s",IF(AND(S9="Up",V9="Long"),"s",IF(AND(S9="SW",V9="Long"),"s","o"))))) -> s | I9: 76.61 | J9: 73.61 | K9: =IF(J9="","",(J9-I9)/I9) -> -0.039159379 | L9: =IF(OR($Y9="",J9=""),"",IF($V9="Long",(($J9*$Y9)-$X9),($X9-($J9*$Y9)))) -> -42 | M9: =IF(L9="","",IF(AK9="",#N/A,IF(AH9="Open",AK9-L9,#N/A))) -> 0 | N9: =IF(OR($Y9="",L9=""),"",IF($BF9="Long",(($J9*$Y9)-$X9),($X9-($J9*$Y9)))) -> -42 | O9: =IF(N9="",#N/A,SUM($N$4:N9)) -> -69.38 | P9: =IF(OR($Y9="",L9=""),"",IF($BF9="Long",(($J9*$Y9)-$X9)/(X9*0.06),($X9-($J9*$Y9))/(X9*0.06))) -> -0.65265631 | Q9: =IF($N9="",#N/A,SUM($P$4:P9)) -> -1.1314999 | R9: =IF(AND(AH9="MOC",AC9=""),#N/A,IFERROR(Q9-AJ9,Q9-0)) -> -0.18977313 | S9: =IF(T9="Down","Dwn",IF(T9="Up","Up",IF(AND(T9="",K9=""),"",IF(AND(K9<0,T9="Yes"),"Dwn",IF(AND(K9>0,T9="Yes"),"Up",IF(AND(K9<0,T9="No"),"Up",IF(AND(K9>0,T9="No"),"Dwn",IF(T9="NA","SW","err")))))))) -> SW | T9: NA | U9: =I9 -> 76.61 | V9: Long | W9: 14 | X9: =IF(W9="","",U9*W9) -> 1072.54 | Y9: =IF(W9="","",W9) -> 14 | Z9: 73.61 | AA9: =IF($Z9="","",IF($V9="Long",(($Z9*$Y9)-$X9),($X9-($Z9*$Y9)))) -> -42 | AB9: =IF($AC9="","",IF($V9="Long",(($AC9*$Y9)-$X9),($X9-($AC9*$Y9)))) -> 14.84 | AC9: 77.67 | AD9: =IF(AC9="","",IF(OR($Y9="",CV9=""),"",IF($BF9="Long",(($AC9*$Y9)-$X9),($X9-($AC9*$Y9))))) -> 14.84 | AE9: =IF(OR($Y9="",$AD9=""),"",IF($BF9="Long",(($AC9*$Y9)-$X9)/($X9*0.06),($X9-($AC9*$Y9))/($X9*0.06))) -> 0.23060523 | AF9: =IF($AC9="",#N/A,SUM(AD$4:AD9)) -> -192.71 | AG9: =IF(OR(AD9="",AC9=""),"",AD9-N9) -> 56.84 | AH9: Open | AI9: =IF(AND(AH9="MOC",AC9=""),"",IF(Z9="","",IF(AH9="Skip",0,IF(AK9=0,0,AK9/(X9*0.06))))) -> -0.65265631 | AJ9: =IF(AI9="",#N/A,SUM($AI$4:AI9)) -> -0.94172674 | AK9: =IF(AH9="","",IF(AH9="Skip","",IF(OR(AH9="open",AH9="Other"),AA9,IF(AH9="MOC",AB9,"Err")))) -> -42 | AL9: =IF(AI9="",#N/A,IF(AH9="Skip",SUM($AK$4:AK9),SUM($AK$4:AK9))) -> -57.12 | AM9: =IF(OR($Y9="",$L9=""),"",IF($BF9="Long",(($AC9*$Y9)-$X9)/($X9*0.06),($X9-($AC9*$Y9))/($X9*0.06))) -> 0.23060523 | AO9: =IF(AND($S9="SW",$BF9="Long"),$HU9,"") -> 0.23060523 | AP9: =IF($AC9="",#N/A,SUM(AO$4:AO9)) -> 1.1273769 | AQ9: =IF(AND($S9="UP",$BF9="Long"),$HU9,"") | AR9: =IF($AC9="",#N/A,SUM(AQ$4:AQ9)) -> 0 | AS9: =IF(AND($S9="Dwn",$BF9="Short"),$HU9,"") | AT9: =IF($AC9="",#N/A,SUM(AS$4:AS9)) -> -4.0663839 | AU9: =IF(AND(S9="SW",BF9="Long"),$AD9,"") -> 14.84 | AV9: =IF($AC9="",#N/A,SUM(AU$4:AU9)) -> 70.09 | AW9: =IF(AND(S9="UP",BF9="Long"),$AD9,"") | AX9: =IF($AC9="",#N/A,SUM(AW$4:AW9)) -> 0 | AY9: =IF(AND(S9="Dwn",BF9="Short"),$AD9,"") | AZ9: =IF($AC9="",#N/A,SUM(AY$4:AY9)) -> -262.8 | BA9: =IF(AD9="",#N/A,SUM($AD$4:AD9)) -> -192.71 | BC9: =IF(K9="","",IF(AND(K9>0,T9="Yes"),1,"")) | BD9: =IF(K9="","",IF(AND($K9>0,$T9="No"),1,"")) | BE9: =IF(K9="","",IF(AND($K9>0,$T9="NA"),1,"")) | BF9: =IF(S9="Dwn","Short","Long") -> Long | BG9: =IF(K9="","",IF(AND($K9<0,$T9="Yes"),1,"")) | BH9: =IF(K9="","",IF(AND($K9<0,$T9="No"),1,"")) | BI9: =IF(K9="","",IF(AND($K9<0,$T9="NA"),1,"")) -> 1 | BO9: =IF(J9="",#N/A,IF(S9="SW",(COUNTIFS(K$4:$K9,">0",S$4:$S9,"SW")/COUNTIF(S$4:$S9,"SW")),#N/A)) -> 0 | BP9: =IF($J9="",#N/A,IF($S9="DWN",(COUNTIFS($K$4:$K9,"<0",$S$4:$S9,"DWN")/COUNTIF($S$4:$S9,"DWN")),#N/A)) -> #N/A | BQ9: =IF($J9="",#N/A,IF($S9="UP",(COUNTIFS($K$4:$K9,">0",$S$4:$S9,"UP")/COUNTIF($S$4:$S9,"UP")),#N/A)) -> #N/A | BR9: =IF(J9="",#N/A,COUNTIF($K$4:K9,">0")/COUNT($J$4:J9)) -> 0.16666667 | BS9: =IF($AH9="Skip","",IF($J9="","",IF(AND($V9="Long",$L9>0),$P9,""))) | BT9: =IF($AH9="Skip","",IF($J9="","",IF(AND($V9="Long",$L9<0),$P9,""))) -> -0.65265631 | BU9: =IF($AH9="Skip","",IF($J9="","",IF(AND($V9="Short",$L9>0),$P9,""))) | BV9: =IF($AH9="Skip","",IF($J9="","",IF(AND($V9="Short",$L9<0),$P9,""))) | BW9: =IF(AND($S9="Up",$BF9="Long"),$N9,"") | BX9: =IF($J9="",#N/A,SUM($BW$4:BW9)) -> 0 | BY9: =IF(AND($S9="Dwn",$BF9="Short"),$N9,"") | BZ9: =IF($J9="",#N/A,SUM($BY$4:BY9)) -> 13.92 | CA9: =IF(AND($S9="SW",$BF9="Long"),$N9,"") -> -42 | CB9: =IF($J9="",#N/A,SUM($CA$4:CA9)) -> -83.3 | CC9: =IF(AND($S9="Up",$BF9="Long"),$P9,"") | CD9: =IF($J9="",#N/A,SUM($CC$4:CC9)) -> 0 | CE9: =IF(AND($S9="Dwn",$BF9="Short"),$P9,"") | CF9: =IF($J9="",#N/A,SUM($CE$4:CE9)) -> 0.20039738 | CG9: =IF(AND($S9="SW",$BF9="Long"),$P9,"") -> -0.65265631 | CH9: =IF($J9="",#N/A,SUM($CG$4:CG9)) -> -1.3318973 | CI9: =IF(AND($S9="Up",$BF9="Long",$E9=CI$2),$P9,"") | CJ9: =IF($J9="",#N/A,SUM(CI$4:CI9)) -> 0 | CK9: =IF(AND($S9="Dwn",$BF9="Short",$E9=CI$2),$P9,"") | CL9: =IF($J9="",#N/A,SUM(CK$4:CK9)) -> 0 | CM9: =IF(AND($S9="SW",$BF9="Long",$E9=CI$2),$P9,"") | CN9: =IF($J9="",#N/A,SUM(CM$4:CM9)) -> 0 | CO9: =IF($J9="",#N/A,SUM(CM$4:CM9,CK$4:CK9,CI$4:CI9)) -> 0 | CP9: =IF(AND($S9="Up",$BF9="Long",$E9=CP$2),$P9,"") | CQ9: =IF($J9="",#N/A,SUM(CP$4:CP9)) -> 0 | CR9: =IF(AND($S9="Dwn",$BF9="Short",$E9=CP$2),$P9,"") | CS9: =IF($J9="",#N/A,SUM(CR$4:CR9)) -> 0 | CT9: =IF(AND($S9="SW",$BF9="Long",$E9=CP$2),$P9,"") | CU9: =IF($J9="",#N/A,SUM(CT$4:CT9)) -> 0 | CV9: =IF($J9="",#N/A,SUM(CT$4:CT9,CR$4:CR9,CP$4:CP9)) -> 0 | CW9: =IF(AND($S9="Up",$BF9="Long",$E9=CW$2),$P9,"") | CX9: =IF($J9="",#N/A,SUM(CW$4:CW9)) -> 0 | CY9: =IF(AND($S9="Dwn",$BF9="Short",$E9=CW$2),$P9,"") | CZ9: =IF($J9="",#N/A,SUM(CY$4:CY9)) -> 0 | DA9: =IF(AND($S9="SW",$BF9="Long",$E9=CW$2),$P9,"") | DB9: =IF($J9="",#N/A,SUM(DA$4:DA9)) -> 0 | DC9: =IF($J9="",#N/A,SUM(DA$4:DA9,CY$4:CY9,CW$4:CW9)) -> 0 | DD9: =IF(AND($S9="Up",$BF9="Long",$E9=DD$2),$P9,"") | DE9: =IF($J9="",#N/A,SUM(DD$4:DD9)) -> 0 | DF9: =IF(AND($S9="Dwn",$BF9="Short",$E9=DD$2),$P9,"") | DG9: =IF($J9="",#N/A,SUM(DF$4:DF9)) -> 0.67884406 | DH9: =IF(AND($S9="SW",$BF9="Long",$E9=DD$2),$P9,"") | DI9: =IF($J9="",#N/A,SUM(DH$4:DH9)) -> 0 | DJ9: =IF($J9="",#N/A,SUM(DH$4:DH9,DF$4:DF9,DD$4:DD9)) -> 0.67884406 | DK9: =IF(AND($S9="Up",$BF9="Long",$E9=DK$2),$P9,"") | DL9: =IF($J9="",#N/A,SUM(DK$4:DK9)) -> 0 | DM9: =IF(AND($S9="Dwn",$BF9="Short",$E9=DK$2),$P9,"") | DN9: =IF($J9="",#N/A,SUM(DM$4:DM9)) -> 0 | DO9: =IF(AND($S9="SW",$BF9="Long",$E9=DK$2),$P9,"") | DP9: =IF($J9="",#N/A,SUM(DO$4:DO9)) -> 0 | DQ9: =IF($J9="",#N/A,SUM(DO$4:DO9,DM$4:DM9,DK$4:DK9)) -> 0 | DR9: =IF(AND($S9="Up",$BF9="Long",$E9=DR$2),$P9,"") | DS9: =IF($J9="",#N/A,SUM(DR$4:DR9)) -> 0 | DT9: =IF(AND($S9="Dwn",$BF9="Short",$E9=DR$2),$P9,"") | DU9: =IF($J9="",#N/A,SUM(DT$4:DT9)) -> 0 | DV9: =IF(AND($S9="SW",$BF9="Long",$E9=DR$2),$P9,"") -> -0.65265631 | DW9: =IF($J9="",#N/A,SUM(DV$4:DV9)) -> -1.3318973 | DX9: =IF($J9="",#N/A,SUM(DV$4:DV9,DT$4:DT9,DR$4:DR9)) -> -1.3318973 | DY9: =IF(AND($S9="Up",$BF9="Long",$E9=DY$2),$P9,"") | DZ9: =IF($J9="",#N/A,SUM(DY$4:DY9)) -> 0 | EA9: =IF(AND($S9="Dwn",$BF9="Short",$E9=DY$2),$P9,"") | EB9: =IF($J9="",#N/A,SUM(EA$4:EA9)) -> -0.47844667 | EC9: =IF(AND($S9="SW",$BF9="Long",$E9=DY$2),$P9,"") | ED9: =IF($J9="",#N/A,SUM(EC$4:EC9)) -> 0 | EE9: =IF($J9="",#N/A,SUM(EC$4:EC9,EA$4:EA9,DY$4:DY9)) -> -0.47844667 | EF9: =IF(AND($S9="Up",$BF9="Long",$E9=EF$2),$P9,"") | EG9: =IF($J9="",#N/A,SUM(EF$4:EF9)) -> 0 | EH9: =IF(AND($S9="Dwn",$BF9="Short",$E9=EF$2),$P9,"") | EI9: =IF($J9="",#N/A,SUM(EH$4:EH9)) -> 0 | EJ9: =IF(AND($S9="SW",$BF9="Long",$E9=EF$2),$P9,"") | EK9: =IF($J9="",#N/A,SUM(EJ$4:EJ9)) -> 0 | EL9: =IF($J9="",#N/A,SUM(EJ$4:EJ9,EH$4:EH9,EF$4:EF9)) -> 0 | EM9: =IF(AND($S9="Up",$BF9="Long",$E9=EM$2),$P9,"") | EN9: =IF($J9="",#N/A,SUM(EM$4:EM9)) -> 0 | EO9: =IF(AND($S9="Dwn",$BF9="Short",$E9=EM$2),$P9,"") | EP9: =IF($J9="",#N/A,SUM(EO$4:EO9)) -> 0 | EQ9: =IF(AND($S9="SW",$BF9="Long",$E9=EM$2),$P9,"") | ER9: =IF($J9="",#N/A,SUM(EQ$4:EQ9)) -> 0 | ES9: =IF($J9="",#N/A,SUM(EQ$4:EQ9,EO$4:EO9,EM$4:EM9)) -> 0 | ET9: =IF(AND($S9="Up",$BF9="Long",$E9=ET$2),$P9,"") | EU9: =IF($J9="",#N/A,SUM(ET$4:ET9)) -> 0 | EV9: =IF(AND($S9="Dwn",$BF9="Short",$E9=ET$2),$P9,"") | EW9: =IF($J9="",#N/A,SUM(EV$4:EV9)) -> 0 | EX9: =IF(AND($S9="SW",$BF9="Long",$E9=ET$2),$P9,"") | EY9: =IF($J9="",#N/A,SUM(EX$4:EX9)) -> 0 | EZ9: =IF($J9="",#N/A,SUM(EX$4:EX9,EV$4:EV9,ET$4:ET9)) -> 0 | FA9: =IF(AND($S9="Up",$BF9="Long",$E9=FA$2),$P9,"") | FB9: =IF($J9="",#N/A,SUM(FA$4:FA9)) -> 0 | FC9: =IF(AND($S9="Dwn",$BF9="Short",$E9=FA$2),$P9,"") | FD9: =IF($J9="",#N/A,SUM(FC$4:FC9)) -> 0 | FE9: =IF(AND($S9="SW",$BF9="Long",$E9=FA$2),$P9,"") | FF9: =IF($J9="",#N/A,SUM(FE$4:FE9)) -> 0 | FG9: =IF($J9="",#N/A,SUM(FE$4:FE9,FC$4:FC9,FA$4:FA9)) -> 0 | FH9: =IF(AND($S9="Up",$BF9="Long",$E9=FH$2),$P9,"") | FI9: =IF($J9="",#N/A,SUM(FH$4:FH9)) -> 0 | FJ9: =IF(AND($S9="Dwn",$BF9="Short",$E9=FH$2),$P9,"") | FK9: =IF($J9="",#N/A,SUM(FJ$4:FJ9)) -> 0 | FL9: =IF(AND($S9="SW",$BF9="Long",$E9=FH$2),$P9,"") | FM9: =IF($J9="",#N/A,SUM(FL$4:FL9)) -> 0 | FN9: =IF($J9="",#N/A,SUM(FL$4:FL9,FJ$4:FJ9,FH$4:FH9)) -> 0 | FO9: =IF(AND($S9="Up",$BF9="Long",$E9=FO$2),$P9,"") | FP9: =IF($J9="",#N/A,SUM(FO$4:FO9)) -> 0 | FQ9: =IF(AND($S9="Dwn",$BF9="Short",$E9=FO$2),$P9,"") | FR9: =IF($J9="",#N/A,SUM(FQ$4:FQ9)) -> 0 | FS9: =IF(AND($S9="SW",$BF9="Long",$E9=FO$2),$P9,"") | FT9: =IF($J9="",#N/A,SUM(FS$4:FS9)) -> 0 | FU9: =IF($J9="",#N/A,SUM(FS$4:FS9,FQ$4:FQ9,FO$4:FO9)) -> 0 | FV9: =IF(AND($S9="Up",$BF9="Long",$E9=FV$2),$P9,"") | FW9: =IF($J9="",#N/A,SUM(FV$4:FV9)) -> 0 | FX9: =IF(AND($S9="Dwn",$BF9="Short",$E9=FV$2),$P9,"") | FY9: =IF($J9="",#N/A,SUM(FX$4:FX9)) -> 0 | FZ9: =IF(AND($S9="SW",$BF9="Long",$E9=FV$2),$P9,"") | GA9: =IF($J9="",#N/A,SUM(FZ$4:FZ9)) -> 0 | GB9: =IF($J9="",#N/A,SUM(FZ$4:FZ9,FX$4:FX9,FV$4:FV9)) -> 0 | GC9: =IF(AND($S9="Up",$BF9="Long",$E9=GC$2),$P9,"") | GD9: =IF($J9="",#N/A,SUM(GC$4:GC9)) -> 0 | GE9: =IF(AND($S9="Dwn",$BF9="Short",$E9=GC$2),$P9,"") | GF9: =IF($J9="",#N/A,SUM(GE$4:GE9)) -> 0 | GG9: =IF(AND($S9="SW",$BF9="Long",$E9=GC$2),$P9,"") | GH9: =IF($J9="",#N/A,SUM(GG$4:GG9)) -> 0 | GI9: =IF($J9="",#N/A,SUM(GG$4:GG9,GE$4:GE9,GC$4:GC9)) -> 0 | GJ9: =IF(AND($S9="Up",$BF9="Long",$E9=GJ$2),$P9,"") | GK9: =IF($J9="",#N/A,SUM(GJ$4:GJ9)) -> 0 | GL9: =IF(AND($S9="Dwn",$BF9="Short",$E9=GJ$2),$P9,"") | GM9: =IF($J9="",#N/A,SUM(GL$4:GL9)) -> 0 | GN9: =IF(AND($S9="SW",$BF9="Long",$E9=GJ$2),$P9,"") | GO9: =IF($J9="",#N/A,SUM(GN$4:GN9)) -> 0 | GP9: =IF($J9="",#N/A,SUM(GN$4:GN9,GL$4:GL9,GJ$4:GJ9)) -> 0 | GS9: =IF(J9="","",IF(D9="Y",P9,"")) -> -0.65265631 | GT9: =IF(GS9="",NA(),SUM($GS$4:GS9)) -> -1.1314999 | GU9: =IF(AND($S9="Up",$BF9="Long",$D9="Y"),$GS9,"") | GV9: =IF(GU9="",NA(),SUM($GU$4:GU9)) -> #N/A | GW9: =IF(AND($S9="SW",$BF9="Long",$D9="Y"),$GS9,"") -> -0.65265631 | GX9: =IF(GW9="",NA(),SUM($GW$4:GW9)) -> -1.3318973 | GY9: =IF(AND($S9="Dwn",$BF9="Short",$D9="Y"),$GS9,"") | GZ9: =IF(GY9="",NA(),SUM($GY$4:GY9)) -> #N/A | HA9: =IF($J9="","",IF($D9="N",$P9,"")) | HB9: =IF(HA9="",NA(),SUM($HA$4:HA9)) -> #N/A | HC9: =IF(AND($S9="Up",$BF9="Long",$D9="N"),$HA9,"") | HD9: =IF(HC9="",NA(),SUM($HC$4:HC9)) -> #N/A | HE9: =IF(AND($S9="SW",$BF9="Long",$D9="N"),$HA9,"") | HF9: =IF(HE9="",NA(),SUM($HE$4:HE9)) -> #N/A | HG9: =IF(AND($S9="Dwn",$BF9="Short",$D9="N"),$HA9,"") | HH9: =IF(HG9="",NA(),SUM($HG$4:HG9)) -> #N/A | HI9: =IF($AC9="","",IF(AND($S9="Dwn",$K9<0),$HU9-P9,"")) | HJ9: =IF($J9="",#N/A,SUM(HI$4:$HI9)) -> -0.80152672 | HK9: =IF($AC9="","",IF(AND($S9="Dwn",$K9>0),$HU9-$P9,"")) | HL9: =IF($J9="",#N/A,SUM($HK$4:HK9)) -> -3.4652546 | HM9: =IF($AC9="","",IF(AND($S9="Up",$K9>0),$HU9-$P9,"")) | HN9: =IF($J9="",#N/A,SUM($HM$4:HM9)) -> 0 | HO9: =IF($AC9="","",IF(AND($S9="Up",$K9<0),$HU9-$P9,"")) | HP9: =IF($J9="",#N/A,SUM($HO$4:HO9)) -> 0 | HQ9: =IF($AC9="","",IF(AND($S9="SW",$K9>0),$HU9-$P9,"")) | HR9: =IF($J9="",#N/A,SUM($HQ$4:HQ9)) -> 0 | HS9: =IF($AC9="","",IF(AND($S9="SW",$K9<0),$HU9-$P9,"")) -> 0.88326154 | HT9: =IF($J9="",#N/A,SUM($HS$4:HS9)) -> 2.4592741 | HU9: =IF(OR($Y9="",$AC9=""),"",IF($BF9="Long",(($AC9*$Y9)-$X9)/($X9*0.06),($X9-($AC9*$Y9))/($X9*0.06))) -> 0.23060523 | HV9: =IF($J9="",#N/A,SUM(HU$4:$HU9)) -> -2.939007
A10: MS | B10: on 4/11/25 Before Market Eastern Stan | C10: =IF(S10="Dwn",2,IF(S10="Up",1,IF(S10="SW",3,"x"))) -> 3 | D10: =_xlfn.XLOOKUP(A10,[1]SP500!$A$2:$A$502,[1]SP500!$D$2:$D$502,"N") -> Y | E10: =IFERROR(_xlfn.XLOOKUP(A10,[1]SP500!$A$2:$A$655,[1]SP500!$B$2:$B$655),"") -> XLF | F10: 45758 | G10: =IF(ISNUMBER(FIND("After",B10,1)),"AMC",IF(ISNUMBER(FIND("Before",B10,1)),"BMO","err")) -> BMO | H10: =IF(AH10="Skip","sk",IF(OR(S10="",V10=""),"",IF(AND(S10="Dwn",V10="Short"),"s",IF(AND(S10="Up",V10="Long"),"s",IF(AND(S10="SW",V10="Long"),"s","o"))))) -> s | I10: 106.58 | J10: 102.89 | K10: =IF(J10="","",(J10-I10)/I10) -> -0.03462188 | L10: =IF(OR($Y10="",J10=""),"",IF($V10="Long",(($J10*$Y10)-$X10),($X10-($J10*$Y10)))) -> -36.9 | M10: =IF(L10="","",IF(AK10="",#N/A,IF(AH10="Open",AK10-L10,#N/A))) -> 11.9 | N10: =IF(OR($Y10="",L10=""),"",IF($BF10="Long",(($J10*$Y10)-$X10),($X10-($J10*$Y10)))) -> -36.9 | O10: =IF(N10="",#N/A,SUM($N$4:N10)) -> -106.28 | P10: =IF(OR($Y10="",L10=""),"",IF($BF10="Long",(($J10*$Y10)-$X10)/(X10*0.06),($X10-($J10*$Y10))/(X10*0.06))) -> -0.57703134 | Q10: =IF($N10="",#N/A,SUM($P$4:P10)) -> -1.7085312 | R10: =IF(AND(AH10="MOC",AC10=""),#N/A,IFERROR(Q10-AJ10,Q10-0)) -> -0.37586182 | S10: =IF(T10="Down","Dwn",IF(T10="Up","Up",IF(AND(T10="",K10=""),"",IF(AND(K10<0,T10="Yes"),"Dwn",IF(AND(K10>0,T10="Yes"),"Up",IF(AND(K10<0,T10="No"),"Up",IF(AND(K10>0,T10="No"),"Dwn",IF(T10="NA","SW","err")))))))) -> SW | T10: NA | U10: =I10 -> 106.58 | V10: Long | W10: 10 | X10: =IF(W10="","",U10*W10) -> 1065.8 | Y10: =IF(W10="","",W10) -> 10 | Z10: 104.08 | AA10: =IF($Z10="","",IF($V10="Long",(($Z10*$Y10)-$X10),($X10-($Z10*$Y10)))) -> -25 | AB10: =IF($AC10="","",IF($V10="Long",(($AC10*$Y10)-$X10),($X10-($AC10*$Y10)))) -> 15.4 | AC10: 108.12 | AD10: =IF(AC10="","",IF(OR($Y10="",CV10=""),"",IF($BF10="Long",(($AC10*$Y10)-$X10),($X10-($AC10*$Y10))))) -> 15.4 | AE10: =IF(OR($Y10="",$AD10=""),"",IF($BF10="Long",(($AC10*$Y10)-$X10)/($X10*0.06),($X10-($AC10*$Y10))/($X10*0.06))) -> 0.24082067 | AF10: =IF($AC10="",#N/A,SUM(AD$4:AD10)) -> -177.31 | AG10: =IF(OR(AD10="",AC10=""),"",AD10-N10) -> 52.3 | AH10: Open | AI10: =IF(AND(AH10="MOC",AC10=""),"",IF(Z10="","",IF(AH10="Skip",0,IF(AK10=0,0,AK10/(X10*0.06))))) -> -0.39094264 | AJ10: =IF(AI10="",#N/A,SUM($AI$4:AI10)) -> -1.3326694 | AK10: =IF(AH10="","",IF(AH10="Skip","",IF(OR(AH10="open",AH10="Other"),AA10,IF(AH10="MOC",AB10,"Err")))) -> -25 | AL10: =IF(AI10="",#N/A,IF(AH10="Skip",SUM($AK$4:AK10),SUM($AK$4:AK10))) -> -82.12 | AM10: =IF(OR($Y10="",$L10=""),"",IF($BF10="Long",(($AC10*$Y10)-$X10)/($X10*0.06),($X10-($AC10*$Y10))/($X10*0.06))) -> 0.24082067 | AO10: =IF(AND($S10="SW",$BF10="Long"),$HU10,"") -> 0.24082067 | AP10: =IF($AC10="",#N/A,SUM(AO$4:AO10)) -> 1.3681976 | AQ10: =IF(AND($S10="UP",$BF10="Long"),$HU10,"") | AR10: =IF($AC10="",#N/A,SUM(AQ$4:AQ10)) -> 0 | AS10: =IF(AND($S10="Dwn",$BF10="Short"),$HU10,"") | AT10: =IF($AC10="",#N/A,SUM(AS$4:AS10)) -> -4.0663839 | AU10: =IF(AND(S10="SW",BF10="Long"),$AD10,"") -> 15.4 | AV10: =IF($AC10="",#N/A,SUM(AU$4:AU10)) -> 85.49 | AW10: =IF(AND(S10="UP",BF10="Long"),$AD10,"") | AX10: =IF($AC10="",#N/A,SUM(AW$4:AW10)) -> 0 | AY10: =IF(AND(S10="Dwn",BF10="Short"),$AD10,"") | AZ10: =IF($AC10="",#N/A,SUM(AY$4:AY10)) -> -262.8 | BA10: =IF(AD10="",#N/A,SUM($AD$4:AD10)) -> -177.31 | BC10: =IF(K10="","",IF(AND(K10>0,T10="Yes"),1,"")) | BD10: =IF(K10="","",IF(AND($K10>0,$T10="No"),1,"")) | BE10: =IF(K10="","",IF(AND($K10>0,$T10="NA"),1,"")) | BF10: =IF(S10="Dwn","Short","Long") -> Long | BG10: =IF(K10="","",IF(AND($K10<0,$T10="Yes"),1,"")) | BH10: =IF(K10="","",IF(AND($K10<0,$T10="No"),1,"")) | BI10: =IF(K10="","",IF(AND($K10<0,$T10="NA"),1,"")) -> 1 | BO10: =IF(J10="",#N/A,IF(S10="SW",(COUNTIFS(K$4:$K10,">0",S$4:$S10,"SW")/COUNTIF(S$4:$S10,"SW")),#N/A)) -> 0 | BP10: =IF($J10="",#N/A,IF($S10="DWN",(COUNTIFS($K$4:$K10,"<0",$S$4:$S10,"DWN")/COUNTIF($S$4:$S10,"DWN")),#N/A)) -> #N/A | BQ10: =IF($J10="",#N/A,IF($S10="UP",(COUNTIFS($K$4:$K10,">0",$S$4:$S10,"UP")/COUNTIF($S$4:$S10,"UP")),#N/A)) -> #N/A | BR10: =IF(J10="",#N/A,COUNTIF($K$4:K10,">0")/COUNT($J$4:J10)) -> 0.14285714 | BS10: =IF($AH10="Skip","",IF($J10="","",IF(AND($V10="Long",$L10>0),$P10,""))) | BT10: =IF($AH10="Skip","",IF($J10="","",IF(AND($V10="Long",$L10<0),$P10,""))) -> -0.57703134 | BU10: =IF($AH10="Skip","",IF($J10="","",IF(AND($V10="Short",$L10>0),$P10,""))) | BV10: =IF($AH10="Skip","",IF($J10="","",IF(AND($V10="Short",$L10<0),$P10,""))) | BW10: =IF(AND($S10="Up",$BF10="Long"),$N10,"") | BX10: =IF($J10="",#N/A,SUM($BW$4:BW10)) -> 0 | BY10: =IF(AND($S10="Dwn",$BF10="Short"),$N10,"") | BZ10: =IF($J10="",#N/A,SUM($BY$4:BY10)) -> 13.92 | CA10: =IF(AND($S10="SW",$BF10="Long"),$N10,"") -> -36.9 | CB10: =IF($J10="",#N/A,SUM($CA$4:CA10)) -> -120.2 | CC10: =IF(AND($S10="Up",$BF10="Long"),$P10,"") | CD10: =IF($J10="",#N/A,SUM($CC$4:CC10)) -> 0 | CE10: =IF(AND($S10="Dwn",$BF10="Short"),$P10,"") | CF10: =IF($J10="",#N/A,SUM($CE$4:CE10)) -> 0.20039738 | CG10: =IF(AND($S10="SW",$BF10="Long"),$P10,"") -> -0.57703134 | CH10: =IF($J10="",#N/A,SUM($CG$4:CG10)) -> -1.9089286 | CI10: =IF(AND($S10="Up",$BF10="Long",$E10=CI$2),$P10,"") | CJ10: =IF($J10="",#N/A,SUM(CI$4:CI10)) -> 0 | CK10: =IF(AND($S10="Dwn",$BF10="Short",$E10=CI$2),$P10,"") | CL10: =IF($J10="",#N/A,SUM(CK$4:CK10)) -> 0 | CM10: =IF(AND($S10="SW",$BF10="Long",$E10=CI$2),$P10,"") | CN10: =IF($J10="",#N/A,SUM(CM$4:CM10)) -> 0 | CO10: =IF($J10="",#N/A,SUM(CM$4:CM10,CK$4:CK10,CI$4:CI10)) -> 0 | CP10: =IF(AND($S10="Up",$BF10="Long",$E10=CP$2),$P10,"") | CQ10: =IF($J10="",#N/A,SUM(CP$4:CP10)) -> 0 | CR10: =IF(AND($S10="Dwn",$BF10="Short",$E10=CP$2),$P10,"") | CS10: =IF($J10="",#N/A,SUM(CR$4:CR10)) -> 0 | CT10: =IF(AND($S10="SW",$BF10="Long",$E10=CP$2),$P10,"") | CU10: =IF($J10="",#N/A,SUM(CT$4:CT10)) -> 0 | CV10: =IF($J10="",#N/A,SUM(CT$4:CT10,CR$4:CR10,CP$4:CP10)) -> 0 | CW10: =IF(AND($S10="Up",$BF10="Long",$E10=CW$2),$P10,"") | CX10: =IF($J10="",#N/A,SUM(CW$4:CW10)) -> 0 | CY10: =IF(AND($S10="Dwn",$BF10="Short",$E10=CW$2),$P10,"") | CZ10: =IF($J10="",#N/A,SUM(CY$4:CY10)) -> 0 | DA10: =IF(AND($S10="SW",$BF10="Long",$E10=CW$2),$P10,"") | DB10: =IF($J10="",#N/A,SUM(DA$4:DA10)) -> 0 | DC10: =IF($J10="",#N/A,SUM(DA$4:DA10,CY$4:CY10,CW$4:CW10)) -> 0 | DD10: =IF(AND($S10="Up",$BF10="Long",$E10=DD$2),$P10,"") | DE10: =IF($J10="",#N/A,SUM(DD$4:DD10)) -> 0 | DF10: =IF(AND($S10="Dwn",$BF10="Short",$E10=DD$2),$P10,"") | DG10: =IF($J10="",#N/A,SUM(DF$4:DF10)) -> 0.67884406 | DH10: =IF(AND($S10="SW",$BF10="Long",$E10=DD$2),$P10,"") | DI10: =IF($J10="",#N/A,SUM(DH$4:DH10)) -> 0 | DJ10: =IF($J10="",#N/A,SUM(DH$4:DH10,DF$4:DF10,DD$4:DD10)) -> 0.67884406 | DK10: =IF(AND($S10="Up",$BF10="Long",$E10=DK$2),$P10,"") | DL10: =IF($J10="",#N/A,SUM(DK$4:DK10)) -> 0 | DM10: =IF(AND($S10="Dwn",$BF10="Short",$E10=DK$2),$P10,"") | DN10: =IF($J10="",#N/A,SUM(DM$4:DM10)) -> 0 | DO10: =IF(AND($S10="SW",$BF10="Long",$E10=DK$2),$P10,"") | DP10: =IF($J10="",#N/A,SUM(DO$4:DO10)) -> 0 | DQ10: =IF($J10="",#N/A,SUM(DO$4:DO10,DM$4:DM10,DK$4:DK10)) -> 0 | DR10: =IF(AND($S10="Up",$BF10="Long",$E10=DR$2),$P10,"") | DS10: =IF($J10="",#N/A,SUM(DR$4:DR10)) -> 0 | DT10: =IF(AND($S10="Dwn",$BF10="Short",$E10=DR$2),$P10,"") | DU10: =IF($J10="",#N/A,SUM(DT$4:DT10)) -> 0 | DV10: =IF(AND($S10="SW",$BF10="Long",$E10=DR$2),$P10,"") -> -0.57703134 | DW10: =IF($J10="",#N/A,SUM(DV$4:DV10)) -> -1.9089286 | DX10: =IF($J10="",#N/A,SUM(DV$4:DV10,DT$4:DT10,DR$4:DR10)) -> -1.9089286 | DY10: =IF(AND($S10="Up",$BF10="Long",$E10=DY$2),$P10,"") | DZ10: =IF($J10="",#N/A,SUM(DY$4:DY10)) -> 0 | EA10: =IF(AND($S10="Dwn",$BF10="Short",$E10=DY$2),$P10,"") | EB10: =IF($J10="",#N/A,SUM(EA$4:EA10)) -> -0.47844667 | EC10: =IF(AND($S10="SW",$BF10="Long",$E10=DY$2),$P10,"") | ED10: =IF($J10="",#N/A,SUM(EC$4:EC10)) -> 0 | EE10: =IF($J10="",#N/A,SUM(EC$4:EC10,EA$4:EA10,DY$4:DY10)) -> -0.47844667 | EF10: =IF(AND($S10="Up",$BF10="Long",$E10=EF$2),$P10,"") | EG10: =IF($J10="",#N/A,SUM(EF$4:EF10)) -> 0 | EH10: =IF(AND($S10="Dwn",$BF10="Short",$E10=EF$2),$P10,"") | EI10: =IF($J10="",#N/A,SUM(EH$4:EH10)) -> 0 | EJ10: =IF(AND($S10="SW",$BF10="Long",$E10=EF$2),$P10,"") | EK10: =IF($J10="",#N/A,SUM(EJ$4:EJ10)) -> 0 | EL10: =IF($J10="",#N/A,SUM(EJ$4:EJ10,EH$4:EH10,EF$4:EF10)) -> 0 | EM10: =IF(AND($S10="Up",$BF10="Long",$E10=EM$2),$P10,"") | EN10: =IF($J10="",#N/A,SUM(EM$4:EM10)) -> 0 | EO10: =IF(AND($S10="Dwn",$BF10="Short",$E10=EM$2),$P10,"") | EP10: =IF($J10="",#N/A,SUM(EO$4:EO10)) -> 0 | EQ10: =IF(AND($S10="SW",$BF10="Long",$E10=EM$2),$P10,"") | ER10: =IF($J10="",#N/A,SUM(EQ$4:EQ10)) -> 0 | ES10: =IF($J10="",#N/A,SUM(EQ$4:EQ10,EO$4:EO10,EM$4:EM10)) -> 0 | ET10: =IF(AND($S10="Up",$BF10="Long",$E10=ET$2),$P10,"") | EU10: =IF($J10="",#N/A,SUM(ET$4:ET10)) -> 0 | EV10: =IF(AND($S10="Dwn",$BF10="Short",$E10=ET$2),$P10,"") | EW10: =IF($J10="",#N/A,SUM(EV$4:EV10)) -> 0 | EX10: =IF(AND($S10="SW",$BF10="Long",$E10=ET$2),$P10,"") | EY10: =IF($J10="",#N/A,SUM(EX$4:EX10)) -> 0 | EZ10: =IF($J10="",#N/A,SUM(EX$4:EX10,EV$4:EV10,ET$4:ET10)) -> 0 | FA10: =IF(AND($S10="Up",$BF10="Long",$E10=FA$2),$P10,"") | FB10: =IF($J10="",#N/A,SUM(FA$4:FA10)) -> 0 | FC10: =IF(AND($S10="Dwn",$BF10="Short",$E10=FA$2),$P10,"") | FD10: =IF($J10="",#N/A,SUM(FC$4:FC10)) -> 0 | FE10: =IF(AND($S10="SW",$BF10="Long",$E10=FA$2),$P10,"") | FF10: =IF($J10="",#N/A,SUM(FE$4:FE10)) -> 0 | FG10: =IF($J10="",#N/A,SUM(FE$4:FE10,FC$4:FC10,FA$4:FA10)) -> 0 | FH10: =IF(AND($S10="Up",$BF10="Long",$E10=FH$2),$P10,"") | FI10: =IF($J10="",#N/A,SUM(FH$4:FH10)) -> 0 | FJ10: =IF(AND($S10="Dwn",$BF10="Short",$E10=FH$2),$P10,"") | FK10: =IF($J10="",#N/A,SUM(FJ$4:FJ10)) -> 0 | FL10: =IF(AND($S10="SW",$BF10="Long",$E10=FH$2),$P10,"") | FM10: =IF($J10="",#N/A,SUM(FL$4:FL10)) -> 0 | FN10: =IF($J10="",#N/A,SUM(FL$4:FL10,FJ$4:FJ10,FH$4:FH10)) -> 0 | FO10: =IF(AND($S10="Up",$BF10="Long",$E10=FO$2),$P10,"") | FP10: =IF($J10="",#N/A,SUM(FO$4:FO10)) -> 0 | FQ10: =IF(AND($S10="Dwn",$BF10="Short",$E10=FO$2),$P10,"") | FR10: =IF($J10="",#N/A,SUM(FQ$4:FQ10)) -> 0 | FS10: =IF(AND($S10="SW",$BF10="Long",$E10=FO$2),$P10,"") | FT10: =IF($J10="",#N/A,SUM(FS$4:FS10)) -> 0 | FU10: =IF($J10="",#N/A,SUM(FS$4:FS10,FQ$4:FQ10,FO$4:FO10)) -> 0 | FV10: =IF(AND($S10="Up",$BF10="Long",$E10=FV$2),$P10,"") | FW10: =IF($J10="",#N/A,SUM(FV$4:FV10)) -> 0 | FX10: =IF(AND($S10="Dwn",$BF10="Short",$E10=FV$2),$P10,"") | FY10: =IF($J10="",#N/A,SUM(FX$4:FX10)) -> 0 | FZ10: =IF(AND($S10="SW",$BF10="Long",$E10=FV$2),$P10,"") | GA10: =IF($J10="",#N/A,SUM(FZ$4:FZ10)) -> 0 | GB10: =IF($J10="",#N/A,SUM(FZ$4:FZ10,FX$4:FX10,FV$4:FV10)) -> 0 | GC10: =IF(AND($S10="Up",$BF10="Long",$E10=GC$2),$P10,"") | GD10: =IF($J10="",#N/A,SUM(GC$4:GC10)) -> 0 | GE10: =IF(AND($S10="Dwn",$BF10="Short",$E10=GC$2),$P10,"") | GF10: =IF($J10="",#N/A,SUM(GE$4:GE10)) -> 0 | GG10: =IF(AND($S10="SW",$BF10="Long",$E10=GC$2),$P10,"") | GH10: =IF($J10="",#N/A,SUM(GG$4:GG10)) -> 0 | GI10: =IF($J10="",#N/A,SUM(GG$4:GG10,GE$4:GE10,GC$4:GC10)) -> 0 | GJ10: =IF(AND($S10="Up",$BF10="Long",$E10=GJ$2),$P10,"") | GK10: =IF($J10="",#N/A,SUM(GJ$4:GJ10)) -> 0 | GL10: =IF(AND($S10="Dwn",$BF10="Short",$E10=GJ$2),$P10,"") | GM10: =IF($J10="",#N/A,SUM(GL$4:GL10)) -> 0 | GN10: =IF(AND($S10="SW",$BF10="Long",$E10=GJ$2),$P10,"") | GO10: =IF($J10="",#N/A,SUM(GN$4:GN10)) -> 0 | GP10: =IF($J10="",#N/A,SUM(GN$4:GN10,GL$4:GL10,GJ$4:GJ10)) -> 0 | GS10: =IF(J10="","",IF(D10="Y",P10,"")) -> -0.57703134 | GT10: =IF(GS10="",NA(),SUM($GS$4:GS10)) -> -1.7085312 | GU10: =IF(AND($S10="Up",$BF10="Long",$D10="Y"),$GS10,"") | GV10: =IF(GU10="",NA(),SUM($GU$4:GU10)) -> #N/A | GW10: =IF(AND($S10="SW",$BF10="Long",$D10="Y"),$GS10,"") -> -0.57703134 | GX10: =IF(GW10="",NA(),SUM($GW$4:GW10)) -> -1.9089286 | GY10: =IF(AND($S10="Dwn",$BF10="Short",$D10="Y"),$GS10,"") | GZ10: =IF(GY10="",NA(),SUM($GY$4:GY10)) -> #N/A | HA10: =IF($J10="","",IF($D10="N",$P10,"")) | HB10: =IF(HA10="",NA(),SUM($HA$4:HA10)) -> #N/A | HC10: =IF(AND($S10="Up",$BF10="Long",$D10="N"),$HA10,"") | HD10: =IF(HC10="",NA(),SUM($HC$4:HC10)) -> #N/A | HE10: =IF(AND($S10="SW",$BF10="Long",$D10="N"),$HA10,"") | HF10: =IF(HE10="",NA(),SUM($HE$4:HE10)) -> #N/A | HG10: =IF(AND($S10="Dwn",$BF10="Short",$D10="N"),$HA10,"") | HH10: =IF(HG10="",NA(),SUM($HG$4:HG10)) -> #N/A | HI10: =IF($AC10="","",IF(AND($S10="Dwn",$K10<0),$HU10-P10,"")) | HJ10: =IF($J10="",#N/A,SUM(HI$4:$HI10)) -> -0.80152672 | HK10: =IF($AC10="","",IF(AND($S10="Dwn",$K10>0),$HU10-$P10,"")) | HL10: =IF($J10="",#N/A,SUM($HK$4:HK10)) -> -3.4652546 | HM10: =IF($AC10="","",IF(AND($S10="Up",$K10>0),$HU10-$P10,"")) | HN10: =IF($J10="",#N/A,SUM($HM$4:HM10)) -> 0 | HO10: =IF($AC10="","",IF(AND($S10="Up",$K10<0),$HU10-$P10,"")) | HP10: =IF($J10="",#N/A,SUM($HO$4:HO10)) -> 0 | HQ10: =IF($AC10="","",IF(AND($S10="SW",$K10>0),$HU10-$P10,"")) | HR10: =IF($J10="",#N/A,SUM($HQ$4:HQ10)) -> 0 | HS10: =IF($AC10="","",IF(AND($S10="SW",$K10<0),$HU10-$P10,"")) -> 0.817852 | HT10: =IF($J10="",#N/A,SUM($HS$4:HS10)) -> 3.2771261 | HU10: =IF(OR($Y10="",$AC10=""),"",IF($BF10="Long",(($AC10*$Y10)-$X10)/($X10*0.06),($X10-($AC10*$Y10))/($X10*0.06))) -> 0.24082067 | HV10: =IF($J10="",#N/A,SUM(HU$4:$HU10)) -> -2.6981863
A11: FAST | B11: on 4/11/25 Before Market Eastern Stan | C11: =IF(S11="Dwn",2,IF(S11="Up",1,IF(S11="SW",3,"x"))) -> 3 | D11: =_xlfn.XLOOKUP(A11,[1]SP500!$A$2:$A$502,[1]SP500!$D$2:$D$502,"N") -> Y | E11: =IFERROR(_xlfn.XLOOKUP(A11,[1]SP500!$A$2:$A$655,[1]SP500!$B$2:$B$655),"") -> XLI | F11: 45758 | G11: =IF(ISNUMBER(FIND("After",B11,1)),"AMC",IF(ISNUMBER(FIND("Before",B11,1)),"BMO","err")) -> BMO | H11: =IF(AH11="Skip","sk",IF(OR(S11="",V11=""),"",IF(AND(S11="Dwn",V11="Short"),"s",IF(AND(S11="Up",V11="Long"),"s",IF(AND(S11="SW",V11="Long"),"s","o"))))) -> s | I11: 75.79 | J11: 75.21 | K11: =IF(J11="","",(J11-I11)/I11) -> -0.0076527246 | L11: =IF(OR($Y11="",J11=""),"",IF($V11="Long",(($J11*$Y11)-$X11),($X11-($J11*$Y11)))) -> -8.7 | M11: =IF(L11="","",IF(AK11="",#N/A,IF(AH11="Open",AK11-L11,#N/A))) -> 2.1 | N11: =IF(OR($Y11="",L11=""),"",IF($BF11="Long",(($J11*$Y11)-$X11),($X11-($J11*$Y11)))) -> -8.7 | O11: =IF(N11="",#N/A,SUM($N$4:N11)) -> -114.98 | P11: =IF(OR($Y11="",L11=""),"",IF($BF11="Long",(($J11*$Y11)-$X11)/(X11*0.06),($X11-($J11*$Y11))/(X11*0.06))) -> -0.12754541 | Q11: =IF($N11="",#N/A,SUM($P$4:P11)) -> -1.8360766 | R11: =IF(AND(AH11="MOC",AC11=""),#N/A,IFERROR(Q11-AJ11,Q11-0)) -> -0.40664865 | S11: =IF(T11="Down","Dwn",IF(T11="Up","Up",IF(AND(T11="",K11=""),"",IF(AND(K11<0,T11="Yes"),"Dwn",IF(AND(K11>0,T11="Yes"),"Up",IF(AND(K11<0,T11="No"),"Up",IF(AND(K11>0,T11="No"),"Dwn",IF(T11="NA","SW","err")))))))) -> SW | T11: NA | U11: =I11 -> 75.79 | V11: Long | W11: 15 | X11: =IF(W11="","",U11*W11) -> 1136.85 | Y11: =IF(W11="","",W11) -> 15 | Z11: 75.35 | AA11: =IF($Z11="","",IF($V11="Long",(($Z11*$Y11)-$X11),($X11-($Z11*$Y11)))) -> -6.6 | AB11: =IF($AC11="","",IF($V11="Long",(($AC11*$Y11)-$X11),($X11-($AC11*$Y11)))) -> 72.75 | AC11: 80.64 | AD11: =IF(AC11="","",IF(OR($Y11="",CV11=""),"",IF($BF11="Long",(($AC11*$Y11)-$X11),($X11-($AC11*$Y11))))) -> 72.75 | AE11: =IF(OR($Y11="",$AD11=""),"",IF($BF11="Long",(($AC11*$Y11)-$X11)/($X11*0.06),($X11-($AC11*$Y11))/($X11*0.06))) -> 1.0665435 | AF11: =IF($AC11="",#N/A,SUM(AD$4:AD11)) -> -104.56 | AG11: =IF(OR(AD11="",AC11=""),"",AD11-N11) -> 81.45 | AH11: Open | AI11: =IF(AND(AH11="MOC",AC11=""),"",IF(Z11="","",IF(AH11="Skip",0,IF(AK11=0,0,AK11/(X11*0.06))))) -> -0.096758587 | AJ11: =IF(AI11="",#N/A,SUM($AI$4:AI11)) -> -1.429428 | AK11: =IF(AH11="","",IF(AH11="Skip","",IF(OR(AH11="open",AH11="Other"),AA11,IF(AH11="MOC",AB11,"Err")))) -> -6.6 | AL11: =IF(AI11="",#N/A,IF(AH11="Skip",SUM($AK$4:AK11),SUM($AK$4:AK11))) -> -88.72 | AM11: =IF(OR($Y11="",$L11=""),"",IF($BF11="Long",(($AC11*$Y11)-$X11)/($X11*0.06),($X11-($AC11*$Y11))/($X11*0.06))) -> 1.0665435 | AO11: =IF(AND($S11="SW",$BF11="Long"),$HU11,"") -> 1.0665435 | AP11: =IF($AC11="",#N/A,SUM(AO$4:AO11)) -> 2.4347411 | AQ11: =IF(AND($S11="UP",$BF11="Long"),$HU11,"") | AR11: =IF($AC11="",#N/A,SUM(AQ$4:AQ11)) -> 0 | AS11: =IF(AND($S11="Dwn",$BF11="Short"),$HU11,"") | AT11: =IF($AC11="",#N/A,SUM(AS$4:AS11)) -> -4.0663839 | AU11: =IF(AND(S11="SW",BF11="Long"),$AD11,"") -> 72.75 | AV11: =IF($AC11="",#N/A,SUM(AU$4:AU11)) -> 158.24 | AW11: =IF(AND(S11="UP",BF11="Long"),$AD11,"") | AX11: =IF($AC11="",#N/A,SUM(AW$4:AW11)) -> 0 | AY11: =IF(AND(S11="Dwn",BF11="Short"),$AD11,"") | AZ11: =IF($AC11="",#N/A,SUM(AY$4:AY11)) -> -262.8 | BA11: =IF(AD11="",#N/A,SUM($AD$4:AD11)) -> -104.56 | BC11: =IF(K11="","",IF(AND(K11>0,T11="Yes"),1,"")) | BD11: =IF(K11="","",IF(AND($K11>0,$T11="No"),1,"")) | BE11: =IF(K11="","",IF(AND($K11>0,$T11="NA"),1,"")) | BF11: =IF(S11="Dwn","Short","Long") -> Long | BG11: =IF(K11="","",IF(AND($K11<0,$T11="Yes"),1,"")) | BH11: =IF(K11="","",IF(AND($K11<0,$T11="No"),1,"")) | BI11: =IF(K11="","",IF(AND($K11<0,$T11="NA"),1,"")) -> 1 | BO11: =IF(J11="",#N/A,IF(S11="SW",(COUNTIFS(K$4:$K11,">0",S$4:$S11,"SW")/COUNTIF(S$4:$S11,"SW")),#N/A)) -> 0 | BP11: =IF($J11="",#N/A,IF($S11="DWN",(COUNTIFS($K$4:$K11,"<0",$S$4:$S11,"DWN")/COUNTIF($S$4:$S11,"DWN")),#N/A)) -> #N/A | BQ11: =IF($J11="",#N/A,IF($S11="UP",(COUNTIFS($K$4:$K11,">0",$S$4:$S11,"UP")/COUNTIF($S$4:$S11,"UP")),#N/A)) -> #N/A | BR11: =IF(J11="",#N/A,COUNTIF($K$4:K11,">0")/COUNT($J$4:J11)) -> 0.125 | BS11: =IF($AH11="Skip","",IF($J11="","",IF(AND($V11="Long",$L11>0),$P11,""))) | BT11: =IF($AH11="Skip","",IF($J11="","",IF(AND($V11="Long",$L11<0),$P11,""))) -> -0.12754541 | BU11: =IF($AH11="Skip","",IF($J11="","",IF(AND($V11="Short",$L11>0),$P11,""))) | BV11: =IF($AH11="Skip","",IF($J11="","",IF(AND($V11="Short",$L11<0),$P11,""))) | BW11: =IF(AND($S11="Up",$BF11="Long"),$N11,"") | BX11: =IF($J11="",#N/A,SUM($BW$4:BW11)) -> 0 | BY11: =IF(AND($S11="Dwn",$BF11="Short"),$N11,"") | BZ11: =IF($J11="",#N/A,SUM($BY$4:BY11)) -> 13.92 | CA11: =IF(AND($S11="SW",$BF11="Long"),$N11,"") -> -8.7 | CB11: =IF($J11="",#N/A,SUM($CA$4:CA11)) -> -128.9 | CC11: =IF(AND($S11="Up",$BF11="Long"),$P11,"") | CD11: =IF($J11="",#N/A,SUM($CC$4:CC11)) -> 0 | CE11: =IF(AND($S11="Dwn",$BF11="Short"),$P11,"") | CF11: =IF($J11="",#N/A,SUM($CE$4:CE11)) -> 0.20039738 | CG11: =IF(AND($S11="SW",$BF11="Long"),$P11,"") -> -0.12754541 | CH11: =IF($J11="",#N/A,SUM($CG$4:CG11)) -> -2.036474 | CI11: =IF(AND($S11="Up",$BF11="Long",$E11=CI$2),$P11,"") | CJ11: =IF($J11="",#N/A,SUM(CI$4:CI11)) -> 0 | CK11: =IF(AND($S11="Dwn",$BF11="Short",$E11=CI$2),$P11,"") | CL11: =IF($J11="",#N/A,SUM(CK$4:CK11)) -> 0 | CM11: =IF(AND($S11="SW",$BF11="Long",$E11=CI$2),$P11,"") | CN11: =IF($J11="",#N/A,SUM(CM$4:CM11)) -> 0 | CO11: =IF($J11="",#N/A,SUM(CM$4:CM11,CK$4:CK11,CI$4:CI11)) -> 0 | CP11: =IF(AND($S11="Up",$BF11="Long",$E11=CP$2),$P11,"") | CQ11: =IF($J11="",#N/A,SUM(CP$4:CP11)) -> 0 | CR11: =IF(AND($S11="Dwn",$BF11="Short",$E11=CP$2),$P11,"") | CS11: =IF($J11="",#N/A,SUM(CR$4:CR11)) -> 0 | CT11: =IF(AND($S11="SW",$BF11="Long",$E11=CP$2),$P11,"") | CU11: =IF($J11="",#N/A,SUM(CT$4:CT11)) -> 0 | CV11: =IF($J11="",#N/A,SUM(CT$4:CT11,CR$4:CR11,CP$4:CP11)) -> 0 | CW11: =IF(AND($S11="Up",$BF11="Long",$E11=CW$2),$P11,"") | CX11: =IF($J11="",#N/A,SUM(CW$4:CW11)) -> 0 | CY11: =IF(AND($S11="Dwn",$BF11="Short",$E11=CW$2),$P11,"") | CZ11: =IF($J11="",#N/A,SUM(CY$4:CY11)) -> 0 | DA11: =IF(AND($S11="SW",$BF11="Long",$E11=CW$2),$P11,"") | DB11: =IF($J11="",#N/A,SUM(DA$4:DA11)) -> 0 | DC11: =IF($J11="",#N/A,SUM(DA$4:DA11,CY$4:CY11,CW$4:CW11)) -> 0 | DD11: =IF(AND($S11="Up",$BF11="Long",$E11=DD$2),$P11,"") | DE11: =IF($J11="",#N/A,SUM(DD$4:DD11)) -> 0 | DF11: =IF(AND($S11="Dwn",$BF11="Short",$E11=DD$2),$P11,"") | DG11: =IF($J11="",#N/A,SUM(DF$4:DF11)) -> 0.67884406 | DH11: =IF(AND($S11="SW",$BF11="Long",$E11=DD$2),$P11,"") | DI11: =IF($J11="",#N/A,SUM(DH$4:DH11)) -> 0 | DJ11: =IF($J11="",#N/A,SUM(DH$4:DH11,DF$4:DF11,DD$4:DD11)) -> 0.67884406 | DK11: =IF(AND($S11="Up",$BF11="Long",$E11=DK$2),$P11,"") | DL11: =IF($J11="",#N/A,SUM(DK$4:DK11)) -> 0 | DM11: =IF(AND($S11="Dwn",$BF11="Short",$E11=DK$2),$P11,"") | DN11: =IF($J11="",#N/A,SUM(DM$4:DM11)) -> 0 | DO11: =IF(AND($S11="SW",$BF11="Long",$E11=DK$2),$P11,"") | DP11: =IF($J11="",#N/A,SUM(DO$4:DO11)) -> 0 | DQ11: =IF($J11="",#N/A,SUM(DO$4:DO11,DM$4:DM11,DK$4:DK11)) -> 0 | DR11: =IF(AND($S11="Up",$BF11="Long",$E11=DR$2),$P11,"") | DS11: =IF($J11="",#N/A,SUM(DR$4:DR11)) -> 0 | DT11: =IF(AND($S11="Dwn",$BF11="Short",$E11=DR$2),$P11,"") | DU11: =IF($J11="",#N/A,SUM(DT$4:DT11)) -> 0 | DV11: =IF(AND($S11="SW",$BF11="Long",$E11=DR$2),$P11,"") | DW11: =IF($J11="",#N/A,SUM(DV$4:DV11)) -> -1.9089286 | DX11: =IF($J11="",#N/A,SUM(DV$4:DV11,DT$4:DT11,DR$4:DR11)) -> -1.9089286 | DY11: =IF(AND($S11="Up",$BF11="Long",$E11=DY$2),$P11,"") | DZ11: =IF($J11="",#N/A,SUM(DY$4:DY11)) -> 0 | EA11: =IF(AND($S11="Dwn",$BF11="Short",$E11=DY$2),$P11,"") | EB11: =IF($J11="",#N/A,SUM(EA$4:EA11)) -> -0.47844667 | EC11: =IF(AND($S11="SW",$BF11="Long",$E11=DY$2),$P11,"") -> -0.12754541 | ED11: =IF($J11="",#N/A,SUM(EC$4:EC11)) -> -0.12754541 | EE11: =IF($J11="",#N/A,SUM(EC$4:EC11,EA$4:EA11,DY$4:DY11)) -> -0.60599208 | EF11: =IF(AND($S11="Up",$BF11="Long",$E11=EF$2),$P11,"") | EG11: =IF($J11="",#N/A,SUM(EF$4:EF11)) -> 0 | EH11: =IF(AND($S11="Dwn",$BF11="Short",$E11=EF$2),$P11,"") | EI11: =IF($J11="",#N/A,SUM(EH$4:EH11)) -> 0 | EJ11: =IF(AND($S11="SW",$BF11="Long",$E11=EF$2),$P11,"") | EK11: =IF($J11="",#N/A,SUM(EJ$4:EJ11)) -> 0 | EL11: =IF($J11="",#N/A,SUM(EJ$4:EJ11,EH$4:EH11,EF$4:EF11)) -> 0 | EM11: =IF(AND($S11="Up",$BF11="Long",$E11=EM$2),$P11,"") | EN11: =IF($J11="",#N/A,SUM(EM$4:EM11)) -> 0 | EO11: =IF(AND($S11="Dwn",$BF11="Short",$E11=EM$2),$P11,"") | EP11: =IF($J11="",#N/A,SUM(EO$4:EO11)) -> 0 | EQ11: =IF(AND($S11="SW",$BF11="Long",$E11=EM$2),$P11,"") | ER11: =IF($J11="",#N/A,SUM(EQ$4:EQ11)) -> 0 | ES11: =IF($J11="",#N/A,SUM(EQ$4:EQ11,EO$4:EO11,EM$4:EM11)) -> 0 | ET11: =IF(AND($S11="Up",$BF11="Long",$E11=ET$2),$P11,"") | EU11: =IF($J11="",#N/A,SUM(ET$4:ET11)) -> 0 | EV11: =IF(AND($S11="Dwn",$BF11="Short",$E11=ET$2),$P11,"") | EW11: =IF($J11="",#N/A,SUM(EV$4:EV11)) -> 0 | EX11: =IF(AND($S11="SW",$BF11="Long",$E11=ET$2),$P11,"") | EY11: =IF($J11="",#N/A,SUM(EX$4:EX11)) -> 0 | EZ11: =IF($J11="",#N/A,SUM(EX$4:EX11,EV$4:EV11,ET$4:ET11)) -> 0 | FA11: =IF(AND($S11="Up",$BF11="Long",$E11=FA$2),$P11,"") | FB11: =IF($J11="",#N/A,SUM(FA$4:FA11)) -> 0 | FC11: =IF(AND($S11="Dwn",$BF11="Short",$E11=FA$2),$P11,"") | FD11: =IF($J11="",#N/A,SUM(FC$4:FC11)) -> 0 | FE11: =IF(AND($S11="SW",$BF11="Long",$E11=FA$2),$P11,"") | FF11: =IF($J11="",#N/A,SUM(FE$4:FE11)) -> 0 | FG11: =IF($J11="",#N/A,SUM(FE$4:FE11,FC$4:FC11,FA$4:FA11)) -> 0 | FH11: =IF(AND($S11="Up",$BF11="Long",$E11=FH$2),$P11,"") | FI11: =IF($J11="",#N/A,SUM(FH$4:FH11)) -> 0 | FJ11: =IF(AND($S11="Dwn",$BF11="Short",$E11=FH$2),$P11,"") | FK11: =IF($J11="",#N/A,SUM(FJ$4:FJ11)) -> 0 | FL11: =IF(AND($S11="SW",$BF11="Long",$E11=FH$2),$P11,"") | FM11: =IF($J11="",#N/A,SUM(FL$4:FL11)) -> 0 | FN11: =IF($J11="",#N/A,SUM(FL$4:FL11,FJ$4:FJ11,FH$4:FH11)) -> 0 | FO11: =IF(AND($S11="Up",$BF11="Long",$E11=FO$2),$P11,"") | FP11: =IF($J11="",#N/A,SUM(FO$4:FO11)) -> 0 | FQ11: =IF(AND($S11="Dwn",$BF11="Short",$E11=FO$2),$P11,"") | FR11: =IF($J11="",#N/A,SUM(FQ$4:FQ11)) -> 0 | FS11: =IF(AND($S11="SW",$BF11="Long",$E11=FO$2),$P11,"") | FT11: =IF($J11="",#N/A,SUM(FS$4:FS11)) -> 0 | FU11: =IF($J11="",#N/A,SUM(FS$4:FS11,FQ$4:FQ11,FO$4:FO11)) -> 0 | FV11: =IF(AND($S11="Up",$BF11="Long",$E11=FV$2),$P11,"") | FW11: =IF($J11="",#N/A,SUM(FV$4:FV11)) -> 0 | FX11: =IF(AND($S11="Dwn",$BF11="Short",$E11=FV$2),$P11,"") | FY11: =IF($J11="",#N/A,SUM(FX$4:FX11)) -> 0 | FZ11: =IF(AND($S11="SW",$BF11="Long",$E11=FV$2),$P11,"") | GA11: =IF($J11="",#N/A,SUM(FZ$4:FZ11)) -> 0 | GB11: =IF($J11="",#N/A,SUM(FZ$4:FZ11,FX$4:FX11,FV$4:FV11)) -> 0 | GC11: =IF(AND($S11="Up",$BF11="Long",$E11=GC$2),$P11,"") | GD11: =IF($J11="",#N/A,SUM(GC$4:GC11)) -> 0 | GE11: =IF(AND($S11="Dwn",$BF11="Short",$E11=GC$2),$P11,"") | GF11: =IF($J11="",#N/A,SUM(GE$4:GE11)) -> 0 | GG11: =IF(AND($S11="SW",$BF11="Long",$E11=GC$2),$P11,"") | GH11: =IF($J11="",#N/A,SUM(GG$4:GG11)) -> 0 | GI11: =IF($J11="",#N/A,SUM(GG$4:GG11,GE$4:GE11,GC$4:GC11)) -> 0 | GJ11: =IF(AND($S11="Up",$BF11="Long",$E11=GJ$2),$P11,"") | GK11: =IF($J11="",#N/A,SUM(GJ$4:GJ11)) -> 0 | GL11: =IF(AND($S11="Dwn",$BF11="Short",$E11=GJ$2),$P11,"") | GM11: =IF($J11="",#N/A,SUM(GL$4:GL11)) -> 0 | GN11: =IF(AND($S11="SW",$BF11="Long",$E11=GJ$2),$P11,"") | GO11: =IF($J11="",#N/A,SUM(GN$4:GN11)) -> 0 | GP11: =IF($J11="",#N/A,SUM(GN$4:GN11,GL$4:GL11,GJ$4:GJ11)) -> 0 | GS11: =IF(J11="","",IF(D11="Y",P11,"")) -> -0.12754541 | GT11: =IF(GS11="",NA(),SUM($GS$4:GS11)) -> -1.8360766 | GU11: =IF(AND($S11="Up",$BF11="Long",$D11="Y"),$GS11,"") | GV11: =IF(GU11="",NA(),SUM($GU$4:GU11)) -> #N/A | GW11: =IF(AND($S11="SW",$BF11="Long",$D11="Y"),$GS11,"") -> -0.12754541 | GX11: =IF(GW11="",NA(),SUM($GW$4:GW11)) -> -2.036474 | GY11: =IF(AND($S11="Dwn",$BF11="Short",$D11="Y"),$GS11,"") | GZ11: =IF(GY11="",NA(),SUM($GY$4:GY11)) -> #N/A | HA11: =IF($J11="","",IF($D11="N",$P11,"")) | HB11: =IF(HA11="",NA(),SUM($HA$4:HA11)) -> #N/A | HC11: =IF(AND($S11="Up",$BF11="Long",$D11="N"),$HA11,"") | HD11: =IF(HC11="",NA(),SUM($HC$4:HC11)) -> #N/A | HE11: =IF(AND($S11="SW",$BF11="Long",$D11="N"),$HA11,"") | HF11: =IF(HE11="",NA(),SUM($HE$4:HE11)) -> #N/A | HG11: =IF(AND($S11="Dwn",$BF11="Short",$D11="N"),$HA11,"") | HH11: =IF(HG11="",NA(),SUM($HG$4:HG11)) -> #N/A | HI11: =IF($AC11="","",IF(AND($S11="Dwn",$K11<0),$HU11-P11,"")) | HJ11: =IF($J11="",#N/A,SUM(HI$4:$HI11)) -> -0.80152672 | HK11: =IF($AC11="","",IF(AND($S11="Dwn",$K11>0),$HU11-$P11,"")) | HL11: =IF($J11="",#N/A,SUM($HK$4:HK11)) -> -3.4652546 | HM11: =IF($AC11="","",IF(AND($S11="Up",$K11>0),$HU11-$P11,"")) | HN11: =IF($J11="",#N/A,SUM($HM$4:HM11)) -> 0 | HO11: =IF($AC11="","",IF(AND($S11="Up",$K11<0),$HU11-$P11,"")) | HP11: =IF($J11="",#N/A,SUM($HO$4:HO11)) -> 0 | HQ11: =IF($AC11="","",IF(AND($S11="SW",$K11>0),$HU11-$P11,"")) | HR11: =IF($J11="",#N/A,SUM($HQ$4:HQ11)) -> 0 | HS11: =IF($AC11="","",IF(AND($S11="SW",$K11<0),$HU11-$P11,"")) -> 1.1940889 | HT11: =IF($J11="",#N/A,SUM($HS$4:HS11)) -> 4.4712151 | HU11: =IF(OR($Y11="",$AC11=""),"",IF($BF11="Long",(($AC11*$Y11)-$X11)/($X11*0.06),($X11-($AC11*$Y11))/($X11*0.06))) -> 1.0665435 | HV11: =IF($J11="",#N/A,SUM(HU$4:$HU11)) -> -1.6316428
A12: GS | B12: on 4/14/25 Before Market Eastern Stan | C12: =IF(S12="Dwn",2,IF(S12="Up",1,IF(S12="SW",3,"x"))) -> 3 | D12: =_xlfn.XLOOKUP(A12,[1]SP500!$A$2:$A$502,[1]SP500!$D$2:$D$502,"N") -> Y | E12: =IFERROR(_xlfn.XLOOKUP(A12,[1]SP500!$A$2:$A$655,[1]SP500!$B$2:$B$655),"") -> XLF | F12: 45761 | G12: =IF(ISNUMBER(FIND("After",B12,1)),"AMC",IF(ISNUMBER(FIND("Before",B12,1)),"BMO","err")) -> BMO | H12: =IF(AH12="Skip","sk",IF(OR(S12="",V12=""),"",IF(AND(S12="Dwn",V12="Short"),"s",IF(AND(S12="Up",V12="Long"),"s",IF(AND(S12="SW",V12="Long"),"s","o"))))) -> s | I12: 494.44 | J12: 510 | K12: =IF(J12="","",(J12-I12)/I12) -> 0.031469946 | L12: =IF(OR($Y12="",J12=""),"",IF($V12="Long",(($J12*$Y12)-$X12),($X12-($J12*$Y12)))) -> 31.12 | M12: =IF(L12="","",IF(AK12="",#N/A,IF(AH12="Open",AK12-L12,#N/A))) -> 0 | N12: =IF(OR($Y12="",L12=""),"",IF($BF12="Long",(($J12*$Y12)-$X12),($X12-($J12*$Y12)))) -> 31.12 | O12: =IF(N12="",#N/A,SUM($N$4:N12)) -> -83.86 | P12: =IF(OR($Y12="",L12=""),"",IF($BF12="Long",(($J12*$Y12)-$X12)/(X12*0.06),($X12-($J12*$Y12))/(X12*0.06))) -> 0.5244991 | Q12: =IF($N12="",#N/A,SUM($P$4:P12)) -> -1.3115775 | R12: =IF(AND(AH12="MOC",AC12=""),#N/A,IFERROR(Q12-AJ12,Q12-0)) -> -0.40664865 | S12: =IF(T12="Down","Dwn",IF(T12="Up","Up",IF(AND(T12="",K12=""),"",IF(AND(K12<0,T12="Yes"),"Dwn",IF(AND(K12>0,T12="Yes"),"Up",IF(AND(K12<0,T12="No"),"Up",IF(AND(K12>0,T12="No"),"Dwn",IF(T12="NA","SW","err")))))))) -> SW | T12: NA | U12: =I12 -> 494.44 | V12: Long | W12: 2 | X12: =IF(W12="","",U12*W12) -> 988.88 | Y12: =IF(W12="","",W12) -> 2 | Z12: 510 | AA12: =IF($Z12="","",IF($V12="Long",(($Z12*$Y12)-$X12),($X12-($Z12*$Y12)))) -> 31.12 | AB12: =IF($AC12="","",IF($V12="Long",(($AC12*$Y12)-$X12),($X12-($AC12*$Y12)))) -> 19.08 | AC12: 503.98 | AD12: =IF(AC12="","",IF(OR($Y12="",CV12=""),"",IF($BF12="Long",(($AC12*$Y12)-$X12),($X12-($AC12*$Y12))))) -> 19.08 | AE12: =IF(OR($Y12="",$AD12=""),"",IF($BF12="Long",(($AC12*$Y12)-$X12)/($X12*0.06),($X12-($AC12*$Y12))/($X12*0.06))) -> 0.32157592 | AF12: =IF($AC12="",#N/A,SUM(AD$4:AD12)) -> -85.48 | AG12: =IF(OR(AD12="",AC12=""),"",AD12-N12) -> -12.04 | AH12: Open | AI12: =IF(AND(AH12="MOC",AC12=""),"",IF(Z12="","",IF(AH12="Skip",0,IF(AK12=0,0,AK12/(X12*0.06))))) -> 0.5244991 | AJ12: =IF(AI12="",#N/A,SUM($AI$4:AI12)) -> -0.90492887 | AK12: =IF(AH12="","",IF(AH12="Skip","",IF(OR(AH12="open",AH12="Other"),AA12,IF(AH12="MOC",AB12,"Err")))) -> 31.12 | AL12: =IF(AI12="",#N/A,IF(AH12="Skip",SUM($AK$4:AK12),SUM($AK$4:AK12))) -> -57.6 | AM12: =IF(OR($Y12="",$L12=""),"",IF($BF12="Long",(($AC12*$Y12)-$X12)/($X12*0.06),($X12-($AC12*$Y12))/($X12*0.06))) -> 0.32157592 | AO12: =IF(AND($S12="SW",$BF12="Long"),$HU12,"") -> 0.32157592 | AP12: =IF($AC12="",#N/A,SUM(AO$4:AO12)) -> 2.756317 | AQ12: =IF(AND($S12="UP",$BF12="Long"),$HU12,"") | AR12: =IF($AC12="",#N/A,SUM(AQ$4:AQ12)) -> 0 | AS12: =IF(AND($S12="Dwn",$BF12="Short"),$HU12,"") | AT12: =IF($AC12="",#N/A,SUM(AS$4:AS12)) -> -4.0663839 | AU12: =IF(AND(S12="SW",BF12="Long"),$AD12,"") -> 19.08 | AV12: =IF($AC12="",#N/A,SUM(AU$4:AU12)) -> 177.32 | AW12: =IF(AND(S12="UP",BF12="Long"),$AD12,"") | AX12: =IF($AC12="",#N/A,SUM(AW$4:AW12)) -> 0 | AY12: =IF(AND(S12="Dwn",BF12="Short"),$AD12,"") | AZ12: =IF($AC12="",#N/A,SUM(AY$4:AY12)) -> -262.8 | BA12: =IF(AD12="",#N/A,SUM($AD$4:AD12)) -> -85.48 | BC12: =IF(K12="","",IF(AND(K12>0,T12="Yes"),1,"")) | BD12: =IF(K12="","",IF(AND($K12>0,$T12="No"),1,"")) | BE12: =IF(K12="","",IF(AND($K12>0,$T12="NA"),1,"")) -> 1 | BF12: =IF(S12="Dwn","Short","Long") -> Long | BG12: =IF(K12="","",IF(AND($K12<0,$T12="Yes"),1,"")) | BH12: =IF(K12="","",IF(AND($K12<0,$T12="No"),1,"")) | BI12: =IF(K12="","",IF(AND($K12<0,$T12="NA"),1,"")) | BO12: =IF(J12="",#N/A,IF(S12="SW",(COUNTIFS(K$4:$K12,">0",S$4:$S12,"SW")/COUNTIF(S$4:$S12,"SW")),#N/A)) -> 0.14285714 | BP12: =IF($J12="",#N/A,IF($S12="DWN",(COUNTIFS($K$4:$K12,"<0",$S$4:$S12,"DWN")/COUNTIF($S$4:$S12,"DWN")),#N/A)) -> #N/A | BQ12: =IF($J12="",#N/A,IF($S12="UP",(COUNTIFS($K$4:$K12,">0",$S$4:$S12,"UP")/COUNTIF($S$4:$S12,"UP")),#N/A)) -> #N/A | BR12: =IF(J12="",#N/A,COUNTIF($K$4:K12,">0")/COUNT($J$4:J12)) -> 0.22222222 | BS12: =IF($AH12="Skip","",IF($J12="","",IF(AND($V12="Long",$L12>0),$P12,""))) -> 0.5244991 | BT12: =IF($AH12="Skip","",IF($J12="","",IF(AND($V12="Long",$L12<0),$P12,""))) | BU12: =IF($AH12="Skip","",IF($J12="","",IF(AND($V12="Short",$L12>0),$P12,""))) | BV12: =IF($AH12="Skip","",IF($J12="","",IF(AND($V12="Short",$L12<0),$P12,""))) | BW12: =IF(AND($S12="Up",$BF12="Long"),$N12,"") | BX12: =IF($J12="",#N/A,SUM($BW$4:BW12)) -> 0 | BY12: =IF(AND($S12="Dwn",$BF12="Short"),$N12,"") | BZ12: =IF($J12="",#N/A,SUM($BY$4:BY12)) -> 13.92 | CA12: =IF(AND($S12="SW",$BF12="Long"),$N12,"") -> 31.12 | CB12: =IF($J12="",#N/A,SUM($CA$4:CA12)) -> -97.78 | CC12: =IF(AND($S12="Up",$BF12="Long"),$P12,"") | CD12: =IF($J12="",#N/A,SUM($CC$4:CC12)) -> 0 | CE12: =IF(AND($S12="Dwn",$BF12="Short"),$P12,"") | CF12: =IF($J12="",#N/A,SUM($CE$4:CE12)) -> 0.20039738 | CG12: =IF(AND($S12="SW",$BF12="Long"),$P12,"") -> 0.5244991 | CH12: =IF($J12="",#N/A,SUM($CG$4:CG12)) -> -1.5119749 | CI12: =IF(AND($S12="Up",$BF12="Long",$E12=CI$2),$P12,"") | CJ12: =IF($J12="",#N/A,SUM(CI$4:CI12)) -> 0 | CK12: =IF(AND($S12="Dwn",$BF12="Short",$E12=CI$2),$P12,"") | CL12: =IF($J12="",#N/A,SUM(CK$4:CK12)) -> 0 | CM12: =IF(AND($S12="SW",$BF12="Long",$E12=CI$2),$P12,"") | CN12: =IF($J12="",#N/A,SUM(CM$4:CM12)) -> 0 | CO12: =IF($J12="",#N/A,SUM(CM$4:CM12,CK$4:CK12,CI$4:CI12)) -> 0 | CP12: =IF(AND($S12="Up",$BF12="Long",$E12=CP$2),$P12,"") | CQ12: =IF($J12="",#N/A,SUM(CP$4:CP12)) -> 0 | CR12: =IF(AND($S12="Dwn",$BF12="Short",$E12=CP$2),$P12,"") | CS12: =IF($J12="",#N/A,SUM(CR$4:CR12)) -> 0 | CT12: =IF(AND($S12="SW",$BF12="Long",$E12=CP$2),$P12,"") | CU12: =IF($J12="",#N/A,SUM(CT$4:CT12)) -> 0 | CV12: =IF($J12="",#N/A,SUM(CT$4:CT12,CR$4:CR12,CP$4:CP12)) -> 0 | CW12: =IF(AND($S12="Up",$BF12="Long",$E12=CW$2),$P12,"") | CX12: =IF($J12="",#N/A,SUM(CW$4:CW12)) -> 0 | CY12: =IF(AND($S12="Dwn",$BF12="Short",$E12=CW$2),$P12,"") | CZ12: =IF($J12="",#N/A,SUM(CY$4:CY12)) -> 0 | DA12: =IF(AND($S12="SW",$BF12="Long",$E12=CW$2),$P12,"") | DB12: =IF($J12="",#N/A,SUM(DA$4:DA12)) -> 0 | DC12: =IF($J12="",#N/A,SUM(DA$4:DA12,CY$4:CY12,CW$4:CW12)) -> 0 | DD12: =IF(AND($S12="Up",$BF12="Long",$E12=DD$2),$P12,"") | DE12: =IF($J12="",#N/A,SUM(DD$4:DD12)) -> 0 | DF12: =IF(AND($S12="Dwn",$BF12="Short",$E12=DD$2),$P12,"") | DG12: =IF($J12="",#N/A,SUM(DF$4:DF12)) -> 0.67884406 | DH12: =IF(AND($S12="SW",$BF12="Long",$E12=DD$2),$P12,"") | DI12: =IF($J12="",#N/A,SUM(DH$4:DH12)) -> 0 | DJ12: =IF($J12="",#N/A,SUM(DH$4:DH12,DF$4:DF12,DD$4:DD12)) -> 0.67884406 | DK12: =IF(AND($S12="Up",$BF12="Long",$E12=DK$2),$P12,"") | DL12: =IF($J12="",#N/A,SUM(DK$4:DK12)) -> 0 | DM12: =IF(AND($S12="Dwn",$BF12="Short",$E12=DK$2),$P12,"") | DN12: =IF($J12="",#N/A,SUM(DM$4:DM12)) -> 0 | DO12: =IF(AND($S12="SW",$BF12="Long",$E12=DK$2),$P12,"") | DP12: =IF($J12="",#N/A,SUM(DO$4:DO12)) -> 0 | DQ12: =IF($J12="",#N/A,SUM(DO$4:DO12,DM$4:DM12,DK$4:DK12)) -> 0 | DR12: =IF(AND($S12="Up",$BF12="Long",$E12=DR$2),$P12,"") | DS12: =IF($J12="",#N/A,SUM(DR$4:DR12)) -> 0 | DT12: =IF(AND($S12="Dwn",$BF12="Short",$E12=DR$2),$P12,"") | DU12: =IF($J12="",#N/A,SUM(DT$4:DT12)) -> 0 | DV12: =IF(AND($S12="SW",$BF12="Long",$E12=DR$2),$P12,"") -> 0.5244991 | DW12: =IF($J12="",#N/A,SUM(DV$4:DV12)) -> -1.3844295 | DX12: =IF($J12="",#N/A,SUM(DV$4:DV12,DT$4:DT12,DR$4:DR12)) -> -1.3844295 | DY12: =IF(AND($S12="Up",$BF12="Long",$E12=DY$2),$P12,"") | DZ12: =IF($J12="",#N/A,SUM(DY$4:DY12)) -> 0 | EA12: =IF(AND($S12="Dwn",$BF12="Short",$E12=DY$2),$P12,"") | EB12: =IF($J12="",#N/A,SUM(EA$4:EA12)) -> -0.47844667 | EC12: =IF(AND($S12="SW",$BF12="Long",$E12=DY$2),$P12,"") | ED12: =IF($J12="",#N/A,SUM(EC$4:EC12)) -> -0.12754541 | EE12: =IF($J12="",#N/A,SUM(EC$4:EC12,EA$4:EA12,DY$4:DY12)) -> -0.60599208 | EF12: =IF(AND($S12="Up",$BF12="Long",$E12=EF$2),$P12,"") | EG12: =IF($J12="",#N/A,SUM(EF$4:EF12)) -> 0 | EH12: =IF(AND($S12="Dwn",$BF12="Short",$E12=EF$2),$P12,"") | EI12: =IF($J12="",#N/A,SUM(EH$4:EH12)) -> 0 | EJ12: =IF(AND($S12="SW",$BF12="Long",$E12=EF$2),$P12,"") | EK12: =IF($J12="",#N/A,SUM(EJ$4:EJ12)) -> 0 | EL12: =IF($J12="",#N/A,SUM(EJ$4:EJ12,EH$4:EH12,EF$4:EF12)) -> 0 | EM12: =IF(AND($S12="Up",$BF12="Long",$E12=EM$2),$P12,"") | EN12: =IF($J12="",#N/A,SUM(EM$4:EM12)) -> 0 | EO12: =IF(AND($S12="Dwn",$BF12="Short",$E12=EM$2),$P12,"") | EP12: =IF($J12="",#N/A,SUM(EO$4:EO12)) -> 0 | EQ12: =IF(AND($S12="SW",$BF12="Long",$E12=EM$2),$P12,"") | ER12: =IF($J12="",#N/A,SUM(EQ$4:EQ12)) -> 0 | ES12: =IF($J12="",#N/A,SUM(EQ$4:EQ12,EO$4:EO12,EM$4:EM12)) -> 0 | ET12: =IF(AND($S12="Up",$BF12="Long",$E12=ET$2),$P12,"") | EU12: =IF($J12="",#N/A,SUM(ET$4:ET12)) -> 0 | EV12: =IF(AND($S12="Dwn",$BF12="Short",$E12=ET$2),$P12,"") | EW12: =IF($J12="",#N/A,SUM(EV$4:EV12)) -> 0 | EX12: =IF(AND($S12="SW",$BF12="Long",$E12=ET$2),$P12,"") | EY12: =IF($J12="",#N/A,SUM(EX$4:EX12)) -> 0 | EZ12: =IF($J12="",#N/A,SUM(EX$4:EX12,EV$4:EV12,ET$4:ET12)) -> 0 | FA12: =IF(AND($S12="Up",$BF12="Long",$E12=FA$2),$P12,"") | FB12: =IF($J12="",#N/A,SUM(FA$4:FA12)) -> 0 | FC12: =IF(AND($S12="Dwn",$BF12="Short",$E12=FA$2),$P12,"") | FD12: =IF($J12="",#N/A,SUM(FC$4:FC12)) -> 0 | FE12: =IF(AND($S12="SW",$BF12="Long",$E12=FA$2),$P12,"") | FF12: =IF($J12="",#N/A,SUM(FE$4:FE12)) -> 0 | FG12: =IF($J12="",#N/A,SUM(FE$4:FE12,FC$4:FC12,FA$4:FA12)) -> 0 | FH12: =IF(AND($S12="Up",$BF12="Long",$E12=FH$2),$P12,"") | FI12: =IF($J12="",#N/A,SUM(FH$4:FH12)) -> 0 | FJ12: =IF(AND($S12="Dwn",$BF12="Short",$E12=FH$2),$P12,"") | FK12: =IF($J12="",#N/A,SUM(FJ$4:FJ12)) -> 0 | FL12: =IF(AND($S12="SW",$BF12="Long",$E12=FH$2),$P12,"") | FM12: =IF($J12="",#N/A,SUM(FL$4:FL12)) -> 0 | FN12: =IF($J12="",#N/A,SUM(FL$4:FL12,FJ$4:FJ12,FH$4:FH12)) -> 0 | FO12: =IF(AND($S12="Up",$BF12="Long",$E12=FO$2),$P12,"") | FP12: =IF($J12="",#N/A,SUM(FO$4:FO12)) -> 0 | FQ12: =IF(AND($S12="Dwn",$BF12="Short",$E12=FO$2),$P12,"") | FR12: =IF($J12="",#N/A,SUM(FQ$4:FQ12)) -> 0 | FS12: =IF(AND($S12="SW",$BF12="Long",$E12=FO$2),$P12,"") | FT12: =IF($J12="",#N/A,SUM(FS$4:FS12)) -> 0 | FU12: =IF($J12="",#N/A,SUM(FS$4:FS12,FQ$4:FQ12,FO$4:FO12)) -> 0 | FV12: =IF(AND($S12="Up",$BF12="Long",$E12=FV$2),$P12,"") | FW12: =IF($J12="",#N/A,SUM(FV$4:FV12)) -> 0 | FX12: =IF(AND($S12="Dwn",$BF12="Short",$E12=FV$2),$P12,"") | FY12: =IF($J12="",#N/A,SUM(FX$4:FX12)) -> 0 | FZ12: =IF(AND($S12="SW",$BF12="Long",$E12=FV$2),$P12,"") | GA12: =IF($J12="",#N/A,SUM(FZ$4:FZ12)) -> 0 | GB12: =IF($J12="",#N/A,SUM(FZ$4:FZ12,FX$4:FX12,FV$4:FV12)) -> 0 | GC12: =IF(AND($S12="Up",$BF12="Long",$E12=GC$2),$P12,"") | GD12: =IF($J12="",#N/A,SUM(GC$4:GC12)) -> 0 | GE12: =IF(AND($S12="Dwn",$BF12="Short",$E12=GC$2),$P12,"") | GF12: =IF($J12="",#N/A,SUM(GE$4:GE12)) -> 0 | GG12: =IF(AND($S12="SW",$BF12="Long",$E12=GC$2),$P12,"") | GH12: =IF($J12="",#N/A,SUM(GG$4:GG12)) -> 0 | GI12: =IF($J12="",#N/A,SUM(GG$4:GG12,GE$4:GE12,GC$4:GC12)) -> 0 | GJ12: =IF(AND($S12="Up",$BF12="Long",$E12=GJ$2),$P12,"") | GK12: =IF($J12="",#N/A,SUM(GJ$4:GJ12)) -> 0 | GL12: =IF(AND($S12="Dwn",$BF12="Short",$E12=GJ$2),$P12,"") | GM12: =IF($J12="",#N/A,SUM(GL$4:GL12)) -> 0 | GN12: =IF(AND($S12="SW",$BF12="Long",$E12=GJ$2),$P12,"") | GO12: =IF($J12="",#N/A,SUM(GN$4:GN12)) -> 0 | GP12: =IF($J12="",#N/A,SUM(GN$4:GN12,GL$4:GL12,GJ$4:GJ12)) -> 0 | GS12: =IF(J12="","",IF(D12="Y",P12,"")) -> 0.5244991 | GT12: =IF(GS12="",NA(),SUM($GS$4:GS12)) -> -1.3115775 | GU12: =IF(AND($S12="Up",$BF12="Long",$D12="Y"),$GS12,"") | GV12: =IF(GU12="",NA(),SUM($GU$4:GU12)) -> #N/A | GW12: =IF(AND($S12="SW",$BF12="Long",$D12="Y"),$GS12,"") -> 0.5244991 | GX12: =IF(GW12="",NA(),SUM($GW$4:GW12)) -> -1.5119749 | GY12: =IF(AND($S12="Dwn",$BF12="Short",$D12="Y"),$GS12,"") | GZ12: =IF(GY12="",NA(),SUM($GY$4:GY12)) -> #N/A | HA12: =IF($J12="","",IF($D12="N",$P12,"")) | HB12: =IF(HA12="",NA(),SUM($HA$4:HA12)) -> #N/A | HC12: =IF(AND($S12="Up",$BF12="Long",$D12="N"),$HA12,"") | HD12: =IF(HC12="",NA(),SUM($HC$4:HC12)) -> #N/A | HE12: =IF(AND($S12="SW",$BF12="Long",$D12="N"),$HA12,"") | HF12: =IF(HE12="",NA(),SUM($HE$4:HE12)) -> #N/A | HG12: =IF(AND($S12="Dwn",$BF12="Short",$D12="N"),$HA12,"") | HH12: =IF(HG12="",NA(),SUM($HG$4:HG12)) -> #N/A | HI12: =IF($AC12="","",IF(AND($S12="Dwn",$K12<0),$HU12-P12,"")) | HJ12: =IF($J12="",#N/A,SUM(HI$4:$HI12)) -> -0.80152672 | HK12: =IF($AC12="","",IF(AND($S12="Dwn",$K12>0),$HU12-$P12,"")) | HL12: =IF($J12="",#N/A,SUM($HK$4:HK12)) -> -3.4652546 | HM12: =IF($AC12="","",IF(AND($S12="Up",$K12>0),$HU12-$P12,"")) | HN12: =IF($J12="",#N/A,SUM($HM$4:HM12)) -> 0 | HO12: =IF($AC12="","",IF(AND($S12="Up",$K12<0),$HU12-$P12,"")) | HP12: =IF($J12="",#N/A,SUM($HO$4:HO12)) -> 0 | HQ12: =IF($AC12="","",IF(AND($S12="SW",$K12>0),$HU12-$P12,"")) -> -0.20292317 | HR12: =IF($J12="",#N/A,SUM($HQ$4:HQ12)) -> -0.20292317 | HS12: =IF($AC12="","",IF(AND($S12="SW",$K12<0),$HU12-$P12,"")) | HT12: =IF($J12="",#N/A,SUM($HS$4:HS12)) -> 4.4712151 | HU12: =IF(OR($Y12="",$AC12=""),"",IF($BF12="Long",(($AC12*$Y12)-$X12)/($X12*0.06),($X12-($AC12*$Y12))/($X12*0.06))) -> 0.32157592 | HV12: =IF($J12="",#N/A,SUM(HU$4:$HU12)) -> -1.3100669
A13: MTB | B13: on 4/14/25 Before Market Eastern Stan | C13: =IF(S13="Dwn",2,IF(S13="Up",1,IF(S13="SW",3,"x"))) -> 2 | D13: =_xlfn.XLOOKUP(A13,[1]SP500!$A$2:$A$502,[1]SP500!$D$2:$D$502,"N") -> Y | E13: =IFERROR(_xlfn.XLOOKUP(A13,[1]SP500!$A$2:$A$655,[1]SP500!$B$2:$B$655),"") -> XLF | F13: 45761 | G13: =IF(ISNUMBER(FIND("After",B13,1)),"AMC",IF(ISNUMBER(FIND("Before",B13,1)),"BMO","err")) -> BMO | H13: =IF(AH13="Skip","sk",IF(OR(S13="",V13=""),"",IF(AND(S13="Dwn",V13="Short"),"s",IF(AND(S13="Up",V13="Long"),"s",IF(AND(S13="SW",V13="Long"),"s","o"))))) -> sk | I13: 157.95 | J13: 157 | K13: =IF(J13="","",(J13-I13)/I13) -> -0.0060145616 | L13: =IF(OR($Y13="",J13=""),"",IF($V13="Long",(($J13*$Y13)-$X13),($X13-($J13*$Y13)))) -> 6.7162805 | M13: =IF(L13="","",IF(AK13="",#N/A,IF(AH13="Open",AK13-L13,#N/A))) -> #N/A | N13: =IF(OR($Y13="",L13=""),"",IF($BF13="Long",(($J13*$Y13)-$X13),($X13-($J13*$Y13)))) -> 6.7162805 | O13: =IF(N13="",#N/A,SUM($N$4:N13)) -> -77.14372 | P13: =IF(OR($Y13="",L13=""),"",IF($BF13="Long",(($J13*$Y13)-$X13)/(X13*0.06),($X13-($J13*$Y13))/(X13*0.06))) -> 0.10024269 | Q13: =IF($N13="",#N/A,SUM($P$4:P13)) -> -1.2113348 | R13: =IF(AND(AH13="MOC",AC13=""),#N/A,IFERROR(Q13-AJ13,Q13-0)) -> -0.30640595 | S13: =IF(T13="Down","Dwn",IF(T13="Up","Up",IF(AND(T13="",K13=""),"",IF(AND(K13<0,T13="Yes"),"Dwn",IF(AND(K13>0,T13="Yes"),"Up",IF(AND(K13<0,T13="No"),"Up",IF(AND(K13>0,T13="No"),"Dwn",IF(T13="NA","SW","err")))))))) -> Dwn | T13: Yes | U13: =I13 -> 157.95 | V13: Short | W13: =IF(I13="","",1116.67/I13) -> 7.0697689 | X13: =IF(W13="","",U13*W13) -> 1116.67 | Y13: =IF(W13="","",W13) -> 7.0697689 | Z13: =J13 -> 157 | AA13: =IF($Z13="","",IF($V13="Long",(($Z13*$Y13)-$X13),($X13-($Z13*$Y13)))) -> 6.7162805 | AB13: =IF($AC13="","",IF($V13="Long",(($AC13*$Y13)-$X13),($X13-($AC13*$Y13)))) -> -3.8883729 | AC13: 158.5 | AD13: =IF(AC13="","",IF(OR($Y13="",CV13=""),"",IF($BF13="Long",(($AC13*$Y13)-$X13),($X13-($AC13*$Y13))))) -> -3.8883729 | AE13: =IF(OR($Y13="",$AD13=""),"",IF($BF13="Long",(($AC13*$Y13)-$X13)/($X13*0.06),($X13-($AC13*$Y13))/($X13*0.06))) -> -0.058035243 | AF13: =IF($AC13="",#N/A,SUM(AD$4:AD13)) -> -89.368373 | AG13: =IF(OR(AD13="",AC13=""),"",AD13-N13) -> -10.604653 | AH13: Skip | AI13: =IF(AND(AH13="MOC",AC13=""),"",IF(Z13="","",IF(AH13="Skip",0,IF(AK13=0,0,AK13/(X13*0.06))))) -> 0 | AJ13: =IF(AI13="",#N/A,SUM($AI$4:AI13)) -> -0.90492887 | AK13: =IF(AH13="","",IF(AH13="Skip","",IF(OR(AH13="open",AH13="Other"),AA13,IF(AH13="MOC",AB13,"Err")))) | AL13: =IF(AI13="",#N/A,IF(AH13="Skip",SUM($AK$4:AK13),SUM($AK$4:AK13))) -> -57.6 | AM13: =IF(OR($Y13="",$L13=""),"",IF($BF13="Long",(($AC13*$Y13)-$X13)/($X13*0.06),($X13-($AC13*$Y13))/($X13*0.06))) -> -0.058035243 | AO13: =IF(AND($S13="SW",$BF13="Long"),$HU13,"") | AP13: =IF($AC13="",#N/A,SUM(AO$4:AO13)) -> 2.756317 | AQ13: =IF(AND($S13="UP",$BF13="Long"),$HU13,"") | AR13: =IF($AC13="",#N/A,SUM(AQ$4:AQ13)) -> 0 | AS13: =IF(AND($S13="Dwn",$BF13="Short"),$HU13,"") -> -0.058035243 | AT13: =IF($AC13="",#N/A,SUM(AS$4:AS13)) -> -4.1244191 | AU13: =IF(AND(S13="SW",BF13="Long"),$AD13,"") | AV13: =IF($AC13="",#N/A,SUM(AU$4:AU13)) -> 177.32 | AW13: =IF(AND(S13="UP",BF13="Long"),$AD13,"") | AX13: =IF($AC13="",#N/A,SUM(AW$4:AW13)) -> 0 | AY13: =IF(AND(S13="Dwn",BF13="Short"),$AD13,"") -> -3.8883729 | AZ13: =IF($AC13="",#N/A,SUM(AY$4:AY13)) -> -266.68837 | BA13: =IF(AD13="",#N/A,SUM($AD$4:AD13)) -> -89.368373 | BC13: =IF(K13="","",IF(AND(K13>0,T13="Yes"),1,"")) | BD13: =IF(K13="","",IF(AND($K13>0,$T13="No"),1,"")) | BE13: =IF(K13="","",IF(AND($K13>0,$T13="NA"),1,"")) | BF13: =IF(S13="Dwn","Short","Long") -> Short | BG13: =IF(K13="","",IF(AND($K13<0,$T13="Yes"),1,"")) -> 1 | BH13: =IF(K13="","",IF(AND($K13<0,$T13="No"),1,"")) | BI13: =IF(K13="","",IF(AND($K13<0,$T13="NA"),1,"")) | BO13: =IF(J13="",#N/A,IF(S13="SW",(COUNTIFS(K$4:$K13,">0",S$4:$S13,"SW")/COUNTIF(S$4:$S13,"SW")),#N/A)) -> #N/A | BP13: =IF($J13="",#N/A,IF($S13="DWN",(COUNTIFS($K$4:$K13,"<0",$S$4:$S13,"DWN")/COUNTIF($S$4:$S13,"DWN")),#N/A)) -> 0.66666667 | BQ13: =IF($J13="",#N/A,IF($S13="UP",(COUNTIFS($K$4:$K13,">0",$S$4:$S13,"UP")/COUNTIF($S$4:$S13,"UP")),#N/A)) -> #N/A | BR13: =IF(J13="",#N/A,COUNTIF($K$4:K13,">0")/COUNT($J$4:J13)) -> 0.2 | BS13: =IF($AH13="Skip","",IF($J13="","",IF(AND($V13="Long",$L13>0),$P13,""))) | BT13: =IF($AH13="Skip","",IF($J13="","",IF(AND($V13="Long",$L13<0),$P13,""))) | BU13: =IF($AH13="Skip","",IF($J13="","",IF(AND($V13="Short",$L13>0),$P13,""))) | BV13: =IF($AH13="Skip","",IF($J13="","",IF(AND($V13="Short",$L13<0),$P13,""))) | BW13: =IF(AND($S13="Up",$BF13="Long"),$N13,"") | BX13: =IF($J13="",#N/A,SUM($BW$4:BW13)) -> 0 | BY13: =IF(AND($S13="Dwn",$BF13="Short"),$N13,"") -> 6.7162805 | BZ13: =IF($J13="",#N/A,SUM($BY$4:BY13)) -> 20.63628 | CA13: =IF(AND($S13="SW",$BF13="Long"),$N13,"") | CB13: =IF($J13="",#N/A,SUM($CA$4:CA13)) -> -97.78 | CC13: =IF(AND($S13="Up",$BF13="Long"),$P13,"") | CD13: =IF($J13="",#N/A,SUM($CC$4:CC13)) -> 0 | CE13: =IF(AND($S13="Dwn",$BF13="Short"),$P13,"") -> 0.10024269 | CF13: =IF($J13="",#N/A,SUM($CE$4:CE13)) -> 0.30064008 | CG13: =IF(AND($S13="SW",$BF13="Long"),$P13,"") | CH13: =IF($J13="",#N/A,SUM($CG$4:CG13)) -> -1.5119749 | CI13: =IF(AND($S13="Up",$BF13="Long",$E13=CI$2),$P13,"") | CJ13: =IF($J13="",#N/A,SUM(CI$4:CI13)) -> 0 | CK13: =IF(AND($S13="Dwn",$BF13="Short",$E13=CI$2),$P13,"") | CL13: =IF($J13="",#N/A,SUM(CK$4:CK13)) -> 0 | CM13: =IF(AND($S13="SW",$BF13="Long",$E13=CI$2),$P13,"") | CN13: =IF($J13="",#N/A,SUM(CM$4:CM13)) -> 0 | CO13: =IF($J13="",#N/A,SUM(CM$4:CM13,CK$4:CK13,CI$4:CI13)) -> 0 | CP13: =IF(AND($S13="Up",$BF13="Long",$E13=CP$2),$P13,"") | CQ13: =IF($J13="",#N/A,SUM(CP$4:CP13)) -> 0 | CR13: =IF(AND($S13="Dwn",$BF13="Short",$E13=CP$2),$P13,"") | CS13: =IF($J13="",#N/A,SUM(CR$4:CR13)) -> 0 | CT13: =IF(AND($S13="SW",$BF13="Long",$E13=CP$2),$P13,"") | CU13: =IF($J13="",#N/A,SUM(CT$4:CT13)) -> 0 | CV13: =IF($J13="",#N/A,SUM(CT$4:CT13,CR$4:CR13,CP$4:CP13)) -> 0 | CW13: =IF(AND($S13="Up",$BF13="Long",$E13=CW$2),$P13,"") | CX13: =IF($J13="",#N/A,SUM(CW$4:CW13)) -> 0 | CY13: =IF(AND($S13="Dwn",$BF13="Short",$E13=CW$2),$P13,"") | CZ13: =IF($J13="",#N/A,SUM(CY$4:CY13)) -> 0 | DA13: =IF(AND($S13="SW",$BF13="Long",$E13=CW$2),$P13,"") | DB13: =IF($J13="",#N/A,SUM(DA$4:DA13)) -> 0 | DC13: =IF($J13="",#N/A,SUM(DA$4:DA13,CY$4:CY13,CW$4:CW13)) -> 0 | DD13: =IF(AND($S13="Up",$BF13="Long",$E13=DD$2),$P13,"") | DE13: =IF($J13="",#N/A,SUM(DD$4:DD13)) -> 0 | DF13: =IF(AND($S13="Dwn",$BF13="Short",$E13=DD$2),$P13,"") | DG13: =IF($J13="",#N/A,SUM(DF$4:DF13)) -> 0.67884406 | DH13: =IF(AND($S13="SW",$BF13="Long",$E13=DD$2),$P13,"") | DI13: =IF($J13="",#N/A,SUM(DH$4:DH13)) -> 0 | DJ13: =IF($J13="",#N/A,SUM(DH$4:DH13,DF$4:DF13,DD$4:DD13)) -> 0.67884406 | DK13: =IF(AND($S13="Up",$BF13="Long",$E13=DK$2),$P13,"") | DL13: =IF($J13="",#N/A,SUM(DK$4:DK13)) -> 0 | DM13: =IF(AND($S13="Dwn",$BF13="Short",$E13=DK$2),$P13,"") | DN13: =IF($J13="",#N/A,SUM(DM$4:DM13)) -> 0 | DO13: =IF(AND($S13="SW",$BF13="Long",$E13=DK$2),$P13,"") | DP13: =IF($J13="",#N/A,SUM(DO$4:DO13)) -> 0 | DQ13: =IF($J13="",#N/A,SUM(DO$4:DO13,DM$4:DM13,DK$4:DK13)) -> 0 | DR13: =IF(AND($S13="Up",$BF13="Long",$E13=DR$2),$P13,"") | DS13: =IF($J13="",#N/A,SUM(DR$4:DR13)) -> 0 | DT13: =IF(AND($S13="Dwn",$BF13="Short",$E13=DR$2),$P13,"") -> 0.10024269 | DU13: =IF($J13="",#N/A,SUM(DT$4:DT13)) -> 0.10024269 | DV13: =IF(AND($S13="SW",$BF13="Long",$E13=DR$2),$P13,"") | DW13: =IF($J13="",#N/A,SUM(DV$4:DV13)) -> -1.3844295 | DX13: =IF($J13="",#N/A,SUM(DV$4:DV13,DT$4:DT13,DR$4:DR13)) -> -1.2841868 | DY13: =IF(AND($S13="Up",$BF13="Long",$E13=DY$2),$P13,"") | DZ13: =IF($J13="",#N/A,SUM(DY$4:DY13)) -> 0 | EA13: =IF(AND($S13="Dwn",$BF13="Short",$E13=DY$2),$P13,"") | EB13: =IF($J13="",#N/A,SUM(EA$4:EA13)) -> -0.47844667 | EC13: =IF(AND($S13="SW",$BF13="Long",$E13=DY$2),$P13,"") | ED13: =IF($J13="",#N/A,SUM(EC$4:EC13)) -> -0.12754541 | EE13: =IF($J13="",#N/A,SUM(EC$4:EC13,EA$4:EA13,DY$4:DY13)) -> -0.60599208 | EF13: =IF(AND($S13="Up",$BF13="Long",$E13=EF$2),$P13,"") | EG13: =IF($J13="",#N/A,SUM(EF$4:EF13)) -> 0 | EH13: =IF(AND($S13="Dwn",$BF13="Short",$E13=EF$2),$P13,"") | EI13: =IF($J13="",#N/A,SUM(EH$4:EH13)) -> 0 | EJ13: =IF(AND($S13="SW",$BF13="Long",$E13=EF$2),$P13,"") | EK13: =IF($J13="",#N/A,SUM(EJ$4:EJ13)) -> 0 | EL13: =IF($J13="",#N/A,SUM(EJ$4:EJ13,EH$4:EH13,EF$4:EF13)) -> 0 | EM13: =IF(AND($S13="Up",$BF13="Long",$E13=EM$2),$P13,"") | EN13: =IF($J13="",#N/A,SUM(EM$4:EM13)) -> 0 | EO13: =IF(AND($S13="Dwn",$BF13="Short",$E13=EM$2),$P13,"") | EP13: =IF($J13="",#N/A,SUM(EO$4:EO13)) -> 0 | EQ13: =IF(AND($S13="SW",$BF13="Long",$E13=EM$2),$P13,"") | ER13: =IF($J13="",#N/A,SUM(EQ$4:EQ13)) -> 0 | ES13: =IF($J13="",#N/A,SUM(EQ$4:EQ13,EO$4:EO13,EM$4:EM13)) -> 0 | ET13: =IF(AND($S13="Up",$BF13="Long",$E13=ET$2),$P13,"") | EU13: =IF($J13="",#N/A,SUM(ET$4:ET13)) -> 0 | EV13: =IF(AND($S13="Dwn",$BF13="Short",$E13=ET$2),$P13,"") | EW13: =IF($J13="",#N/A,SUM(EV$4:EV13)) -> 0 | EX13: =IF(AND($S13="SW",$BF13="Long",$E13=ET$2),$P13,"") | EY13: =IF($J13="",#N/A,SUM(EX$4:EX13)) -> 0 | EZ13: =IF($J13="",#N/A,SUM(EX$4:EX13,EV$4:EV13,ET$4:ET13)) -> 0 | FA13: =IF(AND($S13="Up",$BF13="Long",$E13=FA$2),$P13,"") | FB13: =IF($J13="",#N/A,SUM(FA$4:FA13)) -> 0 | FC13: =IF(AND($S13="Dwn",$BF13="Short",$E13=FA$2),$P13,"") | FD13: =IF($J13="",#N/A,SUM(FC$4:FC13)) -> 0 | FE13: =IF(AND($S13="SW",$BF13="Long",$E13=FA$2),$P13,"") | FF13: =IF($J13="",#N/A,SUM(FE$4:FE13)) -> 0 | FG13: =IF($J13="",#N/A,SUM(FE$4:FE13,FC$4:FC13,FA$4:FA13)) -> 0 | FH13: =IF(AND($S13="Up",$BF13="Long",$E13=FH$2),$P13,"") | FI13: =IF($J13="",#N/A,SUM(FH$4:FH13)) -> 0 | FJ13: =IF(AND($S13="Dwn",$BF13="Short",$E13=FH$2),$P13,"") | FK13: =IF($J13="",#N/A,SUM(FJ$4:FJ13)) -> 0 | FL13: =IF(AND($S13="SW",$BF13="Long",$E13=FH$2),$P13,"") | FM13: =IF($J13="",#N/A,SUM(FL$4:FL13)) -> 0 | FN13: =IF($J13="",#N/A,SUM(FL$4:FL13,FJ$4:FJ13,FH$4:FH13)) -> 0 | FO13: =IF(AND($S13="Up",$BF13="Long",$E13=FO$2),$P13,"") | FP13: =IF($J13="",#N/A,SUM(FO$4:FO13)) -> 0 | FQ13: =IF(AND($S13="Dwn",$BF13="Short",$E13=FO$2),$P13,"") | FR13: =IF($J13="",#N/A,SUM(FQ$4:FQ13)) -> 0 | FS13: =IF(AND($S13="SW",$BF13="Long",$E13=FO$2),$P13,"") | FT13: =IF($J13="",#N/A,SUM(FS$4:FS13)) -> 0 | FU13: =IF($J13="",#N/A,SUM(FS$4:FS13,FQ$4:FQ13,FO$4:FO13)) -> 0 | FV13: =IF(AND($S13="Up",$BF13="Long",$E13=FV$2),$P13,"") | FW13: =IF($J13="",#N/A,SUM(FV$4:FV13)) -> 0 | FX13: =IF(AND($S13="Dwn",$BF13="Short",$E13=FV$2),$P13,"") | FY13: =IF($J13="",#N/A,SUM(FX$4:FX13)) -> 0 | FZ13: =IF(AND($S13="SW",$BF13="Long",$E13=FV$2),$P13,"") | GA13: =IF($J13="",#N/A,SUM(FZ$4:FZ13)) -> 0 | GB13: =IF($J13="",#N/A,SUM(FZ$4:FZ13,FX$4:FX13,FV$4:FV13)) -> 0 | GC13: =IF(AND($S13="Up",$BF13="Long",$E13=GC$2),$P13,"") | GD13: =IF($J13="",#N/A,SUM(GC$4:GC13)) -> 0 | GE13: =IF(AND($S13="Dwn",$BF13="Short",$E13=GC$2),$P13,"") | GF13: =IF($J13="",#N/A,SUM(GE$4:GE13)) -> 0 | GG13: =IF(AND($S13="SW",$BF13="Long",$E13=GC$2),$P13,"") | GH13: =IF($J13="",#N/A,SUM(GG$4:GG13)) -> 0 | GI13: =IF($J13="",#N/A,SUM(GG$4:GG13,GE$4:GE13,GC$4:GC13)) -> 0 | GJ13: =IF(AND($S13="Up",$BF13="Long",$E13=GJ$2),$P13,"") | GK13: =IF($J13="",#N/A,SUM(GJ$4:GJ13)) -> 0 | GL13: =IF(AND($S13="Dwn",$BF13="Short",$E13=GJ$2),$P13,"") | GM13: =IF($J13="",#N/A,SUM(GL$4:GL13)) -> 0 | GN13: =IF(AND($S13="SW",$BF13="Long",$E13=GJ$2),$P13,"") | GO13: =IF($J13="",#N/A,SUM(GN$4:GN13)) -> 0 | GP13: =IF($J13="",#N/A,SUM(GN$4:GN13,GL$4:GL13,GJ$4:GJ13)) -> 0 | GS13: =IF(J13="","",IF(D13="Y",P13,"")) -> 0.10024269 | GT13: =IF(GS13="",NA(),SUM($GS$4:GS13)) -> -1.2113348 | GU13: =IF(AND($S13="Up",$BF13="Long",$D13="Y"),$GS13,"") | GV13: =IF(GU13="",NA(),SUM($GU$4:GU13)) -> #N/A | GW13: =IF(AND($S13="SW",$BF13="Long",$D13="Y"),$GS13,"") | GX13: =IF(GW13="",NA(),SUM($GW$4:GW13)) -> #N/A | GY13: =IF(AND($S13="Dwn",$BF13="Short",$D13="Y"),$GS13,"") -> 0.10024269 | GZ13: =IF(GY13="",NA(),SUM($GY$4:GY13)) -> 0.30064008 | HA13: =IF($J13="","",IF($D13="N",$P13,"")) | HB13: =IF(HA13="",NA(),SUM($HA$4:HA13)) -> #N/A | HC13: =IF(AND($S13="Up",$BF13="Long",$D13="N"),$HA13,"") | HD13: =IF(HC13="",NA(),SUM($HC$4:HC13)) -> #N/A | HE13: =IF(AND($S13="SW",$BF13="Long",$D13="N"),$HA13,"") | HF13: =IF(HE13="",NA(),SUM($HE$4:HE13)) -> #N/A | HG13: =IF(AND($S13="Dwn",$BF13="Short",$D13="N"),$HA13,"") | HH13: =IF(HG13="",NA(),SUM($HG$4:HG13)) -> #N/A | HI13: =IF($AC13="","",IF(AND($S13="Dwn",$K13<0),$HU13-P13,"")) -> -0.15827794 | HJ13: =IF($J13="",#N/A,SUM(HI$4:$HI13)) -> -0.95980465 | HK13: =IF($AC13="","",IF(AND($S13="Dwn",$K13>0),$HU13-$P13,"")) | HL13: =IF($J13="",#N/A,SUM($HK$4:HK13)) -> -3.4652546 | HM13: =IF($AC13="","",IF(AND($S13="Up",$K13>0),$HU13-$P13,"")) | HN13: =IF($J13="",#N/A,SUM($HM$4:HM13)) -> 0 | HO13: =IF($AC13="","",IF(AND($S13="Up",$K13<0),$HU13-$P13,"")) | HP13: =IF($J13="",#N/A,SUM($HO$4:HO13)) -> 0 | HQ13: =IF($AC13="","",IF(AND($S13="SW",$K13>0),$HU13-$P13,"")) | HR13: =IF($J13="",#N/A,SUM($HQ$4:HQ13)) -> -0.20292317 | HS13: =IF($AC13="","",IF(AND($S13="SW",$K13<0),$HU13-$P13,"")) | HT13: =IF($J13="",#N/A,SUM($HS$4:HS13)) -> 4.4712151 | HU13: =IF(OR($Y13="",$AC13=""),"",IF($BF13="Long",(($AC13*$Y13)-$X13)/($X13*0.06),($X13-($AC13*$Y13))/($X13*0.06))) -> -0.058035243 | HV13: =IF($J13="",#N/A,SUM(HU$4:$HU13)) -> -1.3681021
A14: C | B14: on 4/15/25 Before Market Eastern Stan | C14: =IF(S14="Dwn",2,IF(S14="Up",1,IF(S14="SW",3,"x"))) -> 3 | D14: =_xlfn.XLOOKUP(A14,[1]SP500!$A$2:$A$502,[1]SP500!$D$2:$D$502,"N") -> Y | E14: =IFERROR(_xlfn.XLOOKUP(A14,[1]SP500!$A$2:$A$655,[1]SP500!$B$2:$B$655),"") -> XLF | F14: 45762 | G14: =IF(ISNUMBER(FIND("After",B14,1)),"AMC",IF(ISNUMBER(FIND("Before",B14,1)),"BMO","err")) -> BMO | H14: =IF(AH14="Skip","sk",IF(OR(S14="",V14=""),"",IF(AND(S14="Dwn",V14="Short"),"s",IF(AND(S14="Up",V14="Long"),"s",IF(AND(S14="SW",V14="Long"),"s","o"))))) -> s | I14: 63.22 | J14: 64.19 | K14: =IF(J14="","",(J14-I14)/I14) -> 0.015343246 | L14: =IF(OR($Y14="",J14=""),"",IF($V14="Long",(($J14*$Y14)-$X14),($X14-($J14*$Y14)))) -> 17.46 | M14: =IF(L14="","",IF(AK14="",#N/A,IF(AH14="Open",AK14-L14,#N/A))) -> 0.72 | N14: =IF(OR($Y14="",L14=""),"",IF($BF14="Long",(($J14*$Y14)-$X14),($X14-($J14*$Y14)))) -> 17.46 | O14: =IF(N14="",#N/A,SUM($N$4:N14)) -> -59.68372 | P14: =IF(OR($Y14="",L14=""),"",IF($BF14="Long",(($J14*$Y14)-$X14)/(X14*0.06),($X14-($J14*$Y14))/(X14*0.06))) -> 0.25572076 | Q14: =IF($N14="",#N/A,SUM($P$4:P14)) -> -0.95561407 | R14: =IF(AND(AH14="MOC",AC14=""),#N/A,IFERROR(Q14-AJ14,Q14-0)) -> -0.31695114 | S14: =IF(T14="Down","Dwn",IF(T14="Up","Up",IF(AND(T14="",K14=""),"",IF(AND(K14<0,T14="Yes"),"Dwn",IF(AND(K14>0,T14="Yes"),"Up",IF(AND(K14<0,T14="No"),"Up",IF(AND(K14>0,T14="No"),"Dwn",IF(T14="NA","SW","err")))))))) -> SW | T14: NA | U14: =I14 -> 63.22 | V14: Long | W14: 18 | X14: =IF(W14="","",U14*W14) -> 1137.96 | Y14: =IF(W14="","",W14) -> 18 | Z14: 64.23 | AA14: =IF($Z14="","",IF($V14="Long",(($Z14*$Y14)-$X14),($X14-($Z14*$Y14)))) -> 18.18 | AB14: =IF($AC14="","",IF($V14="Long",(($AC14*$Y14)-$X14),($X14-($AC14*$Y14)))) -> 19.98 | AC14: 64.33 | AD14: =IF(AC14="","",IF(OR($Y14="",CV14=""),"",IF($BF14="Long",(($AC14*$Y14)-$X14),($X14-($AC14*$Y14))))) -> 19.98 | AE14: =IF(OR($Y14="",$AD14=""),"",IF($BF14="Long",(($AC14*$Y14)-$X14)/($X14*0.06),($X14-($AC14*$Y14))/($X14*0.06))) -> 0.29262891 | AF14: =IF($AC14="",#N/A,SUM(AD$4:AD14)) -> -69.388373 | AG14: =IF(OR(AD14="",AC14=""),"",AD14-N14) -> 2.52 | AH14: Open | AI14: =IF(AND(AH14="MOC",AC14=""),"",IF(Z14="","",IF(AH14="Skip",0,IF(AK14=0,0,AK14/(X14*0.06))))) -> 0.26626595 | AJ14: =IF(AI14="",#N/A,SUM($AI$4:AI14)) -> -0.63866293 | AK14: =IF(AH14="","",IF(AH14="Skip","",IF(OR(AH14="open",AH14="Other"),AA14,IF(AH14="MOC",AB14,"Err")))) -> 18.18 | AL14: =IF(AI14="",#N/A,IF(AH14="Skip",SUM($AK$4:AK14),SUM($AK$4:AK14))) -> -39.42 | AM14: =IF(OR($Y14="",$L14=""),"",IF($BF14="Long",(($AC14*$Y14)-$X14)/($X14*0.06),($X14-($AC14*$Y14))/($X14*0.06))) -> 0.29262891 | AO14: =IF(AND($S14="SW",$BF14="Long"),$HU14,"") -> 0.29262891 | AP14: =IF($AC14="",#N/A,SUM(AO$4:AO14)) -> 3.0489459 | AQ14: =IF(AND($S14="UP",$BF14="Long"),$HU14,"") | AR14: =IF($AC14="",#N/A,SUM(AQ$4:AQ14)) -> 0 | AS14: =IF(AND($S14="Dwn",$BF14="Short"),$HU14,"") | AT14: =IF($AC14="",#N/A,SUM(AS$4:AS14)) -> -4.1244191 | AU14: =IF(AND(S14="SW",BF14="Long"),$AD14,"") -> 19.98 | AV14: =IF($AC14="",#N/A,SUM(AU$4:AU14)) -> 197.3 | AW14: =IF(AND(S14="UP",BF14="Long"),$AD14,"") | AX14: =IF($AC14="",#N/A,SUM(AW$4:AW14)) -> 0 | AY14: =IF(AND(S14="Dwn",BF14="Short"),$AD14,"") | AZ14: =IF($AC14="",#N/A,SUM(AY$4:AY14)) -> -266.68837 | BA14: =IF(AD14="",#N/A,SUM($AD$4:AD14)) -> -69.388373 | BC14: =IF(K14="","",IF(AND(K14>0,T14="Yes"),1,"")) | BD14: =IF(K14="","",IF(AND($K14>0,$T14="No"),1,"")) | BE14: =IF(K14="","",IF(AND($K14>0,$T14="NA"),1,"")) -> 1 | BF14: =IF(S14="Dwn","Short","Long") -> Long | BG14: =IF(K14="","",IF(AND($K14<0,$T14="Yes"),1,"")) | BH14: =IF(K14="","",IF(AND($K14<0,$T14="No"),1,"")) | BI14: =IF(K14="","",IF(AND($K14<0,$T14="NA"),1,"")) | BO14: =IF(J14="",#N/A,IF(S14="SW",(COUNTIFS(K$4:$K14,">0",S$4:$S14,"SW")/COUNTIF(S$4:$S14,"SW")),#N/A)) -> 0.25 | BP14: =IF($J14="",#N/A,IF($S14="DWN",(COUNTIFS($K$4:$K14,"<0",$S$4:$S14,"DWN")/COUNTIF($S$4:$S14,"DWN")),#N/A)) -> #N/A | BQ14: =IF($J14="",#N/A,IF($S14="UP",(COUNTIFS($K$4:$K14,">0",$S$4:$S14,"UP")/COUNTIF($S$4:$S14,"UP")),#N/A)) -> #N/A | BR14: =IF(J14="",#N/A,COUNTIF($K$4:K14,">0")/COUNT($J$4:J14)) -> 0.27272727 | BS14: =IF($AH14="Skip","",IF($J14="","",IF(AND($V14="Long",$L14>0),$P14,""))) -> 0.25572076 | BT14: =IF($AH14="Skip","",IF($J14="","",IF(AND($V14="Long",$L14<0),$P14,""))) | BU14: =IF($AH14="Skip","",IF($J14="","",IF(AND($V14="Short",$L14>0),$P14,""))) | BV14: =IF($AH14="Skip","",IF($J14="","",IF(AND($V14="Short",$L14<0),$P14,""))) | BW14: =IF(AND($S14="Up",$BF14="Long"),$N14,"") | BX14: =IF($J14="",#N/A,SUM($BW$4:BW14)) -> 0 | BY14: =IF(AND($S14="Dwn",$BF14="Short"),$N14,"") | BZ14: =IF($J14="",#N/A,SUM($BY$4:BY14)) -> 20.63628 | CA14: =IF(AND($S14="SW",$BF14="Long"),$N14,"") -> 17.46 | CB14: =IF($J14="",#N/A,SUM($CA$4:CA14)) -> -80.32 | CC14: =IF(AND($S14="Up",$BF14="Long"),$P14,"") | CD14: =IF($J14="",#N/A,SUM($CC$4:CC14)) -> 0 | CE14: =IF(AND($S14="Dwn",$BF14="Short"),$P14,"") | CF14: =IF($J14="",#N/A,SUM($CE$4:CE14)) -> 0.30064008 | CG14: =IF(AND($S14="SW",$BF14="Long"),$P14,"") -> 0.25572076 | CH14: =IF($J14="",#N/A,SUM($CG$4:CG14)) -> -1.2562541 | CI14: =IF(AND($S14="Up",$BF14="Long",$E14=CI$2),$P14,"") | CJ14: =IF($J14="",#N/A,SUM(CI$4:CI14)) -> 0 | CK14: =IF(AND($S14="Dwn",$BF14="Short",$E14=CI$2),$P14,"") | CL14: =IF($J14="",#N/A,SUM(CK$4:CK14)) -> 0 | CM14: =IF(AND($S14="SW",$BF14="Long",$E14=CI$2),$P14,"") | CN14: =IF($J14="",#N/A,SUM(CM$4:CM14)) -> 0 | CO14: =IF($J14="",#N/A,SUM(CM$4:CM14,CK$4:CK14,CI$4:CI14)) -> 0 | CP14: =IF(AND($S14="Up",$BF14="Long",$E14=CP$2),$P14,"") | CQ14: =IF($J14="",#N/A,SUM(CP$4:CP14)) -> 0 | CR14: =IF(AND($S14="Dwn",$BF14="Short",$E14=CP$2),$P14,"") | CS14: =IF($J14="",#N/A,SUM(CR$4:CR14)) -> 0 | CT14: =IF(AND($S14="SW",$BF14="Long",$E14=CP$2),$P14,"") | CU14: =IF($J14="",#N/A,SUM(CT$4:CT14)) -> 0 | CV14: =IF($J14="",#N/A,SUM(CT$4:CT14,CR$4:CR14,CP$4:CP14)) -> 0 | CW14: =IF(AND($S14="Up",$BF14="Long",$E14=CW$2),$P14,"") | CX14: =IF($J14="",#N/A,SUM(CW$4:CW14)) -> 0 | CY14: =IF(AND($S14="Dwn",$BF14="Short",$E14=CW$2),$P14,"") | CZ14: =IF($J14="",#N/A,SUM(CY$4:CY14)) -> 0 | DA14: =IF(AND($S14="SW",$BF14="Long",$E14=CW$2),$P14,"") | DB14: =IF($J14="",#N/A,SUM(DA$4:DA14)) -> 0 | DC14: =IF($J14="",#N/A,SUM(DA$4:DA14,CY$4:CY14,CW$4:CW14)) -> 0 | DD14: =IF(AND($S14="Up",$BF14="Long",$E14=DD$2),$P14,"") | DE14: =IF($J14="",#N/A,SUM(DD$4:DD14)) -> 0 | DF14: =IF(AND($S14="Dwn",$BF14="Short",$E14=DD$2),$P14,"") | DG14: =IF($J14="",#N/A,SUM(DF$4:DF14)) -> 0.67884406 | DH14: =IF(AND($S14="SW",$BF14="Long",$E14=DD$2),$P14,"") | DI14: =IF($J14="",#N/A,SUM(DH$4:DH14)) -> 0 | DJ14: =IF($J14="",#N/A,SUM(DH$4:DH14,DF$4:DF14,DD$4:DD14)) -> 0.67884406 | DK14: =IF(AND($S14="Up",$BF14="Long",$E14=DK$2),$P14,"") | DL14: =IF($J14="",#N/A,SUM(DK$4:DK14)) -> 0 | DM14: =IF(AND($S14="Dwn",$BF14="Short",$E14=DK$2),$P14,"") | DN14: =IF($J14="",#N/A,SUM(DM$4:DM14)) -> 0 | DO14: =IF(AND($S14="SW",$BF14="Long",$E14=DK$2),$P14,"") | DP14: =IF($J14="",#N/A,SUM(DO$4:DO14)) -> 0 | DQ14: =IF($J14="",#N/A,SUM(DO$4:DO14,DM$4:DM14,DK$4:DK14)) -> 0 | DR14: =IF(AND($S14="Up",$BF14="Long",$E14=DR$2),$P14,"") | DS14: =IF($J14="",#N/A,SUM(DR$4:DR14)) -> 0 | DT14: =IF(AND($S14="Dwn",$BF14="Short",$E14=DR$2),$P14,"") | DU14: =IF($J14="",#N/A,SUM(DT$4:DT14)) -> 0.10024269 | DV14: =IF(AND($S14="SW",$BF14="Long",$E14=DR$2),$P14,"") -> 0.25572076 | DW14: =IF($J14="",#N/A,SUM(DV$4:DV14)) -> -1.1287087 | DX14: =IF($J14="",#N/A,SUM(DV$4:DV14,DT$4:DT14,DR$4:DR14)) -> -1.028466 | DY14: =IF(AND($S14="Up",$BF14="Long",$E14=DY$2),$P14,"") | DZ14: =IF($J14="",#N/A,SUM(DY$4:DY14)) -> 0 | EA14: =IF(AND($S14="Dwn",$BF14="Short",$E14=DY$2),$P14,"") | EB14: =IF($J14="",#N/A,SUM(EA$4:EA14)) -> -0.47844667 | EC14: =IF(AND($S14="SW",$BF14="Long",$E14=DY$2),$P14,"") | ED14: =IF($J14="",#N/A,SUM(EC$4:EC14)) -> -0.12754541 | EE14: =IF($J14="",#N/A,SUM(EC$4:EC14,EA$4:EA14,DY$4:DY14)) -> -0.60599208 | EF14: =IF(AND($S14="Up",$BF14="Long",$E14=EF$2),$P14,"") | EG14: =IF($J14="",#N/A,SUM(EF$4:EF14)) -> 0 | EH14: =IF(AND($S14="Dwn",$BF14="Short",$E14=EF$2),$P14,"") | EI14: =IF($J14="",#N/A,SUM(EH$4:EH14)) -> 0 | EJ14: =IF(AND($S14="SW",$BF14="Long",$E14=EF$2),$P14,"") | EK14: =IF($J14="",#N/A,SUM(EJ$4:EJ14)) -> 0 | EL14: =IF($J14="",#N/A,SUM(EJ$4:EJ14,EH$4:EH14,EF$4:EF14)) -> 0 | EM14: =IF(AND($S14="Up",$BF14="Long",$E14=EM$2),$P14,"") | EN14: =IF($J14="",#N/A,SUM(EM$4:EM14)) -> 0 | EO14: =IF(AND($S14="Dwn",$BF14="Short",$E14=EM$2),$P14,"") | EP14: =IF($J14="",#N/A,SUM(EO$4:EO14)) -> 0 | EQ14: =IF(AND($S14="SW",$BF14="Long",$E14=EM$2),$P14,"") | ER14: =IF($J14="",#N/A,SUM(EQ$4:EQ14)) -> 0 | ES14: =IF($J14="",#N/A,SUM(EQ$4:EQ14,EO$4:EO14,EM$4:EM14)) -> 0 | ET14: =IF(AND($S14="Up",$BF14="Long",$E14=ET$2),$P14,"") | EU14: =IF($J14="",#N/A,SUM(ET$4:ET14)) -> 0 | EV14: =IF(AND($S14="Dwn",$BF14="Short",$E14=ET$2),$P14,"") | EW14: =IF($J14="",#N/A,SUM(EV$4:EV14)) -> 0 | EX14: =IF(AND($S14="SW",$BF14="Long",$E14=ET$2),$P14,"") | EY14: =IF($J14="",#N/A,SUM(EX$4:EX14)) -> 0 | EZ14: =IF($J14="",#N/A,SUM(EX$4:EX14,EV$4:EV14,ET$4:ET14)) -> 0 | FA14: =IF(AND($S14="Up",$BF14="Long",$E14=FA$2),$P14,"") | FB14: =IF($J14="",#N/A,SUM(FA$4:FA14)) -> 0 | FC14: =IF(AND($S14="Dwn",$BF14="Short",$E14=FA$2),$P14,"") | FD14: =IF($J14="",#N/A,SUM(FC$4:FC14)) -> 0 | FE14: =IF(AND($S14="SW",$BF14="Long",$E14=FA$2),$P14,"") | FF14: =IF($J14="",#N/A,SUM(FE$4:FE14)) -> 0 | FG14: =IF($J14="",#N/A,SUM(FE$4:FE14,FC$4:FC14,FA$4:FA14)) -> 0 | FH14: =IF(AND($S14="Up",$BF14="Long",$E14=FH$2),$P14,"") | FI14: =IF($J14="",#N/A,SUM(FH$4:FH14)) -> 0 | FJ14: =IF(AND($S14="Dwn",$BF14="Short",$E14=FH$2),$P14,"") | FK14: =IF($J14="",#N/A,SUM(FJ$4:FJ14)) -> 0 | FL14: =IF(AND($S14="SW",$BF14="Long",$E14=FH$2),$P14,"") | FM14: =IF($J14="",#N/A,SUM(FL$4:FL14)) -> 0 | FN14: =IF($J14="",#N/A,SUM(FL$4:FL14,FJ$4:FJ14,FH$4:FH14)) -> 0 | FO14: =IF(AND($S14="Up",$BF14="Long",$E14=FO$2),$P14,"") | FP14: =IF($J14="",#N/A,SUM(FO$4:FO14)) -> 0 | FQ14: =IF(AND($S14="Dwn",$BF14="Short",$E14=FO$2),$P14,"") | FR14: =IF($J14="",#N/A,SUM(FQ$4:FQ14)) -> 0 | FS14: =IF(AND($S14="SW",$BF14="Long",$E14=FO$2),$P14,"") | FT14: =IF($J14="",#N/A,SUM(FS$4:FS14)) -> 0 | FU14: =IF($J14="",#N/A,SUM(FS$4:FS14,FQ$4:FQ14,FO$4:FO14)) -> 0 | FV14: =IF(AND($S14="Up",$BF14="Long",$E14=FV$2),$P14,"") | FW14: =IF($J14="",#N/A,SUM(FV$4:FV14)) -> 0 | FX14: =IF(AND($S14="Dwn",$BF14="Short",$E14=FV$2),$P14,"") | FY14: =IF($J14="",#N/A,SUM(FX$4:FX14)) -> 0 | FZ14: =IF(AND($S14="SW",$BF14="Long",$E14=FV$2),$P14,"") | GA14: =IF($J14="",#N/A,SUM(FZ$4:FZ14)) -> 0 | GB14: =IF($J14="",#N/A,SUM(FZ$4:FZ14,FX$4:FX14,FV$4:FV14)) -> 0 | GC14: =IF(AND($S14="Up",$BF14="Long",$E14=GC$2),$P14,"") | GD14: =IF($J14="",#N/A,SUM(GC$4:GC14)) -> 0 | GE14: =IF(AND($S14="Dwn",$BF14="Short",$E14=GC$2),$P14,"") | GF14: =IF($J14="",#N/A,SUM(GE$4:GE14)) -> 0 | GG14: =IF(AND($S14="SW",$BF14="Long",$E14=GC$2),$P14,"") | GH14: =IF($J14="",#N/A,SUM(GG$4:GG14)) -> 0 | GI14: =IF($J14="",#N/A,SUM(GG$4:GG14,GE$4:GE14,GC$4:GC14)) -> 0 | GJ14: =IF(AND($S14="Up",$BF14="Long",$E14=GJ$2),$P14,"") | GK14: =IF($J14="",#N/A,SUM(GJ$4:GJ14)) -> 0 | GL14: =IF(AND($S14="Dwn",$BF14="Short",$E14=GJ$2),$P14,"") | GM14: =IF($J14="",#N/A,SUM(GL$4:GL14)) -> 0 | GN14: =IF(AND($S14="SW",$BF14="Long",$E14=GJ$2),$P14,"") | GO14: =IF($J14="",#N/A,SUM(GN$4:GN14)) -> 0 | GP14: =IF($J14="",#N/A,SUM(GN$4:GN14,GL$4:GL14,GJ$4:GJ14)) -> 0 | GS14: =IF(J14="","",IF(D14="Y",P14,"")) -> 0.25572076 | GT14: =IF(GS14="",NA(),SUM($GS$4:GS14)) -> -0.95561407 | GU14: =IF(AND($S14="Up",$BF14="Long",$D14="Y"),$GS14,"") | GV14: =IF(GU14="",NA(),SUM($GU$4:GU14)) -> #N/A | GW14: =IF(AND($S14="SW",$BF14="Long",$D14="Y"),$GS14,"") -> 0.25572076 | GX14: =IF(GW14="",NA(),SUM($GW$4:GW14)) -> -1.2562541 | GY14: =IF(AND($S14="Dwn",$BF14="Short",$D14="Y"),$GS14,"") | GZ14: =IF(GY14="",NA(),SUM($GY$4:GY14)) -> #N/A | HA14: =IF($J14="","",IF($D14="N",$P14,"")) | HB14: =IF(HA14="",NA(),SUM($HA$4:HA14)) -> #N/A | HC14: =IF(AND($S14="Up",$BF14="Long",$D14="N"),$HA14,"") | HD14: =IF(HC14="",NA(),SUM($HC$4:HC14)) -> #N/A | HE14: =IF(AND($S14="SW",$BF14="Long",$D14="N"),$HA14,"") | HF14: =IF(HE14="",NA(),SUM($HE$4:HE14)) -> #N/A | HG14: =IF(AND($S14="Dwn",$BF14="Short",$D14="N"),$HA14,"") | HH14: =IF(HG14="",NA(),SUM($HG$4:HG14)) -> #N/A | HI14: =IF($AC14="","",IF(AND($S14="Dwn",$K14<0),$HU14-P14,"")) | HJ14: =IF($J14="",#N/A,SUM(HI$4:$HI14)) -> -0.95980465 | HK14: =IF($AC14="","",IF(AND($S14="Dwn",$K14>0),$HU14-$P14,"")) | HL14: =IF($J14="",#N/A,SUM($HK$4:HK14)) -> -3.4652546 | HM14: =IF($AC14="","",IF(AND($S14="Up",$K14>0),$HU14-$P14,"")) | HN14: =IF($J14="",#N/A,SUM($HM$4:HM14)) -> 0 | HO14: =IF($AC14="","",IF(AND($S14="Up",$K14<0),$HU14-$P14,"")) | HP14: =IF($J14="",#N/A,SUM($HO$4:HO14)) -> 0 | HQ14: =IF($AC14="","",IF(AND($S14="SW",$K14>0),$HU14-$P14,"")) -> 0.036908151 | HR14: =IF($J14="",#N/A,SUM($HQ$4:HQ14)) -> -0.16601502 | HS14: =IF($AC14="","",IF(AND($S14="SW",$K14<0),$HU14-$P14,"")) | HT14: =IF($J14="",#N/A,SUM($HS$4:HS14)) -> 4.4712151 | HU14: =IF(OR($Y14="",$AC14=""),"",IF($BF14="Long",(($AC14*$Y14)-$X14)/($X14*0.06),($X14-($AC14*$Y14))/($X14*0.06))) -> 0.29262891 | HV14: =IF($J14="",#N/A,SUM(HU$4:$HU14)) -> -1.0754732
